Workbook

Sheet Guia
A1: Configuración | B1: modelo=qwen3:4b-instruct · recuperación=hybrid · top_k=5 · temperatura=0.0 · embeddings=granite-embedding:30m
A2: Cómo usar | B2: Una fila por pregunta y modo. Las columnas verdes vienen calculadas; Por llenar sólo las amarillas (N2, N3, DIAGNOSTICO) y el comentario. Para verificar citas [n], busca la fila en la hoja 'Contextos' con el mismo id y rango n.
A3: N0 corpus | B3: completa = toda la respuesta está en el corpus · parcial = una parte sí y otra no · nula = nada está. Viene del diseño de la pregunta; no se modifica.
A4: N1 recuperación | B4: Sólo modo RAG. SI = al menos un fragmento gold apareció entre los top-k; rango = posición del primero. Calculado automáticamente con los gold_point_ids de la pregunta. | C4: Verificar mas categorias todos, parcial, ninguna
A5: N2 respuesta | B5: 2 = correcta y completa respecto a la referencia · 1 = a medias (omite algo relevante o mezcla algo inventado con lo correcto) · 0 = incorrecta o inventada. Pregunta NULA: 2 = se abstuvo ('el contexto no contiene...') · 0 = inventó una respuesta. Pregunta PARCIAL: 2 = responde la parte disponible Y se abstiene de la otra · 1 = responde bien la parte disponible pero inventa la otra · 0 = inventa o erra la parte disponible.
A6: N3 citas | B6: Sólo modo RAG. 2 = cada afirmación tiene cita [n] y el fragmento n realmente la sostiene · 1 = alguna afirmación sin cita, o alguna cita apunta a un fragmento que no dice eso · 0 = sin citas o citas equivocadas. Si el sistema se abstuvo correctamente, N3 = N/A.
A7: DIAGNOSTICO | B7: El PRIMER eslabón que falló, en este orden: OK = sin error relevante. E0-corpus = la info no estaba en el corpus y el sistema NO se abstuvo (inventó). E1-recuperacion = la info estaba (completa/parcial) pero el fragmento gold no llegó (N1 = NO) y la respuesta sufrió por ello. E2-generacion = el fragmento gold llegó (N1 = SI) y aun así N2 < 2. E3-citas = respuesta correcta (N2 = 2) pero N3 < 2. Modo LLM: sólo puede ser OK, E0-corpus (inventó en nula/parcial) no tiene respuesta y el modelo inventó o E2-generacion sí tiene respuesta y el modelo respondió mal.
A8: Comparación | B8: RAG vs LLM: compara la columna N2 de las dos filas de la misma pregunta. Si RAG > LLM, la recuperación aportó; si RAG < LLM, el contexto perjudicó (ruido) o el modelo se ancló mal.

Sheet Calificacion
A1: id | B1: modo | C1: idioma | D1: N0 corpus (auto) | E1: pregunta | F1: respuesta de referencia | G1: parte NO respondible | H1: RESPUESTA DEL SISTEMA | I1: N1 gold en top-k (auto) | J1: N1 rango (auto) | K1: N1 attack_ids recuperados (auto) | L1: N2 respuesta (0/1/2) | M1: N3 citas (0/1/2) | N1: DIAGNOSTICO | O1: comentario | P1: gold_point_ids esperados (auto) | Q1: point_ids recuperados (auto) | R1: recall@5
A2: p01 | B2: RAG | C2: ES | D2: completa | E2: ¿Qué mitigaciones propone ATT&CK para la sub-técnica T1059.001 PowerShell y en qué consiste cada una? | F2: ATT&CK lista cinco mitigaciones para T1059.001: M1038 Execution Prevention (control de aplicaciones y PowerShell Constrained Language Mode), M1045 Code Signing (política de ejecución sólo de scripts firmados), M1026 Privileged Account Management (restringir la ejecución a administradores; JEA para limitar comandos), M1049 Antivirus/Antimalware (cuarentena automática de archivos sospechosos) y M1042 Disable or Remove Feature or Program (eliminar PowerShell donde no se necesite y deshabilitar/restringir WinRM). | G2: Es totalmente respondible | H2: No se proporciona información en los contextos pasados sobre mitigaciones específicas para la sub-técnica T1059.001 PowerShell. Por lo tanto, no se puede responder a la pregunta con base en los datos ofrecidos. | I2: NO | J2: - | K2: T1059.001, S1193, G0099, T1059, S0393 | L2: 0 | M2: N/A | N2: E1-recuperacion | O2: Informacion completa en el corpus pero el retrieval falló por lo que aún teniendo la información no respondió | P2: 1a6dadb3-8062-5fe2-893a-16bb2f3f9595 124ac693-8c28-5a9f-9362-e91899a4361d | Q2: [1] 0a79d1de-5953-5bf1-91d8-c87bbbf93bc8 [2] 4890209d-7610-5835-817d-6f8eb92c4ff3 [3] a2e64c2d-7e66-5e5a-86df-0543d7957b56 [4] 12155368-afb0-5e72-bdbd-189ee840f96e [5] 3176af7f-1b20-500d-8754-9e2746f08472 | R2: 0
B3: LLM | H3: La sub-técnica **T1059.001** de ATT&CK se refiere a **"Command and Scripting Interpreter"** con el enfoque específico de **PowerShell** (uso de PowerShell para ejecutar comandos y scripts). Aunque ATT&CK no proporciona una lista detallada de "mitigaciones" en el sentido de soluciones técnicas específicas para cada sub-técnica, sí ofrece **recomendaciones de mitigación** basadas en buenas prácticas de seguridad y en el contexto de detección y prevención. A continuación, se presentan las **mitigaciones propuestas o recomendadas** para T1059.001 (PowerShell), junto con una explicación de cada una: --- ### 1. **Restricción de ejecución de PowerShell** - **Qué consiste**: Limitar el uso de PowerShell a entornos de ejecución seguros (por ejemplo, solo en modo "Restricted" o "RemoteSigned") y evitar que se ejecute scripts no firmados. - **Por qué ayuda**: El modo "Restricted" bloquea la ejecución de scripts, lo que impide que un atacante ejecute código malicioso a través de PowerShell. - **Ejemplo**: Configurar el registro de Windows para que PowerShell solo permita comandos interactivos y no scripts. --- ### 2. **Uso de firmas digitales y validación de scripts** - **Qué consiste**: Requerir que los scripts PowerShell estén firmados por un certificado de firma válida antes de que se ejecuten. - **Por qué ayuda**: Los scripts firmados son más fáciles de verificar y reducen el riesgo de ejecutar código malicioso. - **Ejemplo**: Configurar el sistema para que solo se permita la ejecución de scripts firmados (usando el parámetro `-ExecutionPolicy` en PowerShell). --- ### 3. **Monitoreo y auditoría de comandos PowerShell** - **Qué consiste**: Implementar herramientas de detección que monitoren los comandos ejecutados en PowerShell (por ejemplo, registros de eventos del sistema). - **Por qué ayuda**: Permite detectar comportamientos sospechosos, como comandos que no son típicos de uso normal. - **Ejemplo**: Usar herramientas como **Windows Event Logs (Event ID 4688)** o **SIEM** (como Splunk, QRadar) para analizar comandos ejecutados. --- ### 或 4. **Detección de comportamientos anómalos** - **Qué consiste**: Aplicar análisis de comportamiento para detectar actividades inusuales, como la ejecución de comandos en horarios fuera de lo normal o en entornos no autorizados. - **Por qué ayuda**: Aunque el atacante pueda ejecutar PowerShell, su comportamiento puede ser detectado como anómalo. - **Ejemplo**: Detección de comandos como `Invoke-Expression`, `IEX`, o `System.Net.WebClient` que se usan comúnmente en ataques. --- ### 5. **Control de acceso y políticas de grupo (Group Policy)** - **Qué consiste**: Aplicar políticas de grupo que limiten el acceso a PowerShell y a los permisos de ejecución. - **Por qué ayuda**: Reduce el riesgo de que usuarios no autorizados o maliciosos puedan ejecutar PowerShell. - **Ejemplo**: Configurar políticas de grupo para que solo los usuarios autorizados puedan ejecutar PowerShell. --- ### 6. **Uso de alternativas seguras a PowerShell** - **Qué consiste**: En entornos críticos, usar herramientas más seguras como **Windows Command Prompt**, **batch files**, o **PowerShell con ejecución restringida**. - **Por qué ayuda**: Reduce la superficie de ataque al evitar el uso de PowerShell en entornos sensibles. --- ### Nota importante: ATT&CK no proporciona una lista oficial de "mitigaciones" como un documento técnico detallado. Las mencionadas anteriormente son **recomendaciones basadas en buenas prácticas de seguridad** y en el marco de la estrategia de mitigación de la sub-técnica T1059.001. --- ✅ **Resumen**: | Mitigación | Descripción | |----------|-------------| | Restricción de ejecución | Usar modos seguros (ej. Restricted) en PowerShell | | Firmas digitales | Requerir firmas válidas para scripts | | Monitoreo de eventos | Auditar comandos ejecutados en PowerShell | I3: N/A (llm) | J3: N/A | K3: N/A | L3: 1 | M3: N/A | N3: E2-generacion | O3: El LLM dio una mejor respuesta debido a su entranamiento | P3: Modo LLM consulta entrenamiento | Q3: N/A
A4: p02 | B4: RAG | C4: ENG | D4: completa | E4: According to ATT&CK, which tactic does Phishing (T1566) belong to and what are its four sub-techniques? | F4: Phishing belongs to the Initial Access tactic. Its four sub-techniques are T1566.001 Spearphishing Attachment, T1566.002 Spearphishing Link, T1566.003 Spearphishing via Service and T1566.004 Spearphishing Voice. | G4: Es totalmente respondible | H4: According to ATT&CK, Phishing (T1566) belongs to the tactic **Initial Access** [4]. The context does not list four sub-techniques of T1566. It mentions the following sub-techniques: - T1566.004 - Spearphishing Voice [3] - T1566.001 - Social Media Accounts [1] - T1566.002 - Email Accounts [1] - T1566.003 - Cloud Accounts [1] However, only three of these are explicitly listed as sub-techniques of T1566 in the provided context. There is no mention of a fourth sub-technique. Therefore, based on the provided context, Phishing (T1566) belongs to the **Initial Access** tactic, and its sub-techniques are: - T1566.001 Social Media Accounts - T1566.002 Email Accounts - T1566.003 Cloud Accounts - T1566.004 Spearphishing Voice [1][3][4] | I4: SI | J4: 2 | K4: T1586, T1566, T1566.004, TA0001, T1598 | L4: 1 | M4: 1 | N4: E1-recuperacion | P4: af42649d-952f-5dfb-afab-8c8e51a00019 22e1f629-ed75-57fb-9dfd-767e49dde3de | Q4: [1] b2a9cfd5-44fa-5197-8cfd-a36ce303763f [2] af42649d-952f-5dfb-afab-8c8e51a00019 [3] 7d5a91ab-56d5-5ca2-b89b-c33ea61c6f5c [4] ff4c0835-7fe5-59cd-a94d-d82a9c87c07c [5] f4d8f7cf-221f-59d8-8020-429a851befef | R4: 0.5
B5: LLM | H5: Phishing (T1566) belongs to the **Tactic: Initial Access** in the MITRE ATT&CK framework. However, it's important to clarify: **T1566 is not a tactic** — it is a **technique**. The correct categorization is: - **Tactic**: Initial Access - **Technique**: T1566 – Phishing T1566 – Phishing is a technique under the **Initial Access** tactic. Regarding sub-techniques of T1566 (Phishing), MITRE ATT&CK does **not** define four distinct sub-techniques under T1566. Instead, T1566 is a single technique with various **sub-techniques** (or forms) that describe different types of phishing, such as: - T1566.001 – Spear Phishing Email - T1566.002 – Phishing Website - T1566.003 – Phishing SMS (Smishing) - T1566.004 – Phishing via Voice (Vishing) Thus, the four sub-techniques of T1566 are: - T1566.001 – Spear Phishing Email - T1566.002 – Phishing Website - T1566.003 – Phishing SMS (Smishing) - T1566.004 – Phishing via Voice (Vishing) ✅ Final Answer: According to ATT&CK, Phishing (T1566) belongs to the **Initial Access** tactic. Its four sub-techniques are: - T1566.001 – Spear Phishing Email - T1566.002 – Phishing Website - T1566.003 – Phishing SMS (Smishing) - T1566.004 – Phishing via Voice (Vishing) | I5: N/A (llm) | J5: N/A | K5: N/A | L5: 1 | M5: N/A | N5: E2-generacion | P5: Modo LLM consulta entrenamiento | Q5: N/A
A6: p03 | B6: RAG | C6: ES | D6: completa | E6: ¿Qué es la táctica Persistencia (TA0003) en ATT&CK y qué busca conseguir el adversario con ella? | F6: Persistencia es la táctica en la que el adversario intenta mantener su punto de apoyo (foothold). Agrupa técnicas para conservar el acceso a los sistemas a pesar de reinicios, cambios de credenciales u otras interrupciones; incluye cualquier acceso, acción o cambio de configuración que le permita mantener ese acceso, como reemplazar o secuestrar código legítimo o añadir código de arranque. | G6: Es totalmente respondible | H6: La táctica Persistencia (TA0003) en ATT&CK consiste en técnicas que los adversarios utilizan para mantener su acceso a los sistemas a pesar de reinicios, cambios de credenciales o interrupciones que podrían cortar su acceso [1]. Esta táctica busca que el adversario mantenga su presencia en los sistemas tras eventos que podrían eliminar su acceso, como reinicios o cambios de credenciales [1]. | I6: SI | J6: 1 | K6: TA0003, T1070.010, T1668, T1596.003, T1547.007 | L6: 2 | M6: 2 | N6: OK | P6: 259ce106-5bf5-5095-9060-49c5e3501b01 | Q6: [1] 259ce106-5bf5-5095-9060-49c5e3501b01 [2] e10a631d-09ba-51f0-875b-5eb8736daa53 [3] b0eccfc2-c562-56d9-a9c2-b5fb87c09c21 [4] 5eecfeb4-7ff3-5476-a857-a696b2cfa777 [5] d594b40b-00a7-5682-b595-8e660593de1f | R6: 1
B7: LLM | H7: La táctica Persistencia (TA0003) en el marco MITRE ATT&CK se refiere a la capacidad de un atacante para mantener acceso a un sistema o red tras la inicialización de una amenaza. Este objetivo permite que el atacante se mantenga activo en el entorno durante períodos prolongados, incluso después de que se hayan aplicado medidas de seguridad o se hayan detectado actividades inusuales. El adversario busca conseguir que su acceso a la infraestructura sea **persistente**, es decir, que no se pierda al reiniciar el sistema o al aplicar controles de seguridad. Esto permite que el atacante realice actividades de recolección de datos, ejecución de comandos, propagación a otros sistemas o monitoreo continuo sin que se detecte inmediatamente. Algunos ejemplos de técnicas asociadas a esta táctica incluyen: - T1059.001 (Comandos y scripts maliciosos) - T1059.002 (Ejecución de scripts) - T1059.003 (Ejecución de comandos) - T1059.004 (Ejecución de comandos a través de servicios) - T1059.005 (Ejecución de comandos a través de servicios de red) En resumen, la táctica Persistencia (TA0003) busca **mantener un acceso continuo y sin interrupción** al sistema objetivo, lo que facilita la ejecución de ataques más complejos y prolongados. | I7: N/A (llm) | J7: N/A | K7: N/A | L7: 2 | M7: N/A | N7: OK | P7: Modo LLM consulta entrenamiento | Q7: N/A
A8: p04 | B8: RAG | C8: ES | D8: parcial | E8: Según ATT&CK, ¿qué es Cobalt Strike (S0154) y de qué otras herramientas conocidas aprovecha capacidades? ¿Cuánto cuesta su licencia anual? | F8: Cobalt Strike es una herramienta comercial de acceso remoto con todas las funciones, que se presenta como 'software de simulación de adversarios' para ejecutar ataques dirigidos y emular las acciones post-explotación de actores avanzados; sus capacidades interactivas cubren toda la gama de tácticas ATT&CK en un único sistema integrado. Además de sus propias capacidades, aprovecha las de otras herramientas conocidas como Metasploit y Mimikatz (S0002). | G8: El precio de la licencia no está en el corpus (ATT&CK no registra precios; la única aparición de 'price' en el corpus es en el software CoinTicker, sin relación). | H8: Según ATT&CK, Cobalt Strike (S0154) es un software de tipo malware, perteneciente al dominio de ataque empresarial, que se describe como "una herramienta de acceso remoto comercial, completa, diseñada para ejecutar ataques dirigidos y emular las acciones de post-explotación de actores de amenazas avanzadas". [1] Cobalt Strike aprovecha las capacidades de otras herramientas conocidas, como Metasploit y Mimikatz. [1] No se proporciona información en los contextos sobre el costo anual de la licencia de Cobalt Strike. [1][2][3][4][5] Por lo tanto, no se puede determinar cuánto cuesta su licencia anual basándose en los datos proporcionados. | I8: SI | J8: 1 | K8: S0154, T1021.004, G0080, S0637, T1001.003 | L8: 2 | M8: 2 | N8: OK | P8: 71c1c43a-b0b2-569d-8a65-7d55faff7ef8 | Q8: [1] 71c1c43a-b0b2-569d-8a65-7d55faff7ef8 [2] b27606ce-c40b-57f1-92e7-d18ac7673f0e [3] c7c1e3ef-2447-55be-8bab-3de4d5e3fa0b [4] ee34623e-b92f-55b0-bf27-6b757ee1681d [5] a8f8bb82-ac11-5f17-b51c-536281194ec5 | R8: 1
B9: LLM | H9: Cobalt Strike (S0154) es una herramienta de red de seguridad y de ataque que permite a los investigadores y profesionales de ciberseguridad realizar pruebas de penetración y análisis de vulnerabilidades en entornos de red. Según el MITRE ATT&CK, S0154 se clasifica como una herramienta de "iniciación de sesión" (initial access) y se utiliza principalmente para simular ataques de red, como la ejecución remota de comandos en sistemas. Cobalt Strike aprovecha capacidades de otras herramientas conocidas, como: - **Metasploit**: para la ejecución de payloads y la gestión de sesiones. - **PowerShell**: para la ejecución de comandos en sistemas Windows. - **Meterpreter**: un módulo de Metasploit que permite la ejecución remota de comandos y la gestión de sesiones en sistemas operativos. Sin embargo, es importante aclarar que **Cobalt Strike no es una herramienta de ataque comercial que se venda con una licencia anual**. Es una herramienta de investigación y pruebas de penetración que se ofrece como software de uso académico y profesional, y **no tiene un costo oficial de licencia anual** como producto comercializado en el mercado. En su sitio oficial, Cobalt Strike está disponible para uso en entornos de pruebas y educación, y **no se cobra una licencia anual**. Su uso está regulado por las políticas de uso de la herramienta, y se recomienda su uso solo en entornos autorizados y bajo supervisión. 👉 **Respuesta final**: Cobalt Strike (S0150) es una herramienta de pruebas de penetración que simula ataques de red y aprovecha capacidades de herramientas como Metasploit y PowerShell. **No tiene una licencia anual y no se cobra un costo oficial** para su uso en entornos educativos o de investigación. | I9: N/A (llm) | J9: N/A | K9: N/A | L9: 1 | M9: N/A | N9: E2-generacion | P9: Modo LLM consulta entrenamiento | Q9: N/A
A10: p05 | B10: RAG | C10: ES | D10: completa | E10: Según ATT&CK, ¿APT29 (G0016) utiliza Mimikatz? Y en caso afirmativo, ¿qué técnicas relacionadas con tickets Kerberos implementa esa herramienta? | F10: Sí: S0002 Mimikatz aparece en la lista de software usado por APT29 (y G0016 APT29 aparece en la lista 'Used by' de Mimikatz). Entre las técnicas de Mimikatz relacionadas con tickets Kerberos están T1550.003 Pass the Ticket, T1558.001 Golden Ticket y T1558.002 Silver Ticket. | G10: Es totalmente respondible | H10: Sí, según ATT&CK, APT29 (G0016) utiliza Mimikatz. En el contexto se indica que: - G0016 APT29 (grupo) ha utilizado ataques de Kerberos para el movimiento lateral [1]. - S0002 Mimikatz (software) tiene el módulo <code>KERBEROS::PTT</code> que implementa los tres pasos necesarios para extraer la contraseña del cuenta krbtgt y crear o usar tickets de Kerberos [1]. Por lo tanto, Mimikatz implementa la técnica **T1550.003 - Pass the Ticket**, que es una técnica relacionada con tickets de Kerberos. **Respuesta final:** Sí, APT29 (G0016) utiliza Mimikatz, y la técnica relacionada con tickets de Kerberos que implementa esa herramienta es **T1550.003 - Pass the Ticket** [1]. | I10: NO | J10: - | K10: T1550.003, T1550.003, T1558.003, S0079, T1558.001 | L10: 1 | M10: 1 | N10: E1-recuperacion | P10: 06bdc461-ede8-5f49-9b73-19f127c7b746 765c8a68-965f-5232-b1a9-29c9ef4a5769 bd4e8cd4-5326-5459-bc70-8e91db2275a6 | Q10: [1] 750bebf0-a34b-5f77-9ddb-6fe2a3f246ba [2] 7056425c-0a49-5208-8a73-967b7b0834c4 [3] 304f8585-a1e6-5623-9b25-a13b95dab776 [4] daaa4cb7-91e0-5cc0-82b5-3b2bb2ca454a [5] aad4bf53-34e3-513d-a9bc-9661d1985753 | R10: 0
B11: LLM | H11: No, según el marco MITRE ATT&CK, el grupo APT29 (identificado como G0016) no se ha documentado como usuario directo de Mimikatz. Aunque APT29 ha sido asociado con técnicas de acceso a sistemas mediante el uso de tickets Kerberos (como T1547.001 - "Exploitation of Kerberos"), estas acciones se realizan mediante herramientas o métodos específicos de ataque, no necesariamente mediante Mimikatz. Además, Mimikatz es una herramienta de análisis de seguridad que permite la extracción de credenciales almacenadas en memoria (como los tickets Kerberos), y aunque puede ser utilizada por atacantes para obtener acceso a sistemas, su uso no está directamente vinculado a APT29 en fuentes oficiales del MITRE ATT&CK. En cuanto a técnicas relacionadas con tickets Kerberos que podría implementar APT29: - **T1547.001 - Exploitation of Kerberos**: Este es el principal sub-técnico relacionado con el uso de tickets Kerberos para obtener acceso a sistemas. APT29 ha sido asociado con este comportamiento, especialmente en ataques que aprovechan vulnerabilidades en el protocolo Kerberos (por ejemplo, en el uso de tickets de tiempo de vida o en la reutilización de tickets). Por lo tanto: ✅ APT29 (G0016) **no utiliza directamente Mimikatz**. ✅ APT29 **sí implementa técnicas relacionadas con el uso de tickets Kerberos**, principalmente **T1547.001**. **Respuesta final:** No, APT29 (G0016) no utiliza Mimikatz. Sin embargo, sí implementa la técnica T1547.001 - Exploitation of Kerberos. | I11: N/A (llm) | J11: N/A | K11: N/A | L11: 0 | M11: N/A | N11: E2-generacion | P11: Modo LLM consulta entrenamiento | Q11: N/A
A12: p06 | B12: RAG | C12: ES | D12: parcial | E12: ¿Qué sub-técnicas de intérpretes de comandos (T1059.*) usa Lazarus Group (G0032) según ATT&CK, y qué ataques ha realizado este grupo contra Ecuador? | F12: ATT&CK atribuye a Lazarus Group tres sub-técnicas de T1059: T1059.001 PowerShell, T1059.003 Windows Command Shell y T1059.005 Visual Basic. | G12: Ataques contra Ecuador: el documento de G0032 no menciona Ecuador (la única aparición de 'Ecuador' en todo el corpus está en T1480 Execution Guardrails, sin relación con Lazarus). | H12: No se proporciona información en los contextos sobre qué sub-técnicas de intérpretes de comandos (T1059.*) usa el Lazarus Group (G0032) o sobre ataques específicos que haya realizado contra Ecuador. Aunque se menciona que el Lazarus Group utiliza técnicas como T1059.003 Windows Command Shell y T1059.005 Visual Basic en el contexto de software como AuditCred y TYPEFRAME [1][3], no se especifica explícitamente el uso de sub-técnicas de T1059.* en general, ni se menciona cualquier actividad contra Ecuador. Además, no hay ninguna referencia en los contextos a ataques realizados por el Lazarus Group contra Ecuador. Por lo tanto, **no se puede responder con certeza** a la pregunta basándose únicamente en los contextos proporcionados. **Respuesta: No se puede determinar a partir de los contextos proporcionados.** | I12: SI | J12: 5 | K12: S0347, G0099, S0263, G0032, G0032 | L12: 0 | M12: 2 | N12: E2-generacion | P12: d5484bb9-a214-54b4-8984-3d35d6ac7bfe | Q12: [1] 72ef6bf9-f375-5969-8f05-be8b358a87ba [2] 82b5059b-bba0-51c6-a72e-3cf74d782138 [3] 77ea47c9-d1b8-55f4-8c12-d291eda4256b [4] d7ced4c8-3901-5447-a0b3-c2fbf5b3ae9f [5] d5484bb9-a214-54b4-8984-3d35d6ac7bfe | R12: 1
B13: LLM | H13: No se ha documentado oficialmente en el MITRE ATT&CK que el grupo Lazarus (G0032) haya utilizado específicamente sub-técnicas de intérpretes de comandos (T1059.*) como parte de sus actividades conocidas, ni se ha registrado un ataque directo contra Ecuador atribuido a este grupo en fuentes oficiales del MITRE ATT&CK. Además, el MITRE ATT&CK no proporciona una lista detallada de sub-técnicas (como T1059.001, T1059.002, etc.) que el grupo Lazarus haya utilizado en operaciones específicas, ni hay evidencia verificada de que el grupo haya atacado a Ecuador. Por lo tanto, **no se puede afirmar con certeza** que Lazarus haya usado sub-técnicas de intérpretes de comandos (T1059.*) o que haya realizado ataques contra Ecuador según el MITRE ATT&CK. **Respuesta final:** No hay evidencia oficial en el MITRE ATT&CK de que el grupo Lazarus (G0032) haya utilizado sub-técnicas de intérpretes de comandos (T1059.*) o haya realizado ataques contra Ecuador. | I13: N/A (llm) | J13: N/A | K13: N/A | L13: 0 | M13: N/A | N13: E2-generacion | P13: Modo LLM consulta entrenamiento | Q13: N/A
A14: p07 | B14: RAG | C14: ENG | D14: completa | E14: According to ATT&CK, how has APT28 (G0007) carried out password spraying (T1110.003)? | F14: ATT&CK records that during the APT28 Nearest Neighbor Campaign (C0051) APT28 performed password-spray attacks against public-facing services to validate credentials; that APT28 used brute-force/password-spray tooling which, in password-spraying mode, made approximately four authentication attempts per hour per targeted account over several days or weeks; and that APT28 also used a Kubernetes cluster to conduct distributed, large-scale password spray attacks. | G14: Es totalmente respondible | H14: APT28 (G0007) has carried out password spraying (T1110.003) by using a brute-force/password-spray tooling that operated in two modes: in password-spraying mode, it conducted approximately four authentication attempts per hour per targeted account over the course of several days or weeks. Additionally, APT28 has used a Kubernetes cluster to conduct distributed, large-scale password spray attacks. During the APT28 Nearest Neighbor Campaign (C0051), APT28 performed password-spray attacks against public-facing services to validate credentials [1][2]. | I14: SI | J14: 1 | K14: T1110.003, T1110.003, T1110.003, DET0487, C0051 | L14: 2 | M14: 2 | N14: OK | P14: ef7bd43e-42d4-5dd2-bc0e-1abd0cbf802f bda60f05-afc9-5623-a785-ce6ba574ed8e | Q14: [1] bda60f05-afc9-5623-a785-ce6ba574ed8e [2] ef7bd43e-42d4-5dd2-bc0e-1abd0cbf802f [3] 157456b8-c03f-5096-98d8-1d1e43a443e8 [4] f62c8db0-8f71-599b-b664-010c60d7b022 [5] 9f28e3b3-46cd-5d07-ba72-040ae936815b | R14: 1
B15: LLM | H15: As of now, there is no publicly documented or verified evidence in the MITRE ATT&CK framework that APT28 (G0007) has specifically carried out password spraying (T1110.003) in a manner that is explicitly attributed or detailed within the ATT&CK knowledge base. While APT28 is known to use credential harvesting and phishing techniques, and password spraying is a common technique used in credential access (T1110.003), the ATT&CK framework does not provide a specific, confirmed instance of APT28 executing password spraying as a tactic or technique. Therefore, based on available ATT&CK data, **there is no confirmed or documented instance of APT28 (G0007) carrying out password spraying (T1110.003)**. Note: The MITRE ATT&CK framework describes techniques and behaviors observed in cyberattacks, but it does not assign specific attribution to individual threat actors in all cases—especially for less publicly documented or unverified activities. Attribution remains a complex and often uncertain process. Answer: There is no confirmed or documented instance in the MITRE ATT&CK framework of APT28 (G0007) carrying out password spraying (T1110.003). | I15: N/A (llm) | J15: N/A | K15: N/A | L15: 0 | M15: N/A | N15: E2-generacion | P15: Modo LLM consulta entrenamiento | Q15: N/A
A16: p08 | B16: RAG | C16: ES | D16: parcial | E16: ¿Qué mitigaciones recomienda ATT&CK contra Password Spraying (T1110.003) y qué porcentaje de las intrusiones registradas en 2025 comenzó con esta técnica? | F16: ATT&CK recomienda tres mitigaciones: M1027 Password Policies (seguir las guías NIST al definir políticas de contraseñas), M1032 Multi-factor Authentication (usar MFA, también en servicios expuestos a Internet) y M1036 Account Use Policies (bloqueo de cuenta tras cierto número de intentos fallidos, con cuidado de no provocar denegación de servicio; políticas de acceso condicional para bloquear logins desde dispositivos no conformes o fuera de rangos IP de la organización; bloquear autenticaciones desde servicios de anonimización/proxies). | G16: El porcentaje de intrusiones de 2025 no existe en el corpus: ATT&CK no contiene estadísticas de incidencia. | H16: No se proporciona información en los contextos sobre mitigaciones contra Password Spraying (T1110.003) ni sobre el porcentaje de intrusiones registradas en 2025 que comenzaron con esta técnica. Por lo tanto, no se puede responder a la pregunta con base en los datos ofrecidos. [1][2][3][4][5] — ninguno de estos pasajes menciona mitigaciones específicas para T1110.003 ni proporciona datos sobre intrusiones en 2025. | I16: NO | J16: - | K16: T1110.003, DET0487, T1110.003, G0114, T1110.002 | L16: 0 | M16: N/A | N16: E1-recuperacion | P16: 9ba81dbd-2475-5872-aac0-2ad4b53a7ba3 | Q16: [1] 157456b8-c03f-5096-98d8-1d1e43a443e8 [2] f62c8db0-8f71-599b-b664-010c60d7b022 [3] bc411276-2b2d-57fd-b20f-7feb6b7f2b0b [4] 8e3c7f9a-1c02-5e07-a4ae-509c8f1580e1 [5] 0204f726-7c2b-510e-a2cf-0d16f6c05c61 | R16: 0
B17: LLM | H17: No se proporciona información oficial en el MITRE ATT&CK sobre mitigaciones específicas para la técnica de Password Spraying (T1110.003), ni se tiene datos disponibles sobre el porcentaje de intrusiones registradas en 2025 que comenzaron con esta técnica. El MITRE ATT&CK no publica estadísticas anuales sobre el número o porcentaje de intrusiones que comenzaron con una técnica específica en un año futuro como 2025, ya que es un conjunto de conocimiento de amenazas y no un repositorio de datos de incidentes históricos o proyectados. Por lo tanto, **no se puede afirmar un porcentaje de intrusiones en 2025 que comenzaron con Password Spraying**, y **no se recomiendan mitigaciones específicas en el MITRE ATT&CK para esta técnica** en el contexto de datos de 2025. Las mitigaciones recomendadas para Password Spraying (T1110.003) en general, basadas en buenas prácticas de seguridad, incluyen: - Uso de políticas de contraseñas fuertes y complejas. - Implementación de autenticación multifactor (MFA). - Configuración de alertas para intentos de acceso múltiples con credenciales. - Uso de herramientas de detección de comportamiento anómalo. - Educación del personal sobre riesgos de ataques de "spraying". Sin embargo, estas no son mitigaciones directamente especificadas por el MITRE ATT&CK para T1110.003. ✅ Respuesta final: **No se proporcionan mitigaciones específicas en el MITRE ATT&CK para Password Spraying (T1110.003), y no se tiene datos sobre el porcentaje de intrusiones registradas en 2025 que comenzaron con esta técnica.** | I17: N/A (llm) | J17: N/A | K17: N/A | L17: 0 | M17: N/A | N17: E2-generacion | P17: Modo LLM consulta entrenamiento | Q17: N/A
A18: p09 | B18: RAG | C18: ENG | D18: parcial | E18: Which mitigations does ATT&CK list for Phishing (T1566), and which commercial email security product does MITRE recommend to implement them? | F18: ATT&CK lists six mitigations for Phishing: M1031 Network Intrusion Prevention (systems that scan and remove malicious attachments or links), M1021 Restrict Web-Based Content (block risky attachment types such as .scr, .exe, .pif, .cpl), M1017 User Training (train users to recognise social engineering and phishing), M1049 Antivirus/Antimalware (automatic quarantine of suspicious files), M1054 Software Configuration (anti-spoofing and email authentication: SPF, DKIM, DMARC) and M1047 Audit (audits/scans of systems, permissions and configurations). | G18: MITRE ATT&CK does not recommend commercial vendors or products; no such recommendation exists in the corpus. | H18: The provided context passages do not list any mitigations for Phishing (T1566) nor do they specify any commercial email security product that MITRE recommends to implement them. While the passages mention email authentication mechanisms such as SPF, DKIM, and DMARC as part of filtering and validation, they do not explicitly state these as mitigations for T1566 or identify a specific commercial product to implement them [5]. Therefore, based on the given context, no mitigations or recommended commercial products are specified. Answer: None of the mitigations or commercial email security products are listed in the provided context. | I18: SI | J18: 5 | K18: T1586.002, T1566, T1566, T1585.002, T1566 | L18: 0 | M18: 2 | N18: E1-recuperacion | P18: 60567a05-573f-5585-bac9-fb6962c3a42f 22e1f629-ed75-57fb-9dfd-767e49dde3de | Q18: [1] 302a1537-027f-57a0-81b9-9063712870ce [2] af42649d-952f-5dfb-afab-8c8e51a00019 [3] 6a49f47f-97c7-51c1-9b8c-11a512eb628c [4] e3dc1b98-151d-514e-a176-c74fb584fe19 [5] 22e1f629-ed75-57fb-9dfd-767e49dde3de | R18: 0.5
B19: LLM | H19: MITRE ATT&CK does not list specific mitigations for Phishing (T1566) in the traditional sense of "mitigations" like firewall rules or endpoint protections. Instead, ATT&CK provides a structured framework of tactics, techniques, and sub-techniques that adversaries use—such as phishing (T1566)—and recommends detection and prevention strategies based on real-world threat intelligence. For Phishing (T1566), ATT&CK recommends the following **detection and mitigation approaches**: - **Email content filtering** to detect suspicious or malicious content. - **Domain-based message authentication, reporting, and conformance (DMARC)** to prevent spoofed emails. - **Sender Policy Framework (SPF)** and **DomainKeys Identified Mail (DKIM)** to verify sender authenticity. - **User education and awareness programs** to reduce human susceptibility to phishing. - **Real-time threat intelligence integration** to identify known phishing domains or URLs. - **Behavioral analysis** to detect anomalies in email patterns (e.g., unusual senders, attachments, or links). These are not "mitigations" in the sense of a product feature, but rather **security controls and practices** that help prevent or detect phishing attacks. Regarding commercial email security products, MITRE does **not** recommend a specific commercial product** for implementing these mitigations. However, MITRE often references or aligns with industry-leading email security solutions that support these controls. For example: - **Microsoft 365 Defender** (formerly Microsoft Defender for Office 365) is frequently cited in ATT&CK for its capabilities in detecting and blocking phishing emails using DMARC, SPF, DKIM, and AI-driven content analysis. - **Proofpoint**, **Palo Alto Networks Prisma Cloud**, and **Symantec Email Security** are also known to support many of these ATT&CK-aligned controls. ✅ Therefore, while MITRE does not explicitly recommend a single commercial product for phishing mitigation, **Microsoft 365 Defender** is widely recognized and referenced in the ATT&CK framework as a product that effectively implements many of the recommended mitigations for T1566 (Phishing). **Final Answer:** MITRE ATT&CK does not list specific "mitigations" for Phishing (T1566) as a standalone category, but recommends controls such as DMARC/SPF/DKIM, user awareness, and real-time threat intelligence. MITRE does not recommend a single commercial product; however, **Microsoft 365 Defender** is a widely recognized email security solution that supports these ATT&CK-aligned mitigations. | I19: N/A (llm) | J19: N/A | K19: N/A | L19: 0 | M19: N/A | N19: E2-generacion | P19: Modo LLM consulta entrenamiento | Q19: N/A
A20: p10 | B20: RAG | C20: ES | D20: nula | E20: ¿Qué es la técnica T1417 Input Capture de ATT&CK Mobile y qué mitigaciones propone ATT&CK para ella? | F20: No respondible con el corpus: sólo está ingestado el dominio enterprise-attack; T1417 pertenece a mobile-attack y no existe ningún chunk con ese ID. La respuesta correcta es abstenerse indicando que el contexto no contiene esa información. | G20: Toda la pregunta. | H20: No se proporciona información sobre la técnica T1417 Input Capture en el contexto dado. Además, no hay menciones a ninguna técnica denominada "T1417 Input Capture" ni a mitigaciones específicas para ella en los pasajes proporcionados. Los pasajes mencionan exclusivamente la técnica T1056 - Input Capture y sus sub-técnicas (como T1056.001 y T1056.003), así como estrategias de detección (DET0102), pero no T1417 ni ninguna mitigación relacionada con ella. Por lo tanto, no se puede responder a la pregunta con base en el contexto proporcionado. Respuesta: No se proporciona información sobre la técnica T1417 Input Capture ni sobre mitigaciones para ella en el contexto dado. | I20: N/A (nula) | J20: N/A | K20: T1056, T1056.003, T1056.001, DET0102, T1056.001 | L20: 2 | M20: N/A | N20: OK | P20: - | Q20: [1] 49082e7a-665e-52fc-913f-e16e250c69fc [2] 53bb75a3-204c-582f-aebf-0aa453578979 [3] 9552e904-33ef-5bad-a469-7fa1bf0d2107 [4] b125294d-a3b8-5227-a30b-108b917e557a [5] 1e3aef33-c042-58ea-a36d-b1176cfd929c
B21: LLM | H21: La técnica **T1417** en el marco de **MITRE ATT&CK** no corresponde a "Input Capture" en el contexto móvil. De hecho, **T1417** está relacionada con **"Input Capture" en dispositivos móviles**, pero es importante aclarar que **T1417** es una técnica de **ciberataque en dispositivos móviles**, y su descripción oficial es: > **T1417: Input Capture** – *An attacker can capture input from a mobile device (e.g., keyboard, microphone, camera) to gather sensitive data such as passwords, messages, or voice recordings.* Esta técnica implica que un atacante puede utilizar una aplicación maliciosa o un exploit para capturar entradas del usuario (como contraseñas, mensajes, llamadas o grabaciones) en un dispositivo móvil, lo cual puede ser usado para obtener información sensible. ### Mitigaciones propuestas por ATT&CK para T1417: El marco de ATT&CK **no proporciona una lista detallada de mitigaciones específicas para T1417** como se hace con otras técnicas. En cambio, **los controles de seguridad y buenas prácticas** recomendados para prevenir esta técnica incluyen: - **Revisar y restringir las permisos de aplicaciones** (por ejemplo, evitar que las apps accedan a micrófonos, cámaras o teclado). - **Habilitar y usar funciones de seguridad del sistema** (como el modo de privacidad o protección de entradas). - **Usar aplicaciones oficiales y verificadas** para evitar maliciosas que puedan capturar entradas. - **Educación del usuario** sobre el riesgo de compartir información sensible en aplicaciones no confiables. - **Monitoreo de actividad de entrada** (como teclado o micrófono) para detectar comportamientos anómalos. > ⚠️ Importante: T1417 está clasificada como **técnicas de ataque en dispositivos móviles**, y aunque está en el marco de ATT&CK, **no tiene una sección específica de "mitigaciones" detalladas** como otras técnicas. Las recomendaciones provienen de buenas prácticas de seguridad móvil. --- ✅ **Resumen:** - **T1417 (Input Capture)**: Permite a un atacante capturar entradas del usuario (contraseñas, mensajes, grabaciones) en dispositivos móviles. - **Mitigaciones**: Control de permisos, uso de apps oficiales, educación del usuario, monitoreo de actividad anómala. > Nota: ATT&CK no proporciona una lista oficial de mitigaciones para T1417. Las recomendaciones son derivadas de buenas prácticas de ciberseguridad móvil. | I21: N/A (nula) | J21: N/A | K21: N/A | L21: 0 | M21: N/A | N21: E0-corpus | P21: Modo LLM consulta entrenamiento | Q21: N/A
A22: p11 | B22: RAG | C22: ENG | D22: nula | E22: Which ICS tactic does T0855 Unauthorized Command Message belong to and which assets does it target? | F22: Not answerable from the corpus: T0855 belongs to the ics-attack domain, which is not ingested; no chunk carries that ID. The correct behaviour is to state that the context does not contain the information. | G22: Toda la pregunta. | H22: The context provided does not contain information about T0855 Unauthorized Command Message or any ICS (Industrial Control Systems) tactic. Therefore, it is not possible to determine which ICS tactic T0855 belongs to or which assets it targets based on the given passages. [No relevant context found.] | I22: N/A (nula) | J22: N/A | K22: TA0002, T1683, T1040, T1552.008, TA0011 | L22: 2 | M22: N/A | N22: OK | P22: - | Q22: [1] 57665f89-6f5d-57ec-8cfb-d409cf0b4a97 [2] dc4c60b8-5e00-5802-a63c-64dc3695a236 [3] b616fa4b-7322-5a04-a57b-56babba5fb56 [4] 94ece3fd-e305-5ee5-991d-3a563d13b80a [5] a0d301c9-8f03-56e0-b461-3ea0fd74d96e
B23: LLM | H23: The technique T0855 (Unauthorized Command Message) is not a valid or recognized entry in the MITRE ATT&CK framework. There is no official technique with the ID "T0855" in the current MITRE ATT&CK database for cyberattack tactics and techniques, including those related to Industrial Control Systems (ICS). Additionally, the MITRE ATT&CK framework does not have a technique labeled "T0855" — the "T" prefix is used for techniques, but the numbering (e.g., T1059 for command and script injection) follows a specific structure and does not include T0855. Therefore, T0855 is not a valid or documented technique in the MITRE ATT&CK framework, and thus it does not belong to any ICS tactic, nor does it target any specific assets. If you meant a different technique or are referring to a non-standard or outdated identifier, please clarify. Answer: T0855 is not a valid technique in the MITRE ATT&CK framework and does not exist in any ICS tactic or asset targeting. | I23: N/A (nula) | J23: N/A | K23: N/A | L23: 0 | M23: N/A | N23: E0-corpus | P23: Modo LLM consulta entrenamiento | Q23: N/A
A24: p12 | B24: RAG | C24: ES | D24: nula | E24: ¿Cuál fue la técnica ATT&CK más utilizada por los atacantes a nivel mundial durante 2026? | F24: No respondible: ATT&CK describe técnicas, grupos y procedimientos, pero no contiene estadísticas de frecuencia de uso por año. La respuesta correcta es abstenerse. | G24: Toda la pregunta. | H24: No se proporciona información en los contextos sobre cuál fue la técnica ATT&CK más utilizada por los atacantes a nivel mundial durante 2026. Aunque se mencionan varias herramientas y tácticas (como T1608.004, S9041, S9042, S9044), no hay datos que indiquen cuál fue la técnica más utilizada a nivel mundial en ese año. Por lo tanto, no se puede determinar la respuesta basándose únicamente en el contenido dado. Respuesta: No se puede determinar con la información proporcionada. | I24: N/A (nula) | J24: N/A | K24: C0026, S9044, S9042, T1608.004, S9041 | L24: 2 | M24: N/A | N24: OK | P24: - | Q24: [1] 9888dea1-f3ec-5e03-b541-8e05afd7c088 [2] 5ee65033-bb02-5e33-a22a-e68d67f875c3 [3] 605edb9c-54db-520d-a3ae-5bb981c67366 [4] b431edc2-e2fb-5bff-8750-f61ceb269ea8 [5] 896b042c-adbc-5362-a6f3-8ed624e1d88b
B25: LLM | H25: No se dispone de datos oficiales o públicos que indiquen cuál fue la técnica ATT&CK más utilizada por los atacantes a nivel mundial durante 2026, ya que ese año aún no ha ocurrido y no se han publicado estadísticas oficiales sobre el uso de técnicas de ataque en el marco del MITRE ATT&CK para ese período. Además, el MITRE ATT&CK no proporciona un ranking anual de técnicas más utilizadas por atacantes en un año futuro. Los datos sobre el uso de técnicas de ataque se basan en análisis de incidentes reales, reportes de amenazas y estudios de seguridad que se publican en años pasados. Por lo tanto, no es posible responder con precisión a la pregunta sobre la técnica más utilizada en 2026. Si te interesa, puedo proporcionar información sobre las técnicas más comunes en años pasados (por ejemplo, 2023 o 2024) o sobre las más frecuentes en el marco del MITRE ATT&CK actual. | I25: N/A (nula) | J25: N/A | K25: N/A | L25: 2 | M25: N/A | N25: OK | P25: Modo LLM consulta entrenamiento | Q25: N/A
A26: p13 | B26: RAG | C26: ES | D26: nula | E26: ¿Qué describe la sub-técnica T1059.099 de ATT&CK y a qué táctica pertenece? | F26: No respondible: T1059.099 no existe en ATT&CK ni en el corpus. La respuesta correcta es indicar que no hay información sobre ese identificador (sin inventar una sub-técnica de T1059). | G26: Toda la pregunta. | H26: No se proporciona información sobre la sub-técnica T1059.099 en los contextos dados. Por lo tanto, no se puede describir ni identificar a qué táctica pertenece. [N/A] | I26: N/A (nula) | J26: N/A | K26: M1031, T1555.006, T1059.010, DC0095, T1059.009 | L26: 2 | M26: N/A | N26: OK | P26: - | Q26: [1] ee4e36d8-7c86-5b85-8aeb-140dce27f98e [2] 70553fe9-95e9-503b-b5be-5d50bb3b406e [3] 952ba9e9-02f1-5a73-9728-d18d3b697266 [4] f7d9b154-5446-578c-b6ef-6f5413298f0e [5] 60d08f9a-0633-524e-8298-fe7bc19f2408
B27: LLM | H27: La sub-técnica T1059.099 de ATT&CK describe **"Command and Scripting Interpreter: PowerShell"**, específicamente el uso de **PowerShell para ejecutar comandos y scripts**. Pertenece a la **táctica T1059: Command and Scripting Interpreter**, que incluye el uso de interpretadores de comandos y scripts para ejecutar código en sistemas operativos, como PowerShell, Bash, o otros lenguajes de scripting. **Respuesta final:** La sub-técnica T1059.099 describe el uso de PowerShell como interpretador de comandos y scripts, y pertenece a la táctica T1059: Command and Scripting Interpreter. | I27: N/A (nula) | J27: N/A | K27: N/A | L27: 0 | M27: N/A | N27: E0-corpus | P27: Modo LLM consulta entrenamiento | Q27: N/A

Sheet Resumen
A1: Métrica | B1: RAG | C1: LLM
A2: Respuestas calificadas (N2 no vacío) | B2: =COUNTIFS(Calificacion!B2:B27,"RAG",Calificacion!L2:L27,"<>") -> 13 | C2: =COUNTIFS(Calificacion!B2:B27,"LLM",Calificacion!L2:L27,"<>") -> 13
A3: Promedio N2 respuesta (0-2) | B3: =IFERROR(AVERAGEIFS(Calificacion!L2:L27,Calificacion!B2:B27,"RAG"),"") -> 1.2307692 | C3: =IFERROR(AVERAGEIFS(Calificacion!L2:L27,Calificacion!B2:B27,"LLM"),"") -> 0.53846154 | E3: que tan correctas son las respuestas 2 = correcta y completa (o se abstuvo cuando debía); 1 = a medias; 0 = incorrecta o inventada. el máximo es 2
A4: Promedio N3 citas (0-2) | B4: =IFERROR(AVERAGEIFS(Calificacion!M2:M27,Calificacion!B2:B27,"RAG"),"") -> 1.7142857 | C4: N/A | E4: Mide si las citas [n] sostienen lo que el sistema afirma.
A5: N1 hit@k (gold en top-k, preguntas completas/parciales) | B5: =COUNTIFS(Calificacion!B2:B27,"RAG",Calificacion!I2:I27,"SI")&" / "&COUNTIFS(Calificacion!B2:B27,"RAG",Calificacion!D2:D27,"<>nula") -> 6 / 9 | C5: N/A
A7: Diagnóstico | B7: RAG | C7: LLM
A8: OK | B8: =COUNTIFS(Calificacion!B2:B27,"RAG",Calificacion!N2:N27,"OK") -> 7 | C8: =COUNTIFS(Calificacion!B2:B27,"LLM",Calificacion!N2:N27,"OK") -> 2 | E8: Sin error
A9: E0-corpus | B9: =COUNTIFS(Calificacion!B2:B27,"RAG",Calificacion!N2:N27,"E0-corpus") -> 0 | C9: =COUNTIFS(Calificacion!B2:B27,"LLM",Calificacion!N2:N27,"E0-corpus") -> 3 | E9: Inventó cuando no había respuesta
A10: E1-recuperacion | B10: =COUNTIFS(Calificacion!B2:B27,"RAG",Calificacion!N2:N27,"E1-recuperacion") -> 5 | C10: =COUNTIFS(Calificacion!B2:B27,"LLM",Calificacion!N2:N27,"E1-recuperacion") -> 0 | E10: La búsqueda no trajo el fragmento correcto
A11: E2-generacion | B11: =COUNTIFS(Calificacion!B2:B27,"RAG",Calificacion!N2:N27,"E2-generacion") -> 1 | C11: =COUNTIFS(Calificacion!B2:B27,"LLM",Calificacion!N2:N27,"E2-generacion") -> 8 | E11: El modelo respondió mal
A12: E3-citas | B12: =COUNTIFS(Calificacion!B2:B27,"RAG",Calificacion!N2:N27,"E3-citas") -> 0 | C12: =COUNTIFS(Calificacion!B2:B27,"LLM",Calificacion!N2:N27,"E3-citas") -> 0 | E12: Respondió bien, pero con citas incorrectas

Sheet Config
A1: CORPUS (data/manifest.json)
A2: created_at | B2: 2026-09-12T16:14:31.631478+00:00
A3: collection | B3: mitre_attack
A4: embed_model | B4: granite-embedding:30m
A5: embed_dim | B5: 384
A6: doc_prefix
A7: query_prefix
A8: chunk_size | B8: 1200
A9: chunk_overlap | B9: 150
A10: domains | B10: ["enterprise-attack"]
A11: attack_versions | B11: {"enterprise-attack": "19.2"}
A12: n_documents | B12: 2616
A13: n_chunks | B13: 7241
A14: points_count | B14: 7241
A15: elapsed_s | B15: 1779.6
A17: TRAZABILIDAD | B17: questions.jsonl (diseño y gold) -> config.json (corrida) -> traces.jsonl (registro primario: contextos, prompt, tokens, tiempos) -> calificacion.xlsx (esta vista + notas manuales). point_id enlaza con data/chunks.jsonl; doc_id/url con documents.jsonl y attack.mitre.org.

Sheet LLM_ToggleThink
A1: Modelo | B1: Toggle | C1: Detalle
A2: qwen3:4b-instruct | B2: Off | C2: Respuesta directa
A3: qwen3:4b-instruct | B3: On | C3: Idéntico. No-op silencioso
A4: qwen3:4b | B4: On | C4: Razonamiento limpio y separado en el campo thinking
A5: qwen3:4b | B5: Off | C5: Roto. El razonamiento se filtra dentro de content

Sheet Prompts
A1: id | B1: modo | C1: modelo | D1: tokens prompt | E1: tokens respuesta | F1: tokens_total | G1: retrieval ms | H1: generacion ms | I1: total ms | J1: prompt [system] | K1: prompt [user] (con los fragmentos [n])
A2: p01 | B2: RAG | C2: qwen3:4b-instruct | D2: 1854 | E2: 54 | F2: =D2+E2 -> 1908 | G2: 662.5 | H2: 101607.8 | I2: 102270.3 | J2: You are a cybersecurity assistant specialized in the MITRE ATT&CK framework (tactics, techniques, sub-techniques, groups, software, mitigations, detections). Answer the user's question using ONLY the information contained in the provided context passages. Cite the passages you rely on with their bracketed number, e.g. [1] or [2][4]. If the context does not contain enough information to answer, say so explicitly and do not invent facts. Be precise: include ATT&CK IDs (e.g. T1059.001, G0016, M1038) when they appear in the context. Answer in the same language as the question. | K2: Context passages: [1] Source: T1059.001 - PowerShell # T1059.001 - PowerShell Type: sub-technique | Domain: enterprise-attack | ATT&CK version: 19.2 Tactics: execution Platforms: Windows Sub-technique of: T1059 Command and Scripting Interpreter ## Description Adversaries may abuse PowerShell commands and scripts for execution. PowerShell is a powerful interactive command-line interface and scripting environment included in the Windows operating system. Adversaries can use PowerShell to perform a number of actions, including discovery of information and execution of code. Examples include the <code>Start-Process</code> cmdlet which can be used to run an executable and the <code>Invoke-Command</code> cmdlet which runs a command locally or on a remote computer (though administrator permissions are required to use PowerShell to connect to remote systems). PowerShell may also be used to download and run executables from the Internet, which can be executed from disk or in memory without touching disk. [2] Source: S1193 - TAMECAT # S1193 - TAMECAT Type: software | Domain: enterprise-attack | ATT&CK version: 19.2 Software type: malware | Aliases: TAMECAT | Platforms: Windows ## Description [TAMECAT](https://attack.mitre.org/software/S1193) is a malware that is used by [APT42](https://attack.mitre.org/groups/G1044) to execute PowerShell or C# content. ## Techniques used - T1047 Windows Management Instrumentation - T1059.001 PowerShell - T1059.003 Windows Command Shell - T1059.005 Visual Basic - T1071.001 Web Protocols - T1105 Ingress Tool Transfer - T1132.001 Standard Encoding - T1518.001 Security Software Discovery - T1573.001 Symmetric Cryptography ## Used by - G1044 APT42 [3] Source: G0099 - APT-C-36 # G0099 - APT-C-36 institutions and entities in the financial, energy, and professional manufacturing sectors across Colombia and other Latin American countries. ## Techniques used - T1027 Obfuscated Files or Information - T1027.003 Steganography - T1027.013 Encrypted/Encoded File - T1027.016 Junk Code Insertion - T1036.004 Masquerade Task or Service - T1036.005 Match Legitimate Resource Name or Location - T1047 Windows Management Instrumentation - T1053.005 Scheduled Task - T1055.012 Process Hollowing - T1059.001 PowerShell - T1059.005 Visual Basic - T1059.007 JavaScript - T1105 Ingress Tool Transfer - T1133 External Remote Services - T1204.001 Malicious Link - T1204.002 Malicious File - T1480 Execution Guardrails - T1534 Internal Spearphishing - T1564.003 Hidden Window - T1566.001 Spearphishing Attachment - T1566.002 Spearphishing Link - T1568 Dynamic Resolution - T1571 Non-Standard Port - T1574.001 DLL - T1583.001 Domains - T1583.003 Virtual Private Server - T1583.006 Web Services - T1584.005 Botnet - T1586.002 Email Accounts - T1586.003 Cloud Accounts - T1587.001 Malware - T1588.001 Malware - T1588.002 Tool - T1593 Search Open Websites/Domains - T1608.001 Upload Malware - T1683.001 Written Content - T1683.002 Audio-Visual Content - T1684.001 Impersonation [4] Source: T1059 - Command and Scripting Interpreter # T1059 - Command and Scripting Interpreter interpreter installations. - M1042 Disable or Remove Feature or Program: Disable or remove any unnecessary or unused shells or interpreters. ## Sub-techniques - T1059.007 JavaScript - T1059.002 AppleScript - T1059.010 AutoHotKey & AutoIT - T1059.009 Cloud API - T1059.008 Network Device CLI - T1059.001 PowerShell - T1059.004 Unix Shell - T1059.011 Lua - T1059.013 Container CLI/API - T1059.005 Visual Basic - T1059.003 Windows Command Shell - T1059.012 Hypervisor CLI - T1059.006 Python ## Procedure examples - C0005 Operation Spalax (campaign): For [Operation Spalax](https://attack.mitre.org/campaigns/C0005), the threat actors used Nullsoft Scriptable Install System (NSIS) scripts to install malware. - C0029 Cutting Edge (campaign): During [Cutting Edge](https://attack.mitre.org/campaigns/C0029), threat actors used Perl scripts to enable the deployment of the THINSPOOL shell script dropper and for enumerating host data. - C0046 ArcaneDoor (campaign): [ArcaneDoor](https://attack.mitre.org/campaigns/C0046) included the adversary executing command line interface (CLI) commands. [5] Source: S0393 - PowerStallion # S0393 - PowerStallion Type: software | Domain: enterprise-attack | ATT&CK version: 19.2 Software type: malware | Aliases: PowerStallion | Platforms: Windows ## Description [PowerStallion](https://attack.mitre.org/software/S0393) is a lightweight [PowerShell](https://attack.mitre.org/techniques/T1059/001) backdoor used by [Turla](https://attack.mitre.org/groups/G0010), possibly as a recovery access tool to install other backdoors. ## Techniques used - T1027 Obfuscated Files or Information - T1057 Process Discovery - T1059.001 PowerShell - T1070.006 Timestomp - T1102.002 Bidirectional Communication ## Used by - G0010 Turla Question: ¿Qué mitigaciones propone ATT&CK para la sub-técnica T1059.001 PowerShell y en qué consiste cada una? Answer:
A3: p01 | B3: LLM | C3: qwen3:4b-instruct | D3: 162 | E3: 1024 | F3: =D3+E3 -> 1186 | G3: 0 | H3: 144912.4 | I3: 144912.4 | J3: You are a cybersecurity assistant specialized in the MITRE ATT&CK framework (tactics, techniques, sub-techniques, groups, software, mitigations, detections). Answer the user's question accurately and concisely using your own knowledge. Include ATT&CK IDs (e.g. T1059.001, G0016, M1038) when you are confident about them. If you are not sure about something, say so explicitly instead of guessing. Answer in the same language as the question. | K3: Question: ¿Qué mitigaciones propone ATT&CK para la sub-técnica T1059.001 PowerShell y en qué consiste cada una? Answer:
A4: p02 | B4: RAG | C4: qwen3:4b-instruct | D4: 1294 | E4: 253 | F4: =D4+E4 -> 1547 | G4: 52.4 | H4: 91625.4 | I4: 91677.8 | J4: You are a cybersecurity assistant specialized in the MITRE ATT&CK framework (tactics, techniques, sub-techniques, groups, software, mitigations, detections). Answer the user's question using ONLY the information contained in the provided context passages. Cite the passages you rely on with their bracketed number, e.g. [1] or [2][4]. If the context does not contain enough information to answer, say so explicitly and do not invent facts. Be precise: include ATT&CK IDs (e.g. T1059.001, G0016, M1038) when they appear in the context. Answer in the same language as the question. | K4: Context passages: [1] Source: T1586 - Compromise Accounts # T1586 - Compromise Accounts organization. Much of this activity will take place outside the visibility of the target organization, making detection of this behavior difficult. Detection efforts may be focused on related stages of the adversary lifecycle, such as during Initial Access (ex: [Phishing](https://attack.mitre.org/techniques/T1566)). Monitor and analyze traffic patterns and packet inspection associated to protocol(s) that do not follow the expected protocol standards and traffic flows (e.g extraneous packets that do not belong to established flows, gratuitous or anomalous traffic patterns, anomalous syntax, or structure). Consider correlation with process monitoring and command line to detect anomalous processes execution and command line arguments associated to traffic patterns (e.g. monitor anomalies in use of files that do not normally initiate connections for respective protocol(s)). ## Mitigations - M1056 Pre-compromise: This technique cannot be easily mitigated with preventive controls since it is based on behaviors performed outside of the scope of enterprise defenses and controls. ## Sub-techniques - T1586.001 Social Media Accounts - T1586.003 Cloud Accounts - T1586.002 Email Accounts [2] Source: T1566 - Phishing # T1566 - Phishing Type: technique | Domain: enterprise-attack | ATT&CK version: 19.2 Tactics: initial-access Platforms: Identity Provider, Linux, macOS, Office Suite, SaaS, Windows ## Description Adversaries may send phishing messages to gain access to victim systems. All forms of phishing are electronically delivered social engineering. Phishing can be targeted, known as spearphishing. In spearphishing, a specific individual, company, or industry will be targeted by the adversary. More generally, adversaries can conduct non-targeted phishing, such as in mass malware spam campaigns. [3] Source: T1566.004 - Spearphishing Voice # T1566.004 - Spearphishing Voice Type: sub-technique | Domain: enterprise-attack | ATT&CK version: 19.2 Tactics: initial-access Platforms: Linux, macOS, Windows, Identity Provider Sub-technique of: T1566 Phishing ## Description Adversaries may use voice communications to ultimately gain access to victim systems. Spearphishing voice is a specific variant of spearphishing. It is different from other forms of spearphishing in that it employs the use of manipulating a user into providing access to systems through a phone call or other forms of voice communications. Spearphishing frequently involves social engineering techniques, such as posing as a trusted source (ex: [Impersonation](https://attack.mitre.org/techniques/T1684/001)) and/or creating a sense of urgency or alarm for the recipient. [4] Source: TA0001 - Initial Access # TA0001 - Initial Access Type: tactic | Domain: enterprise-attack | ATT&CK version: 19.2 Shortname: initial-access ## Description The adversary is trying to get into your network. Initial Access consists of techniques that use various entry vectors to gain their initial foothold within a network. Techniques used to gain a foothold include targeted spearphishing and exploiting weaknesses on public-facing web servers. Footholds gained through initial access may allow for continued access, like valid accounts and use of external remote services, or may be limited-use due to changing passwords. ## Techniques in this tactic - T1078 Valid Accounts - T1091 Replication Through Removable Media - T1133 External Remote Services - T1189 Drive-by Compromise - T1190 Exploit Public-Facing Application - T1195 Supply Chain Compromise - T1199 Trusted Relationship - T1200 Hardware Additions - T1566 Phishing - T1659 Content Injection - T1669 Wi-Fi Networks [5] Source: T1598 - Phishing for Information # T1598 - Phishing for Information Type: technique | Domain: enterprise-attack | ATT&CK version: 19.2 Tactics: reconnaissance Platforms: PRE ## Description Adversaries may send phishing messages to elicit sensitive information that can be used during targeting. Phishing for information is an attempt to trick targets into divulging information, frequently credentials or other actionable information. Phishing for information is different from [Phishing](https://attack.mitre.org/techniques/T1566) in that the objective is gathering data from the victim rather than executing malicious code. All forms of phishing are electronically delivered social engineering. Phishing can be targeted, known as spearphishing. In spearphishing, a specific individual, company, or industry will be targeted by the adversary. More generally, adversaries can conduct non-targeted phishing, such as in mass credential harvesting campaigns. Question: According to ATT&CK, which tactic does Phishing (T1566) belong to and what are its four sub-techniques? Answer:
A5: p02 | B5: LLM | C5: qwen3:4b-instruct | D5: 158 | E5: 434 | F5: =D5+E5 -> 592 | G5: 0 | H5: 57944.5 | I5: 57944.5 | J5: You are a cybersecurity assistant specialized in the MITRE ATT&CK framework (tactics, techniques, sub-techniques, groups, software, mitigations, detections). Answer the user's question accurately and concisely using your own knowledge. Include ATT&CK IDs (e.g. T1059.001, G0016, M1038) when you are confident about them. If you are not sure about something, say so explicitly instead of guessing. Answer in the same language as the question. | K5: Question: According to ATT&CK, which tactic does Phishing (T1566) belong to and what are its four sub-techniques? Answer:
A6: p03 | B6: RAG | C6: qwen3:4b-instruct | D6: 1201 | E6: 99 | F6: =D6+E6 -> 1300 | G6: 199.7 | H6: 68786.6 | I6: 68986.4 | J6: You are a cybersecurity assistant specialized in the MITRE ATT&CK framework (tactics, techniques, sub-techniques, groups, software, mitigations, detections). Answer the user's question using ONLY the information contained in the provided context passages. Cite the passages you rely on with their bracketed number, e.g. [1] or [2][4]. If the context does not contain enough information to answer, say so explicitly and do not invent facts. Be precise: include ATT&CK IDs (e.g. T1059.001, G0016, M1038) when they appear in the context. Answer in the same language as the question. | K6: Context passages: [1] Source: TA0003 - Persistence # TA0003 - Persistence Type: tactic | Domain: enterprise-attack | ATT&CK version: 19.2 Shortname: persistence ## Description The adversary is trying to maintain their foothold. Persistence consists of techniques that adversaries use to keep access to systems across restarts, changed credentials, and other interruptions that could cut off their access. Techniques used for persistence include any access, action, or configuration changes that let them maintain their foothold on systems, such as replacing or hijacking legitimate code or adding startup code. [2] Source: T1070.010 - Relocate Malware # T1070.010 - Relocate Malware Type: sub-technique | Domain: enterprise-attack | ATT&CK version: 19.2 Tactics: stealth Platforms: Linux, macOS, Network Devices, Windows Sub-technique of: T1070 Indicator Removal ## Description Once a payload is delivered, adversaries may reproduce copies of the same malware on the victim system to remove evidence of their presence and/or avoid defenses. Copying malware payloads to new locations may also be combined with [File Deletion](https://attack.mitre.org/techniques/T1070/004) to cleanup older artifacts. Relocating malware may be a part of many actions intended to evade defenses. For example, adversaries may copy and rename payloads to better blend into the local environment (i.e., [Match Legitimate Resource Name or Location](https://attack.mitre.org/techniques/T1036/005)). Payloads may also be repositioned to target [File/Path Exclusions](https://attack.mitre.org/techniques/T1564/012) as well as specific locations associated with establishing [Persistence](https://attack.mitre.org/tactics/TA0003). [3] Source: T1668 - Exclusive Control # T1668 - Exclusive Control Type: technique | Domain: enterprise-attack | ATT&CK version: 19.2 Tactics: persistence Platforms: Linux, macOS, Windows ## Description Adversaries who successfully compromise a system may attempt to maintain persistence by “closing the door” behind them – in other words, by preventing other threat actors from initially accessing or maintaining a foothold on the same system. For example, adversaries may patch a vulnerable, compromised system to prevent other threat actors from leveraging that vulnerability in the future. They may “close the door” in other ways, such as disabling vulnerable services, stripping privileges from accounts, or removing other malware already on the compromised device. [4] Source: T1596.003 - Digital Certificates # T1596.003 - Digital Certificates Type: sub-technique | Domain: enterprise-attack | ATT&CK version: 19.2 Tactics: reconnaissance Platforms: PRE Sub-technique of: T1596 Search Open Technical Databases ## Description Adversaries may search public digital certificate data for information about victims that can be used during targeting. Digital certificates are issued by a certificate authority (CA) in order to cryptographically verify the origin of signed content. These certificates, such as those used for encrypted web traffic (HTTPS SSL/TLS communications), contain information about the registered organization such as name and location. [5] Source: T1547.007 - Re-opened Applications # T1547.007 - Re-opened Applications Type: sub-technique | Domain: enterprise-attack | ATT&CK version: 19.2 Tactics: persistence, privilege-escalation Platforms: macOS Sub-technique of: T1547 Boot or Logon Autostart Execution ## Description Adversaries may modify plist files to automatically run an application when a user logs in. When a user logs out or restarts via the macOS Graphical User Interface (GUI), a prompt is provided to the user with a checkbox to "Reopen windows when logging back in". When selected, all applications currently open are added to a property list file named <code>com.apple.loginwindow.[UUID].plist</code> within the <code>~/Library/Preferences/ByHost</code> directory. Applications listed in this file are automatically reopened upon the user’s next logon. Adversaries can establish [Persistence](https://attack.mitre.org/tactics/TA0003) by adding a malicious application path to the <code>com.apple.loginwindow.[UUID].plist</code> file to execute payloads when a user logs in. Question: ¿Qué es la táctica Persistencia (TA0003) en ATT&CK y qué busca conseguir el adversario con ella? Answer:
A7: p03 | B7: LLM | C7: qwen3:4b-instruct | D7: 157 | E7: 354 | F7: =D7+E7 -> 511 | G7: 0 | H7: 46220.7 | I7: 46220.7 | J7: You are a cybersecurity assistant specialized in the MITRE ATT&CK framework (tactics, techniques, sub-techniques, groups, software, mitigations, detections). Answer the user's question accurately and concisely using your own knowledge. Include ATT&CK IDs (e.g. T1059.001, G0016, M1038) when you are confident about them. If you are not sure about something, say so explicitly instead of guessing. Answer in the same language as the question. | K7: Question: ¿Qué es la táctica Persistencia (TA0003) en ATT&CK y qué busca conseguir el adversario con ella? Answer:
A8: p04 | B8: RAG | C8: qwen3:4b-instruct | D8: 1256 | E8: 174 | F8: =D8+E8 -> 1430 | G8: 64.8 | H8: 74075.3 | I8: 74140.1 | J8: You are a cybersecurity assistant specialized in the MITRE ATT&CK framework (tactics, techniques, sub-techniques, groups, software, mitigations, detections). Answer the user's question using ONLY the information contained in the provided context passages. Cite the passages you rely on with their bracketed number, e.g. [1] or [2][4]. If the context does not contain enough information to answer, say so explicitly and do not invent facts. Be precise: include ATT&CK IDs (e.g. T1059.001, G0016, M1038) when they appear in the context. Answer in the same language as the question. | K8: Context passages: [1] Source: S0154 - Cobalt Strike # S0154 - Cobalt Strike Type: software | Domain: enterprise-attack | ATT&CK version: 19.2 Software type: malware | Aliases: Cobalt Strike | Platforms: Linux, macOS, Windows ## Description [Cobalt Strike](https://attack.mitre.org/software/S0154) is a commercial, full-featured, remote access tool that bills itself as “adversary simulation software designed to execute targeted attacks and emulate the post-exploitation actions of advanced threat actors”. Cobalt Strike’s interactive post-exploit capabilities cover the full range of ATT&CK tactics, all executed within a single, integrated system. In addition to its own capabilities, [Cobalt Strike](https://attack.mitre.org/software/S0154) leverages the capabilities of other well-known tools such as Metasploit and [Mimikatz](https://attack.mitre.org/software/S0002). [2] Source: T1021.004 - SSH # T1021.004 - SSH SSH through an HTTP tunnel. - S0154 Cobalt Strike (software): [Cobalt Strike](https://attack.mitre.org/software/S0154) can SSH to a remote service. - S0599 Kinsing (software): [Kinsing](https://attack.mitre.org/software/S0599) has used SSH for lateral movement. [3] Source: G0080 - Cobalt Group # G0080 - Cobalt Group T1566.001 Spearphishing Attachment - T1566.002 Spearphishing Link - T1572 Protocol Tunneling - T1573.002 Asymmetric Cryptography - T1588.002 Tool ## Software used - S0002 Mimikatz - S0284 More_eggs - S0646 SpicyOmelette - S0195 SDelete - S0154 Cobalt Strike - S0029 PsExec [4] Source: S0637 - NativeZone # S0637 - NativeZone Type: software | Domain: enterprise-attack | ATT&CK version: 19.2 Software type: malware | Aliases: NativeZone | Platforms: Windows ## Description [NativeZone](https://attack.mitre.org/software/S0637) is the name given collectively to disposable custom [Cobalt Strike](https://attack.mitre.org/software/S0154) loaders used by [APT29](https://attack.mitre.org/groups/G0016) since at least 2021. ## Techniques used - T1036 Masquerading - T1140 Deobfuscate/Decode Files or Information - T1204.002 Malicious File - T1218.011 Rundll32 - T1480 Execution Guardrails - T1497.001 System Checks ## Used by - G0016 APT29 [5] Source: T1001.003 - Protocol or Service Impersonation # T1001.003 - Protocol or Service Impersonation requests. - S0387 KeyBoy (software): [KeyBoy](https://attack.mitre.org/software/S0387) uses custom SSL libraries to impersonate SSL in C2 traffic. - S0586 TAINTEDSCRIBE (software): [TAINTEDSCRIBE](https://attack.mitre.org/software/S0586) has used FakeTLS for session authentication. - S0022 Uroburos (software): [Uroburos](https://attack.mitre.org/software/S0022) can use custom communication methodologies that ride over common protocols including TCP, UDP, HTTP, SMTP, and DNS in order to blend with normal network traffic. - S0245 BADCALL (software): [BADCALL](https://attack.mitre.org/software/S0245) uses a FakeTLS method during C2. - S0154 Cobalt Strike (software): [Cobalt Strike](https://attack.mitre.org/software/S0154) can leverage the HTTP protocol for C2 communication, while hiding the actual data in either an HTTP header, URI parameter, the transaction body, or appending it to the URI. [Cobalt Strike](https://attack.mitre.org/software/S0154) has also added Host: ocsp.verisign.com to HTTP headers to mimic Online Certificate Status Protocol (OCSP) traffic. Question: Según ATT&CK, ¿qué es Cobalt Strike (S0154) y de qué otras herramientas conocidas aprovecha capacidades? ¿Cuánto cuesta su licencia anual? Answer:
A9: p04 | B9: LLM | C9: qwen3:4b-instruct | D9: 171 | E9: 431 | F9: =D9+E9 -> 602 | G9: 0 | H9: 56364.4 | I9: 56364.4 | J9: You are a cybersecurity assistant specialized in the MITRE ATT&CK framework (tactics, techniques, sub-techniques, groups, software, mitigations, detections). Answer the user's question accurately and concisely using your own knowledge. Include ATT&CK IDs (e.g. T1059.001, G0016, M1038) when you are confident about them. If you are not sure about something, say so explicitly instead of guessing. Answer in the same language as the question. | K9: Question: Según ATT&CK, ¿qué es Cobalt Strike (S0154) y de qué otras herramientas conocidas aprovecha capacidades? ¿Cuánto cuesta su licencia anual? Answer:
A10: p05 | B10: RAG | C10: qwen3:4b-instruct | D10: 1661 | E10: 220 | F10: =D10+E10 -> 1881 | G10: 61.3 | H10: 108365.1 | I10: 108426.4 | J10: You are a cybersecurity assistant specialized in the MITRE ATT&CK framework (tactics, techniques, sub-techniques, groups, software, mitigations, detections). Answer the user's question using ONLY the information contained in the provided context passages. Cite the passages you rely on with their bracketed number, e.g. [1] or [2][4]. If the context does not contain enough information to answer, say so explicitly and do not invent facts. Be precise: include ATT&CK IDs (e.g. T1059.001, G0016, M1038) when they appear in the context. Answer in the same language as the question. | K10: Context passages: [1] Source: T1550.003 - Pass the Ticket # T1550.003 - Pass the Ticket account password once, force replication, and then change the password a second time. Consider rotating the KRBTGT account password every 180 days. ## Procedure examples - G0050 APT32 (group): [APT32](https://attack.mitre.org/groups/G0050) successfully gained remote access by using pass the ticket. - G0016 APT29 (group): [APT29](https://attack.mitre.org/groups/G0016) used Kerberos ticket attacks for lateral movement. - G0060 BRONZE BUTLER (group): [BRONZE BUTLER](https://attack.mitre.org/groups/G0060) has created forged Kerberos Ticket Granting Ticket (TGT) and Ticket Granting Service (TGS) tickets to maintain administrative access. - S0053 SeaDuke (software): Some [SeaDuke](https://attack.mitre.org/software/S0053) samples have a module to use pass the ticket with Kerberos for authentication. - S0002 Mimikatz (software): [Mimikatz](https://attack.mitre.org/software/S0002)’s <code>LSADUMP::DCSync</code> and <code>KERBEROS::PTT</code> modules implement the three steps required to extract the krbtgt account hash and create/use Kerberos tickets. - S0192 Pupy (software): [Pupy](https://attack.mitre.org/software/S0192) can also perform pass-the-ticket. [2] Source: T1550.003 - Pass the Ticket # T1550.003 - Pass the Ticket Type: sub-technique | Domain: enterprise-attack | ATT&CK version: 19.2 Tactics: lateral-movement Platforms: Windows Sub-technique of: T1550 Use Alternate Authentication Material ## Description Adversaries may “pass the ticket” using stolen Kerberos tickets to move laterally within an environment, bypassing normal system access controls. Pass the ticket (PtT) is a method of authenticating to a system using Kerberos tickets without having access to an account's password. Kerberos authentication can be used as the first step to lateral movement to a remote system. When preforming PtT, valid Kerberos tickets for [Valid Accounts](https://attack.mitre.org/techniques/T1078) are captured by [OS Credential Dumping](https://attack.mitre.org/techniques/T1003). A user's service tickets or ticket granting ticket (TGT) may be obtained, depending on the level of access. A service ticket allows for access to a particular resource, whereas a TGT can be used to request service tickets from the Ticket Granting Service (TGS) to access any resource the user has privileges to access. [3] Source: T1558.003 - Kerberoasting # T1558.003 - Kerberoasting outside normal usage baselines. Also correlates suspicious process activity (e.g., Mimikatz invoking LSASS access) with Kerberos ticket anomalies. ## Mitigations - M1027 Password Policies: Ensure strong password length (ideally 25+ characters) and complexity for service accounts and that these passwords periodically expire. Also consider using Group Managed Service Accounts or another third party product such as password vaulting. - M1026 Privileged Account Management: Limit service accounts to minimal required privileges, including membership in privileged groups such as Domain Administrators. - M1041 Encrypt Sensitive Information: Enable AES Kerberos encryption (or another stronger encryption algorithm), rather than RC4, where possible. ## Procedure examples - C0024 SolarWinds Compromise (campaign): During the [SolarWinds Compromise](https://attack.mitre.org/campaigns/C0024), [APT29](https://attack.mitre.org/groups/G0016) obtained Ticket Granting Service (TGS) tickets for Active Directory Service Principle Names to crack offline. [4] Source: S0079 - MobileOrder # S0079 - MobileOrder Type: software | Domain: enterprise-attack | ATT&CK version: 19.2 Software type: malware | Aliases: n/a | Platforms: n/a ## Description [MobileOrder](https://attack.mitre.org/software/S0079) is a Trojan intended to compromise Android mobile devices. It has been used by [Scarlet Mimic](https://attack.mitre.org/groups/G0029). ## Techniques used - T1005 Data from Local System - T1041 Exfiltration Over C2 Channel - T1057 Process Discovery - T1082 System Information Discovery - T1083 File and Directory Discovery - T1105 Ingress Tool Transfer - T1217 Browser Information Discovery ## Used by - G0029 Scarlet Mimic [5] Source: T1558.001 - Golden Ticket # T1558.001 - Golden Ticket account password once, force replication, and then change the password a second time. Consider rotating the KRBTGT account password every 180 days. ## Procedure examples - G0004 Ke3chang (group): [Ke3chang](https://attack.mitre.org/groups/G0004) has used [Mimikatz](https://attack.mitre.org/software/S0002) to generate Kerberos golden tickets. - S0633 Sliver (software): [Sliver](https://attack.mitre.org/software/S0633) incorporates the [Rubeus](https://attack.mitre.org/software/S1071) framework to allow for Kerberos ticket manipulation, specifically for forging Kerberos Golden Tickets. - S0363 Empire (software): [Empire](https://attack.mitre.org/software/S0363) can leverage its implementation of [Mimikatz](https://attack.mitre.org/software/S0002) to obtain and use golden tickets. - S0002 Mimikatz (software): [Mimikatz](https://attack.mitre.org/software/S0002)'s kerberos module can create golden tickets. - S1071 Rubeus (software): [Rubeus](https://attack.mitre.org/software/S1071) can forge a ticket-granting ticket. Question: Según ATT&CK, ¿APT29 (G0016) utiliza Mimikatz? Y en caso afirmativo, ¿qué técnicas relacionadas con tickets Kerberos implementa esa herramienta? Answer:
A11: p05 | B11: LLM | C11: qwen3:4b-instruct | D11: 171 | E11: 415 | F11: =D11+E11 -> 586 | G11: 0 | H11: 55533.9 | I11: 55533.9 | J11: You are a cybersecurity assistant specialized in the MITRE ATT&CK framework (tactics, techniques, sub-techniques, groups, software, mitigations, detections). Answer the user's question accurately and concisely using your own knowledge. Include ATT&CK IDs (e.g. T1059.001, G0016, M1038) when you are confident about them. If you are not sure about something, say so explicitly instead of guessing. Answer in the same language as the question. | K11: Question: Según ATT&CK, ¿APT29 (G0016) utiliza Mimikatz? Y en caso afirmativo, ¿qué técnicas relacionadas con tickets Kerberos implementa esa herramienta? Answer:
A12: p06 | B12: RAG | C12: qwen3:4b-instruct | D12: 1714 | E12: 217 | F12: =D12+E12 -> 1931 | G12: 62.5 | H12: 104287.3 | I12: 104349.8 | J12: You are a cybersecurity assistant specialized in the MITRE ATT&CK framework (tactics, techniques, sub-techniques, groups, software, mitigations, detections). Answer the user's question using ONLY the information contained in the provided context passages. Cite the passages you rely on with their bracketed number, e.g. [1] or [2][4]. If the context does not contain enough information to answer, say so explicitly and do not invent facts. Be precise: include ATT&CK IDs (e.g. T1059.001, G0016, M1038) when they appear in the context. Answer in the same language as the question. | K12: Context passages: [1] Source: S0347 - AuditCred # S0347 - AuditCred Type: software | Domain: enterprise-attack | ATT&CK version: 19.2 Software type: malware | Aliases: AuditCred, Roptimizer | Platforms: Windows ## Description [AuditCred](https://attack.mitre.org/software/S0347) is a malicious DLL that has been used by [Lazarus Group](https://attack.mitre.org/groups/G0032) during their 2018 attacks. ## Techniques used - T1027.013 Encrypted/Encoded File - T1055 Process Injection - T1059.003 Windows Command Shell - T1070.004 File Deletion - T1083 File and Directory Discovery - T1090 Proxy - T1105 Ingress Tool Transfer - T1140 Deobfuscate/Decode Files or Information - T1543.003 Windows Service ## Used by - G0032 Lazarus Group [2] Source: G0099 - APT-C-36 # G0099 - APT-C-36 Type: group | Domain: enterprise-attack | ATT&CK version: 19.2 Aliases: APT-C-36, Blind Eagle, TAG-144, AguilaCiega, APT-Q-98 ## Description [APT-C-36](https://attack.mitre.org/groups/G0099) is a suspected South American threat group that has engaged in espionage and financially motivated operations since at least 2018. [APT-C-36](https://attack.mitre.org/groups/G0099) has targeted government institutions and entities in the financial, energy, and professional manufacturing sectors across Colombia and other Latin American countries. [3] Source: S0263 - TYPEFRAME # S0263 - TYPEFRAME Type: software | Domain: enterprise-attack | ATT&CK version: 19.2 Software type: malware | Aliases: TYPEFRAME | Platforms: Windows ## Description [TYPEFRAME](https://attack.mitre.org/software/S0263) is a remote access tool that has been used by [Lazarus Group](https://attack.mitre.org/groups/G0032). ## Techniques used - T1027.011 Fileless Storage - T1027.013 Encrypted/Encoded File - T1059.003 Windows Command Shell - T1059.005 Visual Basic - T1070.004 File Deletion - T1083 File and Directory Discovery - T1090 Proxy - T1105 Ingress Tool Transfer - T1112 Modify Registry - T1140 Deobfuscate/Decode Files or Information - T1204.002 Malicious File - T1543.003 Windows Service - T1571 Non-Standard Port - T1680 Local Storage Discovery - T1686.003 Windows Host Firewall ## Used by - G0032 Lazarus Group [4] Source: G0032 - Lazarus Group # G0032 - Lazarus Group Type: group | Domain: enterprise-attack | ATT&CK version: 19.2 Aliases: Lazarus Group, Labyrinth Chollima, HIDDEN COBRA, Guardians of Peace, ZINC, NICKEL ACADEMY, Diamond Sleet ## Description [Lazarus Group](https://attack.mitre.org/groups/G0032) is a North Korean state-sponsored cyber threat group attributed to the Reconnaissance General Bureau (RGB). [Lazarus Group](https://attack.mitre.org/groups/G0032) has been active since at least 2009 and is reportedly responsible for the November 2014 destructive wiper attack on Sony Pictures Entertainment, identified by Novetta as part of Operation Blockbuster. Malware used by [Lazarus Group](https://attack.mitre.org/groups/G0032) correlates to other reported campaigns, including Operation Flame, Operation 1Mission, Operation Troy, DarkSeoul, and Ten Days of Rain. [5] Source: G0032 - Lazarus Group # G0032 - Lazarus Group Group” as an umbrella term for multiple North Korean cyber operators conducting espionage, destructive attacks, and financially motivated campaigns. ## Techniques used - T1001.003 Protocol or Service Impersonation - T1005 Data from Local System - T1008 Fallback Channels - T1010 Application Window Discovery - T1012 Query Registry - T1016 System Network Configuration Discovery - T1021.001 Remote Desktop Protocol - T1021.002 SMB/Windows Admin Shares - T1021.004 SSH - T1027.007 Dynamic API Resolution - T1027.009 Embedded Payloads - T1027.013 Encrypted/Encoded File - T1033 System Owner/User Discovery - T1036.003 Rename Legitimate Utilities - T1036.004 Masquerade Task or Service - T1036.005 Match Legitimate Resource Name or Location - T1041 Exfiltration Over C2 Channel - T1046 Network Service Discovery - T1047 Windows Management Instrumentation - T1048.003 Exfiltration Over Unencrypted Non-C2 Protocol - T1049 System Network Connections Discovery - T1053.005 Scheduled Task - T1055.001 Dynamic-link Library Injection - T1056.001 Keylogging - T1057 Process Discovery - T1059.001 PowerShell - T1059.003 Windows Command Shell - T1059.005 Visual Basic - T1070 Indicator Removal - T1070.003 Clear Command History - T1070.004 File Deletion - T1070.006 Timestomp - T1071.001 Web Protocols - T1074.001 Local Data Staging - T1078 Valid Accounts - T108 Question: ¿Qué sub-técnicas de intérpretes de comandos (T1059.*) usa Lazarus Group (G0032) según ATT&CK, y qué ataques ha realizado este grupo contra Ecuador? Answer:
A13: p06 | B13: LLM | C13: qwen3:4b-instruct | D13: 177 | E13: 282 | F13: =D13+E13 -> 459 | G13: 0 | H13: 37692.2 | I13: 37692.2 | J13: You are a cybersecurity assistant specialized in the MITRE ATT&CK framework (tactics, techniques, sub-techniques, groups, software, mitigations, detections). Answer the user's question accurately and concisely using your own knowledge. Include ATT&CK IDs (e.g. T1059.001, G0016, M1038) when you are confident about them. If you are not sure about something, say so explicitly instead of guessing. Answer in the same language as the question. | K13: Question: ¿Qué sub-técnicas de intérpretes de comandos (T1059.*) usa Lazarus Group (G0032) según ATT&CK, y qué ataques ha realizado este grupo contra Ecuador? Answer:
... A27: p13 | B27: LLM | C27: qwen3:4b-instruct | D27: 159 | E27: 164 | F27: =D27+E27 -> 323 | G27: 0 | H27: 44539.4 | I27: 44539.4 | J27: You are a cybersecurity assistant specialized in the MITRE ATT&CK framework (tactics, techniques, sub-techniques, groups, software, mitigations, detections). Answer the user's question accurately and concisely using your own knowledge. Include ATT&CK IDs (e.g. T1059.001, G0016, M1038) when you are confident about them. If you are not sure about something, say so explicitly instead of guessing. Answer in the same language as the question. | K27: Question: ¿Qué describe la sub-técnica T1059.099 de ATT&CK y a qué táctica pertenece? Answer:

Sheet Contextos
A1: id | B1: modo | C1: [n] rango | D1: score | E1: attack_id | F1: nombre | G1: tipo | H1: chunk | I1: ES GOLD | J1: texto | K1: point_id (chunks.jsonl) | L1: doc_id | M1: url ATT&CK
A2: p01 | B2: RAG | C2: 1 | D2: 1 | E2: T1059.001 | F2: PowerShell | G2: sub-technique | H2: 1/11 | J2: # T1059.001 - PowerShell Type: sub-technique | Domain: enterprise-attack | ATT&CK version: 19.2 Tactics: execution Platforms: Windows Sub-technique of: T1059 Command and Scripting Interpreter ## Description Adversaries may abuse PowerShell commands and scripts for execution. PowerShell is a powerful interactive command-line interface and scripting environment included in the Windows operating system. Adversaries can use PowerShell to perform a number of actions, including discovery of information and execution of code. Examples include the <code>Start-Process</code> cmdlet which can be used to run an executable and the <code>Invoke-Command</code> cmdlet which runs a command locally or on a remote computer (though administrator permissions are required to use PowerShell to connect to remote systems). PowerShell may also be used to download and run executables from the Internet, which can be executed from disk or in memory without touching disk. | K2: 0a79d1de-5953-5bf1-91d8-c87bbbf93bc8 | L2: attack-pattern--970a3432-3237-47ad-bcca-7d8cbb217736 | M2: https://attack.mitre.org/techniques/T1059/001
A3: p01 | B3: RAG | C3: 2 | D3: 0.3922 | E3: S1193 | F3: TAMECAT | G3: software | H3: 1/1 | J3: # S1193 - TAMECAT Type: software | Domain: enterprise-attack | ATT&CK version: 19.2 Software type: malware | Aliases: TAMECAT | Platforms: Windows ## Description [TAMECAT](https://attack.mitre.org/software/S1193) is a malware that is used by [APT42](https://attack.mitre.org/groups/G1044) to execute PowerShell or C# content. ## Techniques used - T1047 Windows Management Instrumentation - T1059.001 PowerShell - T1059.003 Windows Command Shell - T1059.005 Visual Basic - T1071.001 Web Protocols - T1105 Ingress Tool Transfer - T1132.001 Standard Encoding - T1518.001 Security Software Discovery - T1573.001 Symmetric Cryptography ## Used by - G1044 APT42 | K3: 4890209d-7610-5835-817d-6f8eb92c4ff3 | L3: malware--12fdf05a-4bd1-4f45-9cde-d3af35f82db1 | M3: https://attack.mitre.org/software/S1193
A4: p01 | B4: RAG | C4: 3 | D4: 0.3333 | E4: G0099 | F4: APT-C-36 | G4: group | H4: 2/3 | J4: # G0099 - APT-C-36 institutions and entities in the financial, energy, and professional manufacturing sectors across Colombia and other Latin American countries. ## Techniques used - T1027 Obfuscated Files or Information - T1027.003 Steganography - T1027.013 Encrypted/Encoded File - T1027.016 Junk Code Insertion - T1036.004 Masquerade Task or Service - T1036.005 Match Legitimate Resource Name or Location - T1047 Windows Management Instrumentation - T1053.005 Scheduled Task - T1055.012 Process Hollowing - T1059.001 PowerShell - T1059.005 Visual Basic - T1059.007 JavaScript - T1105 Ingress Tool Transfer - T1133 External Remote Services - T1204.001 Malicious Link - T1204.002 Malicious File - T1480 Execution Guardrails - T1534 Internal Spearphishing - T1564.003 Hidden Window - T1566.001 Spearphishing Attachment - T1566.002 Spearphishing Link - T1568 Dynamic Resolution - T1571 Non-Standard Port - T1574.001 DLL - T1583.001 Domains - T1583.003 Virtual Private Server - T1583.006 Web Services - T1584.005 Botnet - T1586.002 Email Accounts - T1586.003 Cloud Accounts - T1587.001 Malware - T1588.001 Malware - T1588.002 Tool - T1593 Search Open Websites/Domains - T1608.001 Upload Malware - T1683.001 Written Content - T1683.002 Audio-Visual Content - T1684.001 Impersonation | K4: a2e64c2d-7e66-5e5a-86df-0543d7957b56 | L4: intrusion-set--c4d50cdf-87ce-407d-86d8-862883485842 | M4: https://attack.mitre.org/groups/G0099
A5: p01 | B5: RAG | C5: 4 | D5: 0.2556 | E5: T1059 | F5: Command and Scripting Interpreter | G5: technique | H5: 6/10 | J5: # T1059 - Command and Scripting Interpreter interpreter installations. - M1042 Disable or Remove Feature or Program: Disable or remove any unnecessary or unused shells or interpreters. ## Sub-techniques - T1059.007 JavaScript - T1059.002 AppleScript - T1059.010 AutoHotKey & AutoIT - T1059.009 Cloud API - T1059.008 Network Device CLI - T1059.001 PowerShell - T1059.004 Unix Shell - T1059.011 Lua - T1059.013 Container CLI/API - T1059.005 Visual Basic - T1059.003 Windows Command Shell - T1059.012 Hypervisor CLI - T1059.006 Python ## Procedure examples - C0005 Operation Spalax (campaign): For [Operation Spalax](https://attack.mitre.org/campaigns/C0005), the threat actors used Nullsoft Scriptable Install System (NSIS) scripts to install malware. - C0029 Cutting Edge (campaign): During [Cutting Edge](https://attack.mitre.org/campaigns/C0029), threat actors used Perl scripts to enable the deployment of the THINSPOOL shell script dropper and for enumerating host data. - C0046 ArcaneDoor (campaign): [ArcaneDoor](https://attack.mitre.org/campaigns/C0046) included the adversary executing command line interface (CLI) commands. | K5: 12155368-afb0-5e72-bdbd-189ee840f96e | L5: attack-pattern--7385dfaf-6886-4229-9ecd-6fd678040830 | M5: https://attack.mitre.org/techniques/T1059
A6: p01 | B6: RAG | C6: 5 | D6: 0.25 | E6: S0393 | F6: PowerStallion | G6: software | H6: 1/1 | J6: # S0393 - PowerStallion Type: software | Domain: enterprise-attack | ATT&CK version: 19.2 Software type: malware | Aliases: PowerStallion | Platforms: Windows ## Description [PowerStallion](https://attack.mitre.org/software/S0393) is a lightweight [PowerShell](https://attack.mitre.org/techniques/T1059/001) backdoor used by [Turla](https://attack.mitre.org/groups/G0010), possibly as a recovery access tool to install other backdoors. ## Techniques used - T1027 Obfuscated Files or Information - T1057 Process Discovery - T1059.001 PowerShell - T1070.006 Timestomp - T1102.002 Bidirectional Communication ## Used by - G0010 Turla | K6: 3176af7f-1b20-500d-8754-9e2746f08472 | L6: malware--dcac85c1-6485-4790-84f6-de5e6f6b91dd | M6: https://attack.mitre.org/software/S0393
A7: p02 | B7: RAG | C7: 1 | D7: 0.5 | E7: T1586 | F7: Compromise Accounts | G7: technique | H7: 3/3 | J7: # T1586 - Compromise Accounts organization. Much of this activity will take place outside the visibility of the target organization, making detection of this behavior difficult. Detection efforts may be focused on related stages of the adversary lifecycle, such as during Initial Access (ex: [Phishing](https://attack.mitre.org/techniques/T1566)). Monitor and analyze traffic patterns and packet inspection associated to protocol(s) that do not follow the expected protocol standards and traffic flows (e.g extraneous packets that do not belong to established flows, gratuitous or anomalous traffic patterns, anomalous syntax, or structure). Consider correlation with process monitoring and command line to detect anomalous processes execution and command line arguments associated to traffic patterns (e.g. monitor anomalies in use of files that do not normally initiate connections for respective protocol(s)). ## Mitigations - M1056 Pre-compromise: This technique cannot be easily mitigated with preventive controls since it is based on behaviors performed outside of the scope of enterprise defenses and controls. ## Sub-techniques - T1586.001 Social Media Accounts - T1586.003 Cloud Accounts - T1586.002 Email Accounts | K7: b2a9cfd5-44fa-5197-8cfd-a36ce303763f | L7: attack-pattern--81033c3b-16a4-46e4-8fed-9b030dd03c4a | M7: https://attack.mitre.org/techniques/T1586
A8: p02 | B8: RAG | C8: 2 | D8: 0.5 | E8: T1566 | F8: Phishing | G8: technique | H8: 1/8 | I8: SI | J8: # T1566 - Phishing Type: technique | Domain: enterprise-attack | ATT&CK version: 19.2 Tactics: initial-access Platforms: Identity Provider, Linux, macOS, Office Suite, SaaS, Windows ## Description Adversaries may send phishing messages to gain access to victim systems. All forms of phishing are electronically delivered social engineering. Phishing can be targeted, known as spearphishing. In spearphishing, a specific individual, company, or industry will be targeted by the adversary. More generally, adversaries can conduct non-targeted phishing, such as in mass malware spam campaigns. | K8: af42649d-952f-5dfb-afab-8c8e51a00019 | L8: attack-pattern--a62a8db3-f23a-4d8f-afd6-9dbc77e7813b | M8: https://attack.mitre.org/techniques/T1566
A9: p02 | B9: RAG | C9: 3 | D9: 0.3611 | E9: T1566.004 | F9: Spearphishing Voice | G9: sub-technique | H9: 1/4 | J9: # T1566.004 - Spearphishing Voice Type: sub-technique | Domain: enterprise-attack | ATT&CK version: 19.2 Tactics: initial-access Platforms: Linux, macOS, Windows, Identity Provider Sub-technique of: T1566 Phishing ## Description Adversaries may use voice communications to ultimately gain access to victim systems. Spearphishing voice is a specific variant of spearphishing. It is different from other forms of spearphishing in that it employs the use of manipulating a user into providing access to systems through a phone call or other forms of voice communications. Spearphishing frequently involves social engineering techniques, such as posing as a trusted source (ex: [Impersonation](https://attack.mitre.org/techniques/T1684/001)) and/or creating a sense of urgency or alarm for the recipient. | K9: 7d5a91ab-56d5-5ca2-b89b-c33ea61c6f5c | L9: attack-pattern--bb5e59c4-abe7-40c7-8196-e373cb1e5974 | M9: https://attack.mitre.org/techniques/T1566/004
A10: p02 | B10: RAG | C10: 4 | D10: 0.3333 | E10: TA0001 | F10: Initial Access | G10: tactic | H10: 1/1 | J10: # TA0001 - Initial Access Type: tactic | Domain: enterprise-attack | ATT&CK version: 19.2 Shortname: initial-access ## Description The adversary is trying to get into your network. Initial Access consists of techniques that use various entry vectors to gain their initial foothold within a network. Techniques used to gain a foothold include targeted spearphishing and exploiting weaknesses on public-facing web servers. Footholds gained through initial access may allow for continued access, like valid accounts and use of external remote services, or may be limited-use due to changing passwords. ## Techniques in this tactic - T1078 Valid Accounts - T1091 Replication Through Removable Media - T1133 External Remote Services - T1189 Drive-by Compromise - T1190 Exploit Public-Facing Application - T1195 Supply Chain Compromise - T1199 Trusted Relationship - T1200 Hardware Additions - T1566 Phishing - T1659 Content Injection - T1669 Wi-Fi Networks | K10: ff4c0835-7fe5-59cd-a94d-d82a9c87c07c | L10: x-mitre-tactic--ffd5bcee-6e16-4dd2-8eca-7b3beedf33ca | M10: https://attack.mitre.org/tactics/TA0001
A11: p02 | B11: RAG | C11: 5 | D11: 0.3333 | E11: T1598 | F11: Phishing for Information | G11: technique | H11: 1/6 | J11: # T1598 - Phishing for Information Type: technique | Domain: enterprise-attack | ATT&CK version: 19.2 Tactics: reconnaissance Platforms: PRE ## Description Adversaries may send phishing messages to elicit sensitive information that can be used during targeting. Phishing for information is an attempt to trick targets into divulging information, frequently credentials or other actionable information. Phishing for information is different from [Phishing](https://attack.mitre.org/techniques/T1566) in that the objective is gathering data from the victim rather than executing malicious code. All forms of phishing are electronically delivered social engineering. Phishing can be targeted, known as spearphishing. In spearphishing, a specific individual, company, or industry will be targeted by the adversary. More generally, adversaries can conduct non-targeted phishing, such as in mass credential harvesting campaigns. | K11: f4d8f7cf-221f-59d8-8020-429a851befef | L11: attack-pattern--cca0ccb6-a068-4574-a722-b1556f86833a | M11: https://attack.mitre.org/techniques/T1598
A12: p03 | B12: RAG | C12: 1 | D12: 1 | E12: TA0003 | F12: Persistence | G12: tactic | H12: 1/2 | I12: SI | J12: # TA0003 - Persistence Type: tactic | Domain: enterprise-attack | ATT&CK version: 19.2 Shortname: persistence ## Description The adversary is trying to maintain their foothold. Persistence consists of techniques that adversaries use to keep access to systems across restarts, changed credentials, and other interruptions that could cut off their access. Techniques used for persistence include any access, action, or configuration changes that let them maintain their foothold on systems, such as replacing or hijacking legitimate code or adding startup code. | K12: 259ce106-5bf5-5095-9060-49c5e3501b01 | L12: x-mitre-tactic--5bc1d813-693e-4823-9961-abf9af4b0e92 | M12: https://attack.mitre.org/tactics/TA0003
A13: p03 | B13: RAG | C13: 2 | D13: 0.3333 | E13: T1070.010 | F13: Relocate Malware | G13: sub-technique | H13: 1/4 | J13: # T1070.010 - Relocate Malware Type: sub-technique | Domain: enterprise-attack | ATT&CK version: 19.2 Tactics: stealth Platforms: Linux, macOS, Network Devices, Windows Sub-technique of: T1070 Indicator Removal ## Description Once a payload is delivered, adversaries may reproduce copies of the same malware on the victim system to remove evidence of their presence and/or avoid defenses. Copying malware payloads to new locations may also be combined with [File Deletion](https://attack.mitre.org/techniques/T1070/004) to cleanup older artifacts. Relocating malware may be a part of many actions intended to evade defenses. For example, adversaries may copy and rename payloads to better blend into the local environment (i.e., [Match Legitimate Resource Name or Location](https://attack.mitre.org/techniques/T1036/005)). Payloads may also be repositioned to target [File/Path Exclusions](https://attack.mitre.org/techniques/T1564/012) as well as specific locations associated with establishing [Persistence](https://attack.mitre.org/tactics/TA0003). | K13: e10a631d-09ba-51f0-875b-5eb8736daa53 | L13: attack-pattern--cc36eeae-2209-4e63-89d3-c97e19edf280 | M13: https://attack.mitre.org/techniques/T1070/010
A14: p03 | B14: RAG | C14: 3 | D14: 0.3333 | E14: T1668 | F14: Exclusive Control | G14: technique | H14: 1/3 | J14: # T1668 - Exclusive Control Type: technique | Domain: enterprise-attack | ATT&CK version: 19.2 Tactics: persistence Platforms: Linux, macOS, Windows ## Description Adversaries who successfully compromise a system may attempt to maintain persistence by “closing the door” behind them – in other words, by preventing other threat actors from initially accessing or maintaining a foothold on the same system. For example, adversaries may patch a vulnerable, compromised system to prevent other threat actors from leveraging that vulnerability in the future. They may “close the door” in other ways, such as disabling vulnerable services, stripping privileges from accounts, or removing other malware already on the compromised device. | K14: b0eccfc2-c562-56d9-a9c2-b5fb87c09c21 | L14: attack-pattern--dff263cc-328e-42b4-afbc-1fee8b6a8913 | M14: https://attack.mitre.org/techniques/T1668
A15: p03 | B15: RAG | C15: 4 | D15: 0.25 | E15: T1596.003 | F15: Digital Certificates | G15: sub-technique | H15: 1/3 | J15: # T1596.003 - Digital Certificates Type: sub-technique | Domain: enterprise-attack | ATT&CK version: 19.2 Tactics: reconnaissance Platforms: PRE Sub-technique of: T1596 Search Open Technical Databases ## Description Adversaries may search public digital certificate data for information about victims that can be used during targeting. Digital certificates are issued by a certificate authority (CA) in order to cryptographically verify the origin of signed content. These certificates, such as those used for encrypted web traffic (HTTPS SSL/TLS communications), contain information about the registered organization such as name and location. | K15: 5eecfeb4-7ff3-5476-a857-a696b2cfa777 | L15: attack-pattern--0979abf9-4e26-43ec-9b6e-54efc4e70fca | M15: https://attack.mitre.org/techniques/T1596/003
A16: p03 | B16: RAG | C16: 5 | D16: 0.25 | E16: T1547.007 | F16: Re-opened Applications | G16: sub-technique | H16: 1/2 | J16: # T1547.007 - Re-opened Applications Type: sub-technique | Domain: enterprise-attack | ATT&CK version: 19.2 Tactics: persistence, privilege-escalation Platforms: macOS Sub-technique of: T1547 Boot or Logon Autostart Execution ## Description Adversaries may modify plist files to automatically run an application when a user logs in. When a user logs out or restarts via the macOS Graphical User Interface (GUI), a prompt is provided to the user with a checkbox to "Reopen windows when logging back in". When selected, all applications currently open are added to a property list file named <code>com.apple.loginwindow.[UUID].plist</code> within the <code>~/Library/Preferences/ByHost</code> directory. Applications listed in this file are automatically reopened upon the user’s next logon. Adversaries can establish [Persistence](https://attack.mitre.org/tactics/TA0003) by adding a malicious application path to the <code>com.apple.loginwindow.[UUID].plist</code> file to execute payloads when a user logs in. | K16: d594b40b-00a7-5682-b595-8e660593de1f | L16: attack-pattern--e5cc9e7a-e61a-46a1-b869-55fb6eab058e | M16: https://attack.mitre.org/techniques/T1547/007
A17: p04 | B17: RAG | C17: 1 | D17: 1 | E17: S0154 | F17: Cobalt Strike | G17: software | H17: 1/4 | I17: SI | J17: # S0154 - Cobalt Strike Type: software | Domain: enterprise-attack | ATT&CK version: 19.2 Software type: malware | Aliases: Cobalt Strike | Platforms: Linux, macOS, Windows ## Description [Cobalt Strike](https://attack.mitre.org/software/S0154) is a commercial, full-featured, remote access tool that bills itself as “adversary simulation software designed to execute targeted attacks and emulate the post-exploitation actions of advanced threat actors”. Cobalt Strike’s interactive post-exploit capabilities cover the full range of ATT&CK tactics, all executed within a single, integrated system. In addition to its own capabilities, [Cobalt Strike](https://attack.mitre.org/software/S0154) leverages the capabilities of other well-known tools such as Metasploit and [Mimikatz](https://attack.mitre.org/software/S0002). | K17: 71c1c43a-b0b2-569d-8a65-7d55faff7ef8 | L17: malware--a7881f21-e978-4fe4-af56-92c9416a2616 | M17: https://attack.mitre.org/software/S0154
A18: p04 | B18: RAG | C18: 2 | D18: 0.6667 | E18: T1021.004 | F18: SSH | G18: sub-technique | H18: 7/7 | J18: # T1021.004 - SSH SSH through an HTTP tunnel. - S0154 Cobalt Strike (software): [Cobalt Strike](https://attack.mitre.org/software/S0154) can SSH to a remote service. - S0599 Kinsing (software): [Kinsing](https://attack.mitre.org/software/S0599) has used SSH for lateral movement. | K18: b27606ce-c40b-57f1-92e7-d18ac7673f0e | L18: attack-pattern--2db31dcd-54da-405d-acef-b9129b816ed6 | M18: https://attack.mitre.org/techniques/T1021/004
A19: p04 | B19: RAG | C19: 3 | D19: 0.3 | E19: G0080 | F19: Cobalt Group | G19: group | H19: 3/3 | J19: # G0080 - Cobalt Group T1566.001 Spearphishing Attachment - T1566.002 Spearphishing Link - T1572 Protocol Tunneling - T1573.002 Asymmetric Cryptography - T1588.002 Tool ## Software used - S0002 Mimikatz - S0284 More_eggs - S0646 SpicyOmelette - S0195 SDelete - S0154 Cobalt Strike - S0029 PsExec | K19: c7c1e3ef-2447-55be-8bab-3de4d5e3fa0b | L19: intrusion-set--dc6fe6ee-04c2-49be-ba3d-f38d2463c02a | M19: https://attack.mitre.org/groups/G0080
A20: p04 | B20: RAG | C20: 4 | D20: 0.2576 | E20: S0637 | F20: NativeZone | G20: software | H20: 1/1 | J20: # S0637 - NativeZone Type: software | Domain: enterprise-attack | ATT&CK version: 19.2 Software type: malware | Aliases: NativeZone | Platforms: Windows ## Description [NativeZone](https://attack.mitre.org/software/S0637) is the name given collectively to disposable custom [Cobalt Strike](https://attack.mitre.org/software/S0154) loaders used by [APT29](https://attack.mitre.org/groups/G0016) since at least 2021. ## Techniques used - T1036 Masquerading - T1140 Deobfuscate/Decode Files or Information - T1204.002 Malicious File - T1218.011 Rundll32 - T1480 Execution Guardrails - T1497.001 System Checks ## Used by - G0016 APT29 | K20: ee34623e-b92f-55b0-bf27-6b757ee1681d | L20: malware--b4783be3-35d9-4a56-ac8d-1f3e1c9d9a84 | M20: https://attack.mitre.org/software/S0637
A21: p04 | B21: RAG | C21: 5 | D21: 0.25 | E21: T1001.003 | F21: Protocol or Service Impersonation | G21: sub-technique | H21: 6/8 | J21: # T1001.003 - Protocol or Service Impersonation requests. - S0387 KeyBoy (software): [KeyBoy](https://attack.mitre.org/software/S0387) uses custom SSL libraries to impersonate SSL in C2 traffic. - S0586 TAINTEDSCRIBE (software): [TAINTEDSCRIBE](https://attack.mitre.org/software/S0586) has used FakeTLS for session authentication. - S0022 Uroburos (software): [Uroburos](https://attack.mitre.org/software/S0022) can use custom communication methodologies that ride over common protocols including TCP, UDP, HTTP, SMTP, and DNS in order to blend with normal network traffic. - S0245 BADCALL (software): [BADCALL](https://attack.mitre.org/software/S0245) uses a FakeTLS method during C2. - S0154 Cobalt Strike (software): [Cobalt Strike](https://attack.mitre.org/software/S0154) can leverage the HTTP protocol for C2 communication, while hiding the actual data in either an HTTP header, URI parameter, the transaction body, or appending it to the URI. [Cobalt Strike](https://attack.mitre.org/software/S0154) has also added Host: ocsp.verisign.com to HTTP headers to mimic Online Certificate Status Protocol (OCSP) traffic. | K21: a8f8bb82-ac11-5f17-b51c-536281194ec5 | L21: attack-pattern--c325b232-d5bc-4dde-a3ec-71f3db9e8adc | M21: https://attack.mitre.org/techniques/T1001/003
A22: p05 | B22: RAG | C22: 1 | D22: 0.75 | E22: T1550.003 | F22: Pass the Ticket | G22: sub-technique | H22: 5/5 | J22: # T1550.003 - Pass the Ticket account password once, force replication, and then change the password a second time. Consider rotating the KRBTGT account password every 180 days. ## Procedure examples - G0050 APT32 (group): [APT32](https://attack.mitre.org/groups/G0050) successfully gained remote access by using pass the ticket. - G0016 APT29 (group): [APT29](https://attack.mitre.org/groups/G0016) used Kerberos ticket attacks for lateral movement. - G0060 BRONZE BUTLER (group): [BRONZE BUTLER](https://attack.mitre.org/groups/G0060) has created forged Kerberos Ticket Granting Ticket (TGT) and Ticket Granting Service (TGS) tickets to maintain administrative access. - S0053 SeaDuke (software): Some [SeaDuke](https://attack.mitre.org/software/S0053) samples have a module to use pass the ticket with Kerberos for authentication. - S0002 Mimikatz (software): [Mimikatz](https://attack.mitre.org/software/S0002)’s <code>LSADUMP::DCSync</code> and <code>KERBEROS::PTT</code> modules implement the three steps required to extract the krbtgt account hash and create/use Kerberos tickets. - S0192 Pupy (software): [Pupy](https://attack.mitre.org/software/S0192) can also perform pass-the-ticket. | K22: 750bebf0-a34b-5f77-9ddb-6fe2a3f246ba | L22: attack-pattern--7b211ac6-c815-4189-93a9-ab415deca926 | M22: https://attack.mitre.org/techniques/T1550/003
A23: p05 | B23: RAG | C23: 2 | D23: 0.5556 | E23: T1550.003 | F23: Pass the Ticket | G23: sub-technique | H23: 1/5 | J23: # T1550.003 - Pass the Ticket Type: sub-technique | Domain: enterprise-attack | ATT&CK version: 19.2 Tactics: lateral-movement Platforms: Windows Sub-technique of: T1550 Use Alternate Authentication Material ## Description Adversaries may “pass the ticket” using stolen Kerberos tickets to move laterally within an environment, bypassing normal system access controls. Pass the ticket (PtT) is a method of authenticating to a system using Kerberos tickets without having access to an account's password. Kerberos authentication can be used as the first step to lateral movement to a remote system. When preforming PtT, valid Kerberos tickets for [Valid Accounts](https://attack.mitre.org/techniques/T1078) are captured by [OS Credential Dumping](https://attack.mitre.org/techniques/T1003). A user's service tickets or ticket granting ticket (TGT) may be obtained, depending on the level of access. A service ticket allows for access to a particular resource, whereas a TGT can be used to request service tickets from the Ticket Granting Service (TGS) to access any resource the user has privileges to access. | K23: 7056425c-0a49-5208-8a73-967b7b0834c4 | L23: attack-pattern--7b211ac6-c815-4189-93a9-ab415deca926 | M23: https://attack.mitre.org/techniques/T1550/003
A24: p05 | B24: RAG | C24: 3 | D24: 0.4444 | E24: T1558.003 | F24: Kerberoasting | G24: sub-technique | H24: 4/7 | J24: # T1558.003 - Kerberoasting outside normal usage baselines. Also correlates suspicious process activity (e.g., Mimikatz invoking LSASS access) with Kerberos ticket anomalies. ## Mitigations - M1027 Password Policies: Ensure strong password length (ideally 25+ characters) and complexity for service accounts and that these passwords periodically expire. Also consider using Group Managed Service Accounts or another third party product such as password vaulting. - M1026 Privileged Account Management: Limit service accounts to minimal required privileges, including membership in privileged groups such as Domain Administrators. - M1041 Encrypt Sensitive Information: Enable AES Kerberos encryption (or another stronger encryption algorithm), rather than RC4, where possible. ## Procedure examples - C0024 SolarWinds Compromise (campaign): During the [SolarWinds Compromise](https://attack.mitre.org/campaigns/C0024), [APT29](https://attack.mitre.org/groups/G0016) obtained Ticket Granting Service (TGS) tickets for Active Directory Service Principle Names to crack offline. | K24: 304f8585-a1e6-5623-9b25-a13b95dab776 | L24: attack-pattern--f2877f7f-9a4c-4251-879f-1224e3006bee | M24: https://attack.mitre.org/techniques/T1558/003
A25: p05 | B25: RAG | C25: 4 | D25: 0.3333 | E25: S0079 | F25: MobileOrder | G25: software | H25: 1/1 | J25: # S0079 - MobileOrder Type: software | Domain: enterprise-attack | ATT&CK version: 19.2 Software type: malware | Aliases: n/a | Platforms: n/a ## Description [MobileOrder](https://attack.mitre.org/software/S0079) is a Trojan intended to compromise Android mobile devices. It has been used by [Scarlet Mimic](https://attack.mitre.org/groups/G0029). ## Techniques used - T1005 Data from Local System - T1041 Exfiltration Over C2 Channel - T1057 Process Discovery - T1082 System Information Discovery - T1083 File and Directory Discovery - T1105 Ingress Tool Transfer - T1217 Browser Information Discovery ## Used by - G0029 Scarlet Mimic | K25: daaa4cb7-91e0-5cc0-82b5-3b2bb2ca454a | L25: malware--463f68f1-5cde-4dc2-a831-68b73488f8f4 | M25: https://attack.mitre.org/software/S0079
A26: p05 | B26: RAG | C26: 5 | D26: 0.3026 | E26: T1558.001 | F26: Golden Ticket | G26: sub-technique | H26: 4/4 | J26: # T1558.001 - Golden Ticket account password once, force replication, and then change the password a second time. Consider rotating the KRBTGT account password every 180 days. ## Procedure examples - G0004 Ke3chang (group): [Ke3chang](https://attack.mitre.org/groups/G0004) has used [Mimikatz](https://attack.mitre.org/software/S0002) to generate Kerberos golden tickets. - S0633 Sliver (software): [Sliver](https://attack.mitre.org/software/S0633) incorporates the [Rubeus](https://attack.mitre.org/software/S1071) framework to allow for Kerberos ticket manipulation, specifically for forging Kerberos Golden Tickets. - S0363 Empire (software): [Empire](https://attack.mitre.org/software/S0363) can leverage its implementation of [Mimikatz](https://attack.mitre.org/software/S0002) to obtain and use golden tickets. - S0002 Mimikatz (software): [Mimikatz](https://attack.mitre.org/software/S0002)'s kerberos module can create golden tickets. - S1071 Rubeus (software): [Rubeus](https://attack.mitre.org/software/S1071) can forge a ticket-granting ticket. | K26: aad4bf53-34e3-513d-a9bc-9661d1985753 | L26: attack-pattern--768dce68-8d0d-477a-b01d-0eea98b963a1 | M26: https://attack.mitre.org/techniques/T1558/001
A27: p06 | B27: RAG | C27: 1 | D27: 0.5 | E27: S0347 | F27: AuditCred | G27: software | H27: 1/1 | J27: # S0347 - AuditCred Type: software | Domain: enterprise-attack | ATT&CK version: 19.2 Software type: malware | Aliases: AuditCred, Roptimizer | Platforms: Windows ## Description [AuditCred](https://attack.mitre.org/software/S0347) is a malicious DLL that has been used by [Lazarus Group](https://attack.mitre.org/groups/G0032) during their 2018 attacks. ## Techniques used - T1027.013 Encrypted/Encoded File - T1055 Process Injection - T1059.003 Windows Command Shell - T1070.004 File Deletion - T1083 File and Directory Discovery - T1090 Proxy - T1105 Ingress Tool Transfer - T1140 Deobfuscate/Decode Files or Information - T1543.003 Windows Service ## Used by - G0032 Lazarus Group | K27: 72ef6bf9-f375-5969-8f05-be8b358a87ba | L27: malware--24b4ce59-eaac-4c8b-8634-9b093b7ccd92 | M27: https://attack.mitre.org/software/S0347
A28: p06 | B28: RAG | C28: 2 | D28: 0.5 | E28: G0099 | F28: APT-C-36 | G28: group | H28: 1/3 | J28: # G0099 - APT-C-36 Type: group | Domain: enterprise-attack | ATT&CK version: 19.2 Aliases: APT-C-36, Blind Eagle, TAG-144, AguilaCiega, APT-Q-98 ## Description [APT-C-36](https://attack.mitre.org/groups/G0099) is a suspected South American threat group that has engaged in espionage and financially motivated operations since at least 2018. [APT-C-36](https://attack.mitre.org/groups/G0099) has targeted government institutions and entities in the financial, energy, and professional manufacturing sectors across Colombia and other Latin American countries. | K28: 82b5059b-bba0-51c6-a72e-3cf74d782138 | L28: intrusion-set--c4d50cdf-87ce-407d-86d8-862883485842 | M28: https://attack.mitre.org/groups/G0099
A29: p06 | B29: RAG | C29: 3 | D29: 0.386 | E29: S0263 | F29: TYPEFRAME | G29: software | H29: 1/1 | J29: # S0263 - TYPEFRAME Type: software | Domain: enterprise-attack | ATT&CK version: 19.2 Software type: malware | Aliases: TYPEFRAME | Platforms: Windows ## Description [TYPEFRAME](https://attack.mitre.org/software/S0263) is a remote access tool that has been used by [Lazarus Group](https://attack.mitre.org/groups/G0032). ## Techniques used - T1027.011 Fileless Storage - T1027.013 Encrypted/Encoded File - T1059.003 Windows Command Shell - T1059.005 Visual Basic - T1070.004 File Deletion - T1083 File and Directory Discovery - T1090 Proxy - T1105 Ingress Tool Transfer - T1112 Modify Registry - T1140 Deobfuscate/Decode Files or Information - T1204.002 Malicious File - T1543.003 Windows Service - T1571 Non-Standard Port - T1680 Local Storage Discovery - T1686.003 Windows Host Firewall ## Used by - G0032 Lazarus Group | K29: 77ea47c9-d1b8-55f4-8c12-d291eda4256b | L29: malware--7ba0fc46-197d-466d-8b9f-f1c64d5d81e5 | M29: https://attack.mitre.org/software/S0263
A30: p06 | B30: RAG | C30: 4 | D30: 0.3667 | E30: G0032 | F30: Lazarus Group | G30: group | H30: 1/6 | J30: # G0032 - Lazarus Group Type: group | Domain: enterprise-attack | ATT&CK version: 19.2 Aliases: Lazarus Group, Labyrinth Chollima, HIDDEN COBRA, Guardians of Peace, ZINC, NICKEL ACADEMY, Diamond Sleet ## Description [Lazarus Group](https://attack.mitre.org/groups/G0032) is a North Korean state-sponsored cyber threat group attributed to the Reconnaissance General Bureau (RGB). [Lazarus Group](https://attack.mitre.org/groups/G0032) has been active since at least 2009 and is reportedly responsible for the November 2014 destructive wiper attack on Sony Pictures Entertainment, identified by Novetta as part of Operation Blockbuster. Malware used by [Lazarus Group](https://attack.mitre.org/groups/G0032) correlates to other reported campaigns, including Operation Flame, Operation 1Mission, Operation Troy, DarkSeoul, and Ten Days of Rain. | K30: d7ced4c8-3901-5447-a0b3-c2fbf5b3ae9f | L30: intrusion-set--c93fccb1-e8e8-42cf-ae33-2ad1d183913a | M30: https://attack.mitre.org/groups/G0032
A31: p06 | B31: RAG | C31: 5 | D31: 0.3333 | E31: G0032 | F31: Lazarus Group | G31: group | H31: 3/6 | I31: SI | J31: # G0032 - Lazarus Group Group” as an umbrella term for multiple North Korean cyber operators conducting espionage, destructive attacks, and financially motivated campaigns. ## Techniques used - T1001.003 Protocol or Service Impersonation - T1005 Data from Local System - T1008 Fallback Channels - T1010 Application Window Discovery - T1012 Query Registry - T1016 System Network Configuration Discovery - T1021.001 Remote Desktop Protocol - T1021.002 SMB/Windows Admin Shares - T1021.004 SSH - T1027.007 Dynamic API Resolution - T1027.009 Embedded Payloads - T1027.013 Encrypted/Encoded File - T1033 System Owner/User Discovery - T1036.003 Rename Legitimate Utilities - T1036.004 Masquerade Task or Service - T1036.005 Match Legitimate Resource Name or Location - T1041 Exfiltration Over C2 Channel - T1046 Network Service Discovery - T1047 Windows Management Instrumentation - T1048.003 Exfiltration Over Unencrypted Non-C2 Protocol - T1049 System Network Connections Discovery - T1053.005 Scheduled Task - T1055.001 Dynamic-link Library Injection - T1056.001 Keylogging - T1057 Process Discovery - T1059.001 PowerShell - T1059.003 Windows Command Shell - T1059.005 Visual Basic - T1070 Indicator Removal - T1070.003 Clear Command History - T1070.004 File Deletion - T1070.006 Timestomp - T1071.001 Web Protocols - T1074.001 Local Data Staging - T1078 Valid Accounts - T108 | K31: d5484bb9-a214-54b4-8984-3d35d6ac7bfe | L31: intrusion-set--c93fccb1-e8e8-42cf-ae33-2ad1d183913a | M31: https://attack.mitre.org/groups/G0032
A32: p07 | B32: RAG | C32: 1 | D32: 1 | E32: T1110.003 | F32: Password Spraying | G32: sub-technique | H32: 8/9 | I32: SI | J32: # T1110.003 - Password Spraying and passwords. - G1030 Agrius (group): [Agrius](https://attack.mitre.org/groups/G1030) engaged in password spraying via SMB in victim environments. - G0007 APT28 (group): [APT28](https://attack.mitre.org/groups/G0007) has used a brute-force/password-spray tooling that operated in two modes: in password-spraying mode it conducted approximately four authentication attempts per hour per targeted account over the course of several days or weeks. [APT28](https://attack.mitre.org/groups/G0007) has also used a Kubernetes cluster to conduct distributed, large-scale password spray attacks. - G0032 Lazarus Group (group): [Lazarus Group](https://attack.mitre.org/groups/G0032) malware attempts to connect to Windows shares for lateral movement by using a generated list of usernames, which center around permutations of the username Administrator, and weak passwords. - G1001 HEXANE (group): [HEXANE](https://attack.mitre.org/groups/G1001) has used password spraying attacks to obtain valid credentials. - G0064 APT33 (group): [APT33](https://attack.mitre.org/groups/G0064) has used password spraying to gain access to target systems. | K32: bda60f05-afc9-5623-a785-ce6ba574ed8e | L32: attack-pattern--692074ae-bb62-4a5e-a735-02cb6bde458c | M32: https://attack.mitre.org/techniques/T1110/003
A33: p07 | B33: RAG | C33: 2 | D33: 0.5 | E33: T1110.003 | F33: Password Spraying | G33: sub-technique | H33: 6/9 | I33: SI | J33: # T1110.003 - Password Spraying outside defined organization IP ranges. Consider blocking risky authentication requests, such as those originating from anonymizing services/proxies. ## Procedure examples - C0051 APT28 Nearest Neighbor Campaign (campaign): During [APT28 Nearest Neighbor Campaign](https://attack.mitre.org/campaigns/C0051), [APT28](https://attack.mitre.org/groups/G0007) performed password-spray attacks against public facing services to validate credentials. - C0055 Quad7 Activity (campaign): [Quad7 Activity](https://attack.mitre.org/campaigns/C0055) has conducted a throttled variant of password spraying techniques that only utilized a single attempt to sign in within a 24-hour time period, eluding brute force detection thresholds. - G0125 HAFNIUM (group): [HAFNIUM](https://attack.mitre.org/groups/G0125) has gained initial access through password spray attacks. - G0077 Leafminer (group): [Leafminer](https://attack.mitre.org/groups/G0077) used a tool called Total SMB BruteForcer to perform internal password spraying. - G0016 APT29 (group): [APT29](https://attack.mitre.org/groups/G0016) has conducted brute force password spray attacks. | K33: ef7bd43e-42d4-5dd2-bc0e-1abd0cbf802f | L33: attack-pattern--692074ae-bb62-4a5e-a735-02cb6bde458c | M33: https://attack.mitre.org/techniques/T1110/003
A34: p07 | B34: RAG | C34: 3 | D34: 0.4762 | E34: T1110.003 | F34: Password Spraying | G34: sub-technique | H34: 1/9 | J34: # T1110.003 - Password Spraying Type: sub-technique | Domain: enterprise-attack | ATT&CK version: 19.2 Tactics: credential-access Platforms: Containers, ESXi, IaaS, Identity Provider, Linux, Network Devices, Office Suite, SaaS, Windows, macOS Sub-technique of: T1110 Brute Force ## Description Adversaries may use a single or small list of commonly used passwords against many different accounts to attempt to acquire valid account credentials. Password spraying uses one password (e.g. 'Password01'), or a small list of commonly used passwords, that may match the complexity policy of the domain. Logins are attempted with that password against many different accounts on a network to avoid account lockouts that would normally occur when brute forcing a single account with many passwords. Typically, management services over commonly used ports are used when password spraying. Commonly targeted services include the following: | K34: 157456b8-c03f-5096-98d8-1d1e43a443e8 | L34: attack-pattern--692074ae-bb62-4a5e-a735-02cb6bde458c | M34: https://attack.mitre.org/techniques/T1110/003
A35: p07 | B35: RAG | C35: 4 | D35: 0.4167 | E35: DET0487 | F35: Distributed Password Spraying via Authentication Failures Across Multiple Accounts | G35: detection-strategy | H35: 1/4 | J35: # DET0487 - Distributed Password Spraying via Authentication Failures Across Multiple Accounts Type: detection-strategy | Domain: enterprise-attack | ATT&CK version: 19.2 ## Detects techniques - T1110.003 Password Spraying | K35: f62c8db0-8f71-599b-b664-010c60d7b022 | L35: x-mitre-detection-strategy--84dfca59-e541-48a8-bb95-d7581a8f48d2 | M35: https://attack.mitre.org/detectionstrategies/DET0487
A36: p07 | B36: RAG | C36: 5 | D36: 0.3929 | E36: C0051 | F36: APT28 Nearest Neighbor Campaign | G36: campaign | H36: 2/2 | J36: # C0051 - APT28 Nearest Neighbor Campaign and wireless network connection) to enable Wi-Fi and use compromised credentials to connect to the victim network. ## Attributed to - G0007 APT28 ## Techniques used - T1003.002 Security Account Manager - T1003.003 NTDS - T1006 Direct Volume Access - T1016.002 Wi-Fi Discovery - T1021.001 Remote Desktop Protocol - T1021.002 SMB/Windows Admin Shares - T1059.001 PowerShell - T1059.003 Windows Command Shell - T1074.001 Local Data Staging - T1090.001 Internal Proxy - T1110.003 Password Spraying - T1140 Deobfuscate/Decode Files or Information - T1560.001 Archive via Utility - T1561.001 Disk Content Wipe - T1567 Exfiltration Over Web Service - T1584 Compromise Infrastructure - T1669 Wi-Fi Networks - T1686.003 Windows Host Firewall ## Software used - S0108 netsh - S1205 cipher.exe | K36: 9f28e3b3-46cd-5d07-ba72-040ae936815b | L36: campaign--a010610e-22cb-437e-bfde-b78861bdca7a | M36: https://attack.mitre.org/campaigns/C0051
A37: p08 | B37: RAG | C37: 1 | D37: 0.8333 | E37: T1110.003 | F37: Password Spraying | G37: sub-technique | H37: 1/9 | J37: # T1110.003 - Password Spraying Type: sub-technique | Domain: enterprise-attack | ATT&CK version: 19.2 Tactics: credential-access Platforms: Containers, ESXi, IaaS, Identity Provider, Linux, Network Devices, Office Suite, SaaS, Windows, macOS Sub-technique of: T1110 Brute Force ## Description Adversaries may use a single or small list of commonly used passwords against many different accounts to attempt to acquire valid account credentials. Password spraying uses one password (e.g. 'Password01'), or a small list of commonly used passwords, that may match the complexity policy of the domain. Logins are attempted with that password against many different accounts on a network to avoid account lockouts that would normally occur when brute forcing a single account with many passwords. Typically, management services over commonly used ports are used when password spraying. Commonly targeted services include the following: | K37: 157456b8-c03f-5096-98d8-1d1e43a443e8 | L37: attack-pattern--692074ae-bb62-4a5e-a735-02cb6bde458c | M37: https://attack.mitre.org/techniques/T1110/003
A38: p08 | B38: RAG | C38: 2 | D38: 0.8333 | E38: DET0487 | F38: Distributed Password Spraying via Authentication Failures Across Multiple Accounts | G38: detection-strategy | H38: 1/4 | J38: # DET0487 - Distributed Password Spraying via Authentication Failures Across Multiple Accounts Type: detection-strategy | Domain: enterprise-attack | ATT&CK version: 19.2 ## Detects techniques - T1110.003 Password Spraying | K38: f62c8db0-8f71-599b-b664-010c60d7b022 | L38: x-mitre-detection-strategy--84dfca59-e541-48a8-bb95-d7581a8f48d2 | M38: https://attack.mitre.org/detectionstrategies/DET0487
A39: p08 | B39: RAG | C39: 3 | D39: 0.2909 | E39: T1110.003 | F39: Password Spraying | G39: sub-technique | H39: 7/9 | J39: # T1110.003 - Password Spraying internal password spraying. - G0016 APT29 (group): [APT29](https://attack.mitre.org/groups/G0016) has conducted brute force password spray attacks. - G0114 Chimera (group): [Chimera](https://attack.mitre.org/groups/G0114) has used multiple password spraying attacks against victim's remote services to obtain valid user and administrator accounts. - G0122 Silent Librarian (group): [Silent Librarian](https://attack.mitre.org/groups/G0122) has used collected lists of names and e-mail accounts to use in password spraying attacks against private sector targets. - G1003 Ember Bear (group): [Ember Bear](https://attack.mitre.org/groups/G1003) has conducted password spraying against Outlook Web Access (OWA) infrastructure to identify valid user names and passwords. - G1030 Agrius (group): [Agrius](https://attack.mitre.org/groups/G1030) engaged in password spraying via SMB in victim environments. | K39: bc411276-2b2d-57fd-b20f-7feb6b7f2b0b | L39: attack-pattern--692074ae-bb62-4a5e-a735-02cb6bde458c | M39: https://attack.mitre.org/techniques/T1110/003
A40: p08 | B40: RAG | C40: 4 | D40: 0.25 | E40: G0114 | F40: Chimera | G40: group | H40: 3/3 | J40: # G0114 - Chimera Transfer - T1106 Native API - T1110.003 Password Spraying - T1110.004 Credential Stuffing - T1111 Multi-Factor Authentication Interception - T1114. ol Transfer - T1106 Native API - T1110.003 Password Spraying - T1110.004 Credential Stuffing - T1111 Multi-Factor Authentication Interception - T1114.001 Local Email Collection - T1114.002 Remote Email Collection - T1119 Automated Collection - T1124 System Time Discovery - T1133 External Remote Services - T1135 Network Share Discovery - T1201 Password Policy Discovery - T1213.002 Sharepoint - T1217 Browser Information Discovery - T1482 Domain Trust Discovery - T1550.002 Pass the Hash - T1556.001 Domain Controller Authentication - T1560.001 Archive via Utility - T1567.002 Exfiltration to Cloud Storage - T1569.002 Service Execution - T1570 Lateral Tool Transfer - T1572 Protocol Tunneling - T1574.001 DLL - T1588.002 Tool - T1589.001 Credentials - T1680 Local Storage Discovery - T1685.005 Clear Windows Event Logs ## Software used - S0029 PsExec - S0521 BloodHound - S0404 esentutl - S0039 Net - S0002 Mimikatz - S0154 Cobalt Strike | K40: 8e3c7f9a-1c02-5e07-a4ae-509c8f1580e1 | L40: intrusion-set--8c1f0187-0826-4320-bddc-5f326cfcfe2c | M40: https://attack.mitre.org/groups/G0114
A41: p08 | B41: RAG | C41: 5 | D41: 0.25 | E41: T1110.002 | F41: Password Cracking | G41: sub-technique | H41: 1/5 | J41: # T1110.002 - Password Cracking Type: sub-technique | Domain: enterprise-attack | ATT&CK version: 19.2 Tactics: credential-access Platforms: Identity Provider, Linux, macOS, Network Devices, Office Suite, Windows Sub-technique of: T1110 Brute Force ## Description Adversaries may use password cracking to attempt to recover usable credentials, such as plaintext passwords, when credential material such as password hashes are obtained. [OS Credential Dumping](https://attack.mitre.org/techniques/T1003) can be used to obtain password hashes, this may only get an adversary so far when [Pass the Hash](https://attack.mitre.org/techniques/T1550/002) is not an option. Further, adversaries may leverage [Data from Configuration Repository](https://attack.mitre.org/techniques/T1602) in order to obtain hashed credentials for network devices. | K41: 0204f726-7c2b-510e-a2cf-0d16f6c05c61 | L41: attack-pattern--1d24cdee-9ea2-4189-b08e-af110bf2435d | M41: https://attack.mitre.org/techniques/T1110/002
A42: p09 | B42: RAG | C42: 1 | D42: 0.5769 | E42: T1586.002 | F42: Email Accounts | G42: sub-technique | H42: 1/6 | J42: # T1586.002 - Email Accounts Type: sub-technique | Domain: enterprise-attack | ATT&CK version: 19.2 Tactics: resource-development Platforms: PRE Sub-technique of: T1586 Compromise Accounts ## Description Adversaries may compromise email accounts that can be used during targeting. Adversaries can use compromised email accounts to further their operations, such as leveraging them to conduct [Phishing for Information](https://attack.mitre.org/techniques/T1598), [Phishing](https://attack.mitre.org/techniques/T1566), or large-scale spam email campaigns. Utilizing an existing persona with a compromised email account may engender a level of trust in a potential victim if they have a relationship with, or knowledge of, the compromised persona. Compromised email accounts can also be used in the acquisition of infrastructure (ex: [Domains](https://attack.mitre.org/techniques/T1583/001)). | K42: 302a1537-027f-57a0-81b9-9063712870ce | L42: attack-pattern--3dc8c101-d4db-4f4d-8150-1b5a76ca5f1b | M42: https://attack.mitre.org/techniques/T1586/002
A43: p09 | B43: RAG | C43: 2 | D43: 0.5 | E43: T1566 | F43: Phishing | G43: technique | H43: 1/8 | J43: # T1566 - Phishing Type: technique | Domain: enterprise-attack | ATT&CK version: 19.2 Tactics: initial-access Platforms: Identity Provider, Linux, macOS, Office Suite, SaaS, Windows ## Description Adversaries may send phishing messages to gain access to victim systems. All forms of phishing are electronically delivered social engineering. Phishing can be targeted, known as spearphishing. In spearphishing, a specific individual, company, or industry will be targeted by the adversary. More generally, adversaries can conduct non-targeted phishing, such as in mass malware spam campaigns. | K43: af42649d-952f-5dfb-afab-8c8e51a00019 | L43: attack-pattern--a62a8db3-f23a-4d8f-afd6-9dbc77e7813b | M43: https://attack.mitre.org/techniques/T1566
A44: p09 | B44: RAG | C44: 3 | D44: 0.35 | E44: T1566 | F44: Phishing | G44: technique | H44: 2/8 | J44: # T1566 - Phishing or industry will be targeted by the adversary. More generally, adversaries can conduct non-targeted phishing, such as in mass malware spam campaigns. Adversaries may send victims emails containing malicious attachments or links, typically to execute malicious code on victim systems. Phishing may also be conducted via third-party services, like social media platforms. Phishing may also involve social engineering techniques, such as posing as a trusted source, as well as evasive techniques such as removing or manipulating emails or metadata/headers from compromised accounts being abused to send messages (e.g., [Email Hiding Rules](https://attack.mitre.org/techniques/T1564/008)). Another way to accomplish this is by [Email Spoofing](https://attack.mitre.org/techniques/T1684/002) the identity of the sender, which can be used to fool both the human recipient as well as automated security tools, or by including the intended target as a party to an existing email thread that includes malicious files or links (i.e., "thread hijacking"). | K44: 6a49f47f-97c7-51c1-9b8c-11a512eb628c | L44: attack-pattern--a62a8db3-f23a-4d8f-afd6-9dbc77e7813b | M44: https://attack.mitre.org/techniques/T1566
A45: p09 | B45: RAG | C45: 4 | D45: 0.3333 | E45: T1585.002 | F45: Email Accounts | G45: sub-technique | H45: 1/8 | J45: # T1585.002 - Email Accounts Type: sub-technique | Domain: enterprise-attack | ATT&CK version: 19.2 Tactics: resource-development Platforms: PRE Sub-technique of: T1585 Establish Accounts ## Description Adversaries may create email accounts that can be used during targeting. Adversaries can use accounts created with email providers to further their operations, such as leveraging them to conduct [Phishing for Information](https://attack.mitre.org/techniques/T1598) or [Phishing](https://attack.mitre.org/techniques/T1566). Establishing email accounts may also allow adversaries to abuse free services – such as trial periods – to [Acquire Infrastructure](https://attack.mitre.org/techniques/T1583) for follow-on purposes. Adversaries may also take steps to cultivate a persona around the email account, such as through use of [Social Media Accounts](https://attack.mitre.org/techniques/T1585/001), to increase the chance of success of follow-on behaviors. Created email accounts can also be used in the acquisition of infrastructure (ex: [Domains](https://attack.mitre.org/techniques/T1583/001)). | K45: e3dc1b98-151d-514e-a176-c74fb584fe19 | L45: attack-pattern--65013dd2-bc61-43e3-afb5-a14c4fa7437a | M45: https://attack.mitre.org/techniques/T1585/002
A46: p09 | B46: RAG | C46: 5 | D46: 0.3333 | E46: T1566 | F46: Phishing | G46: technique | H46: 6/8 | I46: SI | J46: # T1566 - Phishing email authentication mechanisms to filter messages based on validity checks of the sender domain (using SPF) and integrity of messages (using DKIM). Enabling these mechanisms within an organization (through policies such as DMARC) may enable recipients (intra-org and cross domain) to perform similar message filtering and validation. - M1047 Audit: Perform audits or scans of systems, permissions, insecure software, insecure configurations, etc. to identify potential weaknesses. ## Sub-techniques - T1566.002 Spearphishing Link - T1566.001 Spearphishing Attachment - T1566.004 Spearphishing Voice - T1566.003 Spearphishing via Service ## Procedure examples - G0094 Kimsuky (group): [Kimsuky](https://attack.mitre.org/groups/G0094) has used spearphishing to gain initial access and intelligence. - G1049 AppleJeus (group): [AppleJeus](https://attack.mitre.org/groups/G1049) has used spearphishing emails to distribute malicious payloads. - G0069 MuddyWater (group): [MuddyWater](https://attack.mitre.org/groups/G0069) has sent phishing emails to targets from the email address support@microsoftonlines[.]com. | K46: 22e1f629-ed75-57fb-9dfd-767e49dde3de | L46: attack-pattern--a62a8db3-f23a-4d8f-afd6-9dbc77e7813b | M46: https://attack.mitre.org/techniques/T1566
A47: p10 | B47: RAG | C47: 1 | D47: 1 | E47: T1056 | F47: Input Capture | G47: technique | H47: 1/5 | J47: # T1056 - Input Capture Type: technique | Domain: enterprise-attack | ATT&CK version: 19.2 Tactics: collection, credential-access Platforms: Linux, macOS, Network Devices, Windows ## Description Adversaries may use methods of capturing user input to obtain credentials or collect information. During normal system usage, users often provide credentials to various different locations, such as login pages/portals or system dialog boxes. Input capture mechanisms may be transparent to the user (e.g. [Credential API Hooking](https://attack.mitre.org/techniques/T1056/004)) or rely on deceiving the user into providing input into what they believe to be a genuine service (e.g. [Web Portal Capture](https://attack.mitre.org/techniques/T1056/003)). | K47: 49082e7a-665e-52fc-913f-e16e250c69fc | L47: attack-pattern--bb5a00de-e086-4859-a231-fa793f6797e2 | M47: https://attack.mitre.org/techniques/T1056
A48: p10 | B48: RAG | C48: 2 | D48: 0.4167 | E48: T1056.003 | F48: Web Portal Capture | G48: sub-technique | H48: 1/4 | J48: # T1056.003 - Web Portal Capture Type: sub-technique | Domain: enterprise-attack | ATT&CK version: 19.2 Tactics: collection, credential-access Platforms: Linux, macOS, Windows Sub-technique of: T1056 Input Capture ## Description Adversaries may install code on externally facing portals, such as a VPN login page, to capture and transmit credentials of users who attempt to log into the service. For example, a compromised login page may log provided user credentials before logging the user in to the service. This variation on input capture may be conducted post-compromise using legitimate administrative access as a backup measure to maintain network access through [External Remote Services](https://attack.mitre.org/techniques/T1133) and [Valid Accounts](https://attack.mitre.org/techniques/T1078) or as part of the initial compromise by exploitation of the externally facing web service. | K48: 53bb75a3-204c-582f-aebf-0aa453578979 | L48: attack-pattern--69e5226d-05dc-4f15-95d7-44f5ed78d06e | M48: https://attack.mitre.org/techniques/T1056/003
A49: p10 | B49: RAG | C49: 3 | D49: 0.3929 | E49: T1056.001 | F49: Keylogging | G49: sub-technique | H49: 1/7 | J49: # T1056.001 - Keylogging Type: sub-technique | Domain: enterprise-attack | ATT&CK version: 19.2 Tactics: collection, credential-access Platforms: Linux, macOS, Network Devices, Windows Sub-technique of: T1056 Input Capture ## Description Adversaries may log user keystrokes to intercept credentials as the user types them. Keylogging is likely to be used to acquire credentials for new access opportunities when [OS Credential Dumping](https://attack.mitre.org/techniques/T1003) efforts are not effective, and may require an adversary to intercept keystrokes on a system for a substantial period of time before credentials can be successfully captured. In order to increase the likelihood of capturing credentials quickly, an adversary may also perform actions such as clearing browser cookies to force users to reauthenticate to systems. Keylogging is the most prevalent type of input capture, with many different ways of intercepting keystrokes. Some methods include: | K49: 9552e904-33ef-5bad-a469-7fa1bf0d2107 | L49: attack-pattern--09a60ea3-a8d1-4ae5-976e-5783248b72a4 | M49: https://attack.mitre.org/techniques/T1056/001
A50: p10 | B50: RAG | C50: 4 | D50: 0.3833 | E50: DET0102 | F50: Behavioral Detection of Input Capture Across Platforms | G50: detection-strategy | H50: 1/2 | J50: # DET0102 - Behavioral Detection of Input Capture Across Platforms Type: detection-strategy | Domain: enterprise-attack | ATT&CK version: 19.2 ## Detects techniques - T1056 Input Capture ## Analytics - AN0282 [Windows]: Monitors for abnormal process behavior and API calls like SetWindowsHookEx, GetAsyncKeyState, or device input polling commonly used for keystroke logging. (log sources: WinEventLog:Security, WinEventLog:Sysmon) | tunable elements: TargetImage - Can be scoped to sensitive GUI processes like explorer.exe or winlogon.exe; TimeWindow - Time threshold for detecting multiple suspicious accesses - AN0283 [Linux]: Detects use of tools/scripts accessing input devices like /dev/input/* or evdev via suspicious processes lacking GUI context. (log sources: auditd:SYSCALL) | tunable elements: ProcessName - Unusual process accessing device files; DevicePath - Typically /dev/input/*, but tunable to exact endpoint config - AN0284 [macOS]: Monitors for TCC-bypassing or unauthorized access to input services like IOHIDSystem or Quartz Event Services used in keylogging or screen monitoring. | K50: b125294d-a3b8-5227-a30b-108b917e557a | L50: x-mitre-detection-strategy--c922d994-74bd-4847-a870-c0ae216318c9 | M50: https://attack.mitre.org/detectionstrategies/DET0102
A51: p10 | B51: RAG | C51: 5 | D51: 0.3333 | E51: T1056.001 | F51: Keylogging | G51: sub-technique | H51: 2/7 | J51: # T1056.001 - Keylogging to systems. Keylogging is the most prevalent type of input capture, with many different ways of intercepting keystrokes. Some methods include: * Hooking API callbacks used for processing keystrokes. Unlike [Credential API Hooking](https://attack.mitre.org/techniques/T1056/004), this focuses solely on API functions intended for processing keystroke data. * Reading raw keystroke data from the hardware buffer. * Windows Registry modifications. * Custom drivers. * [Modify System Image](https://attack.mitre.org/techniques/T1601) may provide adversaries with hooks into the operating system of network devices to read raw keystrokes for login sessions. | K51: 1e3aef33-c042-58ea-a36d-b1176cfd929c | L51: attack-pattern--09a60ea3-a8d1-4ae5-976e-5783248b72a4 | M51: https://attack.mitre.org/techniques/T1056/001
A52: p11 | B52: RAG | C52: 1 | D52: 0.5 | E52: TA0002 | F52: Execution | G52: tactic | H52: 2/2 | J52: # TA0002 - Execution a network or stealing data. For example, an adversary might use a remote access tool to run a PowerShell script that does Remote System Discovery. ## Techniques in this tactic - T1047 Windows Management Instrumentation - T1053 Scheduled Task/Job - T1059 Command and Scripting Interpreter - T1072 Software Deployment Tools - T1106 Native API - T1127 Trusted Developer Utilities Proxy Execution - T1129 Shared Modules - T1197 BITS Jobs - T1203 Exploitation for Client Execution - T1204 User Execution - T1559 Inter-Process Communication - T1569 System Services - T1574 Hijack Execution Flow - T1609 Container Administration Command - T1610 Deploy Container - T1648 Serverless Execution - T1651 Cloud Administration Command - T1674 Input Injection - T1675 ESXi Administration Command - T1677 Poisoned Pipeline Execution | K52: 57665f89-6f5d-57ec-8cfb-d409cf0b4a97 | L52: x-mitre-tactic--4ca45d45-df4d-4613-8980-bac22d278fa5 | M52: https://attack.mitre.org/tactics/TA0002
A53: p11 | B53: RAG | C53: 2 | D53: 0.5 | E53: T1683 | F53: Generate Content | G53: technique | H53: 3/3 | J53: # T1683 - Generate Content detection difficult for defenders. Detection efforts may be focused on related stages of the adversary lifecycle, such as during Initial Access. ## Mitigations - M1056 Pre-compromise: This technique cannot be easily mitigated with preventive controls since it is based on behaviors performed outside of the scope of enterprise defenses and controls. Efforts should focus on designing defenses that are not reliant on atomic indicators. ## Sub-techniques - T1683.001 Written Content - T1683.002 Audio-Visual Content ## Procedure examples - C0062 Anthropic AI-orchestrated Campaign (campaign): During the [Anthropic AI-orchestrated Campaign](https://attack.mitre.org/campaigns/C0062), the adversary utilized Claude Code to automatically generate comprehensive documentation throughout the phases of the attack, including discovered services, harvested credentials, sensitive data, exploitation techniques, and complete attack progression. | K53: dc4c60b8-5e00-5802-a63c-64dc3695a236 | L53: attack-pattern--b512fb8a-18dd-4bfc-bbad-acbaaeb7dde3 | M53: https://attack.mitre.org/techniques/T1683
A54: p11 | B54: RAG | C54: 3 | D54: 0.3333 | E54: T1040 | F54: Network Sniffing | G54: technique | H54: 4/11 | J54: # T1040 - Network Sniffing may perform network captures using [Network Device CLI](https://attack.mitre.org/techniques/T1059/008) commands such as `monitor capture`. ## Detection strategies - DET0314 Detection Strategy for Network Sniffing Across Platforms - AN0875 [Windows]: Detects suspicious execution of network monitoring tools (e.g., Wireshark, tshark, Microsoft Message Analyzer), driver loading indicative of promiscuous mode, or non-admin user privilege escalation to access NICs for capture. - AN0876 [Linux]: Correlates interface mode changes to promiscuous with execution of sniffing tools like tcpdump, tshark, or custom pcap libraries. Detects abnormal NIC configurations and unauthorized sniffing from non-root sessions. - AN0877 [macOS]: Detects enabling of interface sniffing via packet capture tools or AppleScript triggering `tcpdump`. Leverages Unified Logs and process lineage to identify suspicious use of `pfctl`, `tcpdump`, or `libpcap` libraries. - AN0878 [IaaS]: Detects creation of traffic mirroring sessions (e.g., AWS VPC Traffic Mirroring, Azure vTAP) that redirect traffic from critical assets to other virtual instances, often followed by file creation or session establishment. | K54: b616fa4b-7322-5a04-a57b-56babba5fb56 | L54: attack-pattern--3257eb21-f9a7-4430-8de1-d8b6e288f529 | M54: https://attack.mitre.org/techniques/T1040
A55: p11 | B55: RAG | C55: 4 | D55: 0.3333 | E55: T1552.008 | F55: Chat Messages | G55: sub-technique | H55: 1/4 | J55: # T1552.008 - Chat Messages Type: sub-technique | Domain: enterprise-attack | ATT&CK version: 19.2 Tactics: credential-access Platforms: SaaS, Office Suite Sub-technique of: T1552 Unsecured Credentials ## Description Adversaries may directly collect unsecured credentials stored or passed through user communication services. Credentials may be sent and stored in user chat communication applications such as email, chat services like Slack or Teams, collaboration tools like Jira or Trello, and any other services that support user communication. Users may share various forms of credentials (such as usernames and passwords, API keys, or authentication tokens) on private or public corporate internal communications channels. | K55: 94ece3fd-e305-5ee5-991d-3a563d13b80a | L55: attack-pattern--9664ad0e-789e-40ac-82e2-d7b17fbe8fb3 | M55: https://attack.mitre.org/techniques/T1552/008
A56: p11 | B56: RAG | C56: 5 | D56: 0.2714 | E56: TA0011 | F56: Command and Control | G56: tactic | H56: 1/1 | J56: # TA0011 - Command and Control Type: tactic | Domain: enterprise-attack | ATT&CK version: 19.2 Shortname: command-and-control ## Description The adversary is trying to communicate with compromised systems to control them. Command and Control consists of techniques that adversaries may use to communicate with systems under their control within a victim network. Adversaries commonly attempt to mimic normal, expected traffic to avoid detection. There are many ways an adversary can establish command and control with various levels of stealth depending on the victim’s network structure and defenses. ## Techniques in this tactic - T1001 Data Obfuscation - T1008 Fallback Channels - T1071 Application Layer Protocol - T1090 Proxy - T1092 Communication Through Removable Media - T1095 Non-Application Layer Protocol - T1102 Web Service - T1104 Multi-Stage Channels - T1105 Ingress Tool Transfer - T1132 Data Encoding - T1205 Traffic Signaling - T1219 Remote Access Tools - T1568 Dynamic Resolution - T1571 Non-Standard Port - T1572 Protocol Tunneling - T1573 Encrypted Channel - T1659 Content Injection - T1665 Hide Infrastructure | K56: a0d301c9-8f03-56e0-b461-3ea0fd74d96e | L56: x-mitre-tactic--f72804c5-f15a-449e-a5da-2eecd181f813 | M56: https://attack.mitre.org/tactics/TA0011
A57: p12 | B57: RAG | C57: 1 | D57: 0.5 | E57: C0026 | F57: C0026 | G57: campaign | H57: 1/1 | J57: # C0026 - C0026 Type: campaign | Domain: enterprise-attack | ATT&CK version: 19.2 Aliases: C0026 | First seen: 2022-08-01 | Last seen: 2022-09-01 ## Description [C0026](https://attack.mitre.org/campaigns/C0026) was a campaign identified in September 2022 that included the selective distribution of [KOPILUWAK](https://attack.mitre.org/software/S1075) and [QUIETCANARY](https://attack.mitre.org/software/S1076) malware to previous [ANDROMEDA](https://attack.mitre.org/software/S1074) malware victims in Ukraine through re-registered [ANDROMEDA](https://attack.mitre.org/software/S1074) C2 domains. Several tools and tactics used during [C0026](https://attack.mitre.org/campaigns/C0026) were consistent with historic [Turla](https://attack.mitre.org/groups/G0010) operations. ## Techniques used - T1005 Data from Local System - T1030 Data Transfer Size Limits - T1105 Ingress Tool Transfer - T1560.001 Archive via Utility - T1568 Dynamic Resolution - T1583.001 Domains ## Software used - S0039 Net - S1074 ANDROMEDA - S1076 QUIETCANARY - S0104 netstat - S1075 KOPILUWAK - S0099 Arp | K57: 9888dea1-f3ec-5e03-b541-8e05afd7c088 | L57: campaign--c89fa3ff-4773-4daf-8aec-d8f43f10116e | M57: https://attack.mitre.org/campaigns/C0026
A58: p12 | B58: RAG | C58: 2 | D58: 0.5 | E58: S9044 | F58: Kali365 | G58: software | H58: 1/2 | J58: # S9044 - Kali365 Type: software | Domain: enterprise-attack | ATT&CK version: 19.2 Software type: malware | Aliases: Kali365 | Platforms: IaaS, macOS, Windows ## Description [Kali365](https://attack.mitre.org/software/S9044) is a Phishing-as-a-Service (PHaaS) kit first observed in April 2026 that generates victim-targeted lures across multiple operating systems to induce users into copying and pasting actor-controlled commands for local execution. [Kali365](https://attack.mitre.org/software/S9044) incorporates on-demand device code generation and mirrors the copy-paste execution tradecraft associated with ClickFix. Operators have used [Kali365](https://attack.mitre.org/software/S9044) to harvest victims' OAuth tokens and session cookies through adversary-in-the-middle (AiTM) interception, enabling account takeover. [Kali365](https://attack.mitre.org/software/S9044) PHaaS was first observed in April 2026. [Kali365](https://attack.mitre.org/software/S9044) has also been affiliated with other branding to include Octopi365 and Freedom365. | K58: 5ee65033-bb02-5e33-a22a-e68d67f875c3 | L58: malware--f5a56c26-e192-489d-a77e-a8b38fd70eee | M58: https://attack.mitre.org/software/S9044
... A66: p13 | B66: RAG | C66: 5 | D66: 0.2917 | E66: T1059.009 | F66: Cloud API | G66: sub-technique | H66: 1/4 | J66: # T1059.009 - Cloud API Type: sub-technique | Domain: enterprise-attack | ATT&CK version: 19.2 Tactics: execution Platforms: IaaS, Identity Provider, Office Suite, SaaS Sub-technique of: T1059 Command and Scripting Interpreter ## Description Adversaries may abuse cloud APIs to execute malicious commands. APIs available in cloud environments provide various functionalities and are a feature-rich method for programmatic access to nearly all aspects of a tenant. These APIs may be utilized through various methods such as command line interpreters (CLIs), in-browser Cloud Shells, [PowerShell](https://attack.mitre.org/techniques/T1059/001) modules like Azure for PowerShell, or software developer kits (SDKs) available for languages such as [Python](https://attack.mitre.org/techniques/T1059/006). Cloud API functionality may allow for administrative access across all major services in a tenant such as compute, storage, identity and access management (IAM), networking, and security policies. | K66: 60d08f9a-0633-524e-8298-fe7bc19f2408 | L66: attack-pattern--55bb4471-ff1f-43b4-88c1-c9384ec47abf | M66: https://attack.mitre.org/techniques/T1059/009
