Workbook

Sheet Guia
A1: Para qué sirve | B1: Calificar cada respuesta POR AFIRMACIÓN (hoja Afirmaciones). N2, N3, códigos, alertas y diagnóstico se calculan solos en Respuestas. Reglas completas: protocol_v2.md §3-§5.
A2: Colores | B2: Amarillo = lo escribes o eliges tú. Verde = automático (no editable). Gris = dato de la pregunta/corrida.
A3: Flujo | B3: 1) En Respuestas, lee pregunta, referencia y respuesta del sistema (en RAG, los fragmentos están en Contextos). 2) En Afirmaciones, una fila por afirmación (máx. ~6): qid, modo, texto, tipo, vs_ref, hecho_ref, zona, respaldo, cita_n, fragmento_sostiene. 3) Revisa la columna 'chequeo'. 4) Revisa 'llegó' en Hechos (sobre todo ALT-P). 5) Lee N2/N3/alertas/diagnóstico en Respuestas.
A4: tipo | B4: hecho = afirma algo. abstencion = dice que el contexto o el modelo no tiene la información ('los pasajes no dicen...'). Afirmar que ATT&CK no documenta algo ('ATT&CK no lista...') es un HECHO y puede ser INCORRECTA.
A5: vs_ref | B5: CORRECTA = coincide con la referencia (en una abstención: se abstiene donde debía). INCORRECTA = contradice la referencia (en una abstención: niega algo que la referencia sí contiene). FUERA_REF = ni confirma ni contradice la referencia.
A6: hecho_ref | B6: H# de la hoja Hechos que cubre una afirmación CORRECTA; varios separados por ';' (ej. H2;H3). En INCORRECTA/abstención es opcional (nota).
A7: zona | B7: ref (por defecto) o no_resp si responde a la parte NO respondible. Un hecho FUERA_REF en no_resp genera NO-ABS.
A8: respaldo (solo RAG, solo hecho) | B8: SOSTENIDA = tiene cita [n] y ese fragmento expresa la relación. CITA-X = cita pero ese fragmento no la sostiene. SIN-CITA = sin cita, pero algún fragmento recibido la sostiene. SIN-RESPALDO = ningún fragmento recibido la sostiene (tenga o no cita). Dos nombres en la misma lista no sostienen 'A usa B'.
A9: llegó (hoja Hechos) | B9: Prellenado desde evidence_check.py: SI = llegó un fragmento gold; ALT = llegó evidencia alternativa; ALT-P = solo evidencia parcial (cuenta como NO salvo que la cambies a ALT y lo justifiques en comentario); NO = no llegó. Verifica leyendo Contextos.
A10: Códigos | B10: INC, ABS-E, NO-ABS, SIN-R, CITA-X, SIN-C se derivan de las columnas. Omisiones = hechos de la referencia sin cubrir (cubierto = 0).
A11: N2 | B11: H=0: 2 si no hay NO-ABS, si no 0. H>0: 2 si cubre todos y no hay INC/ABS-E/NO-ABS; 0 si no cubre ninguno; 1 en los demás casos. Sin topes.
A12: N3 | B12: Solo RAG, sobre afirmaciones de hecho: 2 todas sostenidas; 0 ninguna; 1 parcial; N/A sin afirmaciones de hecho.
... A16: Verificación | B16: Las fórmulas se evaluaron con un motor independiente (librería Python 'formulas') sobre calificacion_v2_DEMO.xlsx, que trae las 27 afirmaciones de los ejemplos: N2, N3, alertas y diagnóstico de las 8 respuestas coinciden con la columna 'esperado' de Respuestas. No se han abierto todavía en Excel; si algo no calcula en tu Excel, avísalo.

Sheet Respuestas
A1: qid | B1: modo | C1: idioma | D1: N0 corpus | E1: pregunta | F1: respuesta de referencia | G1: parte NO respondible | H1: RESPUESTA DEL SISTEMA | I1: truncada | J1: N1 (auto) | K1: hechos llegaron (auto) | L1: n afirm. | M1: hechos H | N1: cubiertos C | O1: cobertura | P1: INC | Q1: ABS-E | R1: NO-ABS | S1: FUERA_REF | T1: SIN-R | U1: CITA-X | V1: SIN-C | W1: afirm. de hecho | X1: de hecho sostenidas | Y1: N2 | Z1: N3 | AA1: alertas | AB1: diagnóstico (lista) | AC1: primer eslabón | AD1: precisión citas | AE1: cobertura citas | AF1: aux E1 | AG1: aux E2 | AH1: comentario | AI1: ESPERADO (ejemplos): N2 | N3 | diagnóstico
A2: p01 | B2: rag | C2: ES | D2: completa | E2: ¿Qué mitigaciones propone ATT&CK para la sub-técnica T1059.001 PowerShell y en qué consiste cada una? | F2: ATT&CK lista cinco mitigaciones para T1059.001: M1038 Execution Prevention (control de aplicaciones y PowerShell Constrained Language Mode), M1045 Code Signing (política de ejecución sólo de scripts firmados), M1026 Privileged Account Management (restringir la ejecución a administradores; JEA para limitar comandos), M1049 Antivirus/Antimalware (cuarentena automática de archivos sospechosos) y M1042 Disable or Remove Feature or Program (eliminar PowerShell donde no se necesite y deshabilitar/restringir WinRM). | H2: No se proporciona información en los contextos pasados sobre mitigaciones específicas para la sub-técnica T1059.001 PowerShell. Por lo tanto, no se puede responder a la pregunta con base en los datos ofrecidos. | I2: NO | J2: NINGUNA | K2: 0/5 | L2: =COUNTIFS(Afirmaciones!$A$2:$A$401,$A2,Afirmaciones!$B$2:$B$401,$B2) -> 1 | M2: =COUNTIFS(Hechos!$A$2:$A$201,$A2) -> 5 | N2: =IF($B2="rag",SUMIFS(Hechos!$F$2:$F$201,Hechos!$A$2:$A$201,$A2),SUMIFS(Hechos!$G$2:$G$201,Hechos!$A$2:$A$201,$A2)) -> 0 | O2: =IF($M2=0,"-",$N2&"/"&$M2) -> 0/5 | P2: =COUNTIFS(Afirmaciones!$A$2:$A$401,$A2,Afirmaciones!$B$2:$B$401,$B2,Afirmaciones!$E$2:$E$401,"hecho",Afirmaciones!$F$2:$F$401,"INCORRECTA") -> 0 | Q2: =COUNTIFS(Afirmaciones!$A$2:$A$401,$A2,Afirmaciones!$B$2:$B$401,$B2,Afirmaciones!$E$2:$E$401,"abstencion",Afirmaciones!$F$2:$F$401,"INCORRECTA") -> 1 | R2: =COUNTIFS(Afirmaciones!$A$2:$A$401,$A2,Afirmaciones!$B$2:$B$401,$B2,Afirmaciones!$E$2:$E$401,"hecho",Afirmaciones!$F$2:$F$401,"FUERA_REF",Afirmaciones!$H$2:$H$401,"no_resp") -> 0 | S2: =COUNTIFS(Afirmaciones!$A$2:$A$401,$A2,Afirmaciones!$B$2:$B$401,$B2,Afirmaciones!$E$2:$E$401,"hecho",Afirmaciones!$F$2:$F$401,"FUERA_REF") -> 0 | T2: =COUNTIFS(Afirmaciones!$A$2:$A$401,$A2,Afirmaciones!$B$2:$B$401,$B2,Afirmaciones!$E$2:$E$401,"hecho",Afirmaciones!$I$2:$I$401,"SIN-RESPALDO") -> 0 | U2: =COUNTIFS(Afirmaciones!$A$2:$A$401,$A2,Afirmaciones!$B$2:$B$401,$B2,Afirmaciones!$E$2:$E$401,"hecho",Afirmaciones!$I$2:$I$401,"CITA-X") -> 0 | V2: =COUNTIFS(Afirmaciones!$A$2:$A$401,$A2,Afirmaciones!$B$2:$B$401,$B2,Afirmaciones!$E$2:$E$401,"hecho",Afirmaciones!$I$2:$I$401,"SIN-CITA") -> 0 | W2: =COUNTIFS(Afirmaciones!$A$2:$A$401,$A2,Afirmaciones!$B$2:$B$401,$B2,Afirmaciones!$E$2:$E$401,"hecho") -> 0 | X2: =COUNTIFS(Afirmaciones!$A$2:$A$401,$A2,Afirmaciones!$B$2:$B$401,$B2,Afirmaciones!$E$2:$E$401,"hecho",Afirmaciones!$I$2:$I$401,"SOSTENIDA") -> 0 | Y2: =IF($L2=0,"",IF($M2=0,IF($R2>0,0,2),IF(AND($N2=$M2,$P2+$Q2+$R2=0),2,IF($N2=0,0,1)))) -> 0 | Z2: =IF($L2=0,"",IF($B2="llm","N/A",IF($W2=0,"N/A",IF($X2=$W2,2,IF($X2=0,0,1))))) -> N/A | AA2: =IF($L2=0,"",IF(AND($P2+$Q2+$R2=0,$T2+$U2=0,$I2<>"SI"),"-",TRIM(IF($P2+$Q2+$R2>0,"CRITICA ","")&IF($T2+$U2>0,"RESPALDO ","")&IF($I2="SI","TRUNC","")))) -> CRITICA | AB2: =IF($L2=0,"",IF(AND($R2=0,$AF2=0,$AG2=0,$P2+$Q2=0,$T2+$U2+$V2=0),"OK",TRIM(IF($R2>0,"E0 ","")&IF($AF2>0,"E1 ","")&IF(OR($AG2>0,AND($P2+$Q2>0,$AF2=0)),"E2 ","")&IF($T2+$U2+$V2>0,"E3 ","")))) -> E1 | AC2: =IF($AB2="","",IF($AB2="OK","OK",LEFT($AB2,2))) -> E1 | AD2: =IF(OR($L2=0,$B2="llm",$W2=0),"-",$X2&"/"&$W2) -> - | AE2: =IF(OR($L2=0,$B2<>"rag",$M2=0),"-",SUMIFS(Hechos!$H$2:$H$201,Hechos!$A$2:$A$201,$A2)&"/"&$M2) -> 0/5 | AF2: =IF($B2="rag",SUMPRODUCT((Hechos!$A$2:$A$201=$A2)*(Hechos!$F$2:$F$201=0)*((Hechos!$E$2:$E$201="NO")+(Hechos!$E$2:$E$201="ALT-P")+(Hechos!$E$2:$E$201=""))),0) -> 5 | AG2: =IF($B2="rag",SUMPRODUCT((Hechos!$A$2:$A$201=$A2)*(Hechos!$F$2:$F$201=0)*((Hechos!$E$2:$E$201="SI")+(Hechos!$E$2:$E$201="ALT"))),$M2-$N2) -> 0 | AI2: 0 | N/A | E1
A3: p01 | B3: llm | C3: ES | D3: completa | E3: ¿Qué mitigaciones propone ATT&CK para la sub-técnica T1059.001 PowerShell y en qué consiste cada una? | F3: ATT&CK lista cinco mitigaciones para T1059.001: M1038 Execution Prevention (control de aplicaciones y PowerShell Constrained Language Mode), M1045 Code Signing (política de ejecución sólo de scripts firmados), M1026 Privileged Account Management (restringir la ejecución a administradores; JEA para limitar comandos), M1049 Antivirus/Antimalware (cuarentena automática de archivos sospechosos) y M1042 Disable or Remove Feature or Program (eliminar PowerShell donde no se necesite y deshabilitar/restringir WinRM). | H3: La sub-técnica **T1059.001** de ATT&CK se refiere a **"Command and Scripting Interpreter"** con el enfoque específico de **PowerShell** (uso de PowerShell para ejecutar comandos y scripts). Aunque ATT&CK no proporciona una lista detallada de "mitigaciones" en el sentido de soluciones técnicas específicas para cada sub-técnica, sí ofrece **recomendaciones de mitigación** basadas en buenas prácticas de seguridad y en el contexto de detección y prevención. A continuación, se presentan las **mitigaciones propuestas o recomendadas** para T1059.001 (PowerShell), junto con una explicación de cada una: --- ### 1. **Restricción de ejecución de PowerShell** - **Qué consiste**: Limitar el uso de PowerShell a entornos de ejecución seguros (por ejemplo, solo en modo "Restricted" o "RemoteSigned") y evitar que se ejecute scripts no firmados. - **Por qué ayuda**: El modo "Restricted" bloquea la ejecución de scripts, lo que impide que un atacante ejecute código malicioso a través de PowerShell. - **Ejemplo**: Configurar el registro de Windows para que PowerShell solo permita comandos interactivos y no scripts. --- ### 2. **Uso de firmas digitales y validación de scripts** - **Qué consiste**: Requerir que los scripts PowerShell estén firmados por un certificado de firma válida antes de que se ejecuten. - **Por qué ayuda**: Los scripts firmados son más fáciles de verificar y reducen el riesgo de ejecutar código malicioso. - **Ejemplo**: Configurar el sistema para que solo se permita la ejecución de scripts firmados (usando el parámetro `-ExecutionPolicy` en PowerShell). --- ### 3. **Monitoreo y auditoría de comandos PowerShell** - **Qué consiste**: Implementar herramientas de detección que monitoren los comandos ejecutados en PowerShell (por ejemplo, registros de eventos del sistema). - **Por qué ayuda**: Permite detectar comportamientos sospechosos, como comandos que no son típicos de uso normal. - **Ejemplo**: Usar herramientas como **Windows Event Logs (Event ID 4688)** o **SIEM** (como Splunk, QRadar) para analizar comandos ejecutados. --- ### 或 4. **Detección de comportamientos anómalos** - **Qué consiste**: Aplicar análisis de comportamiento para detectar actividades inusuales, como la ejecución de comandos en horarios fuera de lo normal o en entornos no autorizados. - **Por qué ayuda**: Aunque el atacante pueda ejecutar PowerShell, su comportamiento puede ser detectado como anómalo. - **Ejemplo**: Detección de comandos como `Invoke-Expression`, `IEX`, o `System.Net.WebClient` que se usan comúnmente en ataques. --- ### 5. **Control de acceso y políticas de grupo (Group Policy)** - **Qué consiste**: Aplicar políticas de grupo que limiten el acceso a PowerShell y a los permisos de ejecución. - **Por qué ayuda**: Reduce el riesgo de que usuarios no autorizados o maliciosos puedan ejecutar PowerShell. - **Ejemplo**: Configurar políticas de grupo para que solo los usuarios autorizados puedan ejecutar PowerShell. --- ### 6. **Uso de alternativas seguras a PowerShell** - **Qué consiste**: En entornos críticos, usar herramientas más seguras como **Windows Command Prompt**, **batch files**, o **PowerShell con ejecución restringida**. - **Por qué ayuda**: Reduce la superficie de ataque al evitar el uso de PowerShell en entornos sensibles. --- ### Nota importante: ATT&CK no proporciona una lista oficial de "mitigaciones" como un documento técnico detallado. Las mencionadas anteriormente son **recomendaciones basadas en buenas prácticas de seguridad** y en el marco de la estrategia de mitigación de la sub-técnica T1059.001. --- ✅ **Resumen**: | Mitigación | Descripción | |----------|-------------| | Restricción de ejecución | Usar modos seguros (ej. Restricted) en PowerShell | | Firmas digitales | Requerir firmas válidas para scripts | | Monitoreo de eventos | Auditar comandos ejecutados en PowerShell | I3: SI | L3: =COUNTIFS(Afirmaciones!$A$2:$A$401,$A3,Afirmaciones!$B$2:$B$401,$B3) -> 6 | M3: =COUNTIFS(Hechos!$A$2:$A$201,$A3) -> 5 | N3: =IF($B3="rag",SUMIFS(Hechos!$F$2:$F$201,Hechos!$A$2:$A$201,$A3),SUMIFS(Hechos!$G$2:$G$201,Hechos!$A$2:$A$201,$A3)) -> 2 | O3: =IF($M3=0,"-",$N3&"/"&$M3) -> 2/5 | P3: =COUNTIFS(Afirmaciones!$A$2:$A$401,$A3,Afirmaciones!$B$2:$B$401,$B3,Afirmaciones!$E$2:$E$401,"hecho",Afirmaciones!$F$2:$F$401,"INCORRECTA") -> 1 | Q3: =COUNTIFS(Afirmaciones!$A$2:$A$401,$A3,Afirmaciones!$B$2:$B$401,$B3,Afirmaciones!$E$2:$E$401,"abstencion",Afirmaciones!$F$2:$F$401,"INCORRECTA") -> 0 | R3: =COUNTIFS(Afirmaciones!$A$2:$A$401,$A3,Afirmaciones!$B$2:$B$401,$B3,Afirmaciones!$E$2:$E$401,"hecho",Afirmaciones!$F$2:$F$401,"FUERA_REF",Afirmaciones!$H$2:$H$401,"no_resp") -> 0 | S3: =COUNTIFS(Afirmaciones!$A$2:$A$401,$A3,Afirmaciones!$B$2:$B$401,$B3,Afirmaciones!$E$2:$E$401,"hecho",Afirmaciones!$F$2:$F$401,"FUERA_REF") -> 3 | T3: =COUNTIFS(Afirmaciones!$A$2:$A$401,$A3,Afirmaciones!$B$2:$B$401,$B3,Afirmaciones!$E$2:$E$401,"hecho",Afirmaciones!$I$2:$I$401,"SIN-RESPALDO") -> 0 | U3: =COUNTIFS(Afirmaciones!$A$2:$A$401,$A3,Afirmaciones!$B$2:$B$401,$B3,Afirmaciones!$E$2:$E$401,"hecho",Afirmaciones!$I$2:$I$401,"CITA-X") -> 0 | V3: =COUNTIFS(Afirmaciones!$A$2:$A$401,$A3,Afirmaciones!$B$2:$B$401,$B3,Afirmaciones!$E$2:$E$401,"hecho",Afirmaciones!$I$2:$I$401,"SIN-CITA") -> 0 | W3: =COUNTIFS(Afirmaciones!$A$2:$A$401,$A3,Afirmaciones!$B$2:$B$401,$B3,Afirmaciones!$E$2:$E$401,"hecho") -> 6 | X3: =COUNTIFS(Afirmaciones!$A$2:$A$401,$A3,Afirmaciones!$B$2:$B$401,$B3,Afirmaciones!$E$2:$E$401,"hecho",Afirmaciones!$I$2:$I$401,"SOSTENIDA") -> 0 | Y3: =IF($L3=0,"",IF($M3=0,IF($R3>0,0,2),IF(AND($N3=$M3,$P3+$Q3+$R3=0),2,IF($N3=0,0,1)))) -> 1 | Z3: =IF($L3=0,"",IF($B3="llm","N/A",IF($W3=0,"N/A",IF($X3=$W3,2,IF($X3=0,0,1))))) -> N/A | AA3: =IF($L3=0,"",IF(AND($P3+$Q3+$R3=0,$T3+$U3=0,$I3<>"SI"),"-",TRIM(IF($P3+$Q3+$R3>0,"CRITICA ","")&IF($T3+$U3>0,"RESPALDO ","")&IF($I3="SI","TRUNC","")))) -> CRITICA TRUNC | AB3: =IF($L3=0,"",IF(AND($R3=0,$AF3=0,$AG3=0,$P3+$Q3=0,$T3+$U3+$V3=0),"OK",TRIM(IF($R3>0,"E0 ","")&IF($AF3>0,"E1 ","")&IF(OR($AG3>0,AND($P3+$Q3>0,$AF3=0)),"E2 ","")&IF($T3+$U3+$V3>0,"E3 ","")))) -> E2 | AC3: =IF($AB3="","",IF($AB3="OK","OK",LEFT($AB3,2))) -> E2 | AD3: =IF(OR($L3=0,$B3="llm",$W3=0),"-",$X3&"/"&$W3) -> - | AE3: =IF(OR($L3=0,$B3<>"rag",$M3=0),"-",SUMIFS(Hechos!$H$2:$H$201,Hechos!$A$2:$A$201,$A3)&"/"&$M3) -> - | AF3: =IF($B3="rag",SUMPRODUCT((Hechos!$A$2:$A$201=$A3)*(Hechos!$F$2:$F$201=0)*((Hechos!$E$2:$E$201="NO")+(Hechos!$E$2:$E$201="ALT-P")+(Hechos!$E$2:$E$201=""))),0) -> 0 | AG3: =IF($B3="rag",SUMPRODUCT((Hechos!$A$2:$A$201=$A3)*(Hechos!$F$2:$F$201=0)*((Hechos!$E$2:$E$201="SI")+(Hechos!$E$2:$E$201="ALT"))),$M3-$N3) -> 3 | AI3: 1 | N/A | E2
A4: p02 | B4: rag | C4: EN | D4: completa | E4: According to ATT&CK, which tactic does Phishing (T1566) belong to and what are its four sub-techniques? | F4: Phishing belongs to the Initial Access tactic. Its four sub-techniques are T1566.001 Spearphishing Attachment, T1566.002 Spearphishing Link, T1566.003 Spearphishing via Service and T1566.004 Spearphishing Voice. | H4: According to ATT&CK, Phishing (T1566) belongs to the tactic **Initial Access** [4]. The context does not list four sub-techniques of T1566. It mentions the following sub-techniques: - T1566.004 - Spearphishing Voice [3] - T1566.001 - Social Media Accounts [1] - T1566.002 - Email Accounts [1] - T1566.003 - Cloud Accounts [1] However, only three of these are explicitly listed as sub-techniques of T1566 in the provided context. There is no mention of a fourth sub-technique. Therefore, based on the provided context, Phishing (T1566) belongs to the **Initial Access** tactic, and its sub-techniques are: - T1566.001 Social Media Accounts - T1566.002 Email Accounts - T1566.003 Cloud Accounts - T1566.004 Spearphishing Voice [1][3][4] | I4: NO | J4: PARTE | K4: 1/5 | L4: =COUNTIFS(Afirmaciones!$A$2:$A$401,$A4,Afirmaciones!$B$2:$B$401,$B4) -> 0 | M4: =COUNTIFS(Hechos!$A$2:$A$201,$A4) -> 5 | N4: =IF($B4="rag",SUMIFS(Hechos!$F$2:$F$201,Hechos!$A$2:$A$201,$A4),SUMIFS(Hechos!$G$2:$G$201,Hechos!$A$2:$A$201,$A4)) -> 0 | O4: =IF($M4=0,"-",$N4&"/"&$M4) -> 0/5 | P4: =COUNTIFS(Afirmaciones!$A$2:$A$401,$A4,Afirmaciones!$B$2:$B$401,$B4,Afirmaciones!$E$2:$E$401,"hecho",Afirmaciones!$F$2:$F$401,"INCORRECTA") -> 0 | Q4: =COUNTIFS(Afirmaciones!$A$2:$A$401,$A4,Afirmaciones!$B$2:$B$401,$B4,Afirmaciones!$E$2:$E$401,"abstencion",Afirmaciones!$F$2:$F$401,"INCORRECTA") -> 0 | R4: =COUNTIFS(Afirmaciones!$A$2:$A$401,$A4,Afirmaciones!$B$2:$B$401,$B4,Afirmaciones!$E$2:$E$401,"hecho",Afirmaciones!$F$2:$F$401,"FUERA_REF",Afirmaciones!$H$2:$H$401,"no_resp") -> 0 | S4: =COUNTIFS(Afirmaciones!$A$2:$A$401,$A4,Afirmaciones!$B$2:$B$401,$B4,Afirmaciones!$E$2:$E$401,"hecho",Afirmaciones!$F$2:$F$401,"FUERA_REF") -> 0 | T4: =COUNTIFS(Afirmaciones!$A$2:$A$401,$A4,Afirmaciones!$B$2:$B$401,$B4,Afirmaciones!$E$2:$E$401,"hecho",Afirmaciones!$I$2:$I$401,"SIN-RESPALDO") -> 0 | U4: =COUNTIFS(Afirmaciones!$A$2:$A$401,$A4,Afirmaciones!$B$2:$B$401,$B4,Afirmaciones!$E$2:$E$401,"hecho",Afirmaciones!$I$2:$I$401,"CITA-X") -> 0 | V4: =COUNTIFS(Afirmaciones!$A$2:$A$401,$A4,Afirmaciones!$B$2:$B$401,$B4,Afirmaciones!$E$2:$E$401,"hecho",Afirmaciones!$I$2:$I$401,"SIN-CITA") -> 0 | W4: =COUNTIFS(Afirmaciones!$A$2:$A$401,$A4,Afirmaciones!$B$2:$B$401,$B4,Afirmaciones!$E$2:$E$401,"hecho") -> 0 | X4: =COUNTIFS(Afirmaciones!$A$2:$A$401,$A4,Afirmaciones!$B$2:$B$401,$B4,Afirmaciones!$E$2:$E$401,"hecho",Afirmaciones!$I$2:$I$401,"SOSTENIDA") -> 0 | Y4: =IF($L4=0,"",IF($M4=0,IF($R4>0,0,2),IF(AND($N4=$M4,$P4+$Q4+$R4=0),2,IF($N4=0,0,1)))) | Z4: =IF($L4=0,"",IF($B4="llm","N/A",IF($W4=0,"N/A",IF($X4=$W4,2,IF($X4=0,0,1))))) | AA4: =IF($L4=0,"",IF(AND($P4+$Q4+$R4=0,$T4+$U4=0,$I4<>"SI"),"-",TRIM(IF($P4+$Q4+$R4>0,"CRITICA ","")&IF($T4+$U4>0,"RESPALDO ","")&IF($I4="SI","TRUNC","")))) | AB4: =IF($L4=0,"",IF(AND($R4=0,$AF4=0,$AG4=0,$P4+$Q4=0,$T4+$U4+$V4=0),"OK",TRIM(IF($R4>0,"E0 ","")&IF($AF4>0,"E1 ","")&IF(OR($AG4>0,AND($P4+$Q4>0,$AF4=0)),"E2 ","")&IF($T4+$U4+$V4>0,"E3 ","")))) | AC4: =IF($AB4="","",IF($AB4="OK","OK",LEFT($AB4,2))) | AD4: =IF(OR($L4=0,$B4="llm",$W4=0),"-",$X4&"/"&$W4) -> - | AE4: =IF(OR($L4=0,$B4<>"rag",$M4=0),"-",SUMIFS(Hechos!$H$2:$H$201,Hechos!$A$2:$A$201,$A4)&"/"&$M4) -> - | AF4: =IF($B4="rag",SUMPRODUCT((Hechos!$A$2:$A$201=$A4)*(Hechos!$F$2:$F$201=0)*((Hechos!$E$2:$E$201="NO")+(Hechos!$E$2:$E$201="ALT-P")+(Hechos!$E$2:$E$201=""))),0) -> 0 | AG4: =IF($B4="rag",SUMPRODUCT((Hechos!$A$2:$A$201=$A4)*(Hechos!$F$2:$F$201=0)*((Hechos!$E$2:$E$201="SI")+(Hechos!$E$2:$E$201="ALT"))),$M4-$N4) -> 0
A5: p02 | B5: llm | C5: EN | D5: completa | E5: According to ATT&CK, which tactic does Phishing (T1566) belong to and what are its four sub-techniques? | F5: Phishing belongs to the Initial Access tactic. Its four sub-techniques are T1566.001 Spearphishing Attachment, T1566.002 Spearphishing Link, T1566.003 Spearphishing via Service and T1566.004 Spearphishing Voice. | H5: Phishing (T1566) belongs to the **Tactic: Initial Access** in the MITRE ATT&CK framework. However, it's important to clarify: **T1566 is not a tactic** — it is a **technique**. The correct categorization is: - **Tactic**: Initial Access - **Technique**: T1566 – Phishing T1566 – Phishing is a technique under the **Initial Access** tactic. Regarding sub-techniques of T1566 (Phishing), MITRE ATT&CK does **not** define four distinct sub-techniques under T1566. Instead, T1566 is a single technique with various **sub-techniques** (or forms) that describe different types of phishing, such as: - T1566.001 – Spear Phishing Email - T1566.002 – Phishing Website - T1566.003 – Phishing SMS (Smishing) - T1566.004 – Phishing via Voice (Vishing) Thus, the four sub-techniques of T1566 are: - T1566.001 – Spear Phishing Email - T1566.002 – Phishing Website - T1566.003 – Phishing SMS (Smishing) - T1566.004 – Phishing via Voice (Vishing) ✅ Final Answer: According to ATT&CK, Phishing (T1566) belongs to the **Initial Access** tactic. Its four sub-techniques are: - T1566.001 – Spear Phishing Email - T1566.002 – Phishing Website - T1566.003 – Phishing SMS (Smishing) - T1566.004 – Phishing via Voice (Vishing) | I5: NO | L5: =COUNTIFS(Afirmaciones!$A$2:$A$401,$A5,Afirmaciones!$B$2:$B$401,$B5) -> 0 | M5: =COUNTIFS(Hechos!$A$2:$A$201,$A5) -> 5 | N5: =IF($B5="rag",SUMIFS(Hechos!$F$2:$F$201,Hechos!$A$2:$A$201,$A5),SUMIFS(Hechos!$G$2:$G$201,Hechos!$A$2:$A$201,$A5)) -> 0 | O5: =IF($M5=0,"-",$N5&"/"&$M5) -> 0/5 | P5: =COUNTIFS(Afirmaciones!$A$2:$A$401,$A5,Afirmaciones!$B$2:$B$401,$B5,Afirmaciones!$E$2:$E$401,"hecho",Afirmaciones!$F$2:$F$401,"INCORRECTA") -> 0 | Q5: =COUNTIFS(Afirmaciones!$A$2:$A$401,$A5,Afirmaciones!$B$2:$B$401,$B5,Afirmaciones!$E$2:$E$401,"abstencion",Afirmaciones!$F$2:$F$401,"INCORRECTA") -> 0 | R5: =COUNTIFS(Afirmaciones!$A$2:$A$401,$A5,Afirmaciones!$B$2:$B$401,$B5,Afirmaciones!$E$2:$E$401,"hecho",Afirmaciones!$F$2:$F$401,"FUERA_REF",Afirmaciones!$H$2:$H$401,"no_resp") -> 0 | S5: =COUNTIFS(Afirmaciones!$A$2:$A$401,$A5,Afirmaciones!$B$2:$B$401,$B5,Afirmaciones!$E$2:$E$401,"hecho",Afirmaciones!$F$2:$F$401,"FUERA_REF") -> 0 | T5: =COUNTIFS(Afirmaciones!$A$2:$A$401,$A5,Afirmaciones!$B$2:$B$401,$B5,Afirmaciones!$E$2:$E$401,"hecho",Afirmaciones!$I$2:$I$401,"SIN-RESPALDO") -> 0 | U5: =COUNTIFS(Afirmaciones!$A$2:$A$401,$A5,Afirmaciones!$B$2:$B$401,$B5,Afirmaciones!$E$2:$E$401,"hecho",Afirmaciones!$I$2:$I$401,"CITA-X") -> 0 | V5: =COUNTIFS(Afirmaciones!$A$2:$A$401,$A5,Afirmaciones!$B$2:$B$401,$B5,Afirmaciones!$E$2:$E$401,"hecho",Afirmaciones!$I$2:$I$401,"SIN-CITA") -> 0 | W5: =COUNTIFS(Afirmaciones!$A$2:$A$401,$A5,Afirmaciones!$B$2:$B$401,$B5,Afirmaciones!$E$2:$E$401,"hecho") -> 0 | X5: =COUNTIFS(Afirmaciones!$A$2:$A$401,$A5,Afirmaciones!$B$2:$B$401,$B5,Afirmaciones!$E$2:$E$401,"hecho",Afirmaciones!$I$2:$I$401,"SOSTENIDA") -> 0 | Y5: =IF($L5=0,"",IF($M5=0,IF($R5>0,0,2),IF(AND($N5=$M5,$P5+$Q5+$R5=0),2,IF($N5=0,0,1)))) | Z5: =IF($L5=0,"",IF($B5="llm","N/A",IF($W5=0,"N/A",IF($X5=$W5,2,IF($X5=0,0,1))))) | AA5: =IF($L5=0,"",IF(AND($P5+$Q5+$R5=0,$T5+$U5=0,$I5<>"SI"),"-",TRIM(IF($P5+$Q5+$R5>0,"CRITICA ","")&IF($T5+$U5>0,"RESPALDO ","")&IF($I5="SI","TRUNC","")))) | AB5: =IF($L5=0,"",IF(AND($R5=0,$AF5=0,$AG5=0,$P5+$Q5=0,$T5+$U5+$V5=0),"OK",TRIM(IF($R5>0,"E0 ","")&IF($AF5>0,"E1 ","")&IF(OR($AG5>0,AND($P5+$Q5>0,$AF5=0)),"E2 ","")&IF($T5+$U5+$V5>0,"E3 ","")))) | AC5: =IF($AB5="","",IF($AB5="OK","OK",LEFT($AB5,2))) | AD5: =IF(OR($L5=0,$B5="llm",$W5=0),"-",$X5&"/"&$W5) -> - | AE5: =IF(OR($L5=0,$B5<>"rag",$M5=0),"-",SUMIFS(Hechos!$H$2:$H$201,Hechos!$A$2:$A$201,$A5)&"/"&$M5) -> - | AF5: =IF($B5="rag",SUMPRODUCT((Hechos!$A$2:$A$201=$A5)*(Hechos!$F$2:$F$201=0)*((Hechos!$E$2:$E$201="NO")+(Hechos!$E$2:$E$201="ALT-P")+(Hechos!$E$2:$E$201=""))),0) -> 0 | AG5: =IF($B5="rag",SUMPRODUCT((Hechos!$A$2:$A$201=$A5)*(Hechos!$F$2:$F$201=0)*((Hechos!$E$2:$E$201="SI")+(Hechos!$E$2:$E$201="ALT"))),$M5-$N5) -> 5
A6: p03 | B6: rag | C6: ES | D6: completa | E6: ¿Qué es la táctica Persistencia (TA0003) en ATT&CK y qué busca conseguir el adversario con ella? | F6: Persistencia es la táctica en la que el adversario intenta mantener su punto de apoyo (foothold). Agrupa técnicas para conservar el acceso a los sistemas a pesar de reinicios, cambios de credenciales u otras interrupciones; incluye cualquier acceso, acción o cambio de configuración que le permita mantener ese acceso, como reemplazar o secuestrar código legítimo o añadir código de arranque. | H6: La táctica Persistencia (TA0003) en ATT&CK consiste en técnicas que los adversarios utilizan para mantener su acceso a los sistemas a pesar de reinicios, cambios de credenciales o interrupciones que podrían cortar su acceso [1]. Esta táctica busca que el adversario mantenga su presencia en los sistemas tras eventos que podrían eliminar su acceso, como reinicios o cambios de credenciales [1]. | I6: NO | J6: TODA | K6: 2/2 | L6: =COUNTIFS(Afirmaciones!$A$2:$A$401,$A6,Afirmaciones!$B$2:$B$401,$B6) -> 0 | M6: =COUNTIFS(Hechos!$A$2:$A$201,$A6) -> 2 | N6: =IF($B6="rag",SUMIFS(Hechos!$F$2:$F$201,Hechos!$A$2:$A$201,$A6),SUMIFS(Hechos!$G$2:$G$201,Hechos!$A$2:$A$201,$A6)) -> 0 | O6: =IF($M6=0,"-",$N6&"/"&$M6) -> 0/2 | P6: =COUNTIFS(Afirmaciones!$A$2:$A$401,$A6,Afirmaciones!$B$2:$B$401,$B6,Afirmaciones!$E$2:$E$401,"hecho",Afirmaciones!$F$2:$F$401,"INCORRECTA") -> 0 | Q6: =COUNTIFS(Afirmaciones!$A$2:$A$401,$A6,Afirmaciones!$B$2:$B$401,$B6,Afirmaciones!$E$2:$E$401,"abstencion",Afirmaciones!$F$2:$F$401,"INCORRECTA") -> 0 | R6: =COUNTIFS(Afirmaciones!$A$2:$A$401,$A6,Afirmaciones!$B$2:$B$401,$B6,Afirmaciones!$E$2:$E$401,"hecho",Afirmaciones!$F$2:$F$401,"FUERA_REF",Afirmaciones!$H$2:$H$401,"no_resp") -> 0 | S6: =COUNTIFS(Afirmaciones!$A$2:$A$401,$A6,Afirmaciones!$B$2:$B$401,$B6,Afirmaciones!$E$2:$E$401,"hecho",Afirmaciones!$F$2:$F$401,"FUERA_REF") -> 0 | T6: =COUNTIFS(Afirmaciones!$A$2:$A$401,$A6,Afirmaciones!$B$2:$B$401,$B6,Afirmaciones!$E$2:$E$401,"hecho",Afirmaciones!$I$2:$I$401,"SIN-RESPALDO") -> 0 | U6: =COUNTIFS(Afirmaciones!$A$2:$A$401,$A6,Afirmaciones!$B$2:$B$401,$B6,Afirmaciones!$E$2:$E$401,"hecho",Afirmaciones!$I$2:$I$401,"CITA-X") -> 0 | V6: =COUNTIFS(Afirmaciones!$A$2:$A$401,$A6,Afirmaciones!$B$2:$B$401,$B6,Afirmaciones!$E$2:$E$401,"hecho",Afirmaciones!$I$2:$I$401,"SIN-CITA") -> 0 | W6: =COUNTIFS(Afirmaciones!$A$2:$A$401,$A6,Afirmaciones!$B$2:$B$401,$B6,Afirmaciones!$E$2:$E$401,"hecho") -> 0 | X6: =COUNTIFS(Afirmaciones!$A$2:$A$401,$A6,Afirmaciones!$B$2:$B$401,$B6,Afirmaciones!$E$2:$E$401,"hecho",Afirmaciones!$I$2:$I$401,"SOSTENIDA") -> 0 | Y6: =IF($L6=0,"",IF($M6=0,IF($R6>0,0,2),IF(AND($N6=$M6,$P6+$Q6+$R6=0),2,IF($N6=0,0,1)))) | Z6: =IF($L6=0,"",IF($B6="llm","N/A",IF($W6=0,"N/A",IF($X6=$W6,2,IF($X6=0,0,1))))) | AA6: =IF($L6=0,"",IF(AND($P6+$Q6+$R6=0,$T6+$U6=0,$I6<>"SI"),"-",TRIM(IF($P6+$Q6+$R6>0,"CRITICA ","")&IF($T6+$U6>0,"RESPALDO ","")&IF($I6="SI","TRUNC","")))) | AB6: =IF($L6=0,"",IF(AND($R6=0,$AF6=0,$AG6=0,$P6+$Q6=0,$T6+$U6+$V6=0),"OK",TRIM(IF($R6>0,"E0 ","")&IF($AF6>0,"E1 ","")&IF(OR($AG6>0,AND($P6+$Q6>0,$AF6=0)),"E2 ","")&IF($T6+$U6+$V6>0,"E3 ","")))) | AC6: =IF($AB6="","",IF($AB6="OK","OK",LEFT($AB6,2))) | AD6: =IF(OR($L6=0,$B6="llm",$W6=0),"-",$X6&"/"&$W6) -> - | AE6: =IF(OR($L6=0,$B6<>"rag",$M6=0),"-",SUMIFS(Hechos!$H$2:$H$201,Hechos!$A$2:$A$201,$A6)&"/"&$M6) -> - | AF6: =IF($B6="rag",SUMPRODUCT((Hechos!$A$2:$A$201=$A6)*(Hechos!$F$2:$F$201=0)*((Hechos!$E$2:$E$201="NO")+(Hechos!$E$2:$E$201="ALT-P")+(Hechos!$E$2:$E$201=""))),0) -> 0 | AG6: =IF($B6="rag",SUMPRODUCT((Hechos!$A$2:$A$201=$A6)*(Hechos!$F$2:$F$201=0)*((Hechos!$E$2:$E$201="SI")+(Hechos!$E$2:$E$201="ALT"))),$M6-$N6) -> 0
A7: p03 | B7: llm | C7: ES | D7: completa | E7: ¿Qué es la táctica Persistencia (TA0003) en ATT&CK y qué busca conseguir el adversario con ella? | F7: Persistencia es la táctica en la que el adversario intenta mantener su punto de apoyo (foothold). Agrupa técnicas para conservar el acceso a los sistemas a pesar de reinicios, cambios de credenciales u otras interrupciones; incluye cualquier acceso, acción o cambio de configuración que le permita mantener ese acceso, como reemplazar o secuestrar código legítimo o añadir código de arranque. | H7: La táctica Persistencia (TA0003) en el marco MITRE ATT&CK se refiere a la capacidad de un atacante para mantener acceso a un sistema o red tras la inicialización de una amenaza. Este objetivo permite que el atacante se mantenga activo en el entorno durante períodos prolongados, incluso después de que se hayan aplicado medidas de seguridad o se hayan detectado actividades inusuales. El adversario busca conseguir que su acceso a la infraestructura sea **persistente**, es decir, que no se pierda al reiniciar el sistema o al aplicar controles de seguridad. Esto permite que el atacante realice actividades de recolección de datos, ejecución de comandos, propagación a otros sistemas o monitoreo continuo sin que se detecte inmediatamente. Algunos ejemplos de técnicas asociadas a esta táctica incluyen: - T1059.001 (Comandos y scripts maliciosos) - T1059.002 (Ejecución de scripts) - T1059.003 (Ejecución de comandos) - T1059.004 (Ejecución de comandos a través de servicios) - T1059.005 (Ejecución de comandos a través de servicios de red) En resumen, la táctica Persistencia (TA0003) busca **mantener un acceso continuo y sin interrupción** al sistema objetivo, lo que facilita la ejecución de ataques más complejos y prolongados. | I7: NO | L7: =COUNTIFS(Afirmaciones!$A$2:$A$401,$A7,Afirmaciones!$B$2:$B$401,$B7) -> 0 | M7: =COUNTIFS(Hechos!$A$2:$A$201,$A7) -> 2 | N7: =IF($B7="rag",SUMIFS(Hechos!$F$2:$F$201,Hechos!$A$2:$A$201,$A7),SUMIFS(Hechos!$G$2:$G$201,Hechos!$A$2:$A$201,$A7)) -> 0 | O7: =IF($M7=0,"-",$N7&"/"&$M7) -> 0/2 | P7: =COUNTIFS(Afirmaciones!$A$2:$A$401,$A7,Afirmaciones!$B$2:$B$401,$B7,Afirmaciones!$E$2:$E$401,"hecho",Afirmaciones!$F$2:$F$401,"INCORRECTA") -> 0 | Q7: =COUNTIFS(Afirmaciones!$A$2:$A$401,$A7,Afirmaciones!$B$2:$B$401,$B7,Afirmaciones!$E$2:$E$401,"abstencion",Afirmaciones!$F$2:$F$401,"INCORRECTA") -> 0 | R7: =COUNTIFS(Afirmaciones!$A$2:$A$401,$A7,Afirmaciones!$B$2:$B$401,$B7,Afirmaciones!$E$2:$E$401,"hecho",Afirmaciones!$F$2:$F$401,"FUERA_REF",Afirmaciones!$H$2:$H$401,"no_resp") -> 0 | S7: =COUNTIFS(Afirmaciones!$A$2:$A$401,$A7,Afirmaciones!$B$2:$B$401,$B7,Afirmaciones!$E$2:$E$401,"hecho",Afirmaciones!$F$2:$F$401,"FUERA_REF") -> 0 | T7: =COUNTIFS(Afirmaciones!$A$2:$A$401,$A7,Afirmaciones!$B$2:$B$401,$B7,Afirmaciones!$E$2:$E$401,"hecho",Afirmaciones!$I$2:$I$401,"SIN-RESPALDO") -> 0 | U7: =COUNTIFS(Afirmaciones!$A$2:$A$401,$A7,Afirmaciones!$B$2:$B$401,$B7,Afirmaciones!$E$2:$E$401,"hecho",Afirmaciones!$I$2:$I$401,"CITA-X") -> 0 | V7: =COUNTIFS(Afirmaciones!$A$2:$A$401,$A7,Afirmaciones!$B$2:$B$401,$B7,Afirmaciones!$E$2:$E$401,"hecho",Afirmaciones!$I$2:$I$401,"SIN-CITA") -> 0 | W7: =COUNTIFS(Afirmaciones!$A$2:$A$401,$A7,Afirmaciones!$B$2:$B$401,$B7,Afirmaciones!$E$2:$E$401,"hecho") -> 0 | X7: =COUNTIFS(Afirmaciones!$A$2:$A$401,$A7,Afirmaciones!$B$2:$B$401,$B7,Afirmaciones!$E$2:$E$401,"hecho",Afirmaciones!$I$2:$I$401,"SOSTENIDA") -> 0 | Y7: =IF($L7=0,"",IF($M7=0,IF($R7>0,0,2),IF(AND($N7=$M7,$P7+$Q7+$R7=0),2,IF($N7=0,0,1)))) | Z7: =IF($L7=0,"",IF($B7="llm","N/A",IF($W7=0,"N/A",IF($X7=$W7,2,IF($X7=0,0,1))))) | AA7: =IF($L7=0,"",IF(AND($P7+$Q7+$R7=0,$T7+$U7=0,$I7<>"SI"),"-",TRIM(IF($P7+$Q7+$R7>0,"CRITICA ","")&IF($T7+$U7>0,"RESPALDO ","")&IF($I7="SI","TRUNC","")))) | AB7: =IF($L7=0,"",IF(AND($R7=0,$AF7=0,$AG7=0,$P7+$Q7=0,$T7+$U7+$V7=0),"OK",TRIM(IF($R7>0,"E0 ","")&IF($AF7>0,"E1 ","")&IF(OR($AG7>0,AND($P7+$Q7>0,$AF7=0)),"E2 ","")&IF($T7+$U7+$V7>0,"E3 ","")))) | AC7: =IF($AB7="","",IF($AB7="OK","OK",LEFT($AB7,2))) | AD7: =IF(OR($L7=0,$B7="llm",$W7=0),"-",$X7&"/"&$W7) -> - | AE7: =IF(OR($L7=0,$B7<>"rag",$M7=0),"-",SUMIFS(Hechos!$H$2:$H$201,Hechos!$A$2:$A$201,$A7)&"/"&$M7) -> - | AF7: =IF($B7="rag",SUMPRODUCT((Hechos!$A$2:$A$201=$A7)*(Hechos!$F$2:$F$201=0)*((Hechos!$E$2:$E$201="NO")+(Hechos!$E$2:$E$201="ALT-P")+(Hechos!$E$2:$E$201=""))),0) -> 0 | AG7: =IF($B7="rag",SUMPRODUCT((Hechos!$A$2:$A$201=$A7)*(Hechos!$F$2:$F$201=0)*((Hechos!$E$2:$E$201="SI")+(Hechos!$E$2:$E$201="ALT"))),$M7-$N7) -> 2
A8: p04 | B8: rag | C8: ES | D8: parcial | E8: Según ATT&CK, ¿qué es Cobalt Strike (S0154) y de qué otras herramientas conocidas aprovecha capacidades? ¿Cuánto cuesta su licencia anual? | F8: Cobalt Strike es una herramienta comercial de acceso remoto con todas las funciones, que se presenta como 'software de simulación de adversarios' para ejecutar ataques dirigidos y emular las acciones post-explotación de actores avanzados; sus capacidades interactivas cubren toda la gama de tácticas ATT&CK en un único sistema integrado. Además de sus propias capacidades, aprovecha las de otras herramientas conocidas como Metasploit y Mimikatz (S0002). | G8: El precio de la licencia no está en el corpus (ATT&CK no registra precios; la única aparición de 'price' en el corpus es en el software CoinTicker, sin relación). | H8: Según ATT&CK, Cobalt Strike (S0154) es un software de tipo malware, perteneciente al dominio de ataque empresarial, que se describe como "una herramienta de acceso remoto comercial, completa, diseñada para ejecutar ataques dirigidos y emular las acciones de post-explotación de actores de amenazas avanzadas". [1] Cobalt Strike aprovecha las capacidades de otras herramientas conocidas, como Metasploit y Mimikatz. [1] No se proporciona información en los contextos sobre el costo anual de la licencia de Cobalt Strike. [1][2][3][4][5] Por lo tanto, no se puede determinar cuánto cuesta su licencia anual basándose en los datos proporcionados. | I8: NO | J8: TODA | K8: 2/2 | L8: =COUNTIFS(Afirmaciones!$A$2:$A$401,$A8,Afirmaciones!$B$2:$B$401,$B8) -> 0 | M8: =COUNTIFS(Hechos!$A$2:$A$201,$A8) -> 2 | N8: =IF($B8="rag",SUMIFS(Hechos!$F$2:$F$201,Hechos!$A$2:$A$201,$A8),SUMIFS(Hechos!$G$2:$G$201,Hechos!$A$2:$A$201,$A8)) -> 0 | O8: =IF($M8=0,"-",$N8&"/"&$M8) -> 0/2 | P8: =COUNTIFS(Afirmaciones!$A$2:$A$401,$A8,Afirmaciones!$B$2:$B$401,$B8,Afirmaciones!$E$2:$E$401,"hecho",Afirmaciones!$F$2:$F$401,"INCORRECTA") -> 0 | Q8: =COUNTIFS(Afirmaciones!$A$2:$A$401,$A8,Afirmaciones!$B$2:$B$401,$B8,Afirmaciones!$E$2:$E$401,"abstencion",Afirmaciones!$F$2:$F$401,"INCORRECTA") -> 0 | R8: =COUNTIFS(Afirmaciones!$A$2:$A$401,$A8,Afirmaciones!$B$2:$B$401,$B8,Afirmaciones!$E$2:$E$401,"hecho",Afirmaciones!$F$2:$F$401,"FUERA_REF",Afirmaciones!$H$2:$H$401,"no_resp") -> 0 | S8: =COUNTIFS(Afirmaciones!$A$2:$A$401,$A8,Afirmaciones!$B$2:$B$401,$B8,Afirmaciones!$E$2:$E$401,"hecho",Afirmaciones!$F$2:$F$401,"FUERA_REF") -> 0 | T8: =COUNTIFS(Afirmaciones!$A$2:$A$401,$A8,Afirmaciones!$B$2:$B$401,$B8,Afirmaciones!$E$2:$E$401,"hecho",Afirmaciones!$I$2:$I$401,"SIN-RESPALDO") -> 0 | U8: =COUNTIFS(Afirmaciones!$A$2:$A$401,$A8,Afirmaciones!$B$2:$B$401,$B8,Afirmaciones!$E$2:$E$401,"hecho",Afirmaciones!$I$2:$I$401,"CITA-X") -> 0 | V8: =COUNTIFS(Afirmaciones!$A$2:$A$401,$A8,Afirmaciones!$B$2:$B$401,$B8,Afirmaciones!$E$2:$E$401,"hecho",Afirmaciones!$I$2:$I$401,"SIN-CITA") -> 0 | W8: =COUNTIFS(Afirmaciones!$A$2:$A$401,$A8,Afirmaciones!$B$2:$B$401,$B8,Afirmaciones!$E$2:$E$401,"hecho") -> 0 | X8: =COUNTIFS(Afirmaciones!$A$2:$A$401,$A8,Afirmaciones!$B$2:$B$401,$B8,Afirmaciones!$E$2:$E$401,"hecho",Afirmaciones!$I$2:$I$401,"SOSTENIDA") -> 0 | Y8: =IF($L8=0,"",IF($M8=0,IF($R8>0,0,2),IF(AND($N8=$M8,$P8+$Q8+$R8=0),2,IF($N8=0,0,1)))) | Z8: =IF($L8=0,"",IF($B8="llm","N/A",IF($W8=0,"N/A",IF($X8=$W8,2,IF($X8=0,0,1))))) | AA8: =IF($L8=0,"",IF(AND($P8+$Q8+$R8=0,$T8+$U8=0,$I8<>"SI"),"-",TRIM(IF($P8+$Q8+$R8>0,"CRITICA ","")&IF($T8+$U8>0,"RESPALDO ","")&IF($I8="SI","TRUNC","")))) | AB8: =IF($L8=0,"",IF(AND($R8=0,$AF8=0,$AG8=0,$P8+$Q8=0,$T8+$U8+$V8=0),"OK",TRIM(IF($R8>0,"E0 ","")&IF($AF8>0,"E1 ","")&IF(OR($AG8>0,AND($P8+$Q8>0,$AF8=0)),"E2 ","")&IF($T8+$U8+$V8>0,"E3 ","")))) | AC8: =IF($AB8="","",IF($AB8="OK","OK",LEFT($AB8,2))) | AD8: =IF(OR($L8=0,$B8="llm",$W8=0),"-",$X8&"/"&$W8) -> - | AE8: =IF(OR($L8=0,$B8<>"rag",$M8=0),"-",SUMIFS(Hechos!$H$2:$H$201,Hechos!$A$2:$A$201,$A8)&"/"&$M8) -> - | AF8: =IF($B8="rag",SUMPRODUCT((Hechos!$A$2:$A$201=$A8)*(Hechos!$F$2:$F$201=0)*((Hechos!$E$2:$E$201="NO")+(Hechos!$E$2:$E$201="ALT-P")+(Hechos!$E$2:$E$201=""))),0) -> 0 | AG8: =IF($B8="rag",SUMPRODUCT((Hechos!$A$2:$A$201=$A8)*(Hechos!$F$2:$F$201=0)*((Hechos!$E$2:$E$201="SI")+(Hechos!$E$2:$E$201="ALT"))),$M8-$N8) -> 0
A9: p04 | B9: llm | C9: ES | D9: parcial | E9: Según ATT&CK, ¿qué es Cobalt Strike (S0154) y de qué otras herramientas conocidas aprovecha capacidades? ¿Cuánto cuesta su licencia anual? | F9: Cobalt Strike es una herramienta comercial de acceso remoto con todas las funciones, que se presenta como 'software de simulación de adversarios' para ejecutar ataques dirigidos y emular las acciones post-explotación de actores avanzados; sus capacidades interactivas cubren toda la gama de tácticas ATT&CK en un único sistema integrado. Además de sus propias capacidades, aprovecha las de otras herramientas conocidas como Metasploit y Mimikatz (S0002). | G9: El precio de la licencia no está en el corpus (ATT&CK no registra precios; la única aparición de 'price' en el corpus es en el software CoinTicker, sin relación). | H9: Cobalt Strike (S0154) es una herramienta de red de seguridad y de ataque que permite a los investigadores y profesionales de ciberseguridad realizar pruebas de penetración y análisis de vulnerabilidades en entornos de red. Según el MITRE ATT&CK, S0154 se clasifica como una herramienta de "iniciación de sesión" (initial access) y se utiliza principalmente para simular ataques de red, como la ejecución remota de comandos en sistemas. Cobalt Strike aprovecha capacidades de otras herramientas conocidas, como: - **Metasploit**: para la ejecución de payloads y la gestión de sesiones. - **PowerShell**: para la ejecución de comandos en sistemas Windows. - **Meterpreter**: un módulo de Metasploit que permite la ejecución remota de comandos y la gestión de sesiones en sistemas operativos. Sin embargo, es importante aclarar que **Cobalt Strike no es una herramienta de ataque comercial que se venda con una licencia anual**. Es una herramienta de investigación y pruebas de penetración que se ofrece como software de uso académico y profesional, y **no tiene un costo oficial de licencia anual** como producto comercializado en el mercado. En su sitio oficial, Cobalt Strike está disponible para uso en entornos de pruebas y educación, y **no se cobra una licencia anual**. Su uso está regulado por las políticas de uso de la herramienta, y se recomienda su uso solo en entornos autorizados y bajo supervisión. 👉 **Respuesta final**: Cobalt Strike (S0150) es una herramienta de pruebas de penetración que simula ataques de red y aprovecha capacidades de herramientas como Metasploit y PowerShell. **No tiene una licencia anual y no se cobra un costo oficial** para su uso en entornos educativos o de investigación. | I9: NO | L9: =COUNTIFS(Afirmaciones!$A$2:$A$401,$A9,Afirmaciones!$B$2:$B$401,$B9) -> 0 | M9: =COUNTIFS(Hechos!$A$2:$A$201,$A9) -> 2 | N9: =IF($B9="rag",SUMIFS(Hechos!$F$2:$F$201,Hechos!$A$2:$A$201,$A9),SUMIFS(Hechos!$G$2:$G$201,Hechos!$A$2:$A$201,$A9)) -> 0 | O9: =IF($M9=0,"-",$N9&"/"&$M9) -> 0/2 | P9: =COUNTIFS(Afirmaciones!$A$2:$A$401,$A9,Afirmaciones!$B$2:$B$401,$B9,Afirmaciones!$E$2:$E$401,"hecho",Afirmaciones!$F$2:$F$401,"INCORRECTA") -> 0 | Q9: =COUNTIFS(Afirmaciones!$A$2:$A$401,$A9,Afirmaciones!$B$2:$B$401,$B9,Afirmaciones!$E$2:$E$401,"abstencion",Afirmaciones!$F$2:$F$401,"INCORRECTA") -> 0 | R9: =COUNTIFS(Afirmaciones!$A$2:$A$401,$A9,Afirmaciones!$B$2:$B$401,$B9,Afirmaciones!$E$2:$E$401,"hecho",Afirmaciones!$F$2:$F$401,"FUERA_REF",Afirmaciones!$H$2:$H$401,"no_resp") -> 0 | S9: =COUNTIFS(Afirmaciones!$A$2:$A$401,$A9,Afirmaciones!$B$2:$B$401,$B9,Afirmaciones!$E$2:$E$401,"hecho",Afirmaciones!$F$2:$F$401,"FUERA_REF") -> 0 | T9: =COUNTIFS(Afirmaciones!$A$2:$A$401,$A9,Afirmaciones!$B$2:$B$401,$B9,Afirmaciones!$E$2:$E$401,"hecho",Afirmaciones!$I$2:$I$401,"SIN-RESPALDO") -> 0 | U9: =COUNTIFS(Afirmaciones!$A$2:$A$401,$A9,Afirmaciones!$B$2:$B$401,$B9,Afirmaciones!$E$2:$E$401,"hecho",Afirmaciones!$I$2:$I$401,"CITA-X") -> 0 | V9: =COUNTIFS(Afirmaciones!$A$2:$A$401,$A9,Afirmaciones!$B$2:$B$401,$B9,Afirmaciones!$E$2:$E$401,"hecho",Afirmaciones!$I$2:$I$401,"SIN-CITA") -> 0 | W9: =COUNTIFS(Afirmaciones!$A$2:$A$401,$A9,Afirmaciones!$B$2:$B$401,$B9,Afirmaciones!$E$2:$E$401,"hecho") -> 0 | X9: =COUNTIFS(Afirmaciones!$A$2:$A$401,$A9,Afirmaciones!$B$2:$B$401,$B9,Afirmaciones!$E$2:$E$401,"hecho",Afirmaciones!$I$2:$I$401,"SOSTENIDA") -> 0 | Y9: =IF($L9=0,"",IF($M9=0,IF($R9>0,0,2),IF(AND($N9=$M9,$P9+$Q9+$R9=0),2,IF($N9=0,0,1)))) | Z9: =IF($L9=0,"",IF($B9="llm","N/A",IF($W9=0,"N/A",IF($X9=$W9,2,IF($X9=0,0,1))))) | AA9: =IF($L9=0,"",IF(AND($P9+$Q9+$R9=0,$T9+$U9=0,$I9<>"SI"),"-",TRIM(IF($P9+$Q9+$R9>0,"CRITICA ","")&IF($T9+$U9>0,"RESPALDO ","")&IF($I9="SI","TRUNC","")))) | AB9: =IF($L9=0,"",IF(AND($R9=0,$AF9=0,$AG9=0,$P9+$Q9=0,$T9+$U9+$V9=0),"OK",TRIM(IF($R9>0,"E0 ","")&IF($AF9>0,"E1 ","")&IF(OR($AG9>0,AND($P9+$Q9>0,$AF9=0)),"E2 ","")&IF($T9+$U9+$V9>0,"E3 ","")))) | AC9: =IF($AB9="","",IF($AB9="OK","OK",LEFT($AB9,2))) | AD9: =IF(OR($L9=0,$B9="llm",$W9=0),"-",$X9&"/"&$W9) -> - | AE9: =IF(OR($L9=0,$B9<>"rag",$M9=0),"-",SUMIFS(Hechos!$H$2:$H$201,Hechos!$A$2:$A$201,$A9)&"/"&$M9) -> - | AF9: =IF($B9="rag",SUMPRODUCT((Hechos!$A$2:$A$201=$A9)*(Hechos!$F$2:$F$201=0)*((Hechos!$E$2:$E$201="NO")+(Hechos!$E$2:$E$201="ALT-P")+(Hechos!$E$2:$E$201=""))),0) -> 0 | AG9: =IF($B9="rag",SUMPRODUCT((Hechos!$A$2:$A$201=$A9)*(Hechos!$F$2:$F$201=0)*((Hechos!$E$2:$E$201="SI")+(Hechos!$E$2:$E$201="ALT"))),$M9-$N9) -> 2
A10: p05 | B10: rag | C10: ES | D10: completa | E10: Según ATT&CK, ¿APT29 (G0016) utiliza Mimikatz? Y en caso afirmativo, ¿qué técnicas relacionadas con tickets Kerberos implementa esa herramienta? | F10: Sí: S0002 Mimikatz aparece en la lista de software usado por APT29 (y G0016 APT29 aparece en la lista 'Used by' de Mimikatz). Entre las técnicas de Mimikatz relacionadas con tickets Kerberos están T1550.003 Pass the Ticket, T1558.001 Golden Ticket y T1558.002 Silver Ticket. | H10: Sí, según ATT&CK, APT29 (G0016) utiliza Mimikatz. En el contexto se indica que: - G0016 APT29 (grupo) ha utilizado ataques de Kerberos para el movimiento lateral [1]. - S0002 Mimikatz (software) tiene el módulo <code>KERBEROS::PTT</code> que implementa los tres pasos necesarios para extraer la contraseña del cuenta krbtgt y crear o usar tickets de Kerberos [1]. Por lo tanto, Mimikatz implementa la técnica **T1550.003 - Pass the Ticket**, que es una técnica relacionada con tickets de Kerberos. **Respuesta final:** Sí, APT29 (G0016) utiliza Mimikatz, y la técnica relacionada con tickets de Kerberos que implementa esa herramienta es **T1550.003 - Pass the Ticket** [1]. | I10: NO | J10: PARTE | K10: 2/4 | L10: =COUNTIFS(Afirmaciones!$A$2:$A$401,$A10,Afirmaciones!$B$2:$B$401,$B10) -> 3 | M10: =COUNTIFS(Hechos!$A$2:$A$201,$A10) -> 4 | N10: =IF($B10="rag",SUMIFS(Hechos!$F$2:$F$201,Hechos!$A$2:$A$201,$A10),SUMIFS(Hechos!$G$2:$G$201,Hechos!$A$2:$A$201,$A10)) -> 2 | O10: =IF($M10=0,"-",$N10&"/"&$M10) -> 2/4 | P10: =COUNTIFS(Afirmaciones!$A$2:$A$401,$A10,Afirmaciones!$B$2:$B$401,$B10,Afirmaciones!$E$2:$E$401,"hecho",Afirmaciones!$F$2:$F$401,"INCORRECTA") -> 0 | Q10: =COUNTIFS(Afirmaciones!$A$2:$A$401,$A10,Afirmaciones!$B$2:$B$401,$B10,Afirmaciones!$E$2:$E$401,"abstencion",Afirmaciones!$F$2:$F$401,"INCORRECTA") -> 0 | R10: =COUNTIFS(Afirmaciones!$A$2:$A$401,$A10,Afirmaciones!$B$2:$B$401,$B10,Afirmaciones!$E$2:$E$401,"hecho",Afirmaciones!$F$2:$F$401,"FUERA_REF",Afirmaciones!$H$2:$H$401,"no_resp") -> 0 | S10: =COUNTIFS(Afirmaciones!$A$2:$A$401,$A10,Afirmaciones!$B$2:$B$401,$B10,Afirmaciones!$E$2:$E$401,"hecho",Afirmaciones!$F$2:$F$401,"FUERA_REF") -> 1 | T10: =COUNTIFS(Afirmaciones!$A$2:$A$401,$A10,Afirmaciones!$B$2:$B$401,$B10,Afirmaciones!$E$2:$E$401,"hecho",Afirmaciones!$I$2:$I$401,"SIN-RESPALDO") -> 1 | U10: =COUNTIFS(Afirmaciones!$A$2:$A$401,$A10,Afirmaciones!$B$2:$B$401,$B10,Afirmaciones!$E$2:$E$401,"hecho",Afirmaciones!$I$2:$I$401,"CITA-X") -> 0 | V10: =COUNTIFS(Afirmaciones!$A$2:$A$401,$A10,Afirmaciones!$B$2:$B$401,$B10,Afirmaciones!$E$2:$E$401,"hecho",Afirmaciones!$I$2:$I$401,"SIN-CITA") -> 0 | W10: =COUNTIFS(Afirmaciones!$A$2:$A$401,$A10,Afirmaciones!$B$2:$B$401,$B10,Afirmaciones!$E$2:$E$401,"hecho") -> 3 | X10: =COUNTIFS(Afirmaciones!$A$2:$A$401,$A10,Afirmaciones!$B$2:$B$401,$B10,Afirmaciones!$E$2:$E$401,"hecho",Afirmaciones!$I$2:$I$401,"SOSTENIDA") -> 2 | Y10: =IF($L10=0,"",IF($M10=0,IF($R10>0,0,2),IF(AND($N10=$M10,$P10+$Q10+$R10=0),2,IF($N10=0,0,1)))) -> 1 | Z10: =IF($L10=0,"",IF($B10="llm","N/A",IF($W10=0,"N/A",IF($X10=$W10,2,IF($X10=0,0,1))))) -> 1 | AA10: =IF($L10=0,"",IF(AND($P10+$Q10+$R10=0,$T10+$U10=0,$I10<>"SI"),"-",TRIM(IF($P10+$Q10+$R10>0,"CRITICA ","")&IF($T10+$U10>0,"RESPALDO ","")&IF($I10="SI","TRUNC","")))) -> RESPALDO | AB10: =IF($L10=0,"",IF(AND($R10=0,$AF10=0,$AG10=0,$P10+$Q10=0,$T10+$U10+$V10=0),"OK",TRIM(IF($R10>0,"E0 ","")&IF($AF10>0,"E1 ","")&IF(OR($AG10>0,AND($P10+$Q10>0,$AF10=0)),"E2 ","")&IF($T10+$U10+$V10>0,"E3 ","")))) -> E1 E2 E3 | AC10: =IF($AB10="","",IF($AB10="OK","OK",LEFT($AB10,2))) -> E1 | AD10: =IF(OR($L10=0,$B10="llm",$W10=0),"-",$X10&"/"&$W10) -> 2/3 | AE10: =IF(OR($L10=0,$B10<>"rag",$M10=0),"-",SUMIFS(Hechos!$H$2:$H$201,Hechos!$A$2:$A$201,$A10)&"/"&$M10) -> 1/4 | AF10: =IF($B10="rag",SUMPRODUCT((Hechos!$A$2:$A$201=$A10)*(Hechos!$F$2:$F$201=0)*((Hechos!$E$2:$E$201="NO")+(Hechos!$E$2:$E$201="ALT-P")+(Hechos!$E$2:$E$201=""))),0) -> 1 | AG10: =IF($B10="rag",SUMPRODUCT((Hechos!$A$2:$A$201=$A10)*(Hechos!$F$2:$F$201=0)*((Hechos!$E$2:$E$201="SI")+(Hechos!$E$2:$E$201="ALT"))),$M10-$N10) -> 1 | AI10: 1 | 1 | E1 E2 E3
A11: p05 | B11: llm | C11: ES | D11: completa | E11: Según ATT&CK, ¿APT29 (G0016) utiliza Mimikatz? Y en caso afirmativo, ¿qué técnicas relacionadas con tickets Kerberos implementa esa herramienta? | F11: Sí: S0002 Mimikatz aparece en la lista de software usado por APT29 (y G0016 APT29 aparece en la lista 'Used by' de Mimikatz). Entre las técnicas de Mimikatz relacionadas con tickets Kerberos están T1550.003 Pass the Ticket, T1558.001 Golden Ticket y T1558.002 Silver Ticket. | H11: No, según el marco MITRE ATT&CK, el grupo APT29 (identificado como G0016) no se ha documentado como usuario directo de Mimikatz. Aunque APT29 ha sido asociado con técnicas de acceso a sistemas mediante el uso de tickets Kerberos (como T1547.001 - "Exploitation of Kerberos"), estas acciones se realizan mediante herramientas o métodos específicos de ataque, no necesariamente mediante Mimikatz. Además, Mimikatz es una herramienta de análisis de seguridad que permite la extracción de credenciales almacenadas en memoria (como los tickets Kerberos), y aunque puede ser utilizada por atacantes para obtener acceso a sistemas, su uso no está directamente vinculado a APT29 en fuentes oficiales del MITRE ATT&CK. En cuanto a técnicas relacionadas con tickets Kerberos que podría implementar APT29: - **T1547.001 - Exploitation of Kerberos**: Este es el principal sub-técnico relacionado con el uso de tickets Kerberos para obtener acceso a sistemas. APT29 ha sido asociado con este comportamiento, especialmente en ataques que aprovechan vulnerabilidades en el protocolo Kerberos (por ejemplo, en el uso de tickets de tiempo de vida o en la reutilización de tickets). Por lo tanto: ✅ APT29 (G0016) **no utiliza directamente Mimikatz**. ✅ APT29 **sí implementa técnicas relacionadas con el uso de tickets Kerberos**, principalmente **T1547.001**. **Respuesta final:** No, APT29 (G0016) no utiliza Mimikatz. Sin embargo, sí implementa la técnica T1547.001 - Exploitation of Kerberos. | I11: NO | L11: =COUNTIFS(Afirmaciones!$A$2:$A$401,$A11,Afirmaciones!$B$2:$B$401,$B11) -> 3 | M11: =COUNTIFS(Hechos!$A$2:$A$201,$A11) -> 4 | N11: =IF($B11="rag",SUMIFS(Hechos!$F$2:$F$201,Hechos!$A$2:$A$201,$A11),SUMIFS(Hechos!$G$2:$G$201,Hechos!$A$2:$A$201,$A11)) -> 0 | O11: =IF($M11=0,"-",$N11&"/"&$M11) -> 0/4 | P11: =COUNTIFS(Afirmaciones!$A$2:$A$401,$A11,Afirmaciones!$B$2:$B$401,$B11,Afirmaciones!$E$2:$E$401,"hecho",Afirmaciones!$F$2:$F$401,"INCORRECTA") -> 2 | Q11: =COUNTIFS(Afirmaciones!$A$2:$A$401,$A11,Afirmaciones!$B$2:$B$401,$B11,Afirmaciones!$E$2:$E$401,"abstencion",Afirmaciones!$F$2:$F$401,"INCORRECTA") -> 0 | R11: =COUNTIFS(Afirmaciones!$A$2:$A$401,$A11,Afirmaciones!$B$2:$B$401,$B11,Afirmaciones!$E$2:$E$401,"hecho",Afirmaciones!$F$2:$F$401,"FUERA_REF",Afirmaciones!$H$2:$H$401,"no_resp") -> 0 | S11: =COUNTIFS(Afirmaciones!$A$2:$A$401,$A11,Afirmaciones!$B$2:$B$401,$B11,Afirmaciones!$E$2:$E$401,"hecho",Afirmaciones!$F$2:$F$401,"FUERA_REF") -> 1 | T11: =COUNTIFS(Afirmaciones!$A$2:$A$401,$A11,Afirmaciones!$B$2:$B$401,$B11,Afirmaciones!$E$2:$E$401,"hecho",Afirmaciones!$I$2:$I$401,"SIN-RESPALDO") -> 0 | U11: =COUNTIFS(Afirmaciones!$A$2:$A$401,$A11,Afirmaciones!$B$2:$B$401,$B11,Afirmaciones!$E$2:$E$401,"hecho",Afirmaciones!$I$2:$I$401,"CITA-X") -> 0 | V11: =COUNTIFS(Afirmaciones!$A$2:$A$401,$A11,Afirmaciones!$B$2:$B$401,$B11,Afirmaciones!$E$2:$E$401,"hecho",Afirmaciones!$I$2:$I$401,"SIN-CITA") -> 0 | W11: =COUNTIFS(Afirmaciones!$A$2:$A$401,$A11,Afirmaciones!$B$2:$B$401,$B11,Afirmaciones!$E$2:$E$401,"hecho") -> 3 | X11: =COUNTIFS(Afirmaciones!$A$2:$A$401,$A11,Afirmaciones!$B$2:$B$401,$B11,Afirmaciones!$E$2:$E$401,"hecho",Afirmaciones!$I$2:$I$401,"SOSTENIDA") -> 0 | Y11: =IF($L11=0,"",IF($M11=0,IF($R11>0,0,2),IF(AND($N11=$M11,$P11+$Q11+$R11=0),2,IF($N11=0,0,1)))) -> 0 | Z11: =IF($L11=0,"",IF($B11="llm","N/A",IF($W11=0,"N/A",IF($X11=$W11,2,IF($X11=0,0,1))))) -> N/A | AA11: =IF($L11=0,"",IF(AND($P11+$Q11+$R11=0,$T11+$U11=0,$I11<>"SI"),"-",TRIM(IF($P11+$Q11+$R11>0,"CRITICA ","")&IF($T11+$U11>0,"RESPALDO ","")&IF($I11="SI","TRUNC","")))) -> CRITICA | AB11: =IF($L11=0,"",IF(AND($R11=0,$AF11=0,$AG11=0,$P11+$Q11=0,$T11+$U11+$V11=0),"OK",TRIM(IF($R11>0,"E0 ","")&IF($AF11>0,"E1 ","")&IF(OR($AG11>0,AND($P11+$Q11>0,$AF11=0)),"E2 ","")&IF($T11+$U11+$V11>0,"E3 ","")))) -> E2 | AC11: =IF($AB11="","",IF($AB11="OK","OK",LEFT($AB11,2))) -> E2 | AD11: =IF(OR($L11=0,$B11="llm",$W11=0),"-",$X11&"/"&$W11) -> - | AE11: =IF(OR($L11=0,$B11<>"rag",$M11=0),"-",SUMIFS(Hechos!$H$2:$H$201,Hechos!$A$2:$A$201,$A11)&"/"&$M11) -> - | AF11: =IF($B11="rag",SUMPRODUCT((Hechos!$A$2:$A$201=$A11)*(Hechos!$F$2:$F$201=0)*((Hechos!$E$2:$E$201="NO")+(Hechos!$E$2:$E$201="ALT-P")+(Hechos!$E$2:$E$201=""))),0) -> 0 | AG11: =IF($B11="rag",SUMPRODUCT((Hechos!$A$2:$A$201=$A11)*(Hechos!$F$2:$F$201=0)*((Hechos!$E$2:$E$201="SI")+(Hechos!$E$2:$E$201="ALT"))),$M11-$N11) -> 4 | AI11: 0 | N/A | E2
A12: p06 | B12: rag | C12: ES | D12: parcial | E12: ¿Qué sub-técnicas de intérpretes de comandos (T1059.*) usa Lazarus Group (G0032) según ATT&CK, y qué ataques ha realizado este grupo contra Ecuador? | F12: ATT&CK atribuye a Lazarus Group tres sub-técnicas de T1059: T1059.001 PowerShell, T1059.003 Windows Command Shell y T1059.005 Visual Basic. | G12: Ataques contra Ecuador: el documento de G0032 no menciona Ecuador (la única aparición de 'Ecuador' en todo el corpus está en T1480 Execution Guardrails, sin relación con Lazarus). | H12: No se proporciona información en los contextos sobre qué sub-técnicas de intérpretes de comandos (T1059.*) usa el Lazarus Group (G0032) o sobre ataques específicos que haya realizado contra Ecuador. Aunque se menciona que el Lazarus Group utiliza técnicas como T1059.003 Windows Command Shell y T1059.005 Visual Basic en el contexto de software como AuditCred y TYPEFRAME [1][3], no se especifica explícitamente el uso de sub-técnicas de T1059.* en general, ni se menciona cualquier actividad contra Ecuador. Además, no hay ninguna referencia en los contextos a ataques realizados por el Lazarus Group contra Ecuador. Por lo tanto, **no se puede responder con certeza** a la pregunta basándose únicamente en los contextos proporcionados. **Respuesta: No se puede determinar a partir de los contextos proporcionados.** | I12: NO | J12: TODA | K12: 3/3 | L12: =COUNTIFS(Afirmaciones!$A$2:$A$401,$A12,Afirmaciones!$B$2:$B$401,$B12) -> 3 | M12: =COUNTIFS(Hechos!$A$2:$A$201,$A12) -> 3 | N12: =IF($B12="rag",SUMIFS(Hechos!$F$2:$F$201,Hechos!$A$2:$A$201,$A12),SUMIFS(Hechos!$G$2:$G$201,Hechos!$A$2:$A$201,$A12)) -> 2 | O12: =IF($M12=0,"-",$N12&"/"&$M12) -> 2/3 | P12: =COUNTIFS(Afirmaciones!$A$2:$A$401,$A12,Afirmaciones!$B$2:$B$401,$B12,Afirmaciones!$E$2:$E$401,"hecho",Afirmaciones!$F$2:$F$401,"INCORRECTA") -> 0 | Q12: =COUNTIFS(Afirmaciones!$A$2:$A$401,$A12,Afirmaciones!$B$2:$B$401,$B12,Afirmaciones!$E$2:$E$401,"abstencion",Afirmaciones!$F$2:$F$401,"INCORRECTA") -> 1 | R12: =COUNTIFS(Afirmaciones!$A$2:$A$401,$A12,Afirmaciones!$B$2:$B$401,$B12,Afirmaciones!$E$2:$E$401,"hecho",Afirmaciones!$F$2:$F$401,"FUERA_REF",Afirmaciones!$H$2:$H$401,"no_resp") -> 0 | S12: =COUNTIFS(Afirmaciones!$A$2:$A$401,$A12,Afirmaciones!$B$2:$B$401,$B12,Afirmaciones!$E$2:$E$401,"hecho",Afirmaciones!$F$2:$F$401,"FUERA_REF") -> 0 | T12: =COUNTIFS(Afirmaciones!$A$2:$A$401,$A12,Afirmaciones!$B$2:$B$401,$B12,Afirmaciones!$E$2:$E$401,"hecho",Afirmaciones!$I$2:$I$401,"SIN-RESPALDO") -> 0 | U12: =COUNTIFS(Afirmaciones!$A$2:$A$401,$A12,Afirmaciones!$B$2:$B$401,$B12,Afirmaciones!$E$2:$E$401,"hecho",Afirmaciones!$I$2:$I$401,"CITA-X") -> 0 | V12: =COUNTIFS(Afirmaciones!$A$2:$A$401,$A12,Afirmaciones!$B$2:$B$401,$B12,Afirmaciones!$E$2:$E$401,"hecho",Afirmaciones!$I$2:$I$401,"SIN-CITA") -> 0 | W12: =COUNTIFS(Afirmaciones!$A$2:$A$401,$A12,Afirmaciones!$B$2:$B$401,$B12,Afirmaciones!$E$2:$E$401,"hecho") -> 1 | X12: =COUNTIFS(Afirmaciones!$A$2:$A$401,$A12,Afirmaciones!$B$2:$B$401,$B12,Afirmaciones!$E$2:$E$401,"hecho",Afirmaciones!$I$2:$I$401,"SOSTENIDA") -> 1 | Y12: =IF($L12=0,"",IF($M12=0,IF($R12>0,0,2),IF(AND($N12=$M12,$P12+$Q12+$R12=0),2,IF($N12=0,0,1)))) -> 1 | Z12: =IF($L12=0,"",IF($B12="llm","N/A",IF($W12=0,"N/A",IF($X12=$W12,2,IF($X12=0,0,1))))) -> 2 | AA12: =IF($L12=0,"",IF(AND($P12+$Q12+$R12=0,$T12+$U12=0,$I12<>"SI"),"-",TRIM(IF($P12+$Q12+$R12>0,"CRITICA ","")&IF($T12+$U12>0,"RESPALDO ","")&IF($I12="SI","TRUNC","")))) -> CRITICA | AB12: =IF($L12=0,"",IF(AND($R12=0,$AF12=0,$AG12=0,$P12+$Q12=0,$T12+$U12+$V12=0),"OK",TRIM(IF($R12>0,"E0 ","")&IF($AF12>0,"E1 ","")&IF(OR($AG12>0,AND($P12+$Q12>0,$AF12=0)),"E2 ","")&IF($T12+$U12+$V12>0,"E3 ","")))) -> E2 | AC12: =IF($AB12="","",IF($AB12="OK","OK",LEFT($AB12,2))) -> E2 | AD12: =IF(OR($L12=0,$B12="llm",$W12=0),"-",$X12&"/"&$W12) -> 1/1 | AE12: =IF(OR($L12=0,$B12<>"rag",$M12=0),"-",SUMIFS(Hechos!$H$2:$H$201,Hechos!$A$2:$A$201,$A12)&"/"&$M12) -> 2/3 | AF12: =IF($B12="rag",SUMPRODUCT((Hechos!$A$2:$A$201=$A12)*(Hechos!$F$2:$F$201=0)*((Hechos!$E$2:$E$201="NO")+(Hechos!$E$2:$E$201="ALT-P")+(Hechos!$E$2:$E$201=""))),0) -> 0 | AG12: =IF($B12="rag",SUMPRODUCT((Hechos!$A$2:$A$201=$A12)*(Hechos!$F$2:$F$201=0)*((Hechos!$E$2:$E$201="SI")+(Hechos!$E$2:$E$201="ALT"))),$M12-$N12) -> 1 | AI12: 1 | 2 | E2
A13: p06 | B13: llm | C13: ES | D13: parcial | E13: ¿Qué sub-técnicas de intérpretes de comandos (T1059.*) usa Lazarus Group (G0032) según ATT&CK, y qué ataques ha realizado este grupo contra Ecuador? | F13: ATT&CK atribuye a Lazarus Group tres sub-técnicas de T1059: T1059.001 PowerShell, T1059.003 Windows Command Shell y T1059.005 Visual Basic. | G13: Ataques contra Ecuador: el documento de G0032 no menciona Ecuador (la única aparición de 'Ecuador' en todo el corpus está en T1480 Execution Guardrails, sin relación con Lazarus). | H13: No se ha documentado oficialmente en el MITRE ATT&CK que el grupo Lazarus (G0032) haya utilizado específicamente sub-técnicas de intérpretes de comandos (T1059.*) como parte de sus actividades conocidas, ni se ha registrado un ataque directo contra Ecuador atribuido a este grupo en fuentes oficiales del MITRE ATT&CK. Además, el MITRE ATT&CK no proporciona una lista detallada de sub-técnicas (como T1059.001, T1059.002, etc.) que el grupo Lazarus haya utilizado en operaciones específicas, ni hay evidencia verificada de que el grupo haya atacado a Ecuador. Por lo tanto, **no se puede afirmar con certeza** que Lazarus haya usado sub-técnicas de intérpretes de comandos (T1059.*) o que haya realizado ataques contra Ecuador según el MITRE ATT&CK. **Respuesta final:** No hay evidencia oficial en el MITRE ATT&CK de que el grupo Lazarus (G0032) haya utilizado sub-técnicas de intérpretes de comandos (T1059.*) o haya realizado ataques contra Ecuador. | I13: NO | L13: =COUNTIFS(Afirmaciones!$A$2:$A$401,$A13,Afirmaciones!$B$2:$B$401,$B13) -> 2 | M13: =COUNTIFS(Hechos!$A$2:$A$201,$A13) -> 3 | N13: =IF($B13="rag",SUMIFS(Hechos!$F$2:$F$201,Hechos!$A$2:$A$201,$A13),SUMIFS(Hechos!$G$2:$G$201,Hechos!$A$2:$A$201,$A13)) -> 0 | O13: =IF($M13=0,"-",$N13&"/"&$M13) -> 0/3 | P13: =COUNTIFS(Afirmaciones!$A$2:$A$401,$A13,Afirmaciones!$B$2:$B$401,$B13,Afirmaciones!$E$2:$E$401,"hecho",Afirmaciones!$F$2:$F$401,"INCORRECTA") -> 1 | Q13: =COUNTIFS(Afirmaciones!$A$2:$A$401,$A13,Afirmaciones!$B$2:$B$401,$B13,Afirmaciones!$E$2:$E$401,"abstencion",Afirmaciones!$F$2:$F$401,"INCORRECTA") -> 0 | R13: =COUNTIFS(Afirmaciones!$A$2:$A$401,$A13,Afirmaciones!$B$2:$B$401,$B13,Afirmaciones!$E$2:$E$401,"hecho",Afirmaciones!$F$2:$F$401,"FUERA_REF",Afirmaciones!$H$2:$H$401,"no_resp") -> 0 | S13: =COUNTIFS(Afirmaciones!$A$2:$A$401,$A13,Afirmaciones!$B$2:$B$401,$B13,Afirmaciones!$E$2:$E$401,"hecho",Afirmaciones!$F$2:$F$401,"FUERA_REF") -> 0 | T13: =COUNTIFS(Afirmaciones!$A$2:$A$401,$A13,Afirmaciones!$B$2:$B$401,$B13,Afirmaciones!$E$2:$E$401,"hecho",Afirmaciones!$I$2:$I$401,"SIN-RESPALDO") -> 0 | U13: =COUNTIFS(Afirmaciones!$A$2:$A$401,$A13,Afirmaciones!$B$2:$B$401,$B13,Afirmaciones!$E$2:$E$401,"hecho",Afirmaciones!$I$2:$I$401,"CITA-X") -> 0 | V13: =COUNTIFS(Afirmaciones!$A$2:$A$401,$A13,Afirmaciones!$B$2:$B$401,$B13,Afirmaciones!$E$2:$E$401,"hecho",Afirmaciones!$I$2:$I$401,"SIN-CITA") -> 0 | W13: =COUNTIFS(Afirmaciones!$A$2:$A$401,$A13,Afirmaciones!$B$2:$B$401,$B13,Afirmaciones!$E$2:$E$401,"hecho") -> 2 | X13: =COUNTIFS(Afirmaciones!$A$2:$A$401,$A13,Afirmaciones!$B$2:$B$401,$B13,Afirmaciones!$E$2:$E$401,"hecho",Afirmaciones!$I$2:$I$401,"SOSTENIDA") -> 0 | Y13: =IF($L13=0,"",IF($M13=0,IF($R13>0,0,2),IF(AND($N13=$M13,$P13+$Q13+$R13=0),2,IF($N13=0,0,1)))) -> 0 | Z13: =IF($L13=0,"",IF($B13="llm","N/A",IF($W13=0,"N/A",IF($X13=$W13,2,IF($X13=0,0,1))))) -> N/A | AA13: =IF($L13=0,"",IF(AND($P13+$Q13+$R13=0,$T13+$U13=0,$I13<>"SI"),"-",TRIM(IF($P13+$Q13+$R13>0,"CRITICA ","")&IF($T13+$U13>0,"RESPALDO ","")&IF($I13="SI","TRUNC","")))) -> CRITICA | AB13: =IF($L13=0,"",IF(AND($R13=0,$AF13=0,$AG13=0,$P13+$Q13=0,$T13+$U13+$V13=0),"OK",TRIM(IF($R13>0,"E0 ","")&IF($AF13>0,"E1 ","")&IF(OR($AG13>0,AND($P13+$Q13>0,$AF13=0)),"E2 ","")&IF($T13+$U13+$V13>0,"E3 ","")))) -> E2 | AC13: =IF($AB13="","",IF($AB13="OK","OK",LEFT($AB13,2))) -> E2 | AD13: =IF(OR($L13=0,$B13="llm",$W13=0),"-",$X13&"/"&$W13) -> - | AE13: =IF(OR($L13=0,$B13<>"rag",$M13=0),"-",SUMIFS(Hechos!$H$2:$H$201,Hechos!$A$2:$A$201,$A13)&"/"&$M13) -> - | AF13: =IF($B13="rag",SUMPRODUCT((Hechos!$A$2:$A$201=$A13)*(Hechos!$F$2:$F$201=0)*((Hechos!$E$2:$E$201="NO")+(Hechos!$E$2:$E$201="ALT-P")+(Hechos!$E$2:$E$201=""))),0) -> 0 | AG13: =IF($B13="rag",SUMPRODUCT((Hechos!$A$2:$A$201=$A13)*(Hechos!$F$2:$F$201=0)*((Hechos!$E$2:$E$201="SI")+(Hechos!$E$2:$E$201="ALT"))),$M13-$N13) -> 3 | AI13: 0 | N/A | E2
A14: p07 | B14: rag | C14: EN | D14: completa | E14: According to ATT&CK, how has APT28 (G0007) carried out password spraying (T1110.003)? | F14: ATT&CK records that during the APT28 Nearest Neighbor Campaign (C0051) APT28 performed password-spray attacks against public-facing services to validate credentials; that APT28 used brute-force/password-spray tooling which, in password-spraying mode, made approximately four authentication attempts per hour per targeted account over several days or weeks; and that APT28 also used a Kubernetes cluster to conduct distributed, large-scale password spray attacks. | H14: APT28 (G0007) has carried out password spraying (T1110.003) by using a brute-force/password-spray tooling that operated in two modes: in password-spraying mode, it conducted approximately four authentication attempts per hour per targeted account over the course of several days or weeks. Additionally, APT28 has used a Kubernetes cluster to conduct distributed, large-scale password spray attacks. During the APT28 Nearest Neighbor Campaign (C0051), APT28 performed password-spray attacks against public-facing services to validate credentials [1][2]. | I14: NO | J14: TODA | K14: 3/3 | L14: =COUNTIFS(Afirmaciones!$A$2:$A$401,$A14,Afirmaciones!$B$2:$B$401,$B14) -> 0 | M14: =COUNTIFS(Hechos!$A$2:$A$201,$A14) -> 3 | N14: =IF($B14="rag",SUMIFS(Hechos!$F$2:$F$201,Hechos!$A$2:$A$201,$A14),SUMIFS(Hechos!$G$2:$G$201,Hechos!$A$2:$A$201,$A14)) -> 0 | O14: =IF($M14=0,"-",$N14&"/"&$M14) -> 0/3 | P14: =COUNTIFS(Afirmaciones!$A$2:$A$401,$A14,Afirmaciones!$B$2:$B$401,$B14,Afirmaciones!$E$2:$E$401,"hecho",Afirmaciones!$F$2:$F$401,"INCORRECTA") -> 0 | Q14: =COUNTIFS(Afirmaciones!$A$2:$A$401,$A14,Afirmaciones!$B$2:$B$401,$B14,Afirmaciones!$E$2:$E$401,"abstencion",Afirmaciones!$F$2:$F$401,"INCORRECTA") -> 0 | R14: =COUNTIFS(Afirmaciones!$A$2:$A$401,$A14,Afirmaciones!$B$2:$B$401,$B14,Afirmaciones!$E$2:$E$401,"hecho",Afirmaciones!$F$2:$F$401,"FUERA_REF",Afirmaciones!$H$2:$H$401,"no_resp") -> 0 | S14: =COUNTIFS(Afirmaciones!$A$2:$A$401,$A14,Afirmaciones!$B$2:$B$401,$B14,Afirmaciones!$E$2:$E$401,"hecho",Afirmaciones!$F$2:$F$401,"FUERA_REF") -> 0 | T14: =COUNTIFS(Afirmaciones!$A$2:$A$401,$A14,Afirmaciones!$B$2:$B$401,$B14,Afirmaciones!$E$2:$E$401,"hecho",Afirmaciones!$I$2:$I$401,"SIN-RESPALDO") -> 0 | U14: =COUNTIFS(Afirmaciones!$A$2:$A$401,$A14,Afirmaciones!$B$2:$B$401,$B14,Afirmaciones!$E$2:$E$401,"hecho",Afirmaciones!$I$2:$I$401,"CITA-X") -> 0 | V14: =COUNTIFS(Afirmaciones!$A$2:$A$401,$A14,Afirmaciones!$B$2:$B$401,$B14,Afirmaciones!$E$2:$E$401,"hecho",Afirmaciones!$I$2:$I$401,"SIN-CITA") -> 0 | W14: =COUNTIFS(Afirmaciones!$A$2:$A$401,$A14,Afirmaciones!$B$2:$B$401,$B14,Afirmaciones!$E$2:$E$401,"hecho") -> 0 | X14: =COUNTIFS(Afirmaciones!$A$2:$A$401,$A14,Afirmaciones!$B$2:$B$401,$B14,Afirmaciones!$E$2:$E$401,"hecho",Afirmaciones!$I$2:$I$401,"SOSTENIDA") -> 0 | Y14: =IF($L14=0,"",IF($M14=0,IF($R14>0,0,2),IF(AND($N14=$M14,$P14+$Q14+$R14=0),2,IF($N14=0,0,1)))) | Z14: =IF($L14=0,"",IF($B14="llm","N/A",IF($W14=0,"N/A",IF($X14=$W14,2,IF($X14=0,0,1))))) | AA14: =IF($L14=0,"",IF(AND($P14+$Q14+$R14=0,$T14+$U14=0,$I14<>"SI"),"-",TRIM(IF($P14+$Q14+$R14>0,"CRITICA ","")&IF($T14+$U14>0,"RESPALDO ","")&IF($I14="SI","TRUNC","")))) | AB14: =IF($L14=0,"",IF(AND($R14=0,$AF14=0,$AG14=0,$P14+$Q14=0,$T14+$U14+$V14=0),"OK",TRIM(IF($R14>0,"E0 ","")&IF($AF14>0,"E1 ","")&IF(OR($AG14>0,AND($P14+$Q14>0,$AF14=0)),"E2 ","")&IF($T14+$U14+$V14>0,"E3 ","")))) | AC14: =IF($AB14="","",IF($AB14="OK","OK",LEFT($AB14,2))) | AD14: =IF(OR($L14=0,$B14="llm",$W14=0),"-",$X14&"/"&$W14) -> - | AE14: =IF(OR($L14=0,$B14<>"rag",$M14=0),"-",SUMIFS(Hechos!$H$2:$H$201,Hechos!$A$2:$A$201,$A14)&"/"&$M14) -> - | AF14: =IF($B14="rag",SUMPRODUCT((Hechos!$A$2:$A$201=$A14)*(Hechos!$F$2:$F$201=0)*((Hechos!$E$2:$E$201="NO")+(Hechos!$E$2:$E$201="ALT-P")+(Hechos!$E$2:$E$201=""))),0) -> 0 | AG14: =IF($B14="rag",SUMPRODUCT((Hechos!$A$2:$A$201=$A14)*(Hechos!$F$2:$F$201=0)*((Hechos!$E$2:$E$201="SI")+(Hechos!$E$2:$E$201="ALT"))),$M14-$N14) -> 0
A15: p07 | B15: llm | C15: EN | D15: completa | E15: According to ATT&CK, how has APT28 (G0007) carried out password spraying (T1110.003)? | F15: ATT&CK records that during the APT28 Nearest Neighbor Campaign (C0051) APT28 performed password-spray attacks against public-facing services to validate credentials; that APT28 used brute-force/password-spray tooling which, in password-spraying mode, made approximately four authentication attempts per hour per targeted account over several days or weeks; and that APT28 also used a Kubernetes cluster to conduct distributed, large-scale password spray attacks. | H15: As of now, there is no publicly documented or verified evidence in the MITRE ATT&CK framework that APT28 (G0007) has specifically carried out password spraying (T1110.003) in a manner that is explicitly attributed or detailed within the ATT&CK knowledge base. While APT28 is known to use credential harvesting and phishing techniques, and password spraying is a common technique used in credential access (T1110.003), the ATT&CK framework does not provide a specific, confirmed instance of APT28 executing password spraying as a tactic or technique. Therefore, based on available ATT&CK data, **there is no confirmed or documented instance of APT28 (G0007) carrying out password spraying (T1110.003)**. Note: The MITRE ATT&CK framework describes techniques and behaviors observed in cyberattacks, but it does not assign specific attribution to individual threat actors in all cases—especially for less publicly documented or unverified activities. Attribution remains a complex and often uncertain process. Answer: There is no confirmed or documented instance in the MITRE ATT&CK framework of APT28 (G0007) carrying out password spraying (T1110.003). | I15: NO | L15: =COUNTIFS(Afirmaciones!$A$2:$A$401,$A15,Afirmaciones!$B$2:$B$401,$B15) -> 0 | M15: =COUNTIFS(Hechos!$A$2:$A$201,$A15) -> 3 | N15: =IF($B15="rag",SUMIFS(Hechos!$F$2:$F$201,Hechos!$A$2:$A$201,$A15),SUMIFS(Hechos!$G$2:$G$201,Hechos!$A$2:$A$201,$A15)) -> 0 | O15: =IF($M15=0,"-",$N15&"/"&$M15) -> 0/3 | P15: =COUNTIFS(Afirmaciones!$A$2:$A$401,$A15,Afirmaciones!$B$2:$B$401,$B15,Afirmaciones!$E$2:$E$401,"hecho",Afirmaciones!$F$2:$F$401,"INCORRECTA") -> 0 | Q15: =COUNTIFS(Afirmaciones!$A$2:$A$401,$A15,Afirmaciones!$B$2:$B$401,$B15,Afirmaciones!$E$2:$E$401,"abstencion",Afirmaciones!$F$2:$F$401,"INCORRECTA") -> 0 | R15: =COUNTIFS(Afirmaciones!$A$2:$A$401,$A15,Afirmaciones!$B$2:$B$401,$B15,Afirmaciones!$E$2:$E$401,"hecho",Afirmaciones!$F$2:$F$401,"FUERA_REF",Afirmaciones!$H$2:$H$401,"no_resp") -> 0 | S15: =COUNTIFS(Afirmaciones!$A$2:$A$401,$A15,Afirmaciones!$B$2:$B$401,$B15,Afirmaciones!$E$2:$E$401,"hecho",Afirmaciones!$F$2:$F$401,"FUERA_REF") -> 0 | T15: =COUNTIFS(Afirmaciones!$A$2:$A$401,$A15,Afirmaciones!$B$2:$B$401,$B15,Afirmaciones!$E$2:$E$401,"hecho",Afirmaciones!$I$2:$I$401,"SIN-RESPALDO") -> 0 | U15: =COUNTIFS(Afirmaciones!$A$2:$A$401,$A15,Afirmaciones!$B$2:$B$401,$B15,Afirmaciones!$E$2:$E$401,"hecho",Afirmaciones!$I$2:$I$401,"CITA-X") -> 0 | V15: =COUNTIFS(Afirmaciones!$A$2:$A$401,$A15,Afirmaciones!$B$2:$B$401,$B15,Afirmaciones!$E$2:$E$401,"hecho",Afirmaciones!$I$2:$I$401,"SIN-CITA") -> 0 | W15: =COUNTIFS(Afirmaciones!$A$2:$A$401,$A15,Afirmaciones!$B$2:$B$401,$B15,Afirmaciones!$E$2:$E$401,"hecho") -> 0 | X15: =COUNTIFS(Afirmaciones!$A$2:$A$401,$A15,Afirmaciones!$B$2:$B$401,$B15,Afirmaciones!$E$2:$E$401,"hecho",Afirmaciones!$I$2:$I$401,"SOSTENIDA") -> 0 | Y15: =IF($L15=0,"",IF($M15=0,IF($R15>0,0,2),IF(AND($N15=$M15,$P15+$Q15+$R15=0),2,IF($N15=0,0,1)))) | Z15: =IF($L15=0,"",IF($B15="llm","N/A",IF($W15=0,"N/A",IF($X15=$W15,2,IF($X15=0,0,1))))) | AA15: =IF($L15=0,"",IF(AND($P15+$Q15+$R15=0,$T15+$U15=0,$I15<>"SI"),"-",TRIM(IF($P15+$Q15+$R15>0,"CRITICA ","")&IF($T15+$U15>0,"RESPALDO ","")&IF($I15="SI","TRUNC","")))) | AB15: =IF($L15=0,"",IF(AND($R15=0,$AF15=0,$AG15=0,$P15+$Q15=0,$T15+$U15+$V15=0),"OK",TRIM(IF($R15>0,"E0 ","")&IF($AF15>0,"E1 ","")&IF(OR($AG15>0,AND($P15+$Q15>0,$AF15=0)),"E2 ","")&IF($T15+$U15+$V15>0,"E3 ","")))) | AC15: =IF($AB15="","",IF($AB15="OK","OK",LEFT($AB15,2))) | AD15: =IF(OR($L15=0,$B15="llm",$W15=0),"-",$X15&"/"&$W15) -> - | AE15: =IF(OR($L15=0,$B15<>"rag",$M15=0),"-",SUMIFS(Hechos!$H$2:$H$201,Hechos!$A$2:$A$201,$A15)&"/"&$M15) -> - | AF15: =IF($B15="rag",SUMPRODUCT((Hechos!$A$2:$A$201=$A15)*(Hechos!$F$2:$F$201=0)*((Hechos!$E$2:$E$201="NO")+(Hechos!$E$2:$E$201="ALT-P")+(Hechos!$E$2:$E$201=""))),0) -> 0 | AG15: =IF($B15="rag",SUMPRODUCT((Hechos!$A$2:$A$201=$A15)*(Hechos!$F$2:$F$201=0)*((Hechos!$E$2:$E$201="SI")+(Hechos!$E$2:$E$201="ALT"))),$M15-$N15) -> 3
A16: p08 | B16: rag | C16: ES | D16: parcial | E16: ¿Qué mitigaciones recomienda ATT&CK contra Password Spraying (T1110.003) y qué porcentaje de las intrusiones registradas en 2025 comenzó con esta técnica? | F16: ATT&CK recomienda tres mitigaciones: M1027 Password Policies (seguir las guías NIST al definir políticas de contraseñas), M1032 Multi-factor Authentication (usar MFA, también en servicios expuestos a Internet) y M1036 Account Use Policies (bloqueo de cuenta tras cierto número de intentos fallidos, con cuidado de no provocar denegación de servicio; políticas de acceso condicional para bloquear logins desde dispositivos no conformes o fuera de rangos IP de la organización; bloquear autenticaciones desde servicios de anonimización/proxies). | G16: El porcentaje de intrusiones de 2025 no existe en el corpus: ATT&CK no contiene estadísticas de incidencia. | H16: No se proporciona información en los contextos sobre mitigaciones contra Password Spraying (T1110.003) ni sobre el porcentaje de intrusiones registradas en 2025 que comenzaron con esta técnica. Por lo tanto, no se puede responder a la pregunta con base en los datos ofrecidos. [1][2][3][4][5] — ninguno de estos pasajes menciona mitigaciones específicas para T1110.003 ni proporciona datos sobre intrusiones en 2025. | I16: NO | J16: NINGUNA | K16: 0/3 | L16: =COUNTIFS(Afirmaciones!$A$2:$A$401,$A16,Afirmaciones!$B$2:$B$401,$B16) -> 0 | M16: =COUNTIFS(Hechos!$A$2:$A$201,$A16) -> 3 | N16: =IF($B16="rag",SUMIFS(Hechos!$F$2:$F$201,Hechos!$A$2:$A$201,$A16),SUMIFS(Hechos!$G$2:$G$201,Hechos!$A$2:$A$201,$A16)) -> 0 | O16: =IF($M16=0,"-",$N16&"/"&$M16) -> 0/3 | P16: =COUNTIFS(Afirmaciones!$A$2:$A$401,$A16,Afirmaciones!$B$2:$B$401,$B16,Afirmaciones!$E$2:$E$401,"hecho",Afirmaciones!$F$2:$F$401,"INCORRECTA") -> 0 | Q16: =COUNTIFS(Afirmaciones!$A$2:$A$401,$A16,Afirmaciones!$B$2:$B$401,$B16,Afirmaciones!$E$2:$E$401,"abstencion",Afirmaciones!$F$2:$F$401,"INCORRECTA") -> 0 | R16: =COUNTIFS(Afirmaciones!$A$2:$A$401,$A16,Afirmaciones!$B$2:$B$401,$B16,Afirmaciones!$E$2:$E$401,"hecho",Afirmaciones!$F$2:$F$401,"FUERA_REF",Afirmaciones!$H$2:$H$401,"no_resp") -> 0 | S16: =COUNTIFS(Afirmaciones!$A$2:$A$401,$A16,Afirmaciones!$B$2:$B$401,$B16,Afirmaciones!$E$2:$E$401,"hecho",Afirmaciones!$F$2:$F$401,"FUERA_REF") -> 0 | T16: =COUNTIFS(Afirmaciones!$A$2:$A$401,$A16,Afirmaciones!$B$2:$B$401,$B16,Afirmaciones!$E$2:$E$401,"hecho",Afirmaciones!$I$2:$I$401,"SIN-RESPALDO") -> 0 | U16: =COUNTIFS(Afirmaciones!$A$2:$A$401,$A16,Afirmaciones!$B$2:$B$401,$B16,Afirmaciones!$E$2:$E$401,"hecho",Afirmaciones!$I$2:$I$401,"CITA-X") -> 0 | V16: =COUNTIFS(Afirmaciones!$A$2:$A$401,$A16,Afirmaciones!$B$2:$B$401,$B16,Afirmaciones!$E$2:$E$401,"hecho",Afirmaciones!$I$2:$I$401,"SIN-CITA") -> 0 | W16: =COUNTIFS(Afirmaciones!$A$2:$A$401,$A16,Afirmaciones!$B$2:$B$401,$B16,Afirmaciones!$E$2:$E$401,"hecho") -> 0 | X16: =COUNTIFS(Afirmaciones!$A$2:$A$401,$A16,Afirmaciones!$B$2:$B$401,$B16,Afirmaciones!$E$2:$E$401,"hecho",Afirmaciones!$I$2:$I$401,"SOSTENIDA") -> 0 | Y16: =IF($L16=0,"",IF($M16=0,IF($R16>0,0,2),IF(AND($N16=$M16,$P16+$Q16+$R16=0),2,IF($N16=0,0,1)))) | Z16: =IF($L16=0,"",IF($B16="llm","N/A",IF($W16=0,"N/A",IF($X16=$W16,2,IF($X16=0,0,1))))) | AA16: =IF($L16=0,"",IF(AND($P16+$Q16+$R16=0,$T16+$U16=0,$I16<>"SI"),"-",TRIM(IF($P16+$Q16+$R16>0,"CRITICA ","")&IF($T16+$U16>0,"RESPALDO ","")&IF($I16="SI","TRUNC","")))) | AB16: =IF($L16=0,"",IF(AND($R16=0,$AF16=0,$AG16=0,$P16+$Q16=0,$T16+$U16+$V16=0),"OK",TRIM(IF($R16>0,"E0 ","")&IF($AF16>0,"E1 ","")&IF(OR($AG16>0,AND($P16+$Q16>0,$AF16=0)),"E2 ","")&IF($T16+$U16+$V16>0,"E3 ","")))) | AC16: =IF($AB16="","",IF($AB16="OK","OK",LEFT($AB16,2))) | AD16: =IF(OR($L16=0,$B16="llm",$W16=0),"-",$X16&"/"&$W16) -> - | AE16: =IF(OR($L16=0,$B16<>"rag",$M16=0),"-",SUMIFS(Hechos!$H$2:$H$201,Hechos!$A$2:$A$201,$A16)&"/"&$M16) -> - | AF16: =IF($B16="rag",SUMPRODUCT((Hechos!$A$2:$A$201=$A16)*(Hechos!$F$2:$F$201=0)*((Hechos!$E$2:$E$201="NO")+(Hechos!$E$2:$E$201="ALT-P")+(Hechos!$E$2:$E$201=""))),0) -> 0 | AG16: =IF($B16="rag",SUMPRODUCT((Hechos!$A$2:$A$201=$A16)*(Hechos!$F$2:$F$201=0)*((Hechos!$E$2:$E$201="SI")+(Hechos!$E$2:$E$201="ALT"))),$M16-$N16) -> 0
A17: p08 | B17: llm | C17: ES | D17: parcial | E17: ¿Qué mitigaciones recomienda ATT&CK contra Password Spraying (T1110.003) y qué porcentaje de las intrusiones registradas en 2025 comenzó con esta técnica? | F17: ATT&CK recomienda tres mitigaciones: M1027 Password Policies (seguir las guías NIST al definir políticas de contraseñas), M1032 Multi-factor Authentication (usar MFA, también en servicios expuestos a Internet) y M1036 Account Use Policies (bloqueo de cuenta tras cierto número de intentos fallidos, con cuidado de no provocar denegación de servicio; políticas de acceso condicional para bloquear logins desde dispositivos no conformes o fuera de rangos IP de la organización; bloquear autenticaciones desde servicios de anonimización/proxies). | G17: El porcentaje de intrusiones de 2025 no existe en el corpus: ATT&CK no contiene estadísticas de incidencia. | H17: No se proporciona información oficial en el MITRE ATT&CK sobre mitigaciones específicas para la técnica de Password Spraying (T1110.003), ni se tiene datos disponibles sobre el porcentaje de intrusiones registradas en 2025 que comenzaron con esta técnica. El MITRE ATT&CK no publica estadísticas anuales sobre el número o porcentaje de intrusiones que comenzaron con una técnica específica en un año futuro como 2025, ya que es un conjunto de conocimiento de amenazas y no un repositorio de datos de incidentes históricos o proyectados. Por lo tanto, **no se puede afirmar un porcentaje de intrusiones en 2025 que comenzaron con Password Spraying**, y **no se recomiendan mitigaciones específicas en el MITRE ATT&CK para esta técnica** en el contexto de datos de 2025. Las mitigaciones recomendadas para Password Spraying (T1110.003) en general, basadas en buenas prácticas de seguridad, incluyen: - Uso de políticas de contraseñas fuertes y complejas. - Implementación de autenticación multifactor (MFA). - Configuración de alertas para intentos de acceso múltiples con credenciales. - Uso de herramientas de detección de comportamiento anómalo. - Educación del personal sobre riesgos de ataques de "spraying". Sin embargo, estas no son mitigaciones directamente especificadas por el MITRE ATT&CK para T1110.003. ✅ Respuesta final: **No se proporcionan mitigaciones específicas en el MITRE ATT&CK para Password Spraying (T1110.003), y no se tiene datos sobre el porcentaje de intrusiones registradas en 2025 que comenzaron con esta técnica.** | I17: NO | L17: =COUNTIFS(Afirmaciones!$A$2:$A$401,$A17,Afirmaciones!$B$2:$B$401,$B17) -> 0 | M17: =COUNTIFS(Hechos!$A$2:$A$201,$A17) -> 3 | N17: =IF($B17="rag",SUMIFS(Hechos!$F$2:$F$201,Hechos!$A$2:$A$201,$A17),SUMIFS(Hechos!$G$2:$G$201,Hechos!$A$2:$A$201,$A17)) -> 0 | O17: =IF($M17=0,"-",$N17&"/"&$M17) -> 0/3 | P17: =COUNTIFS(Afirmaciones!$A$2:$A$401,$A17,Afirmaciones!$B$2:$B$401,$B17,Afirmaciones!$E$2:$E$401,"hecho",Afirmaciones!$F$2:$F$401,"INCORRECTA") -> 0 | Q17: =COUNTIFS(Afirmaciones!$A$2:$A$401,$A17,Afirmaciones!$B$2:$B$401,$B17,Afirmaciones!$E$2:$E$401,"abstencion",Afirmaciones!$F$2:$F$401,"INCORRECTA") -> 0 | R17: =COUNTIFS(Afirmaciones!$A$2:$A$401,$A17,Afirmaciones!$B$2:$B$401,$B17,Afirmaciones!$E$2:$E$401,"hecho",Afirmaciones!$F$2:$F$401,"FUERA_REF",Afirmaciones!$H$2:$H$401,"no_resp") -> 0 | S17: =COUNTIFS(Afirmaciones!$A$2:$A$401,$A17,Afirmaciones!$B$2:$B$401,$B17,Afirmaciones!$E$2:$E$401,"hecho",Afirmaciones!$F$2:$F$401,"FUERA_REF") -> 0 | T17: =COUNTIFS(Afirmaciones!$A$2:$A$401,$A17,Afirmaciones!$B$2:$B$401,$B17,Afirmaciones!$E$2:$E$401,"hecho",Afirmaciones!$I$2:$I$401,"SIN-RESPALDO") -> 0 | U17: =COUNTIFS(Afirmaciones!$A$2:$A$401,$A17,Afirmaciones!$B$2:$B$401,$B17,Afirmaciones!$E$2:$E$401,"hecho",Afirmaciones!$I$2:$I$401,"CITA-X") -> 0 | V17: =COUNTIFS(Afirmaciones!$A$2:$A$401,$A17,Afirmaciones!$B$2:$B$401,$B17,Afirmaciones!$E$2:$E$401,"hecho",Afirmaciones!$I$2:$I$401,"SIN-CITA") -> 0 | W17: =COUNTIFS(Afirmaciones!$A$2:$A$401,$A17,Afirmaciones!$B$2:$B$401,$B17,Afirmaciones!$E$2:$E$401,"hecho") -> 0 | X17: =COUNTIFS(Afirmaciones!$A$2:$A$401,$A17,Afirmaciones!$B$2:$B$401,$B17,Afirmaciones!$E$2:$E$401,"hecho",Afirmaciones!$I$2:$I$401,"SOSTENIDA") -> 0 | Y17: =IF($L17=0,"",IF($M17=0,IF($R17>0,0,2),IF(AND($N17=$M17,$P17+$Q17+$R17=0),2,IF($N17=0,0,1)))) | Z17: =IF($L17=0,"",IF($B17="llm","N/A",IF($W17=0,"N/A",IF($X17=$W17,2,IF($X17=0,0,1))))) | AA17: =IF($L17=0,"",IF(AND($P17+$Q17+$R17=0,$T17+$U17=0,$I17<>"SI"),"-",TRIM(IF($P17+$Q17+$R17>0,"CRITICA ","")&IF($T17+$U17>0,"RESPALDO ","")&IF($I17="SI","TRUNC","")))) | AB17: =IF($L17=0,"",IF(AND($R17=0,$AF17=0,$AG17=0,$P17+$Q17=0,$T17+$U17+$V17=0),"OK",TRIM(IF($R17>0,"E0 ","")&IF($AF17>0,"E1 ","")&IF(OR($AG17>0,AND($P17+$Q17>0,$AF17=0)),"E2 ","")&IF($T17+$U17+$V17>0,"E3 ","")))) | AC17: =IF($AB17="","",IF($AB17="OK","OK",LEFT($AB17,2))) | AD17: =IF(OR($L17=0,$B17="llm",$W17=0),"-",$X17&"/"&$W17) -> - | AE17: =IF(OR($L17=0,$B17<>"rag",$M17=0),"-",SUMIFS(Hechos!$H$2:$H$201,Hechos!$A$2:$A$201,$A17)&"/"&$M17) -> - | AF17: =IF($B17="rag",SUMPRODUCT((Hechos!$A$2:$A$201=$A17)*(Hechos!$F$2:$F$201=0)*((Hechos!$E$2:$E$201="NO")+(Hechos!$E$2:$E$201="ALT-P")+(Hechos!$E$2:$E$201=""))),0) -> 0 | AG17: =IF($B17="rag",SUMPRODUCT((Hechos!$A$2:$A$201=$A17)*(Hechos!$F$2:$F$201=0)*((Hechos!$E$2:$E$201="SI")+(Hechos!$E$2:$E$201="ALT"))),$M17-$N17) -> 3
A18: p09 | B18: rag | C18: EN | D18: parcial | E18: Which mitigations does ATT&CK list for Phishing (T1566), and which commercial email security product does MITRE recommend to implement them? | F18: ATT&CK lists six mitigations for Phishing: M1031 Network Intrusion Prevention (systems that scan and remove malicious attachments or links), M1021 Restrict Web-Based Content (block risky attachment types such as .scr, .exe, .pif, .cpl), M1017 User Training (train users to recognise social engineering and phishing), M1049 Antivirus/Antimalware (automatic quarantine of suspicious files), M1054 Software Configuration (anti-spoofing and email authentication: SPF, DKIM, DMARC) and M1047 Audit (audits/scans of systems, permissions and configurations). | G18: MITRE ATT&CK does not recommend commercial vendors or products; no such recommendation exists in the corpus. | H18: The provided context passages do not list any mitigations for Phishing (T1566) nor do they specify any commercial email security product that MITRE recommends to implement them. While the passages mention email authentication mechanisms such as SPF, DKIM, and DMARC as part of filtering and validation, they do not explicitly state these as mitigations for T1566 or identify a specific commercial product to implement them [5]. Therefore, based on the given context, no mitigations or recommended commercial products are specified. Answer: None of the mitigations or commercial email security products are listed in the provided context. | I18: NO | J18: PARTE | K18: 2/6 | L18: =COUNTIFS(Afirmaciones!$A$2:$A$401,$A18,Afirmaciones!$B$2:$B$401,$B18) -> 3 | M18: =COUNTIFS(Hechos!$A$2:$A$201,$A18) -> 6 | N18: =IF($B18="rag",SUMIFS(Hechos!$F$2:$F$201,Hechos!$A$2:$A$201,$A18),SUMIFS(Hechos!$G$2:$G$201,Hechos!$A$2:$A$201,$A18)) -> 0 | O18: =IF($M18=0,"-",$N18&"/"&$M18) -> 0/6 | P18: =COUNTIFS(Afirmaciones!$A$2:$A$401,$A18,Afirmaciones!$B$2:$B$401,$B18,Afirmaciones!$E$2:$E$401,"hecho",Afirmaciones!$F$2:$F$401,"INCORRECTA") -> 0 | Q18: =COUNTIFS(Afirmaciones!$A$2:$A$401,$A18,Afirmaciones!$B$2:$B$401,$B18,Afirmaciones!$E$2:$E$401,"abstencion",Afirmaciones!$F$2:$F$401,"INCORRECTA") -> 1 | R18: =COUNTIFS(Afirmaciones!$A$2:$A$401,$A18,Afirmaciones!$B$2:$B$401,$B18,Afirmaciones!$E$2:$E$401,"hecho",Afirmaciones!$F$2:$F$401,"FUERA_REF",Afirmaciones!$H$2:$H$401,"no_resp") -> 0 | S18: =COUNTIFS(Afirmaciones!$A$2:$A$401,$A18,Afirmaciones!$B$2:$B$401,$B18,Afirmaciones!$E$2:$E$401,"hecho",Afirmaciones!$F$2:$F$401,"FUERA_REF") -> 0 | T18: =COUNTIFS(Afirmaciones!$A$2:$A$401,$A18,Afirmaciones!$B$2:$B$401,$B18,Afirmaciones!$E$2:$E$401,"hecho",Afirmaciones!$I$2:$I$401,"SIN-RESPALDO") -> 0 | U18: =COUNTIFS(Afirmaciones!$A$2:$A$401,$A18,Afirmaciones!$B$2:$B$401,$B18,Afirmaciones!$E$2:$E$401,"hecho",Afirmaciones!$I$2:$I$401,"CITA-X") -> 0 | V18: =COUNTIFS(Afirmaciones!$A$2:$A$401,$A18,Afirmaciones!$B$2:$B$401,$B18,Afirmaciones!$E$2:$E$401,"hecho",Afirmaciones!$I$2:$I$401,"SIN-CITA") -> 0 | W18: =COUNTIFS(Afirmaciones!$A$2:$A$401,$A18,Afirmaciones!$B$2:$B$401,$B18,Afirmaciones!$E$2:$E$401,"hecho") -> 1 | X18: =COUNTIFS(Afirmaciones!$A$2:$A$401,$A18,Afirmaciones!$B$2:$B$401,$B18,Afirmaciones!$E$2:$E$401,"hecho",Afirmaciones!$I$2:$I$401,"SOSTENIDA") -> 1 | Y18: =IF($L18=0,"",IF($M18=0,IF($R18>0,0,2),IF(AND($N18=$M18,$P18+$Q18+$R18=0),2,IF($N18=0,0,1)))) -> 0 | Z18: =IF($L18=0,"",IF($B18="llm","N/A",IF($W18=0,"N/A",IF($X18=$W18,2,IF($X18=0,0,1))))) -> 2 | AA18: =IF($L18=0,"",IF(AND($P18+$Q18+$R18=0,$T18+$U18=0,$I18<>"SI"),"-",TRIM(IF($P18+$Q18+$R18>0,"CRITICA ","")&IF($T18+$U18>0,"RESPALDO ","")&IF($I18="SI","TRUNC","")))) -> CRITICA | AB18: =IF($L18=0,"",IF(AND($R18=0,$AF18=0,$AG18=0,$P18+$Q18=0,$T18+$U18+$V18=0),"OK",TRIM(IF($R18>0,"E0 ","")&IF($AF18>0,"E1 ","")&IF(OR($AG18>0,AND($P18+$Q18>0,$AF18=0)),"E2 ","")&IF($T18+$U18+$V18>0,"E3 ","")))) -> E1 E2 | AC18: =IF($AB18="","",IF($AB18="OK","OK",LEFT($AB18,2))) -> E1 | AD18: =IF(OR($L18=0,$B18="llm",$W18=0),"-",$X18&"/"&$W18) -> 1/1 | AE18: =IF(OR($L18=0,$B18<>"rag",$M18=0),"-",SUMIFS(Hechos!$H$2:$H$201,Hechos!$A$2:$A$201,$A18)&"/"&$M18) -> 0/6 | AF18: =IF($B18="rag",SUMPRODUCT((Hechos!$A$2:$A$201=$A18)*(Hechos!$F$2:$F$201=0)*((Hechos!$E$2:$E$201="NO")+(Hechos!$E$2:$E$201="ALT-P")+(Hechos!$E$2:$E$201=""))),0) -> 4 | AG18: =IF($B18="rag",SUMPRODUCT((Hechos!$A$2:$A$201=$A18)*(Hechos!$F$2:$F$201=0)*((Hechos!$E$2:$E$201="SI")+(Hechos!$E$2:$E$201="ALT"))),$M18-$N18) -> 2 | AI18: 0 | 2 | E1 E2
A19: p09 | B19: llm | C19: EN | D19: parcial | E19: Which mitigations does ATT&CK list for Phishing (T1566), and which commercial email security product does MITRE recommend to implement them? | F19: ATT&CK lists six mitigations for Phishing: M1031 Network Intrusion Prevention (systems that scan and remove malicious attachments or links), M1021 Restrict Web-Based Content (block risky attachment types such as .scr, .exe, .pif, .cpl), M1017 User Training (train users to recognise social engineering and phishing), M1049 Antivirus/Antimalware (automatic quarantine of suspicious files), M1054 Software Configuration (anti-spoofing and email authentication: SPF, DKIM, DMARC) and M1047 Audit (audits/scans of systems, permissions and configurations). | G19: MITRE ATT&CK does not recommend commercial vendors or products; no such recommendation exists in the corpus. | H19: MITRE ATT&CK does not list specific mitigations for Phishing (T1566) in the traditional sense of "mitigations" like firewall rules or endpoint protections. Instead, ATT&CK provides a structured framework of tactics, techniques, and sub-techniques that adversaries use—such as phishing (T1566)—and recommends detection and prevention strategies based on real-world threat intelligence. For Phishing (T1566), ATT&CK recommends the following **detection and mitigation approaches**: - **Email content filtering** to detect suspicious or malicious content. - **Domain-based message authentication, reporting, and conformance (DMARC)** to prevent spoofed emails. - **Sender Policy Framework (SPF)** and **DomainKeys Identified Mail (DKIM)** to verify sender authenticity. - **User education and awareness programs** to reduce human susceptibility to phishing. - **Real-time threat intelligence integration** to identify known phishing domains or URLs. - **Behavioral analysis** to detect anomalies in email patterns (e.g., unusual senders, attachments, or links). These are not "mitigations" in the sense of a product feature, but rather **security controls and practices** that help prevent or detect phishing attacks. Regarding commercial email security products, MITRE does **not** recommend a specific commercial product** for implementing these mitigations. However, MITRE often references or aligns with industry-leading email security solutions that support these controls. For example: - **Microsoft 365 Defender** (formerly Microsoft Defender for Office 365) is frequently cited in ATT&CK for its capabilities in detecting and blocking phishing emails using DMARC, SPF, DKIM, and AI-driven content analysis. - **Proofpoint**, **Palo Alto Networks Prisma Cloud**, and **Symantec Email Security** are also known to support many of these ATT&CK-aligned controls. ✅ Therefore, while MITRE does not explicitly recommend a single commercial product for phishing mitigation, **Microsoft 365 Defender** is widely recognized and referenced in the ATT&CK framework as a product that effectively implements many of the recommended mitigations for T1566 (Phishing). **Final Answer:** MITRE ATT&CK does not list specific "mitigations" for Phishing (T1566) as a standalone category, but recommends controls such as DMARC/SPF/DKIM, user awareness, and real-time threat intelligence. MITRE does not recommend a single commercial product; however, **Microsoft 365 Defender** is a widely recognized email security solution that supports these ATT&CK-aligned mitigations. | I19: NO | L19: =COUNTIFS(Afirmaciones!$A$2:$A$401,$A19,Afirmaciones!$B$2:$B$401,$B19) -> 6 | M19: =COUNTIFS(Hechos!$A$2:$A$201,$A19) -> 6 | N19: =IF($B19="rag",SUMIFS(Hechos!$F$2:$F$201,Hechos!$A$2:$A$201,$A19),SUMIFS(Hechos!$G$2:$G$201,Hechos!$A$2:$A$201,$A19)) -> 2 | O19: =IF($M19=0,"-",$N19&"/"&$M19) -> 2/6 | P19: =COUNTIFS(Afirmaciones!$A$2:$A$401,$A19,Afirmaciones!$B$2:$B$401,$B19,Afirmaciones!$E$2:$E$401,"hecho",Afirmaciones!$F$2:$F$401,"INCORRECTA") -> 1 | Q19: =COUNTIFS(Afirmaciones!$A$2:$A$401,$A19,Afirmaciones!$B$2:$B$401,$B19,Afirmaciones!$E$2:$E$401,"abstencion",Afirmaciones!$F$2:$F$401,"INCORRECTA") -> 0 | R19: =COUNTIFS(Afirmaciones!$A$2:$A$401,$A19,Afirmaciones!$B$2:$B$401,$B19,Afirmaciones!$E$2:$E$401,"hecho",Afirmaciones!$F$2:$F$401,"FUERA_REF",Afirmaciones!$H$2:$H$401,"no_resp") -> 1 | S19: =COUNTIFS(Afirmaciones!$A$2:$A$401,$A19,Afirmaciones!$B$2:$B$401,$B19,Afirmaciones!$E$2:$E$401,"hecho",Afirmaciones!$F$2:$F$401,"FUERA_REF") -> 2 | T19: =COUNTIFS(Afirmaciones!$A$2:$A$401,$A19,Afirmaciones!$B$2:$B$401,$B19,Afirmaciones!$E$2:$E$401,"hecho",Afirmaciones!$I$2:$I$401,"SIN-RESPALDO") -> 0 | U19: =COUNTIFS(Afirmaciones!$A$2:$A$401,$A19,Afirmaciones!$B$2:$B$401,$B19,Afirmaciones!$E$2:$E$401,"hecho",Afirmaciones!$I$2:$I$401,"CITA-X") -> 0 | V19: =COUNTIFS(Afirmaciones!$A$2:$A$401,$A19,Afirmaciones!$B$2:$B$401,$B19,Afirmaciones!$E$2:$E$401,"hecho",Afirmaciones!$I$2:$I$401,"SIN-CITA") -> 0 | W19: =COUNTIFS(Afirmaciones!$A$2:$A$401,$A19,Afirmaciones!$B$2:$B$401,$B19,Afirmaciones!$E$2:$E$401,"hecho") -> 6 | X19: =COUNTIFS(Afirmaciones!$A$2:$A$401,$A19,Afirmaciones!$B$2:$B$401,$B19,Afirmaciones!$E$2:$E$401,"hecho",Afirmaciones!$I$2:$I$401,"SOSTENIDA") -> 0 | Y19: =IF($L19=0,"",IF($M19=0,IF($R19>0,0,2),IF(AND($N19=$M19,$P19+$Q19+$R19=0),2,IF($N19=0,0,1)))) -> 1 | Z19: =IF($L19=0,"",IF($B19="llm","N/A",IF($W19=0,"N/A",IF($X19=$W19,2,IF($X19=0,0,1))))) -> N/A | AA19: =IF($L19=0,"",IF(AND($P19+$Q19+$R19=0,$T19+$U19=0,$I19<>"SI"),"-",TRIM(IF($P19+$Q19+$R19>0,"CRITICA ","")&IF($T19+$U19>0,"RESPALDO ","")&IF($I19="SI","TRUNC","")))) -> CRITICA | AB19: =IF($L19=0,"",IF(AND($R19=0,$AF19=0,$AG19=0,$P19+$Q19=0,$T19+$U19+$V19=0),"OK",TRIM(IF($R19>0,"E0 ","")&IF($AF19>0,"E1 ","")&IF(OR($AG19>0,AND($P19+$Q19>0,$AF19=0)),"E2 ","")&IF($T19+$U19+$V19>0,"E3 ","")))) -> E0 E2 | AC19: =IF($AB19="","",IF($AB19="OK","OK",LEFT($AB19,2))) -> E0 | AD19: =IF(OR($L19=0,$B19="llm",$W19=0),"-",$X19&"/"&$W19) -> - | AE19: =IF(OR($L19=0,$B19<>"rag",$M19=0),"-",SUMIFS(Hechos!$H$2:$H$201,Hechos!$A$2:$A$201,$A19)&"/"&$M19) -> - | AF19: =IF($B19="rag",SUMPRODUCT((Hechos!$A$2:$A$201=$A19)*(Hechos!$F$2:$F$201=0)*((Hechos!$E$2:$E$201="NO")+(Hechos!$E$2:$E$201="ALT-P")+(Hechos!$E$2:$E$201=""))),0) -> 0 | AG19: =IF($B19="rag",SUMPRODUCT((Hechos!$A$2:$A$201=$A19)*(Hechos!$F$2:$F$201=0)*((Hechos!$E$2:$E$201="SI")+(Hechos!$E$2:$E$201="ALT"))),$M19-$N19) -> 4 | AI19: 1 | N/A | E0 E2
A20: p10 | B20: rag | C20: ES | D20: nula | E20: ¿Qué es la técnica T1417 Input Capture de ATT&CK Mobile y qué mitigaciones propone ATT&CK para ella? | F20: No respondible con el corpus: sólo está ingestado el dominio enterprise-attack; T1417 pertenece a mobile-attack y no existe ningún chunk con ese ID. La respuesta correcta es abstenerse indicando que el contexto no contiene esa información. | G20: Toda la pregunta. | H20: No se proporciona información sobre la técnica T1417 Input Capture en el contexto dado. Además, no hay menciones a ninguna técnica denominada "T1417 Input Capture" ni a mitigaciones específicas para ella en los pasajes proporcionados. Los pasajes mencionan exclusivamente la técnica T1056 - Input Capture y sus sub-técnicas (como T1056.001 y T1056.003), así como estrategias de detección (DET0102), pero no T1417 ni ninguna mitigación relacionada con ella. Por lo tanto, no se puede responder a la pregunta con base en el contexto proporcionado. Respuesta: No se proporciona información sobre la técnica T1417 Input Capture ni sobre mitigaciones para ella en el contexto dado. | I20: NO | J20: N/A | K20: 0/0 | L20: =COUNTIFS(Afirmaciones!$A$2:$A$401,$A20,Afirmaciones!$B$2:$B$401,$B20) -> 0 | M20: =COUNTIFS(Hechos!$A$2:$A$201,$A20) -> 0 | N20: =IF($B20="rag",SUMIFS(Hechos!$F$2:$F$201,Hechos!$A$2:$A$201,$A20),SUMIFS(Hechos!$G$2:$G$201,Hechos!$A$2:$A$201,$A20)) -> 0 | O20: =IF($M20=0,"-",$N20&"/"&$M20) -> - | P20: =COUNTIFS(Afirmaciones!$A$2:$A$401,$A20,Afirmaciones!$B$2:$B$401,$B20,Afirmaciones!$E$2:$E$401,"hecho",Afirmaciones!$F$2:$F$401,"INCORRECTA") -> 0 | Q20: =COUNTIFS(Afirmaciones!$A$2:$A$401,$A20,Afirmaciones!$B$2:$B$401,$B20,Afirmaciones!$E$2:$E$401,"abstencion",Afirmaciones!$F$2:$F$401,"INCORRECTA") -> 0 | R20: =COUNTIFS(Afirmaciones!$A$2:$A$401,$A20,Afirmaciones!$B$2:$B$401,$B20,Afirmaciones!$E$2:$E$401,"hecho",Afirmaciones!$F$2:$F$401,"FUERA_REF",Afirmaciones!$H$2:$H$401,"no_resp") -> 0 | S20: =COUNTIFS(Afirmaciones!$A$2:$A$401,$A20,Afirmaciones!$B$2:$B$401,$B20,Afirmaciones!$E$2:$E$401,"hecho",Afirmaciones!$F$2:$F$401,"FUERA_REF") -> 0 | T20: =COUNTIFS(Afirmaciones!$A$2:$A$401,$A20,Afirmaciones!$B$2:$B$401,$B20,Afirmaciones!$E$2:$E$401,"hecho",Afirmaciones!$I$2:$I$401,"SIN-RESPALDO") -> 0 | U20: =COUNTIFS(Afirmaciones!$A$2:$A$401,$A20,Afirmaciones!$B$2:$B$401,$B20,Afirmaciones!$E$2:$E$401,"hecho",Afirmaciones!$I$2:$I$401,"CITA-X") -> 0 | V20: =COUNTIFS(Afirmaciones!$A$2:$A$401,$A20,Afirmaciones!$B$2:$B$401,$B20,Afirmaciones!$E$2:$E$401,"hecho",Afirmaciones!$I$2:$I$401,"SIN-CITA") -> 0 | W20: =COUNTIFS(Afirmaciones!$A$2:$A$401,$A20,Afirmaciones!$B$2:$B$401,$B20,Afirmaciones!$E$2:$E$401,"hecho") -> 0 | X20: =COUNTIFS(Afirmaciones!$A$2:$A$401,$A20,Afirmaciones!$B$2:$B$401,$B20,Afirmaciones!$E$2:$E$401,"hecho",Afirmaciones!$I$2:$I$401,"SOSTENIDA") -> 0 | Y20: =IF($L20=0,"",IF($M20=0,IF($R20>0,0,2),IF(AND($N20=$M20,$P20+$Q20+$R20=0),2,IF($N20=0,0,1)))) | Z20: =IF($L20=0,"",IF($B20="llm","N/A",IF($W20=0,"N/A",IF($X20=$W20,2,IF($X20=0,0,1))))) | AA20: =IF($L20=0,"",IF(AND($P20+$Q20+$R20=0,$T20+$U20=0,$I20<>"SI"),"-",TRIM(IF($P20+$Q20+$R20>0,"CRITICA ","")&IF($T20+$U20>0,"RESPALDO ","")&IF($I20="SI","TRUNC","")))) | AB20: =IF($L20=0,"",IF(AND($R20=0,$AF20=0,$AG20=0,$P20+$Q20=0,$T20+$U20+$V20=0),"OK",TRIM(IF($R20>0,"E0 ","")&IF($AF20>0,"E1 ","")&IF(OR($AG20>0,AND($P20+$Q20>0,$AF20=0)),"E2 ","")&IF($T20+$U20+$V20>0,"E3 ","")))) | AC20: =IF($AB20="","",IF($AB20="OK","OK",LEFT($AB20,2))) | AD20: =IF(OR($L20=0,$B20="llm",$W20=0),"-",$X20&"/"&$W20) -> - | AE20: =IF(OR($L20=0,$B20<>"rag",$M20=0),"-",SUMIFS(Hechos!$H$2:$H$201,Hechos!$A$2:$A$201,$A20)&"/"&$M20) -> - | AF20: =IF($B20="rag",SUMPRODUCT((Hechos!$A$2:$A$201=$A20)*(Hechos!$F$2:$F$201=0)*((Hechos!$E$2:$E$201="NO")+(Hechos!$E$2:$E$201="ALT-P")+(Hechos!$E$2:$E$201=""))),0) -> 0 | AG20: =IF($B20="rag",SUMPRODUCT((Hechos!$A$2:$A$201=$A20)*(Hechos!$F$2:$F$201=0)*((Hechos!$E$2:$E$201="SI")+(Hechos!$E$2:$E$201="ALT"))),$M20-$N20) -> 0
A21: p10 | B21: llm | C21: ES | D21: nula | E21: ¿Qué es la técnica T1417 Input Capture de ATT&CK Mobile y qué mitigaciones propone ATT&CK para ella? | F21: No respondible con el corpus: sólo está ingestado el dominio enterprise-attack; T1417 pertenece a mobile-attack y no existe ningún chunk con ese ID. La respuesta correcta es abstenerse indicando que el contexto no contiene esa información. | G21: Toda la pregunta. | H21: La técnica **T1417** en el marco de **MITRE ATT&CK** no corresponde a "Input Capture" en el contexto móvil. De hecho, **T1417** está relacionada con **"Input Capture" en dispositivos móviles**, pero es importante aclarar que **T1417** es una técnica de **ciberataque en dispositivos móviles**, y su descripción oficial es: > **T1417: Input Capture** – *An attacker can capture input from a mobile device (e.g., keyboard, microphone, camera) to gather sensitive data such as passwords, messages, or voice recordings.* Esta técnica implica que un atacante puede utilizar una aplicación maliciosa o un exploit para capturar entradas del usuario (como contraseñas, mensajes, llamadas o grabaciones) en un dispositivo móvil, lo cual puede ser usado para obtener información sensible. ### Mitigaciones propuestas por ATT&CK para T1417: El marco de ATT&CK **no proporciona una lista detallada de mitigaciones específicas para T1417** como se hace con otras técnicas. En cambio, **los controles de seguridad y buenas prácticas** recomendados para prevenir esta técnica incluyen: - **Revisar y restringir las permisos de aplicaciones** (por ejemplo, evitar que las apps accedan a micrófonos, cámaras o teclado). - **Habilitar y usar funciones de seguridad del sistema** (como el modo de privacidad o protección de entradas). - **Usar aplicaciones oficiales y verificadas** para evitar maliciosas que puedan capturar entradas. - **Educación del usuario** sobre el riesgo de compartir información sensible en aplicaciones no confiables. - **Monitoreo de actividad de entrada** (como teclado o micrófono) para detectar comportamientos anómalos. > ⚠️ Importante: T1417 está clasificada como **técnicas de ataque en dispositivos móviles**, y aunque está en el marco de ATT&CK, **no tiene una sección específica de "mitigaciones" detalladas** como otras técnicas. Las recomendaciones provienen de buenas prácticas de seguridad móvil. --- ✅ **Resumen:** - **T1417 (Input Capture)**: Permite a un atacante capturar entradas del usuario (contraseñas, mensajes, grabaciones) en dispositivos móviles. - **Mitigaciones**: Control de permisos, uso de apps oficiales, educación del usuario, monitoreo de actividad anómala. > Nota: ATT&CK no proporciona una lista oficial de mitigaciones para T1417. Las recomendaciones son derivadas de buenas prácticas de ciberseguridad móvil. | I21: NO | L21: =COUNTIFS(Afirmaciones!$A$2:$A$401,$A21,Afirmaciones!$B$2:$B$401,$B21) -> 0 | M21: =COUNTIFS(Hechos!$A$2:$A$201,$A21) -> 0 | N21: =IF($B21="rag",SUMIFS(Hechos!$F$2:$F$201,Hechos!$A$2:$A$201,$A21),SUMIFS(Hechos!$G$2:$G$201,Hechos!$A$2:$A$201,$A21)) -> 0 | O21: =IF($M21=0,"-",$N21&"/"&$M21) -> - | P21: =COUNTIFS(Afirmaciones!$A$2:$A$401,$A21,Afirmaciones!$B$2:$B$401,$B21,Afirmaciones!$E$2:$E$401,"hecho",Afirmaciones!$F$2:$F$401,"INCORRECTA") -> 0 | Q21: =COUNTIFS(Afirmaciones!$A$2:$A$401,$A21,Afirmaciones!$B$2:$B$401,$B21,Afirmaciones!$E$2:$E$401,"abstencion",Afirmaciones!$F$2:$F$401,"INCORRECTA") -> 0 | R21: =COUNTIFS(Afirmaciones!$A$2:$A$401,$A21,Afirmaciones!$B$2:$B$401,$B21,Afirmaciones!$E$2:$E$401,"hecho",Afirmaciones!$F$2:$F$401,"FUERA_REF",Afirmaciones!$H$2:$H$401,"no_resp") -> 0 | S21: =COUNTIFS(Afirmaciones!$A$2:$A$401,$A21,Afirmaciones!$B$2:$B$401,$B21,Afirmaciones!$E$2:$E$401,"hecho",Afirmaciones!$F$2:$F$401,"FUERA_REF") -> 0 | T21: =COUNTIFS(Afirmaciones!$A$2:$A$401,$A21,Afirmaciones!$B$2:$B$401,$B21,Afirmaciones!$E$2:$E$401,"hecho",Afirmaciones!$I$2:$I$401,"SIN-RESPALDO") -> 0 | U21: =COUNTIFS(Afirmaciones!$A$2:$A$401,$A21,Afirmaciones!$B$2:$B$401,$B21,Afirmaciones!$E$2:$E$401,"hecho",Afirmaciones!$I$2:$I$401,"CITA-X") -> 0 | V21: =COUNTIFS(Afirmaciones!$A$2:$A$401,$A21,Afirmaciones!$B$2:$B$401,$B21,Afirmaciones!$E$2:$E$401,"hecho",Afirmaciones!$I$2:$I$401,"SIN-CITA") -> 0 | W21: =COUNTIFS(Afirmaciones!$A$2:$A$401,$A21,Afirmaciones!$B$2:$B$401,$B21,Afirmaciones!$E$2:$E$401,"hecho") -> 0 | X21: =COUNTIFS(Afirmaciones!$A$2:$A$401,$A21,Afirmaciones!$B$2:$B$401,$B21,Afirmaciones!$E$2:$E$401,"hecho",Afirmaciones!$I$2:$I$401,"SOSTENIDA") -> 0 | Y21: =IF($L21=0,"",IF($M21=0,IF($R21>0,0,2),IF(AND($N21=$M21,$P21+$Q21+$R21=0),2,IF($N21=0,0,1)))) | Z21: =IF($L21=0,"",IF($B21="llm","N/A",IF($W21=0,"N/A",IF($X21=$W21,2,IF($X21=0,0,1))))) | AA21: =IF($L21=0,"",IF(AND($P21+$Q21+$R21=0,$T21+$U21=0,$I21<>"SI"),"-",TRIM(IF($P21+$Q21+$R21>0,"CRITICA ","")&IF($T21+$U21>0,"RESPALDO ","")&IF($I21="SI","TRUNC","")))) | AB21: =IF($L21=0,"",IF(AND($R21=0,$AF21=0,$AG21=0,$P21+$Q21=0,$T21+$U21+$V21=0),"OK",TRIM(IF($R21>0,"E0 ","")&IF($AF21>0,"E1 ","")&IF(OR($AG21>0,AND($P21+$Q21>0,$AF21=0)),"E2 ","")&IF($T21+$U21+$V21>0,"E3 ","")))) | AC21: =IF($AB21="","",IF($AB21="OK","OK",LEFT($AB21,2))) | AD21: =IF(OR($L21=0,$B21="llm",$W21=0),"-",$X21&"/"&$W21) -> - | AE21: =IF(OR($L21=0,$B21<>"rag",$M21=0),"-",SUMIFS(Hechos!$H$2:$H$201,Hechos!$A$2:$A$201,$A21)&"/"&$M21) -> - | AF21: =IF($B21="rag",SUMPRODUCT((Hechos!$A$2:$A$201=$A21)*(Hechos!$F$2:$F$201=0)*((Hechos!$E$2:$E$201="NO")+(Hechos!$E$2:$E$201="ALT-P")+(Hechos!$E$2:$E$201=""))),0) -> 0 | AG21: =IF($B21="rag",SUMPRODUCT((Hechos!$A$2:$A$201=$A21)*(Hechos!$F$2:$F$201=0)*((Hechos!$E$2:$E$201="SI")+(Hechos!$E$2:$E$201="ALT"))),$M21-$N21) -> 0
A22: p11 | B22: rag | C22: EN | D22: nula | E22: Which ICS tactic does T0855 Unauthorized Command Message belong to and which assets does it target? | F22: Not answerable from the corpus: T0855 belongs to the ics-attack domain, which is not ingested; no chunk carries that ID. The correct behaviour is to state that the context does not contain the information. | G22: Entire question. | H22: The context provided does not contain information about T0855 Unauthorized Command Message or any ICS (Industrial Control Systems) tactic. Therefore, it is not possible to determine which ICS tactic T0855 belongs to or which assets it targets based on the given passages. [No relevant context found.] | I22: NO | J22: N/A | K22: 0/0 | L22: =COUNTIFS(Afirmaciones!$A$2:$A$401,$A22,Afirmaciones!$B$2:$B$401,$B22) -> 0 | M22: =COUNTIFS(Hechos!$A$2:$A$201,$A22) -> 0 | N22: =IF($B22="rag",SUMIFS(Hechos!$F$2:$F$201,Hechos!$A$2:$A$201,$A22),SUMIFS(Hechos!$G$2:$G$201,Hechos!$A$2:$A$201,$A22)) -> 0 | O22: =IF($M22=0,"-",$N22&"/"&$M22) -> - | P22: =COUNTIFS(Afirmaciones!$A$2:$A$401,$A22,Afirmaciones!$B$2:$B$401,$B22,Afirmaciones!$E$2:$E$401,"hecho",Afirmaciones!$F$2:$F$401,"INCORRECTA") -> 0 | Q22: =COUNTIFS(Afirmaciones!$A$2:$A$401,$A22,Afirmaciones!$B$2:$B$401,$B22,Afirmaciones!$E$2:$E$401,"abstencion",Afirmaciones!$F$2:$F$401,"INCORRECTA") -> 0 | R22: =COUNTIFS(Afirmaciones!$A$2:$A$401,$A22,Afirmaciones!$B$2:$B$401,$B22,Afirmaciones!$E$2:$E$401,"hecho",Afirmaciones!$F$2:$F$401,"FUERA_REF",Afirmaciones!$H$2:$H$401,"no_resp") -> 0 | S22: =COUNTIFS(Afirmaciones!$A$2:$A$401,$A22,Afirmaciones!$B$2:$B$401,$B22,Afirmaciones!$E$2:$E$401,"hecho",Afirmaciones!$F$2:$F$401,"FUERA_REF") -> 0 | T22: =COUNTIFS(Afirmaciones!$A$2:$A$401,$A22,Afirmaciones!$B$2:$B$401,$B22,Afirmaciones!$E$2:$E$401,"hecho",Afirmaciones!$I$2:$I$401,"SIN-RESPALDO") -> 0 | U22: =COUNTIFS(Afirmaciones!$A$2:$A$401,$A22,Afirmaciones!$B$2:$B$401,$B22,Afirmaciones!$E$2:$E$401,"hecho",Afirmaciones!$I$2:$I$401,"CITA-X") -> 0 | V22: =COUNTIFS(Afirmaciones!$A$2:$A$401,$A22,Afirmaciones!$B$2:$B$401,$B22,Afirmaciones!$E$2:$E$401,"hecho",Afirmaciones!$I$2:$I$401,"SIN-CITA") -> 0 | W22: =COUNTIFS(Afirmaciones!$A$2:$A$401,$A22,Afirmaciones!$B$2:$B$401,$B22,Afirmaciones!$E$2:$E$401,"hecho") -> 0 | X22: =COUNTIFS(Afirmaciones!$A$2:$A$401,$A22,Afirmaciones!$B$2:$B$401,$B22,Afirmaciones!$E$2:$E$401,"hecho",Afirmaciones!$I$2:$I$401,"SOSTENIDA") -> 0 | Y22: =IF($L22=0,"",IF($M22=0,IF($R22>0,0,2),IF(AND($N22=$M22,$P22+$Q22+$R22=0),2,IF($N22=0,0,1)))) | Z22: =IF($L22=0,"",IF($B22="llm","N/A",IF($W22=0,"N/A",IF($X22=$W22,2,IF($X22=0,0,1))))) | AA22: =IF($L22=0,"",IF(AND($P22+$Q22+$R22=0,$T22+$U22=0,$I22<>"SI"),"-",TRIM(IF($P22+$Q22+$R22>0,"CRITICA ","")&IF($T22+$U22>0,"RESPALDO ","")&IF($I22="SI","TRUNC","")))) | AB22: =IF($L22=0,"",IF(AND($R22=0,$AF22=0,$AG22=0,$P22+$Q22=0,$T22+$U22+$V22=0),"OK",TRIM(IF($R22>0,"E0 ","")&IF($AF22>0,"E1 ","")&IF(OR($AG22>0,AND($P22+$Q22>0,$AF22=0)),"E2 ","")&IF($T22+$U22+$V22>0,"E3 ","")))) | AC22: =IF($AB22="","",IF($AB22="OK","OK",LEFT($AB22,2))) | AD22: =IF(OR($L22=0,$B22="llm",$W22=0),"-",$X22&"/"&$W22) -> - | AE22: =IF(OR($L22=0,$B22<>"rag",$M22=0),"-",SUMIFS(Hechos!$H$2:$H$201,Hechos!$A$2:$A$201,$A22)&"/"&$M22) -> - | AF22: =IF($B22="rag",SUMPRODUCT((Hechos!$A$2:$A$201=$A22)*(Hechos!$F$2:$F$201=0)*((Hechos!$E$2:$E$201="NO")+(Hechos!$E$2:$E$201="ALT-P")+(Hechos!$E$2:$E$201=""))),0) -> 0 | AG22: =IF($B22="rag",SUMPRODUCT((Hechos!$A$2:$A$201=$A22)*(Hechos!$F$2:$F$201=0)*((Hechos!$E$2:$E$201="SI")+(Hechos!$E$2:$E$201="ALT"))),$M22-$N22) -> 0
A23: p11 | B23: llm | C23: EN | D23: nula | E23: Which ICS tactic does T0855 Unauthorized Command Message belong to and which assets does it target? | F23: Not answerable from the corpus: T0855 belongs to the ics-attack domain, which is not ingested; no chunk carries that ID. The correct behaviour is to state that the context does not contain the information. | G23: Entire question. | H23: The technique T0855 (Unauthorized Command Message) is not a valid or recognized entry in the MITRE ATT&CK framework. There is no official technique with the ID "T0855" in the current MITRE ATT&CK database for cyberattack tactics and techniques, including those related to Industrial Control Systems (ICS). Additionally, the MITRE ATT&CK framework does not have a technique labeled "T0855" — the "T" prefix is used for techniques, but the numbering (e.g., T1059 for command and script injection) follows a specific structure and does not include T0855. Therefore, T0855 is not a valid or documented technique in the MITRE ATT&CK framework, and thus it does not belong to any ICS tactic, nor does it target any specific assets. If you meant a different technique or are referring to a non-standard or outdated identifier, please clarify. Answer: T0855 is not a valid technique in the MITRE ATT&CK framework and does not exist in any ICS tactic or asset targeting. | I23: NO | L23: =COUNTIFS(Afirmaciones!$A$2:$A$401,$A23,Afirmaciones!$B$2:$B$401,$B23) -> 0 | M23: =COUNTIFS(Hechos!$A$2:$A$201,$A23) -> 0 | N23: =IF($B23="rag",SUMIFS(Hechos!$F$2:$F$201,Hechos!$A$2:$A$201,$A23),SUMIFS(Hechos!$G$2:$G$201,Hechos!$A$2:$A$201,$A23)) -> 0 | O23: =IF($M23=0,"-",$N23&"/"&$M23) -> - | P23: =COUNTIFS(Afirmaciones!$A$2:$A$401,$A23,Afirmaciones!$B$2:$B$401,$B23,Afirmaciones!$E$2:$E$401,"hecho",Afirmaciones!$F$2:$F$401,"INCORRECTA") -> 0 | Q23: =COUNTIFS(Afirmaciones!$A$2:$A$401,$A23,Afirmaciones!$B$2:$B$401,$B23,Afirmaciones!$E$2:$E$401,"abstencion",Afirmaciones!$F$2:$F$401,"INCORRECTA") -> 0 | R23: =COUNTIFS(Afirmaciones!$A$2:$A$401,$A23,Afirmaciones!$B$2:$B$401,$B23,Afirmaciones!$E$2:$E$401,"hecho",Afirmaciones!$F$2:$F$401,"FUERA_REF",Afirmaciones!$H$2:$H$401,"no_resp") -> 0 | S23: =COUNTIFS(Afirmaciones!$A$2:$A$401,$A23,Afirmaciones!$B$2:$B$401,$B23,Afirmaciones!$E$2:$E$401,"hecho",Afirmaciones!$F$2:$F$401,"FUERA_REF") -> 0 | T23: =COUNTIFS(Afirmaciones!$A$2:$A$401,$A23,Afirmaciones!$B$2:$B$401,$B23,Afirmaciones!$E$2:$E$401,"hecho",Afirmaciones!$I$2:$I$401,"SIN-RESPALDO") -> 0 | U23: =COUNTIFS(Afirmaciones!$A$2:$A$401,$A23,Afirmaciones!$B$2:$B$401,$B23,Afirmaciones!$E$2:$E$401,"hecho",Afirmaciones!$I$2:$I$401,"CITA-X") -> 0 | V23: =COUNTIFS(Afirmaciones!$A$2:$A$401,$A23,Afirmaciones!$B$2:$B$401,$B23,Afirmaciones!$E$2:$E$401,"hecho",Afirmaciones!$I$2:$I$401,"SIN-CITA") -> 0 | W23: =COUNTIFS(Afirmaciones!$A$2:$A$401,$A23,Afirmaciones!$B$2:$B$401,$B23,Afirmaciones!$E$2:$E$401,"hecho") -> 0 | X23: =COUNTIFS(Afirmaciones!$A$2:$A$401,$A23,Afirmaciones!$B$2:$B$401,$B23,Afirmaciones!$E$2:$E$401,"hecho",Afirmaciones!$I$2:$I$401,"SOSTENIDA") -> 0 | Y23: =IF($L23=0,"",IF($M23=0,IF($R23>0,0,2),IF(AND($N23=$M23,$P23+$Q23+$R23=0),2,IF($N23=0,0,1)))) | Z23: =IF($L23=0,"",IF($B23="llm","N/A",IF($W23=0,"N/A",IF($X23=$W23,2,IF($X23=0,0,1))))) | AA23: =IF($L23=0,"",IF(AND($P23+$Q23+$R23=0,$T23+$U23=0,$I23<>"SI"),"-",TRIM(IF($P23+$Q23+$R23>0,"CRITICA ","")&IF($T23+$U23>0,"RESPALDO ","")&IF($I23="SI","TRUNC","")))) | AB23: =IF($L23=0,"",IF(AND($R23=0,$AF23=0,$AG23=0,$P23+$Q23=0,$T23+$U23+$V23=0),"OK",TRIM(IF($R23>0,"E0 ","")&IF($AF23>0,"E1 ","")&IF(OR($AG23>0,AND($P23+$Q23>0,$AF23=0)),"E2 ","")&IF($T23+$U23+$V23>0,"E3 ","")))) | AC23: =IF($AB23="","",IF($AB23="OK","OK",LEFT($AB23,2))) | AD23: =IF(OR($L23=0,$B23="llm",$W23=0),"-",$X23&"/"&$W23) -> - | AE23: =IF(OR($L23=0,$B23<>"rag",$M23=0),"-",SUMIFS(Hechos!$H$2:$H$201,Hechos!$A$2:$A$201,$A23)&"/"&$M23) -> - | AF23: =IF($B23="rag",SUMPRODUCT((Hechos!$A$2:$A$201=$A23)*(Hechos!$F$2:$F$201=0)*((Hechos!$E$2:$E$201="NO")+(Hechos!$E$2:$E$201="ALT-P")+(Hechos!$E$2:$E$201=""))),0) -> 0 | AG23: =IF($B23="rag",SUMPRODUCT((Hechos!$A$2:$A$201=$A23)*(Hechos!$F$2:$F$201=0)*((Hechos!$E$2:$E$201="SI")+(Hechos!$E$2:$E$201="ALT"))),$M23-$N23) -> 0
A24: p12 | B24: rag | C24: ES | D24: nula | E24: ¿Cuál fue la técnica ATT&CK más utilizada por los atacantes a nivel mundial durante 2026? | F24: No respondible: ATT&CK describe técnicas, grupos y procedimientos, pero no contiene estadísticas de frecuencia de uso por año. La respuesta correcta es abstenerse. | G24: Toda la pregunta. | H24: No se proporciona información en los contextos sobre cuál fue la técnica ATT&CK más utilizada por los atacantes a nivel mundial durante 2026. Aunque se mencionan varias herramientas y tácticas (como T1608.004, S9041, S9042, S9044), no hay datos que indiquen cuál fue la técnica más utilizada a nivel mundial en ese año. Por lo tanto, no se puede determinar la respuesta basándose únicamente en el contenido dado. Respuesta: No se puede determinar con la información proporcionada. | I24: NO | J24: N/A | K24: 0/0 | L24: =COUNTIFS(Afirmaciones!$A$2:$A$401,$A24,Afirmaciones!$B$2:$B$401,$B24) -> 0 | M24: =COUNTIFS(Hechos!$A$2:$A$201,$A24) -> 0 | N24: =IF($B24="rag",SUMIFS(Hechos!$F$2:$F$201,Hechos!$A$2:$A$201,$A24),SUMIFS(Hechos!$G$2:$G$201,Hechos!$A$2:$A$201,$A24)) -> 0 | O24: =IF($M24=0,"-",$N24&"/"&$M24) -> - | P24: =COUNTIFS(Afirmaciones!$A$2:$A$401,$A24,Afirmaciones!$B$2:$B$401,$B24,Afirmaciones!$E$2:$E$401,"hecho",Afirmaciones!$F$2:$F$401,"INCORRECTA") -> 0 | Q24: =COUNTIFS(Afirmaciones!$A$2:$A$401,$A24,Afirmaciones!$B$2:$B$401,$B24,Afirmaciones!$E$2:$E$401,"abstencion",Afirmaciones!$F$2:$F$401,"INCORRECTA") -> 0 | R24: =COUNTIFS(Afirmaciones!$A$2:$A$401,$A24,Afirmaciones!$B$2:$B$401,$B24,Afirmaciones!$E$2:$E$401,"hecho",Afirmaciones!$F$2:$F$401,"FUERA_REF",Afirmaciones!$H$2:$H$401,"no_resp") -> 0 | S24: =COUNTIFS(Afirmaciones!$A$2:$A$401,$A24,Afirmaciones!$B$2:$B$401,$B24,Afirmaciones!$E$2:$E$401,"hecho",Afirmaciones!$F$2:$F$401,"FUERA_REF") -> 0 | T24: =COUNTIFS(Afirmaciones!$A$2:$A$401,$A24,Afirmaciones!$B$2:$B$401,$B24,Afirmaciones!$E$2:$E$401,"hecho",Afirmaciones!$I$2:$I$401,"SIN-RESPALDO") -> 0 | U24: =COUNTIFS(Afirmaciones!$A$2:$A$401,$A24,Afirmaciones!$B$2:$B$401,$B24,Afirmaciones!$E$2:$E$401,"hecho",Afirmaciones!$I$2:$I$401,"CITA-X") -> 0 | V24: =COUNTIFS(Afirmaciones!$A$2:$A$401,$A24,Afirmaciones!$B$2:$B$401,$B24,Afirmaciones!$E$2:$E$401,"hecho",Afirmaciones!$I$2:$I$401,"SIN-CITA") -> 0 | W24: =COUNTIFS(Afirmaciones!$A$2:$A$401,$A24,Afirmaciones!$B$2:$B$401,$B24,Afirmaciones!$E$2:$E$401,"hecho") -> 0 | X24: =COUNTIFS(Afirmaciones!$A$2:$A$401,$A24,Afirmaciones!$B$2:$B$401,$B24,Afirmaciones!$E$2:$E$401,"hecho",Afirmaciones!$I$2:$I$401,"SOSTENIDA") -> 0 | Y24: =IF($L24=0,"",IF($M24=0,IF($R24>0,0,2),IF(AND($N24=$M24,$P24+$Q24+$R24=0),2,IF($N24=0,0,1)))) | Z24: =IF($L24=0,"",IF($B24="llm","N/A",IF($W24=0,"N/A",IF($X24=$W24,2,IF($X24=0,0,1))))) | AA24: =IF($L24=0,"",IF(AND($P24+$Q24+$R24=0,$T24+$U24=0,$I24<>"SI"),"-",TRIM(IF($P24+$Q24+$R24>0,"CRITICA ","")&IF($T24+$U24>0,"RESPALDO ","")&IF($I24="SI","TRUNC","")))) | AB24: =IF($L24=0,"",IF(AND($R24=0,$AF24=0,$AG24=0,$P24+$Q24=0,$T24+$U24+$V24=0),"OK",TRIM(IF($R24>0,"E0 ","")&IF($AF24>0,"E1 ","")&IF(OR($AG24>0,AND($P24+$Q24>0,$AF24=0)),"E2 ","")&IF($T24+$U24+$V24>0,"E3 ","")))) | AC24: =IF($AB24="","",IF($AB24="OK","OK",LEFT($AB24,2))) | AD24: =IF(OR($L24=0,$B24="llm",$W24=0),"-",$X24&"/"&$W24) -> - | AE24: =IF(OR($L24=0,$B24<>"rag",$M24=0),"-",SUMIFS(Hechos!$H$2:$H$201,Hechos!$A$2:$A$201,$A24)&"/"&$M24) -> - | AF24: =IF($B24="rag",SUMPRODUCT((Hechos!$A$2:$A$201=$A24)*(Hechos!$F$2:$F$201=0)*((Hechos!$E$2:$E$201="NO")+(Hechos!$E$2:$E$201="ALT-P")+(Hechos!$E$2:$E$201=""))),0) -> 0 | AG24: =IF($B24="rag",SUMPRODUCT((Hechos!$A$2:$A$201=$A24)*(Hechos!$F$2:$F$201=0)*((Hechos!$E$2:$E$201="SI")+(Hechos!$E$2:$E$201="ALT"))),$M24-$N24) -> 0
A25: p12 | B25: llm | C25: ES | D25: nula | E25: ¿Cuál fue la técnica ATT&CK más utilizada por los atacantes a nivel mundial durante 2026? | F25: No respondible: ATT&CK describe técnicas, grupos y procedimientos, pero no contiene estadísticas de frecuencia de uso por año. La respuesta correcta es abstenerse. | G25: Toda la pregunta. | H25: No se dispone de datos oficiales o públicos que indiquen cuál fue la técnica ATT&CK más utilizada por los atacantes a nivel mundial durante 2026, ya que ese año aún no ha ocurrido y no se han publicado estadísticas oficiales sobre el uso de técnicas de ataque en el marco del MITRE ATT&CK para ese período. Además, el MITRE ATT&CK no proporciona un ranking anual de técnicas más utilizadas por atacantes en un año futuro. Los datos sobre el uso de técnicas de ataque se basan en análisis de incidentes reales, reportes de amenazas y estudios de seguridad que se publican en años pasados. Por lo tanto, no es posible responder con precisión a la pregunta sobre la técnica más utilizada en 2026. Si te interesa, puedo proporcionar información sobre las técnicas más comunes en años pasados (por ejemplo, 2023 o 2024) o sobre las más frecuentes en el marco del MITRE ATT&CK actual. | I25: NO | L25: =COUNTIFS(Afirmaciones!$A$2:$A$401,$A25,Afirmaciones!$B$2:$B$401,$B25) -> 0 | M25: =COUNTIFS(Hechos!$A$2:$A$201,$A25) -> 0 | N25: =IF($B25="rag",SUMIFS(Hechos!$F$2:$F$201,Hechos!$A$2:$A$201,$A25),SUMIFS(Hechos!$G$2:$G$201,Hechos!$A$2:$A$201,$A25)) -> 0 | O25: =IF($M25=0,"-",$N25&"/"&$M25) -> - | P25: =COUNTIFS(Afirmaciones!$A$2:$A$401,$A25,Afirmaciones!$B$2:$B$401,$B25,Afirmaciones!$E$2:$E$401,"hecho",Afirmaciones!$F$2:$F$401,"INCORRECTA") -> 0 | Q25: =COUNTIFS(Afirmaciones!$A$2:$A$401,$A25,Afirmaciones!$B$2:$B$401,$B25,Afirmaciones!$E$2:$E$401,"abstencion",Afirmaciones!$F$2:$F$401,"INCORRECTA") -> 0 | R25: =COUNTIFS(Afirmaciones!$A$2:$A$401,$A25,Afirmaciones!$B$2:$B$401,$B25,Afirmaciones!$E$2:$E$401,"hecho",Afirmaciones!$F$2:$F$401,"FUERA_REF",Afirmaciones!$H$2:$H$401,"no_resp") -> 0 | S25: =COUNTIFS(Afirmaciones!$A$2:$A$401,$A25,Afirmaciones!$B$2:$B$401,$B25,Afirmaciones!$E$2:$E$401,"hecho",Afirmaciones!$F$2:$F$401,"FUERA_REF") -> 0 | T25: =COUNTIFS(Afirmaciones!$A$2:$A$401,$A25,Afirmaciones!$B$2:$B$401,$B25,Afirmaciones!$E$2:$E$401,"hecho",Afirmaciones!$I$2:$I$401,"SIN-RESPALDO") -> 0 | U25: =COUNTIFS(Afirmaciones!$A$2:$A$401,$A25,Afirmaciones!$B$2:$B$401,$B25,Afirmaciones!$E$2:$E$401,"hecho",Afirmaciones!$I$2:$I$401,"CITA-X") -> 0 | V25: =COUNTIFS(Afirmaciones!$A$2:$A$401,$A25,Afirmaciones!$B$2:$B$401,$B25,Afirmaciones!$E$2:$E$401,"hecho",Afirmaciones!$I$2:$I$401,"SIN-CITA") -> 0 | W25: =COUNTIFS(Afirmaciones!$A$2:$A$401,$A25,Afirmaciones!$B$2:$B$401,$B25,Afirmaciones!$E$2:$E$401,"hecho") -> 0 | X25: =COUNTIFS(Afirmaciones!$A$2:$A$401,$A25,Afirmaciones!$B$2:$B$401,$B25,Afirmaciones!$E$2:$E$401,"hecho",Afirmaciones!$I$2:$I$401,"SOSTENIDA") -> 0 | Y25: =IF($L25=0,"",IF($M25=0,IF($R25>0,0,2),IF(AND($N25=$M25,$P25+$Q25+$R25=0),2,IF($N25=0,0,1)))) | Z25: =IF($L25=0,"",IF($B25="llm","N/A",IF($W25=0,"N/A",IF($X25=$W25,2,IF($X25=0,0,1))))) | AA25: =IF($L25=0,"",IF(AND($P25+$Q25+$R25=0,$T25+$U25=0,$I25<>"SI"),"-",TRIM(IF($P25+$Q25+$R25>0,"CRITICA ","")&IF($T25+$U25>0,"RESPALDO ","")&IF($I25="SI","TRUNC","")))) | AB25: =IF($L25=0,"",IF(AND($R25=0,$AF25=0,$AG25=0,$P25+$Q25=0,$T25+$U25+$V25=0),"OK",TRIM(IF($R25>0,"E0 ","")&IF($AF25>0,"E1 ","")&IF(OR($AG25>0,AND($P25+$Q25>0,$AF25=0)),"E2 ","")&IF($T25+$U25+$V25>0,"E3 ","")))) | AC25: =IF($AB25="","",IF($AB25="OK","OK",LEFT($AB25,2))) | AD25: =IF(OR($L25=0,$B25="llm",$W25=0),"-",$X25&"/"&$W25) -> - | AE25: =IF(OR($L25=0,$B25<>"rag",$M25=0),"-",SUMIFS(Hechos!$H$2:$H$201,Hechos!$A$2:$A$201,$A25)&"/"&$M25) -> - | AF25: =IF($B25="rag",SUMPRODUCT((Hechos!$A$2:$A$201=$A25)*(Hechos!$F$2:$F$201=0)*((Hechos!$E$2:$E$201="NO")+(Hechos!$E$2:$E$201="ALT-P")+(Hechos!$E$2:$E$201=""))),0) -> 0 | AG25: =IF($B25="rag",SUMPRODUCT((Hechos!$A$2:$A$201=$A25)*(Hechos!$F$2:$F$201=0)*((Hechos!$E$2:$E$201="SI")+(Hechos!$E$2:$E$201="ALT"))),$M25-$N25) -> 0
A26: p13 | B26: rag | C26: ES | D26: nula | E26: ¿Qué describe la sub-técnica T1059.099 de ATT&CK y a qué táctica pertenece? | F26: No respondible: T1059.099 no existe en ATT&CK ni en el corpus. La respuesta correcta es indicar que no hay información sobre ese identificador (sin inventar una sub-técnica de T1059). | G26: Toda la pregunta. | H26: No se proporciona información sobre la sub-técnica T1059.099 en los contextos dados. Por lo tanto, no se puede describir ni identificar a qué táctica pertenece. [N/A] | I26: NO | J26: N/A | K26: 0/0 | L26: =COUNTIFS(Afirmaciones!$A$2:$A$401,$A26,Afirmaciones!$B$2:$B$401,$B26) -> 0 | M26: =COUNTIFS(Hechos!$A$2:$A$201,$A26) -> 0 | N26: =IF($B26="rag",SUMIFS(Hechos!$F$2:$F$201,Hechos!$A$2:$A$201,$A26),SUMIFS(Hechos!$G$2:$G$201,Hechos!$A$2:$A$201,$A26)) -> 0 | O26: =IF($M26=0,"-",$N26&"/"&$M26) -> - | P26: =COUNTIFS(Afirmaciones!$A$2:$A$401,$A26,Afirmaciones!$B$2:$B$401,$B26,Afirmaciones!$E$2:$E$401,"hecho",Afirmaciones!$F$2:$F$401,"INCORRECTA") -> 0 | Q26: =COUNTIFS(Afirmaciones!$A$2:$A$401,$A26,Afirmaciones!$B$2:$B$401,$B26,Afirmaciones!$E$2:$E$401,"abstencion",Afirmaciones!$F$2:$F$401,"INCORRECTA") -> 0 | R26: =COUNTIFS(Afirmaciones!$A$2:$A$401,$A26,Afirmaciones!$B$2:$B$401,$B26,Afirmaciones!$E$2:$E$401,"hecho",Afirmaciones!$F$2:$F$401,"FUERA_REF",Afirmaciones!$H$2:$H$401,"no_resp") -> 0 | S26: =COUNTIFS(Afirmaciones!$A$2:$A$401,$A26,Afirmaciones!$B$2:$B$401,$B26,Afirmaciones!$E$2:$E$401,"hecho",Afirmaciones!$F$2:$F$401,"FUERA_REF") -> 0 | T26: =COUNTIFS(Afirmaciones!$A$2:$A$401,$A26,Afirmaciones!$B$2:$B$401,$B26,Afirmaciones!$E$2:$E$401,"hecho",Afirmaciones!$I$2:$I$401,"SIN-RESPALDO") -> 0 | U26: =COUNTIFS(Afirmaciones!$A$2:$A$401,$A26,Afirmaciones!$B$2:$B$401,$B26,Afirmaciones!$E$2:$E$401,"hecho",Afirmaciones!$I$2:$I$401,"CITA-X") -> 0 | V26: =COUNTIFS(Afirmaciones!$A$2:$A$401,$A26,Afirmaciones!$B$2:$B$401,$B26,Afirmaciones!$E$2:$E$401,"hecho",Afirmaciones!$I$2:$I$401,"SIN-CITA") -> 0 | W26: =COUNTIFS(Afirmaciones!$A$2:$A$401,$A26,Afirmaciones!$B$2:$B$401,$B26,Afirmaciones!$E$2:$E$401,"hecho") -> 0 | X26: =COUNTIFS(Afirmaciones!$A$2:$A$401,$A26,Afirmaciones!$B$2:$B$401,$B26,Afirmaciones!$E$2:$E$401,"hecho",Afirmaciones!$I$2:$I$401,"SOSTENIDA") -> 0 | Y26: =IF($L26=0,"",IF($M26=0,IF($R26>0,0,2),IF(AND($N26=$M26,$P26+$Q26+$R26=0),2,IF($N26=0,0,1)))) | Z26: =IF($L26=0,"",IF($B26="llm","N/A",IF($W26=0,"N/A",IF($X26=$W26,2,IF($X26=0,0,1))))) | AA26: =IF($L26=0,"",IF(AND($P26+$Q26+$R26=0,$T26+$U26=0,$I26<>"SI"),"-",TRIM(IF($P26+$Q26+$R26>0,"CRITICA ","")&IF($T26+$U26>0,"RESPALDO ","")&IF($I26="SI","TRUNC","")))) | AB26: =IF($L26=0,"",IF(AND($R26=0,$AF26=0,$AG26=0,$P26+$Q26=0,$T26+$U26+$V26=0),"OK",TRIM(IF($R26>0,"E0 ","")&IF($AF26>0,"E1 ","")&IF(OR($AG26>0,AND($P26+$Q26>0,$AF26=0)),"E2 ","")&IF($T26+$U26+$V26>0,"E3 ","")))) | AC26: =IF($AB26="","",IF($AB26="OK","OK",LEFT($AB26,2))) | AD26: =IF(OR($L26=0,$B26="llm",$W26=0),"-",$X26&"/"&$W26) -> - | AE26: =IF(OR($L26=0,$B26<>"rag",$M26=0),"-",SUMIFS(Hechos!$H$2:$H$201,Hechos!$A$2:$A$201,$A26)&"/"&$M26) -> - | AF26: =IF($B26="rag",SUMPRODUCT((Hechos!$A$2:$A$201=$A26)*(Hechos!$F$2:$F$201=0)*((Hechos!$E$2:$E$201="NO")+(Hechos!$E$2:$E$201="ALT-P")+(Hechos!$E$2:$E$201=""))),0) -> 0 | AG26: =IF($B26="rag",SUMPRODUCT((Hechos!$A$2:$A$201=$A26)*(Hechos!$F$2:$F$201=0)*((Hechos!$E$2:$E$201="SI")+(Hechos!$E$2:$E$201="ALT"))),$M26-$N26) -> 0
A27: p13 | B27: llm | C27: ES | D27: nula | E27: ¿Qué describe la sub-técnica T1059.099 de ATT&CK y a qué táctica pertenece? | F27: No respondible: T1059.099 no existe en ATT&CK ni en el corpus. La respuesta correcta es indicar que no hay información sobre ese identificador (sin inventar una sub-técnica de T1059). | G27: Toda la pregunta. | H27: La sub-técnica T1059.099 de ATT&CK describe **"Command and Scripting Interpreter: PowerShell"**, específicamente el uso de **PowerShell para ejecutar comandos y scripts**. Pertenece a la **táctica T1059: Command and Scripting Interpreter**, que incluye el uso de interpretadores de comandos y scripts para ejecutar código en sistemas operativos, como PowerShell, Bash, o otros lenguajes de scripting. **Respuesta final:** La sub-técnica T1059.099 describe el uso de PowerShell como interpretador de comandos y scripts, y pertenece a la táctica T1059: Command and Scripting Interpreter. | I27: NO | L27: =COUNTIFS(Afirmaciones!$A$2:$A$401,$A27,Afirmaciones!$B$2:$B$401,$B27) -> 0 | M27: =COUNTIFS(Hechos!$A$2:$A$201,$A27) -> 0 | N27: =IF($B27="rag",SUMIFS(Hechos!$F$2:$F$201,Hechos!$A$2:$A$201,$A27),SUMIFS(Hechos!$G$2:$G$201,Hechos!$A$2:$A$201,$A27)) -> 0 | O27: =IF($M27=0,"-",$N27&"/"&$M27) -> - | P27: =COUNTIFS(Afirmaciones!$A$2:$A$401,$A27,Afirmaciones!$B$2:$B$401,$B27,Afirmaciones!$E$2:$E$401,"hecho",Afirmaciones!$F$2:$F$401,"INCORRECTA") -> 0 | Q27: =COUNTIFS(Afirmaciones!$A$2:$A$401,$A27,Afirmaciones!$B$2:$B$401,$B27,Afirmaciones!$E$2:$E$401,"abstencion",Afirmaciones!$F$2:$F$401,"INCORRECTA") -> 0 | R27: =COUNTIFS(Afirmaciones!$A$2:$A$401,$A27,Afirmaciones!$B$2:$B$401,$B27,Afirmaciones!$E$2:$E$401,"hecho",Afirmaciones!$F$2:$F$401,"FUERA_REF",Afirmaciones!$H$2:$H$401,"no_resp") -> 0 | S27: =COUNTIFS(Afirmaciones!$A$2:$A$401,$A27,Afirmaciones!$B$2:$B$401,$B27,Afirmaciones!$E$2:$E$401,"hecho",Afirmaciones!$F$2:$F$401,"FUERA_REF") -> 0 | T27: =COUNTIFS(Afirmaciones!$A$2:$A$401,$A27,Afirmaciones!$B$2:$B$401,$B27,Afirmaciones!$E$2:$E$401,"hecho",Afirmaciones!$I$2:$I$401,"SIN-RESPALDO") -> 0 | U27: =COUNTIFS(Afirmaciones!$A$2:$A$401,$A27,Afirmaciones!$B$2:$B$401,$B27,Afirmaciones!$E$2:$E$401,"hecho",Afirmaciones!$I$2:$I$401,"CITA-X") -> 0 | V27: =COUNTIFS(Afirmaciones!$A$2:$A$401,$A27,Afirmaciones!$B$2:$B$401,$B27,Afirmaciones!$E$2:$E$401,"hecho",Afirmaciones!$I$2:$I$401,"SIN-CITA") -> 0 | W27: =COUNTIFS(Afirmaciones!$A$2:$A$401,$A27,Afirmaciones!$B$2:$B$401,$B27,Afirmaciones!$E$2:$E$401,"hecho") -> 0 | X27: =COUNTIFS(Afirmaciones!$A$2:$A$401,$A27,Afirmaciones!$B$2:$B$401,$B27,Afirmaciones!$E$2:$E$401,"hecho",Afirmaciones!$I$2:$I$401,"SOSTENIDA") -> 0 | Y27: =IF($L27=0,"",IF($M27=0,IF($R27>0,0,2),IF(AND($N27=$M27,$P27+$Q27+$R27=0),2,IF($N27=0,0,1)))) | Z27: =IF($L27=0,"",IF($B27="llm","N/A",IF($W27=0,"N/A",IF($X27=$W27,2,IF($X27=0,0,1))))) | AA27: =IF($L27=0,"",IF(AND($P27+$Q27+$R27=0,$T27+$U27=0,$I27<>"SI"),"-",TRIM(IF($P27+$Q27+$R27>0,"CRITICA ","")&IF($T27+$U27>0,"RESPALDO ","")&IF($I27="SI","TRUNC","")))) | AB27: =IF($L27=0,"",IF(AND($R27=0,$AF27=0,$AG27=0,$P27+$Q27=0,$T27+$U27+$V27=0),"OK",TRIM(IF($R27>0,"E0 ","")&IF($AF27>0,"E1 ","")&IF(OR($AG27>0,AND($P27+$Q27>0,$AF27=0)),"E2 ","")&IF($T27+$U27+$V27>0,"E3 ","")))) | AC27: =IF($AB27="","",IF($AB27="OK","OK",LEFT($AB27,2))) | AD27: =IF(OR($L27=0,$B27="llm",$W27=0),"-",$X27&"/"&$W27) -> - | AE27: =IF(OR($L27=0,$B27<>"rag",$M27=0),"-",SUMIFS(Hechos!$H$2:$H$201,Hechos!$A$2:$A$201,$A27)&"/"&$M27) -> - | AF27: =IF($B27="rag",SUMPRODUCT((Hechos!$A$2:$A$201=$A27)*(Hechos!$F$2:$F$201=0)*((Hechos!$E$2:$E$201="NO")+(Hechos!$E$2:$E$201="ALT-P")+(Hechos!$E$2:$E$201=""))),0) -> 0 | AG27: =IF($B27="rag",SUMPRODUCT((Hechos!$A$2:$A$201=$A27)*(Hechos!$F$2:$F$201=0)*((Hechos!$E$2:$E$201="SI")+(Hechos!$E$2:$E$201="ALT"))),$M27-$N27) -> 0

Sheet Afirmaciones
A1: qid | B1: modo | C1: n | D1: afirmación | E1: tipo | F1: vs_ref | G1: hecho_ref | H1: zona | I1: respaldo | J1: cita_n | K1: fragmento_sostiene | L1: nota | M1: códigos (auto) | N1: chequeo (auto)
A2: p05 | B2: rag | C2: =IF(A2="","",COUNTIFS($A$2:A2,A2,$B$2:B2,B2)) -> 1 | D2: APT29 (G0016) utiliza Mimikatz | E2: hecho | F2: CORRECTA | G2: H1 | H2: ref | I2: SIN-RESPALDO | J2: 1 | L2: correcta pero ningún fragmento vincula APT29 con Mimikatz | M2: =IF(D2="","",IF(OR(E2="",F2=""),"",IF(TRIM(IF(AND(E2="hecho",F2="INCORRECTA"),"INC ","")&IF(AND(E2="abstencion",F2="INCORRECTA"),"ABS-E ","")&IF(AND(E2="hecho",F2="FUERA_REF",H2="no_resp"),"NO-ABS ","")&IF(AND(E2="hecho",I2="SIN-RESPALDO"),"SIN-R ","")&IF(AND(E2="hecho",I2="CITA-X"),"CITA-X ","")&IF(AND(E2="hecho",I2="SIN-CITA"),"SIN-C ",""))="","-",TRIM(IF(AND(E2="hecho",F2="INCORRECTA"),"INC ","")&IF(AND(E2="abstencion",F2="INCORRECTA"),"ABS-E ","")&IF(AND(E2="hecho",F2="FUERA_REF",H2="no_resp"),"NO-ABS ","")&IF(AND(E2="hecho",I2="SIN-RESPALDO"),"SIN-R ","")&IF(AND(E2="hecho",I2="CITA-X"),"CITA-X ","")&IF(AND(E2="hecho",I2="SIN-CITA"),"SIN-C ",""))))) -> SIN-R | N2: =IF(D2="","",IF(OR(A2="",B2="",E2="",F2=""),"falta qid, modo, tipo o vs_ref",IF(AND(B2="llm",I2<>""),"respaldo no aplica en modo LLM",IF(AND(E2="abstencion",I2<>""),"una abstención no se califica en citas",IF(AND(B2="rag",E2="hecho",I2=""),"falta respaldo","ok"))))) -> ok
A3: p05 | B3: rag | C3: =IF(A3="","",COUNTIFS($A$2:A3,A3,$B$2:B3,B3)) -> 2 | D3: APT29 usó ataques Kerberos para movimiento lateral | E3: hecho | F3: FUERA_REF | H3: ref | I3: SOSTENIDA | J3: 1 | K3: 1 | M3: =IF(D3="","",IF(OR(E3="",F3=""),"",IF(TRIM(IF(AND(E3="hecho",F3="INCORRECTA"),"INC ","")&IF(AND(E3="abstencion",F3="INCORRECTA"),"ABS-E ","")&IF(AND(E3="hecho",F3="FUERA_REF",H3="no_resp"),"NO-ABS ","")&IF(AND(E3="hecho",I3="SIN-RESPALDO"),"SIN-R ","")&IF(AND(E3="hecho",I3="CITA-X"),"CITA-X ","")&IF(AND(E3="hecho",I3="SIN-CITA"),"SIN-C ",""))="","-",TRIM(IF(AND(E3="hecho",F3="INCORRECTA"),"INC ","")&IF(AND(E3="abstencion",F3="INCORRECTA"),"ABS-E ","")&IF(AND(E3="hecho",F3="FUERA_REF",H3="no_resp"),"NO-ABS ","")&IF(AND(E3="hecho",I3="SIN-RESPALDO"),"SIN-R ","")&IF(AND(E3="hecho",I3="CITA-X"),"CITA-X ","")&IF(AND(E3="hecho",I3="SIN-CITA"),"SIN-C ",""))))) -> - | N3: =IF(D3="","",IF(OR(A3="",B3="",E3="",F3=""),"falta qid, modo, tipo o vs_ref",IF(AND(B3="llm",I3<>""),"respaldo no aplica en modo LLM",IF(AND(E3="abstencion",I3<>""),"una abstención no se califica en citas",IF(AND(B3="rag",E3="hecho",I3=""),"falta respaldo","ok"))))) -> ok
A4: p05 | B4: rag | C4: =IF(A4="","",COUNTIFS($A$2:A4,A4,$B$2:B4,B4)) -> 3 | D4: Mimikatz implementa T1550.003 Pass the Ticket | E4: hecho | F4: CORRECTA | G4: H2 | H4: ref | I4: SOSTENIDA | J4: 1 | K4: 1 | M4: =IF(D4="","",IF(OR(E4="",F4=""),"",IF(TRIM(IF(AND(E4="hecho",F4="INCORRECTA"),"INC ","")&IF(AND(E4="abstencion",F4="INCORRECTA"),"ABS-E ","")&IF(AND(E4="hecho",F4="FUERA_REF",H4="no_resp"),"NO-ABS ","")&IF(AND(E4="hecho",I4="SIN-RESPALDO"),"SIN-R ","")&IF(AND(E4="hecho",I4="CITA-X"),"CITA-X ","")&IF(AND(E4="hecho",I4="SIN-CITA"),"SIN-C ",""))="","-",TRIM(IF(AND(E4="hecho",F4="INCORRECTA"),"INC ","")&IF(AND(E4="abstencion",F4="INCORRECTA"),"ABS-E ","")&IF(AND(E4="hecho",F4="FUERA_REF",H4="no_resp"),"NO-ABS ","")&IF(AND(E4="hecho",I4="SIN-RESPALDO"),"SIN-R ","")&IF(AND(E4="hecho",I4="CITA-X"),"CITA-X ","")&IF(AND(E4="hecho",I4="SIN-CITA"),"SIN-C ",""))))) -> - | N4: =IF(D4="","",IF(OR(A4="",B4="",E4="",F4=""),"falta qid, modo, tipo o vs_ref",IF(AND(B4="llm",I4<>""),"respaldo no aplica en modo LLM",IF(AND(E4="abstencion",I4<>""),"una abstención no se califica en citas",IF(AND(B4="rag",E4="hecho",I4=""),"falta respaldo","ok"))))) -> ok
A5: p05 | B5: llm | C5: =IF(A5="","",COUNTIFS($A$2:A5,A5,$B$2:B5,B5)) -> 1 | D5: APT29 no utiliza directamente Mimikatz | E5: hecho | F5: INCORRECTA | G5: H1 | H5: ref | L5: contradice H1 | M5: =IF(D5="","",IF(OR(E5="",F5=""),"",IF(TRIM(IF(AND(E5="hecho",F5="INCORRECTA"),"INC ","")&IF(AND(E5="abstencion",F5="INCORRECTA"),"ABS-E ","")&IF(AND(E5="hecho",F5="FUERA_REF",H5="no_resp"),"NO-ABS ","")&IF(AND(E5="hecho",I5="SIN-RESPALDO"),"SIN-R ","")&IF(AND(E5="hecho",I5="CITA-X"),"CITA-X ","")&IF(AND(E5="hecho",I5="SIN-CITA"),"SIN-C ",""))="","-",TRIM(IF(AND(E5="hecho",F5="INCORRECTA"),"INC ","")&IF(AND(E5="abstencion",F5="INCORRECTA"),"ABS-E ","")&IF(AND(E5="hecho",F5="FUERA_REF",H5="no_resp"),"NO-ABS ","")&IF(AND(E5="hecho",I5="SIN-RESPALDO"),"SIN-R ","")&IF(AND(E5="hecho",I5="CITA-X"),"CITA-X ","")&IF(AND(E5="hecho",I5="SIN-CITA"),"SIN-C ",""))))) -> INC | N5: =IF(D5="","",IF(OR(A5="",B5="",E5="",F5=""),"falta qid, modo, tipo o vs_ref",IF(AND(B5="llm",I5<>""),"respaldo no aplica en modo LLM",IF(AND(E5="abstencion",I5<>""),"una abstención no se califica en citas",IF(AND(B5="rag",E5="hecho",I5=""),"falta respaldo","ok"))))) -> ok
A6: p05 | B6: llm | C6: =IF(A6="","",COUNTIFS($A$2:A6,A6,$B$2:B6,B6)) -> 2 | D6: La técnica de tickets Kerberos es T1547.001 Exploitation of Kerberos | E6: hecho | F6: INCORRECTA | H6: ref | L6: T1547.001 es Registry Run Keys; ese nombre no existe en el corpus | M6: =IF(D6="","",IF(OR(E6="",F6=""),"",IF(TRIM(IF(AND(E6="hecho",F6="INCORRECTA"),"INC ","")&IF(AND(E6="abstencion",F6="INCORRECTA"),"ABS-E ","")&IF(AND(E6="hecho",F6="FUERA_REF",H6="no_resp"),"NO-ABS ","")&IF(AND(E6="hecho",I6="SIN-RESPALDO"),"SIN-R ","")&IF(AND(E6="hecho",I6="CITA-X"),"CITA-X ","")&IF(AND(E6="hecho",I6="SIN-CITA"),"SIN-C ",""))="","-",TRIM(IF(AND(E6="hecho",F6="INCORRECTA"),"INC ","")&IF(AND(E6="abstencion",F6="INCORRECTA"),"ABS-E ","")&IF(AND(E6="hecho",F6="FUERA_REF",H6="no_resp"),"NO-ABS ","")&IF(AND(E6="hecho",I6="SIN-RESPALDO"),"SIN-R ","")&IF(AND(E6="hecho",I6="CITA-X"),"CITA-X ","")&IF(AND(E6="hecho",I6="SIN-CITA"),"SIN-C ",""))))) -> INC | N6: =IF(D6="","",IF(OR(A6="",B6="",E6="",F6=""),"falta qid, modo, tipo o vs_ref",IF(AND(B6="llm",I6<>""),"respaldo no aplica en modo LLM",IF(AND(E6="abstencion",I6<>""),"una abstención no se califica en citas",IF(AND(B6="rag",E6="hecho",I6=""),"falta respaldo","ok"))))) -> ok
A7: p05 | B7: llm | C7: =IF(A7="","",COUNTIFS($A$2:A7,A7,$B$2:B7,B7)) -> 3 | D7: Mimikatz extrae credenciales de memoria | E7: hecho | F7: FUERA_REF | H7: ref | M7: =IF(D7="","",IF(OR(E7="",F7=""),"",IF(TRIM(IF(AND(E7="hecho",F7="INCORRECTA"),"INC ","")&IF(AND(E7="abstencion",F7="INCORRECTA"),"ABS-E ","")&IF(AND(E7="hecho",F7="FUERA_REF",H7="no_resp"),"NO-ABS ","")&IF(AND(E7="hecho",I7="SIN-RESPALDO"),"SIN-R ","")&IF(AND(E7="hecho",I7="CITA-X"),"CITA-X ","")&IF(AND(E7="hecho",I7="SIN-CITA"),"SIN-C ",""))="","-",TRIM(IF(AND(E7="hecho",F7="INCORRECTA"),"INC ","")&IF(AND(E7="abstencion",F7="INCORRECTA"),"ABS-E ","")&IF(AND(E7="hecho",F7="FUERA_REF",H7="no_resp"),"NO-ABS ","")&IF(AND(E7="hecho",I7="SIN-RESPALDO"),"SIN-R ","")&IF(AND(E7="hecho",I7="CITA-X"),"CITA-X ","")&IF(AND(E7="hecho",I7="SIN-CITA"),"SIN-C ",""))))) -> - | N7: =IF(D7="","",IF(OR(A7="",B7="",E7="",F7=""),"falta qid, modo, tipo o vs_ref",IF(AND(B7="llm",I7<>""),"respaldo no aplica en modo LLM",IF(AND(E7="abstencion",I7<>""),"una abstención no se califica en citas",IF(AND(B7="rag",E7="hecho",I7=""),"falta respaldo","ok"))))) -> ok
A8: p09 | B8: rag | C8: =IF(A8="","",COUNTIFS($A$2:A8,A8,$B$2:B8,B8)) -> 1 | D8: Los pasajes no listan ninguna mitigación para T1566 | E8: abstencion | F8: INCORRECTA | G8: H1;H2;H3;H4;H5;H6 | H8: ref | L8: H5 y H6 sí llegaron | M8: =IF(D8="","",IF(OR(E8="",F8=""),"",IF(TRIM(IF(AND(E8="hecho",F8="INCORRECTA"),"INC ","")&IF(AND(E8="abstencion",F8="INCORRECTA"),"ABS-E ","")&IF(AND(E8="hecho",F8="FUERA_REF",H8="no_resp"),"NO-ABS ","")&IF(AND(E8="hecho",I8="SIN-RESPALDO"),"SIN-R ","")&IF(AND(E8="hecho",I8="CITA-X"),"CITA-X ","")&IF(AND(E8="hecho",I8="SIN-CITA"),"SIN-C ",""))="","-",TRIM(IF(AND(E8="hecho",F8="INCORRECTA"),"INC ","")&IF(AND(E8="abstencion",F8="INCORRECTA"),"ABS-E ","")&IF(AND(E8="hecho",F8="FUERA_REF",H8="no_resp"),"NO-ABS ","")&IF(AND(E8="hecho",I8="SIN-RESPALDO"),"SIN-R ","")&IF(AND(E8="hecho",I8="CITA-X"),"CITA-X ","")&IF(AND(E8="hecho",I8="SIN-CITA"),"SIN-C ",""))))) -> ABS-E | N8: =IF(D8="","",IF(OR(A8="",B8="",E8="",F8=""),"falta qid, modo, tipo o vs_ref",IF(AND(B8="llm",I8<>""),"respaldo no aplica en modo LLM",IF(AND(E8="abstencion",I8<>""),"una abstención no se califica en citas",IF(AND(B8="rag",E8="hecho",I8=""),"falta respaldo","ok"))))) -> ok
A9: p09 | B9: rag | C9: =IF(A9="","",COUNTIFS($A$2:A9,A9,$B$2:B9,B9)) -> 2 | D9: Los pasajes mencionan SPF, DKIM y DMARC para filtrado | E9: hecho | F9: CORRECTA | H9: ref | I9: SOSTENIDA | J9: 5 | K9: 5 | L9: verdadera pero no cubre H5: la respuesta niega que sean mitigaciones | M9: =IF(D9="","",IF(OR(E9="",F9=""),"",IF(TRIM(IF(AND(E9="hecho",F9="INCORRECTA"),"INC ","")&IF(AND(E9="abstencion",F9="INCORRECTA"),"ABS-E ","")&IF(AND(E9="hecho",F9="FUERA_REF",H9="no_resp"),"NO-ABS ","")&IF(AND(E9="hecho",I9="SIN-RESPALDO"),"SIN-R ","")&IF(AND(E9="hecho",I9="CITA-X"),"CITA-X ","")&IF(AND(E9="hecho",I9="SIN-CITA"),"SIN-C ",""))="","-",TRIM(IF(AND(E9="hecho",F9="INCORRECTA"),"INC ","")&IF(AND(E9="abstencion",F9="INCORRECTA"),"ABS-E ","")&IF(AND(E9="hecho",F9="FUERA_REF",H9="no_resp"),"NO-ABS ","")&IF(AND(E9="hecho",I9="SIN-RESPALDO"),"SIN-R ","")&IF(AND(E9="hecho",I9="CITA-X"),"CITA-X ","")&IF(AND(E9="hecho",I9="SIN-CITA"),"SIN-C ",""))))) -> - | N9: =IF(D9="","",IF(OR(A9="",B9="",E9="",F9=""),"falta qid, modo, tipo o vs_ref",IF(AND(B9="llm",I9<>""),"respaldo no aplica en modo LLM",IF(AND(E9="abstencion",I9<>""),"una abstención no se califica en citas",IF(AND(B9="rag",E9="hecho",I9=""),"falta respaldo","ok"))))) -> ok
A10: p09 | B10: rag | C10: =IF(A10="","",COUNTIFS($A$2:A10,A10,$B$2:B10,B10)) -> 3 | D10: No hay producto comercial recomendado | E10: abstencion | F10: CORRECTA | H10: no_resp | M10: =IF(D10="","",IF(OR(E10="",F10=""),"",IF(TRIM(IF(AND(E10="hecho",F10="INCORRECTA"),"INC ","")&IF(AND(E10="abstencion",F10="INCORRECTA"),"ABS-E ","")&IF(AND(E10="hecho",F10="FUERA_REF",H10="no_resp"),"NO-ABS ","")&IF(AND(E10="hecho",I10="SIN-RESPALDO"),"SIN-R ","")&IF(AND(E10="hecho",I10="CITA-X"),"CITA-X ","")&IF(AND(E10="hecho",I10="SIN-CITA"),"SIN-C ",""))="","-",TRIM(IF(AND(E10="hecho",F10="INCORRECTA"),"INC ","")&IF(AND(E10="abstencion",F10="INCORRECTA"),"ABS-E ","")&IF(AND(E10="hecho",F10="FUERA_REF",H10="no_resp"),"NO-ABS ","")&IF(AND(E10="hecho",I10="SIN-RESPALDO"),"SIN-R ","")&IF(AND(E10="hecho",I10="CITA-X"),"CITA-X ","")&IF(AND(E10="hecho",I10="SIN-CITA"),"SIN-C ",""))))) -> - | N10: =IF(D10="","",IF(OR(A10="",B10="",E10="",F10=""),"falta qid, modo, tipo o vs_ref",IF(AND(B10="llm",I10<>""),"respaldo no aplica en modo LLM",IF(AND(E10="abstencion",I10<>""),"una abstención no se califica en citas",IF(AND(B10="rag",E10="hecho",I10=""),"falta respaldo","ok"))))) -> ok
A11: p09 | B11: llm | C11: =IF(A11="","",COUNTIFS($A$2:A11,A11,$B$2:B11,B11)) -> 1 | D11: ATT&CK no lista mitigaciones específicas para T1566 | E11: hecho | F11: INCORRECTA | H11: ref | M11: =IF(D11="","",IF(OR(E11="",F11=""),"",IF(TRIM(IF(AND(E11="hecho",F11="INCORRECTA"),"INC ","")&IF(AND(E11="abstencion",F11="INCORRECTA"),"ABS-E ","")&IF(AND(E11="hecho",F11="FUERA_REF",H11="no_resp"),"NO-ABS ","")&IF(AND(E11="hecho",I11="SIN-RESPALDO"),"SIN-R ","")&IF(AND(E11="hecho",I11="CITA-X"),"CITA-X ","")&IF(AND(E11="hecho",I11="SIN-CITA"),"SIN-C ",""))="","-",TRIM(IF(AND(E11="hecho",F11="INCORRECTA"),"INC ","")&IF(AND(E11="abstencion",F11="INCORRECTA"),"ABS-E ","")&IF(AND(E11="hecho",F11="FUERA_REF",H11="no_resp"),"NO-ABS ","")&IF(AND(E11="hecho",I11="SIN-RESPALDO"),"SIN-R ","")&IF(AND(E11="hecho",I11="CITA-X"),"CITA-X ","")&IF(AND(E11="hecho",I11="SIN-CITA"),"SIN-C ",""))))) -> INC | N11: =IF(D11="","",IF(OR(A11="",B11="",E11="",F11=""),"falta qid, modo, tipo o vs_ref",IF(AND(B11="llm",I11<>""),"respaldo no aplica en modo LLM",IF(AND(E11="abstencion",I11<>""),"una abstención no se califica en citas",IF(AND(B11="rag",E11="hecho",I11=""),"falta respaldo","ok"))))) -> ok
A12: p09 | B12: llm | C12: =IF(A12="","",COUNTIFS($A$2:A12,A12,$B$2:B12,B12)) -> 2 | D12: Recomienda DMARC, SPF y DKIM | E12: hecho | F12: CORRECTA | G12: H5 | H12: ref | M12: =IF(D12="","",IF(OR(E12="",F12=""),"",IF(TRIM(IF(AND(E12="hecho",F12="INCORRECTA"),"INC ","")&IF(AND(E12="abstencion",F12="INCORRECTA"),"ABS-E ","")&IF(AND(E12="hecho",F12="FUERA_REF",H12="no_resp"),"NO-ABS ","")&IF(AND(E12="hecho",I12="SIN-RESPALDO"),"SIN-R ","")&IF(AND(E12="hecho",I12="CITA-X"),"CITA-X ","")&IF(AND(E12="hecho",I12="SIN-CITA"),"SIN-C ",""))="","-",TRIM(IF(AND(E12="hecho",F12="INCORRECTA"),"INC ","")&IF(AND(E12="abstencion",F12="INCORRECTA"),"ABS-E ","")&IF(AND(E12="hecho",F12="FUERA_REF",H12="no_resp"),"NO-ABS ","")&IF(AND(E12="hecho",I12="SIN-RESPALDO"),"SIN-R ","")&IF(AND(E12="hecho",I12="CITA-X"),"CITA-X ","")&IF(AND(E12="hecho",I12="SIN-CITA"),"SIN-C ",""))))) -> - | N12: =IF(D12="","",IF(OR(A12="",B12="",E12="",F12=""),"falta qid, modo, tipo o vs_ref",IF(AND(B12="llm",I12<>""),"respaldo no aplica en modo LLM",IF(AND(E12="abstencion",I12<>""),"una abstención no se califica en citas",IF(AND(B12="rag",E12="hecho",I12=""),"falta respaldo","ok"))))) -> ok
A13: p09 | B13: llm | C13: =IF(A13="","",COUNTIFS($A$2:A13,A13,$B$2:B13,B13)) -> 3 | D13: Recomienda educación de usuarios | E13: hecho | F13: CORRECTA | G13: H3 | H13: ref | M13: =IF(D13="","",IF(OR(E13="",F13=""),"",IF(TRIM(IF(AND(E13="hecho",F13="INCORRECTA"),"INC ","")&IF(AND(E13="abstencion",F13="INCORRECTA"),"ABS-E ","")&IF(AND(E13="hecho",F13="FUERA_REF",H13="no_resp"),"NO-ABS ","")&IF(AND(E13="hecho",I13="SIN-RESPALDO"),"SIN-R ","")&IF(AND(E13="hecho",I13="CITA-X"),"CITA-X ","")&IF(AND(E13="hecho",I13="SIN-CITA"),"SIN-C ",""))="","-",TRIM(IF(AND(E13="hecho",F13="INCORRECTA"),"INC ","")&IF(AND(E13="abstencion",F13="INCORRECTA"),"ABS-E ","")&IF(AND(E13="hecho",F13="FUERA_REF",H13="no_resp"),"NO-ABS ","")&IF(AND(E13="hecho",I13="SIN-RESPALDO"),"SIN-R ","")&IF(AND(E13="hecho",I13="CITA-X"),"CITA-X ","")&IF(AND(E13="hecho",I13="SIN-CITA"),"SIN-C ",""))))) -> - | N13: =IF(D13="","",IF(OR(A13="",B13="",E13="",F13=""),"falta qid, modo, tipo o vs_ref",IF(AND(B13="llm",I13<>""),"respaldo no aplica en modo LLM",IF(AND(E13="abstencion",I13<>""),"una abstención no se califica en citas",IF(AND(B13="rag",E13="hecho",I13=""),"falta respaldo","ok"))))) -> ok
A14: p09 | B14: llm | C14: =IF(A14="","",COUNTIFS($A$2:A14,A14,$B$2:B14,B14)) -> 4 | D14: Recomienda filtrado de contenido, inteligencia de amenazas y análisis de comportamiento | E14: hecho | F14: FUERA_REF | H14: ref | M14: =IF(D14="","",IF(OR(E14="",F14=""),"",IF(TRIM(IF(AND(E14="hecho",F14="INCORRECTA"),"INC ","")&IF(AND(E14="abstencion",F14="INCORRECTA"),"ABS-E ","")&IF(AND(E14="hecho",F14="FUERA_REF",H14="no_resp"),"NO-ABS ","")&IF(AND(E14="hecho",I14="SIN-RESPALDO"),"SIN-R ","")&IF(AND(E14="hecho",I14="CITA-X"),"CITA-X ","")&IF(AND(E14="hecho",I14="SIN-CITA"),"SIN-C ",""))="","-",TRIM(IF(AND(E14="hecho",F14="INCORRECTA"),"INC ","")&IF(AND(E14="abstencion",F14="INCORRECTA"),"ABS-E ","")&IF(AND(E14="hecho",F14="FUERA_REF",H14="no_resp"),"NO-ABS ","")&IF(AND(E14="hecho",I14="SIN-RESPALDO"),"SIN-R ","")&IF(AND(E14="hecho",I14="CITA-X"),"CITA-X ","")&IF(AND(E14="hecho",I14="SIN-CITA"),"SIN-C ",""))))) -> - | N14: =IF(D14="","",IF(OR(A14="",B14="",E14="",F14=""),"falta qid, modo, tipo o vs_ref",IF(AND(B14="llm",I14<>""),"respaldo no aplica en modo LLM",IF(AND(E14="abstencion",I14<>""),"una abstención no se califica en citas",IF(AND(B14="rag",E14="hecho",I14=""),"falta respaldo","ok"))))) -> ok
A15: p09 | B15: llm | C15: =IF(A15="","",COUNTIFS($A$2:A15,A15,$B$2:B15,B15)) -> 5 | D15: MITRE no recomienda un producto comercial concreto | E15: hecho | F15: CORRECTA | H15: no_resp | M15: =IF(D15="","",IF(OR(E15="",F15=""),"",IF(TRIM(IF(AND(E15="hecho",F15="INCORRECTA"),"INC ","")&IF(AND(E15="abstencion",F15="INCORRECTA"),"ABS-E ","")&IF(AND(E15="hecho",F15="FUERA_REF",H15="no_resp"),"NO-ABS ","")&IF(AND(E15="hecho",I15="SIN-RESPALDO"),"SIN-R ","")&IF(AND(E15="hecho",I15="CITA-X"),"CITA-X ","")&IF(AND(E15="hecho",I15="SIN-CITA"),"SIN-C ",""))="","-",TRIM(IF(AND(E15="hecho",F15="INCORRECTA"),"INC ","")&IF(AND(E15="abstencion",F15="INCORRECTA"),"ABS-E ","")&IF(AND(E15="hecho",F15="FUERA_REF",H15="no_resp"),"NO-ABS ","")&IF(AND(E15="hecho",I15="SIN-RESPALDO"),"SIN-R ","")&IF(AND(E15="hecho",I15="CITA-X"),"CITA-X ","")&IF(AND(E15="hecho",I15="SIN-CITA"),"SIN-C ",""))))) -> - | N15: =IF(D15="","",IF(OR(A15="",B15="",E15="",F15=""),"falta qid, modo, tipo o vs_ref",IF(AND(B15="llm",I15<>""),"respaldo no aplica en modo LLM",IF(AND(E15="abstencion",I15<>""),"una abstención no se califica en citas",IF(AND(B15="rag",E15="hecho",I15=""),"falta respaldo","ok"))))) -> ok
A16: p09 | B16: llm | C16: =IF(A16="","",COUNTIFS($A$2:A16,A16,$B$2:B16,B16)) -> 6 | D16: Microsoft 365 Defender es ampliamente referenciado en ATT&CK | E16: hecho | F16: FUERA_REF | H16: no_resp | L16: contradice la afirmación anterior | M16: =IF(D16="","",IF(OR(E16="",F16=""),"",IF(TRIM(IF(AND(E16="hecho",F16="INCORRECTA"),"INC ","")&IF(AND(E16="abstencion",F16="INCORRECTA"),"ABS-E ","")&IF(AND(E16="hecho",F16="FUERA_REF",H16="no_resp"),"NO-ABS ","")&IF(AND(E16="hecho",I16="SIN-RESPALDO"),"SIN-R ","")&IF(AND(E16="hecho",I16="CITA-X"),"CITA-X ","")&IF(AND(E16="hecho",I16="SIN-CITA"),"SIN-C ",""))="","-",TRIM(IF(AND(E16="hecho",F16="INCORRECTA"),"INC ","")&IF(AND(E16="abstencion",F16="INCORRECTA"),"ABS-E ","")&IF(AND(E16="hecho",F16="FUERA_REF",H16="no_resp"),"NO-ABS ","")&IF(AND(E16="hecho",I16="SIN-RESPALDO"),"SIN-R ","")&IF(AND(E16="hecho",I16="CITA-X"),"CITA-X ","")&IF(AND(E16="hecho",I16="SIN-CITA"),"SIN-C ",""))))) -> NO-ABS | N16: =IF(D16="","",IF(OR(A16="",B16="",E16="",F16=""),"falta qid, modo, tipo o vs_ref",IF(AND(B16="llm",I16<>""),"respaldo no aplica en modo LLM",IF(AND(E16="abstencion",I16<>""),"una abstención no se califica en citas",IF(AND(B16="rag",E16="hecho",I16=""),"falta respaldo","ok"))))) -> ok
A17: p01 | B17: rag | C17: =IF(A17="","",COUNTIFS($A$2:A17,A17,$B$2:B17,B17)) -> 1 | D17: Los contextos no dan información sobre mitigaciones de T1059.001 | E17: abstencion | F17: INCORRECTA | G17: H1;H2;H3;H4;H5 | H17: ref | L17: H5 solo llegó como evidencia parcial (ALT-P) | M17: =IF(D17="","",IF(OR(E17="",F17=""),"",IF(TRIM(IF(AND(E17="hecho",F17="INCORRECTA"),"INC ","")&IF(AND(E17="abstencion",F17="INCORRECTA"),"ABS-E ","")&IF(AND(E17="hecho",F17="FUERA_REF",H17="no_resp"),"NO-ABS ","")&IF(AND(E17="hecho",I17="SIN-RESPALDO"),"SIN-R ","")&IF(AND(E17="hecho",I17="CITA-X"),"CITA-X ","")&IF(AND(E17="hecho",I17="SIN-CITA"),"SIN-C ",""))="","-",TRIM(IF(AND(E17="hecho",F17="INCORRECTA"),"INC ","")&IF(AND(E17="abstencion",F17="INCORRECTA"),"ABS-E ","")&IF(AND(E17="hecho",F17="FUERA_REF",H17="no_resp"),"NO-ABS ","")&IF(AND(E17="hecho",I17="SIN-RESPALDO"),"SIN-R ","")&IF(AND(E17="hecho",I17="CITA-X"),"CITA-X ","")&IF(AND(E17="hecho",I17="SIN-CITA"),"SIN-C ",""))))) -> ABS-E | N17: =IF(D17="","",IF(OR(A17="",B17="",E17="",F17=""),"falta qid, modo, tipo o vs_ref",IF(AND(B17="llm",I17<>""),"respaldo no aplica en modo LLM",IF(AND(E17="abstencion",I17<>""),"una abstención no se califica en citas",IF(AND(B17="rag",E17="hecho",I17=""),"falta respaldo","ok"))))) -> ok
A18: p01 | B18: llm | C18: =IF(A18="","",COUNTIFS($A$2:A18,A18,$B$2:B18,B18)) -> 1 | D18: ATT&CK no proporciona una lista detallada de mitigaciones por sub-técnica | E18: hecho | F18: INCORRECTA | H18: ref | L18: respuesta truncada (TRUNC) | M18: =IF(D18="","",IF(OR(E18="",F18=""),"",IF(TRIM(IF(AND(E18="hecho",F18="INCORRECTA"),"INC ","")&IF(AND(E18="abstencion",F18="INCORRECTA"),"ABS-E ","")&IF(AND(E18="hecho",F18="FUERA_REF",H18="no_resp"),"NO-ABS ","")&IF(AND(E18="hecho",I18="SIN-RESPALDO"),"SIN-R ","")&IF(AND(E18="hecho",I18="CITA-X"),"CITA-X ","")&IF(AND(E18="hecho",I18="SIN-CITA"),"SIN-C ",""))="","-",TRIM(IF(AND(E18="hecho",F18="INCORRECTA"),"INC ","")&IF(AND(E18="abstencion",F18="INCORRECTA"),"ABS-E ","")&IF(AND(E18="hecho",F18="FUERA_REF",H18="no_resp"),"NO-ABS ","")&IF(AND(E18="hecho",I18="SIN-RESPALDO"),"SIN-R ","")&IF(AND(E18="hecho",I18="CITA-X"),"CITA-X ","")&IF(AND(E18="hecho",I18="SIN-CITA"),"SIN-C ",""))))) -> INC | N18: =IF(D18="","",IF(OR(A18="",B18="",E18="",F18=""),"falta qid, modo, tipo o vs_ref",IF(AND(B18="llm",I18<>""),"respaldo no aplica en modo LLM",IF(AND(E18="abstencion",I18<>""),"una abstención no se califica en citas",IF(AND(B18="rag",E18="hecho",I18=""),"falta respaldo","ok"))))) -> ok
A19: p01 | B19: llm | C19: =IF(A19="","",COUNTIFS($A$2:A19,A19,$B$2:B19,B19)) -> 2 | D19: Limitar PowerShell a modos Restricted/RemoteSigned | E19: hecho | F19: FUERA_REF | H19: ref | M19: =IF(D19="","",IF(OR(E19="",F19=""),"",IF(TRIM(IF(AND(E19="hecho",F19="INCORRECTA"),"INC ","")&IF(AND(E19="abstencion",F19="INCORRECTA"),"ABS-E ","")&IF(AND(E19="hecho",F19="FUERA_REF",H19="no_resp"),"NO-ABS ","")&IF(AND(E19="hecho",I19="SIN-RESPALDO"),"SIN-R ","")&IF(AND(E19="hecho",I19="CITA-X"),"CITA-X ","")&IF(AND(E19="hecho",I19="SIN-CITA"),"SIN-C ",""))="","-",TRIM(IF(AND(E19="hecho",F19="INCORRECTA"),"INC ","")&IF(AND(E19="abstencion",F19="INCORRECTA"),"ABS-E ","")&IF(AND(E19="hecho",F19="FUERA_REF",H19="no_resp"),"NO-ABS ","")&IF(AND(E19="hecho",I19="SIN-RESPALDO"),"SIN-R ","")&IF(AND(E19="hecho",I19="CITA-X"),"CITA-X ","")&IF(AND(E19="hecho",I19="SIN-CITA"),"SIN-C ",""))))) -> - | N19: =IF(D19="","",IF(OR(A19="",B19="",E19="",F19=""),"falta qid, modo, tipo o vs_ref",IF(AND(B19="llm",I19<>""),"respaldo no aplica en modo LLM",IF(AND(E19="abstencion",I19<>""),"una abstención no se califica en citas",IF(AND(B19="rag",E19="hecho",I19=""),"falta respaldo","ok"))))) -> ok
A20: p01 | B20: llm | C20: =IF(A20="","",COUNTIFS($A$2:A20,A20,$B$2:B20,B20)) -> 3 | D20: Requerir scripts firmados | E20: hecho | F20: CORRECTA | G20: H2 | H20: ref | M20: =IF(D20="","",IF(OR(E20="",F20=""),"",IF(TRIM(IF(AND(E20="hecho",F20="INCORRECTA"),"INC ","")&IF(AND(E20="abstencion",F20="INCORRECTA"),"ABS-E ","")&IF(AND(E20="hecho",F20="FUERA_REF",H20="no_resp"),"NO-ABS ","")&IF(AND(E20="hecho",I20="SIN-RESPALDO"),"SIN-R ","")&IF(AND(E20="hecho",I20="CITA-X"),"CITA-X ","")&IF(AND(E20="hecho",I20="SIN-CITA"),"SIN-C ",""))="","-",TRIM(IF(AND(E20="hecho",F20="INCORRECTA"),"INC ","")&IF(AND(E20="abstencion",F20="INCORRECTA"),"ABS-E ","")&IF(AND(E20="hecho",F20="FUERA_REF",H20="no_resp"),"NO-ABS ","")&IF(AND(E20="hecho",I20="SIN-RESPALDO"),"SIN-R ","")&IF(AND(E20="hecho",I20="CITA-X"),"CITA-X ","")&IF(AND(E20="hecho",I20="SIN-CITA"),"SIN-C ",""))))) -> - | N20: =IF(D20="","",IF(OR(A20="",B20="",E20="",F20=""),"falta qid, modo, tipo o vs_ref",IF(AND(B20="llm",I20<>""),"respaldo no aplica en modo LLM",IF(AND(E20="abstencion",I20<>""),"una abstención no se califica en citas",IF(AND(B20="rag",E20="hecho",I20=""),"falta respaldo","ok"))))) -> ok
A21: p01 | B21: llm | C21: =IF(A21="","",COUNTIFS($A$2:A21,A21,$B$2:B21,B21)) -> 4 | D21: Monitoreo, auditoría y detección de anomalías | E21: hecho | F21: FUERA_REF | H21: ref | M21: =IF(D21="","",IF(OR(E21="",F21=""),"",IF(TRIM(IF(AND(E21="hecho",F21="INCORRECTA"),"INC ","")&IF(AND(E21="abstencion",F21="INCORRECTA"),"ABS-E ","")&IF(AND(E21="hecho",F21="FUERA_REF",H21="no_resp"),"NO-ABS ","")&IF(AND(E21="hecho",I21="SIN-RESPALDO"),"SIN-R ","")&IF(AND(E21="hecho",I21="CITA-X"),"CITA-X ","")&IF(AND(E21="hecho",I21="SIN-CITA"),"SIN-C ",""))="","-",TRIM(IF(AND(E21="hecho",F21="INCORRECTA"),"INC ","")&IF(AND(E21="abstencion",F21="INCORRECTA"),"ABS-E ","")&IF(AND(E21="hecho",F21="FUERA_REF",H21="no_resp"),"NO-ABS ","")&IF(AND(E21="hecho",I21="SIN-RESPALDO"),"SIN-R ","")&IF(AND(E21="hecho",I21="CITA-X"),"CITA-X ","")&IF(AND(E21="hecho",I21="SIN-CITA"),"SIN-C ",""))))) -> - | N21: =IF(D21="","",IF(OR(A21="",B21="",E21="",F21=""),"falta qid, modo, tipo o vs_ref",IF(AND(B21="llm",I21<>""),"respaldo no aplica en modo LLM",IF(AND(E21="abstencion",I21<>""),"una abstención no se califica en citas",IF(AND(B21="rag",E21="hecho",I21=""),"falta respaldo","ok"))))) -> ok
A22: p01 | B22: llm | C22: =IF(A22="","",COUNTIFS($A$2:A22,A22,$B$2:B22,B22)) -> 5 | D22: Políticas de grupo para limitar el acceso a PowerShell | E22: hecho | F22: CORRECTA | G22: H3 | H22: ref | L22: cobertura laxa de H3 | M22: =IF(D22="","",IF(OR(E22="",F22=""),"",IF(TRIM(IF(AND(E22="hecho",F22="INCORRECTA"),"INC ","")&IF(AND(E22="abstencion",F22="INCORRECTA"),"ABS-E ","")&IF(AND(E22="hecho",F22="FUERA_REF",H22="no_resp"),"NO-ABS ","")&IF(AND(E22="hecho",I22="SIN-RESPALDO"),"SIN-R ","")&IF(AND(E22="hecho",I22="CITA-X"),"CITA-X ","")&IF(AND(E22="hecho",I22="SIN-CITA"),"SIN-C ",""))="","-",TRIM(IF(AND(E22="hecho",F22="INCORRECTA"),"INC ","")&IF(AND(E22="abstencion",F22="INCORRECTA"),"ABS-E ","")&IF(AND(E22="hecho",F22="FUERA_REF",H22="no_resp"),"NO-ABS ","")&IF(AND(E22="hecho",I22="SIN-RESPALDO"),"SIN-R ","")&IF(AND(E22="hecho",I22="CITA-X"),"CITA-X ","")&IF(AND(E22="hecho",I22="SIN-CITA"),"SIN-C ",""))))) -> - | N22: =IF(D22="","",IF(OR(A22="",B22="",E22="",F22=""),"falta qid, modo, tipo o vs_ref",IF(AND(B22="llm",I22<>""),"respaldo no aplica en modo LLM",IF(AND(E22="abstencion",I22<>""),"una abstención no se califica en citas",IF(AND(B22="rag",E22="hecho",I22=""),"falta respaldo","ok"))))) -> ok
A23: p01 | B23: llm | C23: =IF(A23="","",COUNTIFS($A$2:A23,A23,$B$2:B23,B23)) -> 6 | D23: Usar alternativas (cmd, batch) en entornos críticos | E23: hecho | F23: FUERA_REF | H23: ref | M23: =IF(D23="","",IF(OR(E23="",F23=""),"",IF(TRIM(IF(AND(E23="hecho",F23="INCORRECTA"),"INC ","")&IF(AND(E23="abstencion",F23="INCORRECTA"),"ABS-E ","")&IF(AND(E23="hecho",F23="FUERA_REF",H23="no_resp"),"NO-ABS ","")&IF(AND(E23="hecho",I23="SIN-RESPALDO"),"SIN-R ","")&IF(AND(E23="hecho",I23="CITA-X"),"CITA-X ","")&IF(AND(E23="hecho",I23="SIN-CITA"),"SIN-C ",""))="","-",TRIM(IF(AND(E23="hecho",F23="INCORRECTA"),"INC ","")&IF(AND(E23="abstencion",F23="INCORRECTA"),"ABS-E ","")&IF(AND(E23="hecho",F23="FUERA_REF",H23="no_resp"),"NO-ABS ","")&IF(AND(E23="hecho",I23="SIN-RESPALDO"),"SIN-R ","")&IF(AND(E23="hecho",I23="CITA-X"),"CITA-X ","")&IF(AND(E23="hecho",I23="SIN-CITA"),"SIN-C ",""))))) -> - | N23: =IF(D23="","",IF(OR(A23="",B23="",E23="",F23=""),"falta qid, modo, tipo o vs_ref",IF(AND(B23="llm",I23<>""),"respaldo no aplica en modo LLM",IF(AND(E23="abstencion",I23<>""),"una abstención no se califica en citas",IF(AND(B23="rag",E23="hecho",I23=""),"falta respaldo","ok"))))) -> ok
A24: p06 | B24: rag | C24: =IF(A24="","",COUNTIFS($A$2:A24,A24,$B$2:B24,B24)) -> 1 | D24: Los contextos no dicen qué sub-técnicas T1059.* usa Lazarus | E24: abstencion | F24: INCORRECTA | G24: H1;H2;H3 | H24: ref | L24: H1 llegó en r5 | M24: =IF(D24="","",IF(OR(E24="",F24=""),"",IF(TRIM(IF(AND(E24="hecho",F24="INCORRECTA"),"INC ","")&IF(AND(E24="abstencion",F24="INCORRECTA"),"ABS-E ","")&IF(AND(E24="hecho",F24="FUERA_REF",H24="no_resp"),"NO-ABS ","")&IF(AND(E24="hecho",I24="SIN-RESPALDO"),"SIN-R ","")&IF(AND(E24="hecho",I24="CITA-X"),"CITA-X ","")&IF(AND(E24="hecho",I24="SIN-CITA"),"SIN-C ",""))="","-",TRIM(IF(AND(E24="hecho",F24="INCORRECTA"),"INC ","")&IF(AND(E24="abstencion",F24="INCORRECTA"),"ABS-E ","")&IF(AND(E24="hecho",F24="FUERA_REF",H24="no_resp"),"NO-ABS ","")&IF(AND(E24="hecho",I24="SIN-RESPALDO"),"SIN-R ","")&IF(AND(E24="hecho",I24="CITA-X"),"CITA-X ","")&IF(AND(E24="hecho",I24="SIN-CITA"),"SIN-C ",""))))) -> ABS-E | N24: =IF(D24="","",IF(OR(A24="",B24="",E24="",F24=""),"falta qid, modo, tipo o vs_ref",IF(AND(B24="llm",I24<>""),"respaldo no aplica en modo LLM",IF(AND(E24="abstencion",I24<>""),"una abstención no se califica en citas",IF(AND(B24="rag",E24="hecho",I24=""),"falta respaldo","ok"))))) -> ok
A25: p06 | B25: rag | C25: =IF(A25="","",COUNTIFS($A$2:A25,A25,$B$2:B25,B25)) -> 2 | D25: Lazarus usa T1059.003 y T1059.005 (vía AuditCred y TYPEFRAME) | E25: hecho | F25: CORRECTA | G25: H2;H3 | H25: ref | I25: SOSTENIDA | J25: 1;3 | K25: 1;3 | M25: =IF(D25="","",IF(OR(E25="",F25=""),"",IF(TRIM(IF(AND(E25="hecho",F25="INCORRECTA"),"INC ","")&IF(AND(E25="abstencion",F25="INCORRECTA"),"ABS-E ","")&IF(AND(E25="hecho",F25="FUERA_REF",H25="no_resp"),"NO-ABS ","")&IF(AND(E25="hecho",I25="SIN-RESPALDO"),"SIN-R ","")&IF(AND(E25="hecho",I25="CITA-X"),"CITA-X ","")&IF(AND(E25="hecho",I25="SIN-CITA"),"SIN-C ",""))="","-",TRIM(IF(AND(E25="hecho",F25="INCORRECTA"),"INC ","")&IF(AND(E25="abstencion",F25="INCORRECTA"),"ABS-E ","")&IF(AND(E25="hecho",F25="FUERA_REF",H25="no_resp"),"NO-ABS ","")&IF(AND(E25="hecho",I25="SIN-RESPALDO"),"SIN-R ","")&IF(AND(E25="hecho",I25="CITA-X"),"CITA-X ","")&IF(AND(E25="hecho",I25="SIN-CITA"),"SIN-C ",""))))) -> - | N25: =IF(D25="","",IF(OR(A25="",B25="",E25="",F25=""),"falta qid, modo, tipo o vs_ref",IF(AND(B25="llm",I25<>""),"respaldo no aplica en modo LLM",IF(AND(E25="abstencion",I25<>""),"una abstención no se califica en citas",IF(AND(B25="rag",E25="hecho",I25=""),"falta respaldo","ok"))))) -> ok
A26: p06 | B26: rag | C26: =IF(A26="","",COUNTIFS($A$2:A26,A26,$B$2:B26,B26)) -> 3 | D26: No hay referencia a ataques contra Ecuador | E26: abstencion | F26: CORRECTA | H26: no_resp | M26: =IF(D26="","",IF(OR(E26="",F26=""),"",IF(TRIM(IF(AND(E26="hecho",F26="INCORRECTA"),"INC ","")&IF(AND(E26="abstencion",F26="INCORRECTA"),"ABS-E ","")&IF(AND(E26="hecho",F26="FUERA_REF",H26="no_resp"),"NO-ABS ","")&IF(AND(E26="hecho",I26="SIN-RESPALDO"),"SIN-R ","")&IF(AND(E26="hecho",I26="CITA-X"),"CITA-X ","")&IF(AND(E26="hecho",I26="SIN-CITA"),"SIN-C ",""))="","-",TRIM(IF(AND(E26="hecho",F26="INCORRECTA"),"INC ","")&IF(AND(E26="abstencion",F26="INCORRECTA"),"ABS-E ","")&IF(AND(E26="hecho",F26="FUERA_REF",H26="no_resp"),"NO-ABS ","")&IF(AND(E26="hecho",I26="SIN-RESPALDO"),"SIN-R ","")&IF(AND(E26="hecho",I26="CITA-X"),"CITA-X ","")&IF(AND(E26="hecho",I26="SIN-CITA"),"SIN-C ",""))))) -> - | N26: =IF(D26="","",IF(OR(A26="",B26="",E26="",F26=""),"falta qid, modo, tipo o vs_ref",IF(AND(B26="llm",I26<>""),"respaldo no aplica en modo LLM",IF(AND(E26="abstencion",I26<>""),"una abstención no se califica en citas",IF(AND(B26="rag",E26="hecho",I26=""),"falta respaldo","ok"))))) -> ok
A27: p06 | B27: llm | C27: =IF(A27="","",COUNTIFS($A$2:A27,A27,$B$2:B27,B27)) -> 1 | D27: ATT&CK no documenta que Lazarus use sub-técnicas T1059.* | E27: hecho | F27: INCORRECTA | H27: ref | M27: =IF(D27="","",IF(OR(E27="",F27=""),"",IF(TRIM(IF(AND(E27="hecho",F27="INCORRECTA"),"INC ","")&IF(AND(E27="abstencion",F27="INCORRECTA"),"ABS-E ","")&IF(AND(E27="hecho",F27="FUERA_REF",H27="no_resp"),"NO-ABS ","")&IF(AND(E27="hecho",I27="SIN-RESPALDO"),"SIN-R ","")&IF(AND(E27="hecho",I27="CITA-X"),"CITA-X ","")&IF(AND(E27="hecho",I27="SIN-CITA"),"SIN-C ",""))="","-",TRIM(IF(AND(E27="hecho",F27="INCORRECTA"),"INC ","")&IF(AND(E27="abstencion",F27="INCORRECTA"),"ABS-E ","")&IF(AND(E27="hecho",F27="FUERA_REF",H27="no_resp"),"NO-ABS ","")&IF(AND(E27="hecho",I27="SIN-RESPALDO"),"SIN-R ","")&IF(AND(E27="hecho",I27="CITA-X"),"CITA-X ","")&IF(AND(E27="hecho",I27="SIN-CITA"),"SIN-C ",""))))) -> INC | N27: =IF(D27="","",IF(OR(A27="",B27="",E27="",F27=""),"falta qid, modo, tipo o vs_ref",IF(AND(B27="llm",I27<>""),"respaldo no aplica en modo LLM",IF(AND(E27="abstencion",I27<>""),"una abstención no se califica en citas",IF(AND(B27="rag",E27="hecho",I27=""),"falta respaldo","ok"))))) -> ok
A28: p06 | B28: llm | C28: =IF(A28="","",COUNTIFS($A$2:A28,A28,$B$2:B28,B28)) -> 2 | D28: No hay evidencia de ataques de Lazarus contra Ecuador | E28: hecho | F28: CORRECTA | H28: no_resp | M28: =IF(D28="","",IF(OR(E28="",F28=""),"",IF(TRIM(IF(AND(E28="hecho",F28="INCORRECTA"),"INC ","")&IF(AND(E28="abstencion",F28="INCORRECTA"),"ABS-E ","")&IF(AND(E28="hecho",F28="FUERA_REF",H28="no_resp"),"NO-ABS ","")&IF(AND(E28="hecho",I28="SIN-RESPALDO"),"SIN-R ","")&IF(AND(E28="hecho",I28="CITA-X"),"CITA-X ","")&IF(AND(E28="hecho",I28="SIN-CITA"),"SIN-C ",""))="","-",TRIM(IF(AND(E28="hecho",F28="INCORRECTA"),"INC ","")&IF(AND(E28="abstencion",F28="INCORRECTA"),"ABS-E ","")&IF(AND(E28="hecho",F28="FUERA_REF",H28="no_resp"),"NO-ABS ","")&IF(AND(E28="hecho",I28="SIN-RESPALDO"),"SIN-R ","")&IF(AND(E28="hecho",I28="CITA-X"),"CITA-X ","")&IF(AND(E28="hecho",I28="SIN-CITA"),"SIN-C ",""))))) -> - | N28: =IF(D28="","",IF(OR(A28="",B28="",E28="",F28=""),"falta qid, modo, tipo o vs_ref",IF(AND(B28="llm",I28<>""),"respaldo no aplica en modo LLM",IF(AND(E28="abstencion",I28<>""),"una abstención no se califica en citas",IF(AND(B28="rag",E28="hecho",I28=""),"falta respaldo","ok"))))) -> ok
C29: =IF(A29="","",COUNTIFS($A$2:A29,A29,$B$2:B29,B29)) | M29: =IF(D29="","",IF(OR(E29="",F29=""),"",IF(TRIM(IF(AND(E29="hecho",F29="INCORRECTA"),"INC ","")&IF(AND(E29="abstencion",F29="INCORRECTA"),"ABS-E ","")&IF(AND(E29="hecho",F29="FUERA_REF",H29="no_resp"),"NO-ABS ","")&IF(AND(E29="hecho",I29="SIN-RESPALDO"),"SIN-R ","")&IF(AND(E29="hecho",I29="CITA-X"),"CITA-X ","")&IF(AND(E29="hecho",I29="SIN-CITA"),"SIN-C ",""))="","-",TRIM(IF(AND(E29="hecho",F29="INCORRECTA"),"INC ","")&IF(AND(E29="abstencion",F29="INCORRECTA"),"ABS-E ","")&IF(AND(E29="hecho",F29="FUERA_REF",H29="no_resp"),"NO-ABS ","")&IF(AND(E29="hecho",I29="SIN-RESPALDO"),"SIN-R ","")&IF(AND(E29="hecho",I29="CITA-X"),"CITA-X ","")&IF(AND(E29="hecho",I29="SIN-CITA"),"SIN-C ",""))))) | N29: =IF(D29="","",IF(OR(A29="",B29="",E29="",F29=""),"falta qid, modo, tipo o vs_ref",IF(AND(B29="llm",I29<>""),"respaldo no aplica en modo LLM",IF(AND(E29="abstencion",I29<>""),"una abstención no se califica en citas",IF(AND(B29="rag",E29="hecho",I29=""),"falta respaldo","ok")))))
C30: =IF(A30="","",COUNTIFS($A$2:A30,A30,$B$2:B30,B30)) | M30: =IF(D30="","",IF(OR(E30="",F30=""),"",IF(TRIM(IF(AND(E30="hecho",F30="INCORRECTA"),"INC ","")&IF(AND(E30="abstencion",F30="INCORRECTA"),"ABS-E ","")&IF(AND(E30="hecho",F30="FUERA_REF",H30="no_resp"),"NO-ABS ","")&IF(AND(E30="hecho",I30="SIN-RESPALDO"),"SIN-R ","")&IF(AND(E30="hecho",I30="CITA-X"),"CITA-X ","")&IF(AND(E30="hecho",I30="SIN-CITA"),"SIN-C ",""))="","-",TRIM(IF(AND(E30="hecho",F30="INCORRECTA"),"INC ","")&IF(AND(E30="abstencion",F30="INCORRECTA"),"ABS-E ","")&IF(AND(E30="hecho",F30="FUERA_REF",H30="no_resp"),"NO-ABS ","")&IF(AND(E30="hecho",I30="SIN-RESPALDO"),"SIN-R ","")&IF(AND(E30="hecho",I30="CITA-X"),"CITA-X ","")&IF(AND(E30="hecho",I30="SIN-CITA"),"SIN-C ",""))))) | N30: =IF(D30="","",IF(OR(A30="",B30="",E30="",F30=""),"falta qid, modo, tipo o vs_ref",IF(AND(B30="llm",I30<>""),"respaldo no aplica en modo LLM",IF(AND(E30="abstencion",I30<>""),"una abstención no se califica en citas",IF(AND(B30="rag",E30="hecho",I30=""),"falta respaldo","ok")))))
C31: =IF(A31="","",COUNTIFS($A$2:A31,A31,$B$2:B31,B31)) | M31: =IF(D31="","",IF(OR(E31="",F31=""),"",IF(TRIM(IF(AND(E31="hecho",F31="INCORRECTA"),"INC ","")&IF(AND(E31="abstencion",F31="INCORRECTA"),"ABS-E ","")&IF(AND(E31="hecho",F31="FUERA_REF",H31="no_resp"),"NO-ABS ","")&IF(AND(E31="hecho",I31="SIN-RESPALDO"),"SIN-R ","")&IF(AND(E31="hecho",I31="CITA-X"),"CITA-X ","")&IF(AND(E31="hecho",I31="SIN-CITA"),"SIN-C ",""))="","-",TRIM(IF(AND(E31="hecho",F31="INCORRECTA"),"INC ","")&IF(AND(E31="abstencion",F31="INCORRECTA"),"ABS-E ","")&IF(AND(E31="hecho",F31="FUERA_REF",H31="no_resp"),"NO-ABS ","")&IF(AND(E31="hecho",I31="SIN-RESPALDO"),"SIN-R ","")&IF(AND(E31="hecho",I31="CITA-X"),"CITA-X ","")&IF(AND(E31="hecho",I31="SIN-CITA"),"SIN-C ",""))))) | N31: =IF(D31="","",IF(OR(A31="",B31="",E31="",F31=""),"falta qid, modo, tipo o vs_ref",IF(AND(B31="llm",I31<>""),"respaldo no aplica en modo LLM",IF(AND(E31="abstencion",I31<>""),"una abstención no se califica en citas",IF(AND(B31="rag",E31="hecho",I31=""),"falta respaldo","ok")))))
C32: =IF(A32="","",COUNTIFS($A$2:A32,A32,$B$2:B32,B32)) | M32: =IF(D32="","",IF(OR(E32="",F32=""),"",IF(TRIM(IF(AND(E32="hecho",F32="INCORRECTA"),"INC ","")&IF(AND(E32="abstencion",F32="INCORRECTA"),"ABS-E ","")&IF(AND(E32="hecho",F32="FUERA_REF",H32="no_resp"),"NO-ABS ","")&IF(AND(E32="hecho",I32="SIN-RESPALDO"),"SIN-R ","")&IF(AND(E32="hecho",I32="CITA-X"),"CITA-X ","")&IF(AND(E32="hecho",I32="SIN-CITA"),"SIN-C ",""))="","-",TRIM(IF(AND(E32="hecho",F32="INCORRECTA"),"INC ","")&IF(AND(E32="abstencion",F32="INCORRECTA"),"ABS-E ","")&IF(AND(E32="hecho",F32="FUERA_REF",H32="no_resp"),"NO-ABS ","")&IF(AND(E32="hecho",I32="SIN-RESPALDO"),"SIN-R ","")&IF(AND(E32="hecho",I32="CITA-X"),"CITA-X ","")&IF(AND(E32="hecho",I32="SIN-CITA"),"SIN-C ",""))))) | N32: =IF(D32="","",IF(OR(A32="",B32="",E32="",F32=""),"falta qid, modo, tipo o vs_ref",IF(AND(B32="llm",I32<>""),"respaldo no aplica en modo LLM",IF(AND(E32="abstencion",I32<>""),"una abstención no se califica en citas",IF(AND(B32="rag",E32="hecho",I32=""),"falta respaldo","ok")))))
C33: =IF(A33="","",COUNTIFS($A$2:A33,A33,$B$2:B33,B33)) | M33: =IF(D33="","",IF(OR(E33="",F33=""),"",IF(TRIM(IF(AND(E33="hecho",F33="INCORRECTA"),"INC ","")&IF(AND(E33="abstencion",F33="INCORRECTA"),"ABS-E ","")&IF(AND(E33="hecho",F33="FUERA_REF",H33="no_resp"),"NO-ABS ","")&IF(AND(E33="hecho",I33="SIN-RESPALDO"),"SIN-R ","")&IF(AND(E33="hecho",I33="CITA-X"),"CITA-X ","")&IF(AND(E33="hecho",I33="SIN-CITA"),"SIN-C ",""))="","-",TRIM(IF(AND(E33="hecho",F33="INCORRECTA"),"INC ","")&IF(AND(E33="abstencion",F33="INCORRECTA"),"ABS-E ","")&IF(AND(E33="hecho",F33="FUERA_REF",H33="no_resp"),"NO-ABS ","")&IF(AND(E33="hecho",I33="SIN-RESPALDO"),"SIN-R ","")&IF(AND(E33="hecho",I33="CITA-X"),"CITA-X ","")&IF(AND(E33="hecho",I33="SIN-CITA"),"SIN-C ",""))))) | N33: =IF(D33="","",IF(OR(A33="",B33="",E33="",F33=""),"falta qid, modo, tipo o vs_ref",IF(AND(B33="llm",I33<>""),"respaldo no aplica en modo LLM",IF(AND(E33="abstencion",I33<>""),"una abstención no se califica en citas",IF(AND(B33="rag",E33="hecho",I33=""),"falta respaldo","ok")))))
C34: =IF(A34="","",COUNTIFS($A$2:A34,A34,$B$2:B34,B34)) | M34: =IF(D34="","",IF(OR(E34="",F34=""),"",IF(TRIM(IF(AND(E34="hecho",F34="INCORRECTA"),"INC ","")&IF(AND(E34="abstencion",F34="INCORRECTA"),"ABS-E ","")&IF(AND(E34="hecho",F34="FUERA_REF",H34="no_resp"),"NO-ABS ","")&IF(AND(E34="hecho",I34="SIN-RESPALDO"),"SIN-R ","")&IF(AND(E34="hecho",I34="CITA-X"),"CITA-X ","")&IF(AND(E34="hecho",I34="SIN-CITA"),"SIN-C ",""))="","-",TRIM(IF(AND(E34="hecho",F34="INCORRECTA"),"INC ","")&IF(AND(E34="abstencion",F34="INCORRECTA"),"ABS-E ","")&IF(AND(E34="hecho",F34="FUERA_REF",H34="no_resp"),"NO-ABS ","")&IF(AND(E34="hecho",I34="SIN-RESPALDO"),"SIN-R ","")&IF(AND(E34="hecho",I34="CITA-X"),"CITA-X ","")&IF(AND(E34="hecho",I34="SIN-CITA"),"SIN-C ",""))))) | N34: =IF(D34="","",IF(OR(A34="",B34="",E34="",F34=""),"falta qid, modo, tipo o vs_ref",IF(AND(B34="llm",I34<>""),"respaldo no aplica en modo LLM",IF(AND(E34="abstencion",I34<>""),"una abstención no se califica en citas",IF(AND(B34="rag",E34="hecho",I34=""),"falta respaldo","ok")))))
C35: =IF(A35="","",COUNTIFS($A$2:A35,A35,$B$2:B35,B35)) | M35: =IF(D35="","",IF(OR(E35="",F35=""),"",IF(TRIM(IF(AND(E35="hecho",F35="INCORRECTA"),"INC ","")&IF(AND(E35="abstencion",F35="INCORRECTA"),"ABS-E ","")&IF(AND(E35="hecho",F35="FUERA_REF",H35="no_resp"),"NO-ABS ","")&IF(AND(E35="hecho",I35="SIN-RESPALDO"),"SIN-R ","")&IF(AND(E35="hecho",I35="CITA-X"),"CITA-X ","")&IF(AND(E35="hecho",I35="SIN-CITA"),"SIN-C ",""))="","-",TRIM(IF(AND(E35="hecho",F35="INCORRECTA"),"INC ","")&IF(AND(E35="abstencion",F35="INCORRECTA"),"ABS-E ","")&IF(AND(E35="hecho",F35="FUERA_REF",H35="no_resp"),"NO-ABS ","")&IF(AND(E35="hecho",I35="SIN-RESPALDO"),"SIN-R ","")&IF(AND(E35="hecho",I35="CITA-X"),"CITA-X ","")&IF(AND(E35="hecho",I35="SIN-CITA"),"SIN-C ",""))))) | N35: =IF(D35="","",IF(OR(A35="",B35="",E35="",F35=""),"falta qid, modo, tipo o vs_ref",IF(AND(B35="llm",I35<>""),"respaldo no aplica en modo LLM",IF(AND(E35="abstencion",I35<>""),"una abstención no se califica en citas",IF(AND(B35="rag",E35="hecho",I35=""),"falta respaldo","ok")))))
C36: =IF(A36="","",COUNTIFS($A$2:A36,A36,$B$2:B36,B36)) | M36: =IF(D36="","",IF(OR(E36="",F36=""),"",IF(TRIM(IF(AND(E36="hecho",F36="INCORRECTA"),"INC ","")&IF(AND(E36="abstencion",F36="INCORRECTA"),"ABS-E ","")&IF(AND(E36="hecho",F36="FUERA_REF",H36="no_resp"),"NO-ABS ","")&IF(AND(E36="hecho",I36="SIN-RESPALDO"),"SIN-R ","")&IF(AND(E36="hecho",I36="CITA-X"),"CITA-X ","")&IF(AND(E36="hecho",I36="SIN-CITA"),"SIN-C ",""))="","-",TRIM(IF(AND(E36="hecho",F36="INCORRECTA"),"INC ","")&IF(AND(E36="abstencion",F36="INCORRECTA"),"ABS-E ","")&IF(AND(E36="hecho",F36="FUERA_REF",H36="no_resp"),"NO-ABS ","")&IF(AND(E36="hecho",I36="SIN-RESPALDO"),"SIN-R ","")&IF(AND(E36="hecho",I36="CITA-X"),"CITA-X ","")&IF(AND(E36="hecho",I36="SIN-CITA"),"SIN-C ",""))))) | N36: =IF(D36="","",IF(OR(A36="",B36="",E36="",F36=""),"falta qid, modo, tipo o vs_ref",IF(AND(B36="llm",I36<>""),"respaldo no aplica en modo LLM",IF(AND(E36="abstencion",I36<>""),"una abstención no se califica en citas",IF(AND(B36="rag",E36="hecho",I36=""),"falta respaldo","ok")))))
C37: =IF(A37="","",COUNTIFS($A$2:A37,A37,$B$2:B37,B37)) | M37: =IF(D37="","",IF(OR(E37="",F37=""),"",IF(TRIM(IF(AND(E37="hecho",F37="INCORRECTA"),"INC ","")&IF(AND(E37="abstencion",F37="INCORRECTA"),"ABS-E ","")&IF(AND(E37="hecho",F37="FUERA_REF",H37="no_resp"),"NO-ABS ","")&IF(AND(E37="hecho",I37="SIN-RESPALDO"),"SIN-R ","")&IF(AND(E37="hecho",I37="CITA-X"),"CITA-X ","")&IF(AND(E37="hecho",I37="SIN-CITA"),"SIN-C ",""))="","-",TRIM(IF(AND(E37="hecho",F37="INCORRECTA"),"INC ","")&IF(AND(E37="abstencion",F37="INCORRECTA"),"ABS-E ","")&IF(AND(E37="hecho",F37="FUERA_REF",H37="no_resp"),"NO-ABS ","")&IF(AND(E37="hecho",I37="SIN-RESPALDO"),"SIN-R ","")&IF(AND(E37="hecho",I37="CITA-X"),"CITA-X ","")&IF(AND(E37="hecho",I37="SIN-CITA"),"SIN-C ",""))))) | N37: =IF(D37="","",IF(OR(A37="",B37="",E37="",F37=""),"falta qid, modo, tipo o vs_ref",IF(AND(B37="llm",I37<>""),"respaldo no aplica en modo LLM",IF(AND(E37="abstencion",I37<>""),"una abstención no se califica en citas",IF(AND(B37="rag",E37="hecho",I37=""),"falta respaldo","ok")))))
C38: =IF(A38="","",COUNTIFS($A$2:A38,A38,$B$2:B38,B38)) | M38: =IF(D38="","",IF(OR(E38="",F38=""),"",IF(TRIM(IF(AND(E38="hecho",F38="INCORRECTA"),"INC ","")&IF(AND(E38="abstencion",F38="INCORRECTA"),"ABS-E ","")&IF(AND(E38="hecho",F38="FUERA_REF",H38="no_resp"),"NO-ABS ","")&IF(AND(E38="hecho",I38="SIN-RESPALDO"),"SIN-R ","")&IF(AND(E38="hecho",I38="CITA-X"),"CITA-X ","")&IF(AND(E38="hecho",I38="SIN-CITA"),"SIN-C ",""))="","-",TRIM(IF(AND(E38="hecho",F38="INCORRECTA"),"INC ","")&IF(AND(E38="abstencion",F38="INCORRECTA"),"ABS-E ","")&IF(AND(E38="hecho",F38="FUERA_REF",H38="no_resp"),"NO-ABS ","")&IF(AND(E38="hecho",I38="SIN-RESPALDO"),"SIN-R ","")&IF(AND(E38="hecho",I38="CITA-X"),"CITA-X ","")&IF(AND(E38="hecho",I38="SIN-CITA"),"SIN-C ",""))))) | N38: =IF(D38="","",IF(OR(A38="",B38="",E38="",F38=""),"falta qid, modo, tipo o vs_ref",IF(AND(B38="llm",I38<>""),"respaldo no aplica en modo LLM",IF(AND(E38="abstencion",I38<>""),"una abstención no se califica en citas",IF(AND(B38="rag",E38="hecho",I38=""),"falta respaldo","ok")))))
C39: =IF(A39="","",COUNTIFS($A$2:A39,A39,$B$2:B39,B39)) | M39: =IF(D39="","",IF(OR(E39="",F39=""),"",IF(TRIM(IF(AND(E39="hecho",F39="INCORRECTA"),"INC ","")&IF(AND(E39="abstencion",F39="INCORRECTA"),"ABS-E ","")&IF(AND(E39="hecho",F39="FUERA_REF",H39="no_resp"),"NO-ABS ","")&IF(AND(E39="hecho",I39="SIN-RESPALDO"),"SIN-R ","")&IF(AND(E39="hecho",I39="CITA-X"),"CITA-X ","")&IF(AND(E39="hecho",I39="SIN-CITA"),"SIN-C ",""))="","-",TRIM(IF(AND(E39="hecho",F39="INCORRECTA"),"INC ","")&IF(AND(E39="abstencion",F39="INCORRECTA"),"ABS-E ","")&IF(AND(E39="hecho",F39="FUERA_REF",H39="no_resp"),"NO-ABS ","")&IF(AND(E39="hecho",I39="SIN-RESPALDO"),"SIN-R ","")&IF(AND(E39="hecho",I39="CITA-X"),"CITA-X ","")&IF(AND(E39="hecho",I39="SIN-CITA"),"SIN-C ",""))))) | N39: =IF(D39="","",IF(OR(A39="",B39="",E39="",F39=""),"falta qid, modo, tipo o vs_ref",IF(AND(B39="llm",I39<>""),"respaldo no aplica en modo LLM",IF(AND(E39="abstencion",I39<>""),"una abstención no se califica en citas",IF(AND(B39="rag",E39="hecho",I39=""),"falta respaldo","ok")))))
C40: =IF(A40="","",COUNTIFS($A$2:A40,A40,$B$2:B40,B40)) | M40: =IF(D40="","",IF(OR(E40="",F40=""),"",IF(TRIM(IF(AND(E40="hecho",F40="INCORRECTA"),"INC ","")&IF(AND(E40="abstencion",F40="INCORRECTA"),"ABS-E ","")&IF(AND(E40="hecho",F40="FUERA_REF",H40="no_resp"),"NO-ABS ","")&IF(AND(E40="hecho",I40="SIN-RESPALDO"),"SIN-R ","")&IF(AND(E40="hecho",I40="CITA-X"),"CITA-X ","")&IF(AND(E40="hecho",I40="SIN-CITA"),"SIN-C ",""))="","-",TRIM(IF(AND(E40="hecho",F40="INCORRECTA"),"INC ","")&IF(AND(E40="abstencion",F40="INCORRECTA"),"ABS-E ","")&IF(AND(E40="hecho",F40="FUERA_REF",H40="no_resp"),"NO-ABS ","")&IF(AND(E40="hecho",I40="SIN-RESPALDO"),"SIN-R ","")&IF(AND(E40="hecho",I40="CITA-X"),"CITA-X ","")&IF(AND(E40="hecho",I40="SIN-CITA"),"SIN-C ",""))))) | N40: =IF(D40="","",IF(OR(A40="",B40="",E40="",F40=""),"falta qid, modo, tipo o vs_ref",IF(AND(B40="llm",I40<>""),"respaldo no aplica en modo LLM",IF(AND(E40="abstencion",I40<>""),"una abstención no se califica en citas",IF(AND(B40="rag",E40="hecho",I40=""),"falta respaldo","ok")))))
... C401: =IF(A401="","",COUNTIFS($A$2:A401,A401,$B$2:B401,B401)) | M401: =IF(D401="","",IF(OR(E401="",F401=""),"",IF(TRIM(IF(AND(E401="hecho",F401="INCORRECTA"),"INC ","")&IF(AND(E401="abstencion",F401="INCORRECTA"),"ABS-E ","")&IF(AND(E401="hecho",F401="FUERA_REF",H401="no_resp"),"NO-ABS ","")&IF(AND(E401="hecho",I401="SIN-RESPALDO"),"SIN-R ","")&IF(AND(E401="hecho",I401="CITA-X"),"CITA-X ","")&IF(AND(E401="hecho",I401="SIN-CITA"),"SIN-C ",""))="","-",TRIM(IF(AND(E401="hecho",F401="INCORRECTA"),"INC ","")&IF(AND(E401="abstencion",F401="INCORRECTA"),"ABS-E ","")&IF(AND(E401="hecho",F401="FUERA_REF",H401="no_resp"),"NO-ABS ","")&IF(AND(E401="hecho",I401="SIN-RESPALDO"),"SIN-R ","")&IF(AND(E401="hecho",I401="CITA-X"),"CITA-X ","")&IF(AND(E401="hecho",I401="SIN-CITA"),"SIN-C ",""))))) | N401: =IF(D401="","",IF(OR(A401="",B401="",E401="",F401=""),"falta qid, modo, tipo o vs_ref",IF(AND(B401="llm",I401<>""),"respaldo no aplica en modo LLM",IF(AND(E401="abstencion",I401<>""),"una abstención no se califica en citas",IF(AND(B401="rag",E401="hecho",I401=""),"falta respaldo","ok")))))

Sheet Hechos
A1: qid | B1: hecho | C1: texto del hecho | D1: evidencia (n frag.) | E1: llegó (RAG) | F1: cubierto RAG | G1: cubierto LLM | H1: cubierto y citado RAG
A2: p01 | B2: H1 | C2: M1038 Execution Prevention | D2: 1 | E2: NO | F2: =IF(COUNTIFS(Afirmaciones!$A$2:$A$401,$A2,Afirmaciones!$B$2:$B$401,"rag")=0,"",IF(SUMPRODUCT((Afirmaciones!$A$2:$A$401=$A2)*(Afirmaciones!$F$2:$F$401="CORRECTA")*(Afirmaciones!$H$2:$H$401<>"no_resp")*ISNUMBER(SEARCH(";"&$B2&";",";"&SUBSTITUTE(Afirmaciones!$G$2:$G$401," ","")&";"))*(Afirmaciones!$B$2:$B$401="rag"))>0,1,0)) -> 0 | G2: =IF(COUNTIFS(Afirmaciones!$A$2:$A$401,$A2,Afirmaciones!$B$2:$B$401,"llm")=0,"",IF(SUMPRODUCT((Afirmaciones!$A$2:$A$401=$A2)*(Afirmaciones!$F$2:$F$401="CORRECTA")*(Afirmaciones!$H$2:$H$401<>"no_resp")*ISNUMBER(SEARCH(";"&$B2&";",";"&SUBSTITUTE(Afirmaciones!$G$2:$G$401," ","")&";"))*(Afirmaciones!$B$2:$B$401="llm"))>0,1,0)) -> 0 | H2: =IF(COUNTIFS(Afirmaciones!$A$2:$A$401,$A2,Afirmaciones!$B$2:$B$401,"rag")=0,"",IF(SUMPRODUCT((Afirmaciones!$A$2:$A$401=$A2)*(Afirmaciones!$F$2:$F$401="CORRECTA")*(Afirmaciones!$H$2:$H$401<>"no_resp")*ISNUMBER(SEARCH(";"&$B2&";",";"&SUBSTITUTE(Afirmaciones!$G$2:$G$401," ","")&";"))*(Afirmaciones!$B$2:$B$401="rag")*(Afirmaciones!$I$2:$I$401="SOSTENIDA"))>0,1,0)) -> 0
A3: p01 | B3: H2 | C3: M1045 Code Signing | D3: 1 | E3: NO | F3: =IF(COUNTIFS(Afirmaciones!$A$2:$A$401,$A3,Afirmaciones!$B$2:$B$401,"rag")=0,"",IF(SUMPRODUCT((Afirmaciones!$A$2:$A$401=$A3)*(Afirmaciones!$F$2:$F$401="CORRECTA")*(Afirmaciones!$H$2:$H$401<>"no_resp")*ISNUMBER(SEARCH(";"&$B3&";",";"&SUBSTITUTE(Afirmaciones!$G$2:$G$401," ","")&";"))*(Afirmaciones!$B$2:$B$401="rag"))>0,1,0)) -> 0 | G3: =IF(COUNTIFS(Afirmaciones!$A$2:$A$401,$A3,Afirmaciones!$B$2:$B$401,"llm")=0,"",IF(SUMPRODUCT((Afirmaciones!$A$2:$A$401=$A3)*(Afirmaciones!$F$2:$F$401="CORRECTA")*(Afirmaciones!$H$2:$H$401<>"no_resp")*ISNUMBER(SEARCH(";"&$B3&";",";"&SUBSTITUTE(Afirmaciones!$G$2:$G$401," ","")&";"))*(Afirmaciones!$B$2:$B$401="llm"))>0,1,0)) -> 1 | H3: =IF(COUNTIFS(Afirmaciones!$A$2:$A$401,$A3,Afirmaciones!$B$2:$B$401,"rag")=0,"",IF(SUMPRODUCT((Afirmaciones!$A$2:$A$401=$A3)*(Afirmaciones!$F$2:$F$401="CORRECTA")*(Afirmaciones!$H$2:$H$401<>"no_resp")*ISNUMBER(SEARCH(";"&$B3&";",";"&SUBSTITUTE(Afirmaciones!$G$2:$G$401," ","")&";"))*(Afirmaciones!$B$2:$B$401="rag")*(Afirmaciones!$I$2:$I$401="SOSTENIDA"))>0,1,0)) -> 0
A4: p01 | B4: H3 | C4: M1026 Privileged Account Management | D4: 1 | E4: NO | F4: =IF(COUNTIFS(Afirmaciones!$A$2:$A$401,$A4,Afirmaciones!$B$2:$B$401,"rag")=0,"",IF(SUMPRODUCT((Afirmaciones!$A$2:$A$401=$A4)*(Afirmaciones!$F$2:$F$401="CORRECTA")*(Afirmaciones!$H$2:$H$401<>"no_resp")*ISNUMBER(SEARCH(";"&$B4&";",";"&SUBSTITUTE(Afirmaciones!$G$2:$G$401," ","")&";"))*(Afirmaciones!$B$2:$B$401="rag"))>0,1,0)) -> 0 | G4: =IF(COUNTIFS(Afirmaciones!$A$2:$A$401,$A4,Afirmaciones!$B$2:$B$401,"llm")=0,"",IF(SUMPRODUCT((Afirmaciones!$A$2:$A$401=$A4)*(Afirmaciones!$F$2:$F$401="CORRECTA")*(Afirmaciones!$H$2:$H$401<>"no_resp")*ISNUMBER(SEARCH(";"&$B4&";",";"&SUBSTITUTE(Afirmaciones!$G$2:$G$401," ","")&";"))*(Afirmaciones!$B$2:$B$401="llm"))>0,1,0)) -> 1 | H4: =IF(COUNTIFS(Afirmaciones!$A$2:$A$401,$A4,Afirmaciones!$B$2:$B$401,"rag")=0,"",IF(SUMPRODUCT((Afirmaciones!$A$2:$A$401=$A4)*(Afirmaciones!$F$2:$F$401="CORRECTA")*(Afirmaciones!$H$2:$H$401<>"no_resp")*ISNUMBER(SEARCH(";"&$B4&";",";"&SUBSTITUTE(Afirmaciones!$G$2:$G$401," ","")&";"))*(Afirmaciones!$B$2:$B$401="rag")*(Afirmaciones!$I$2:$I$401="SOSTENIDA"))>0,1,0)) -> 0
A5: p01 | B5: H4 | C5: M1049 Antivirus/Antimalware | D5: 1 | E5: NO | F5: =IF(COUNTIFS(Afirmaciones!$A$2:$A$401,$A5,Afirmaciones!$B$2:$B$401,"rag")=0,"",IF(SUMPRODUCT((Afirmaciones!$A$2:$A$401=$A5)*(Afirmaciones!$F$2:$F$401="CORRECTA")*(Afirmaciones!$H$2:$H$401<>"no_resp")*ISNUMBER(SEARCH(";"&$B5&";",";"&SUBSTITUTE(Afirmaciones!$G$2:$G$401," ","")&";"))*(Afirmaciones!$B$2:$B$401="rag"))>0,1,0)) -> 0 | G5: =IF(COUNTIFS(Afirmaciones!$A$2:$A$401,$A5,Afirmaciones!$B$2:$B$401,"llm")=0,"",IF(SUMPRODUCT((Afirmaciones!$A$2:$A$401=$A5)*(Afirmaciones!$F$2:$F$401="CORRECTA")*(Afirmaciones!$H$2:$H$401<>"no_resp")*ISNUMBER(SEARCH(";"&$B5&";",";"&SUBSTITUTE(Afirmaciones!$G$2:$G$401," ","")&";"))*(Afirmaciones!$B$2:$B$401="llm"))>0,1,0)) -> 0 | H5: =IF(COUNTIFS(Afirmaciones!$A$2:$A$401,$A5,Afirmaciones!$B$2:$B$401,"rag")=0,"",IF(SUMPRODUCT((Afirmaciones!$A$2:$A$401=$A5)*(Afirmaciones!$F$2:$F$401="CORRECTA")*(Afirmaciones!$H$2:$H$401<>"no_resp")*ISNUMBER(SEARCH(";"&$B5&";",";"&SUBSTITUTE(Afirmaciones!$G$2:$G$401," ","")&";"))*(Afirmaciones!$B$2:$B$401="rag")*(Afirmaciones!$I$2:$I$401="SOSTENIDA"))>0,1,0)) -> 0
A6: p01 | B6: H5 | C6: M1042 Disable or Remove Feature or Program (PowerShell/WinRM) | D6: 3 | E6: ALT-P | F6: =IF(COUNTIFS(Afirmaciones!$A$2:$A$401,$A6,Afirmaciones!$B$2:$B$401,"rag")=0,"",IF(SUMPRODUCT((Afirmaciones!$A$2:$A$401=$A6)*(Afirmaciones!$F$2:$F$401="CORRECTA")*(Afirmaciones!$H$2:$H$401<>"no_resp")*ISNUMBER(SEARCH(";"&$B6&";",";"&SUBSTITUTE(Afirmaciones!$G$2:$G$401," ","")&";"))*(Afirmaciones!$B$2:$B$401="rag"))>0,1,0)) -> 0 | G6: =IF(COUNTIFS(Afirmaciones!$A$2:$A$401,$A6,Afirmaciones!$B$2:$B$401,"llm")=0,"",IF(SUMPRODUCT((Afirmaciones!$A$2:$A$401=$A6)*(Afirmaciones!$F$2:$F$401="CORRECTA")*(Afirmaciones!$H$2:$H$401<>"no_resp")*ISNUMBER(SEARCH(";"&$B6&";",";"&SUBSTITUTE(Afirmaciones!$G$2:$G$401," ","")&";"))*(Afirmaciones!$B$2:$B$401="llm"))>0,1,0)) -> 0 | H6: =IF(COUNTIFS(Afirmaciones!$A$2:$A$401,$A6,Afirmaciones!$B$2:$B$401,"rag")=0,"",IF(SUMPRODUCT((Afirmaciones!$A$2:$A$401=$A6)*(Afirmaciones!$F$2:$F$401="CORRECTA")*(Afirmaciones!$H$2:$H$401<>"no_resp")*ISNUMBER(SEARCH(";"&$B6&";",";"&SUBSTITUTE(Afirmaciones!$G$2:$G$401," ","")&";"))*(Afirmaciones!$B$2:$B$401="rag")*(Afirmaciones!$I$2:$I$401="SOSTENIDA"))>0,1,0)) -> 0
A7: p02 | B7: H1 | C7: Phishing pertenece a Initial Access | D7: 1 | E7: SI | F7: =IF(COUNTIFS(Afirmaciones!$A$2:$A$401,$A7,Afirmaciones!$B$2:$B$401,"rag")=0,"",IF(SUMPRODUCT((Afirmaciones!$A$2:$A$401=$A7)*(Afirmaciones!$F$2:$F$401="CORRECTA")*(Afirmaciones!$H$2:$H$401<>"no_resp")*ISNUMBER(SEARCH(";"&$B7&";",";"&SUBSTITUTE(Afirmaciones!$G$2:$G$401," ","")&";"))*(Afirmaciones!$B$2:$B$401="rag"))>0,1,0)) | G7: =IF(COUNTIFS(Afirmaciones!$A$2:$A$401,$A7,Afirmaciones!$B$2:$B$401,"llm")=0,"",IF(SUMPRODUCT((Afirmaciones!$A$2:$A$401=$A7)*(Afirmaciones!$F$2:$F$401="CORRECTA")*(Afirmaciones!$H$2:$H$401<>"no_resp")*ISNUMBER(SEARCH(";"&$B7&";",";"&SUBSTITUTE(Afirmaciones!$G$2:$G$401," ","")&";"))*(Afirmaciones!$B$2:$B$401="llm"))>0,1,0)) | H7: =IF(COUNTIFS(Afirmaciones!$A$2:$A$401,$A7,Afirmaciones!$B$2:$B$401,"rag")=0,"",IF(SUMPRODUCT((Afirmaciones!$A$2:$A$401=$A7)*(Afirmaciones!$F$2:$F$401="CORRECTA")*(Afirmaciones!$H$2:$H$401<>"no_resp")*ISNUMBER(SEARCH(";"&$B7&";",";"&SUBSTITUTE(Afirmaciones!$G$2:$G$401," ","")&";"))*(Afirmaciones!$B$2:$B$401="rag")*(Afirmaciones!$I$2:$I$401="SOSTENIDA"))>0,1,0))
A8: p02 | B8: H2 | C8: T1566.001 Spearphishing Attachment | D8: 1 | E8: NO | F8: =IF(COUNTIFS(Afirmaciones!$A$2:$A$401,$A8,Afirmaciones!$B$2:$B$401,"rag")=0,"",IF(SUMPRODUCT((Afirmaciones!$A$2:$A$401=$A8)*(Afirmaciones!$F$2:$F$401="CORRECTA")*(Afirmaciones!$H$2:$H$401<>"no_resp")*ISNUMBER(SEARCH(";"&$B8&";",";"&SUBSTITUTE(Afirmaciones!$G$2:$G$401," ","")&";"))*(Afirmaciones!$B$2:$B$401="rag"))>0,1,0)) | G8: =IF(COUNTIFS(Afirmaciones!$A$2:$A$401,$A8,Afirmaciones!$B$2:$B$401,"llm")=0,"",IF(SUMPRODUCT((Afirmaciones!$A$2:$A$401=$A8)*(Afirmaciones!$F$2:$F$401="CORRECTA")*(Afirmaciones!$H$2:$H$401<>"no_resp")*ISNUMBER(SEARCH(";"&$B8&";",";"&SUBSTITUTE(Afirmaciones!$G$2:$G$401," ","")&";"))*(Afirmaciones!$B$2:$B$401="llm"))>0,1,0)) | H8: =IF(COUNTIFS(Afirmaciones!$A$2:$A$401,$A8,Afirmaciones!$B$2:$B$401,"rag")=0,"",IF(SUMPRODUCT((Afirmaciones!$A$2:$A$401=$A8)*(Afirmaciones!$F$2:$F$401="CORRECTA")*(Afirmaciones!$H$2:$H$401<>"no_resp")*ISNUMBER(SEARCH(";"&$B8&";",";"&SUBSTITUTE(Afirmaciones!$G$2:$G$401," ","")&";"))*(Afirmaciones!$B$2:$B$401="rag")*(Afirmaciones!$I$2:$I$401="SOSTENIDA"))>0,1,0))
A9: p02 | B9: H3 | C9: T1566.002 Spearphishing Link | D9: 1 | E9: NO | F9: =IF(COUNTIFS(Afirmaciones!$A$2:$A$401,$A9,Afirmaciones!$B$2:$B$401,"rag")=0,"",IF(SUMPRODUCT((Afirmaciones!$A$2:$A$401=$A9)*(Afirmaciones!$F$2:$F$401="CORRECTA")*(Afirmaciones!$H$2:$H$401<>"no_resp")*ISNUMBER(SEARCH(";"&$B9&";",";"&SUBSTITUTE(Afirmaciones!$G$2:$G$401," ","")&";"))*(Afirmaciones!$B$2:$B$401="rag"))>0,1,0)) | G9: =IF(COUNTIFS(Afirmaciones!$A$2:$A$401,$A9,Afirmaciones!$B$2:$B$401,"llm")=0,"",IF(SUMPRODUCT((Afirmaciones!$A$2:$A$401=$A9)*(Afirmaciones!$F$2:$F$401="CORRECTA")*(Afirmaciones!$H$2:$H$401<>"no_resp")*ISNUMBER(SEARCH(";"&$B9&";",";"&SUBSTITUTE(Afirmaciones!$G$2:$G$401," ","")&";"))*(Afirmaciones!$B$2:$B$401="llm"))>0,1,0)) | H9: =IF(COUNTIFS(Afirmaciones!$A$2:$A$401,$A9,Afirmaciones!$B$2:$B$401,"rag")=0,"",IF(SUMPRODUCT((Afirmaciones!$A$2:$A$401=$A9)*(Afirmaciones!$F$2:$F$401="CORRECTA")*(Afirmaciones!$H$2:$H$401<>"no_resp")*ISNUMBER(SEARCH(";"&$B9&";",";"&SUBSTITUTE(Afirmaciones!$G$2:$G$401," ","")&";"))*(Afirmaciones!$B$2:$B$401="rag")*(Afirmaciones!$I$2:$I$401="SOSTENIDA"))>0,1,0))
A10: p02 | B10: H4 | C10: T1566.003 Spearphishing via Service | D10: 1 | E10: NO | F10: =IF(COUNTIFS(Afirmaciones!$A$2:$A$401,$A10,Afirmaciones!$B$2:$B$401,"rag")=0,"",IF(SUMPRODUCT((Afirmaciones!$A$2:$A$401=$A10)*(Afirmaciones!$F$2:$F$401="CORRECTA")*(Afirmaciones!$H$2:$H$401<>"no_resp")*ISNUMBER(SEARCH(";"&$B10&";",";"&SUBSTITUTE(Afirmaciones!$G$2:$G$401," ","")&";"))*(Afirmaciones!$B$2:$B$401="rag"))>0,1,0)) | G10: =IF(COUNTIFS(Afirmaciones!$A$2:$A$401,$A10,Afirmaciones!$B$2:$B$401,"llm")=0,"",IF(SUMPRODUCT((Afirmaciones!$A$2:$A$401=$A10)*(Afirmaciones!$F$2:$F$401="CORRECTA")*(Afirmaciones!$H$2:$H$401<>"no_resp")*ISNUMBER(SEARCH(";"&$B10&";",";"&SUBSTITUTE(Afirmaciones!$G$2:$G$401," ","")&";"))*(Afirmaciones!$B$2:$B$401="llm"))>0,1,0)) | H10: =IF(COUNTIFS(Afirmaciones!$A$2:$A$401,$A10,Afirmaciones!$B$2:$B$401,"rag")=0,"",IF(SUMPRODUCT((Afirmaciones!$A$2:$A$401=$A10)*(Afirmaciones!$F$2:$F$401="CORRECTA")*(Afirmaciones!$H$2:$H$401<>"no_resp")*ISNUMBER(SEARCH(";"&$B10&";",";"&SUBSTITUTE(Afirmaciones!$G$2:$G$401," ","")&";"))*(Afirmaciones!$B$2:$B$401="rag")*(Afirmaciones!$I$2:$I$401="SOSTENIDA"))>0,1,0))
A11: p02 | B11: H5 | C11: T1566.004 Spearphishing Voice | D11: 1 | E11: NO | F11: =IF(COUNTIFS(Afirmaciones!$A$2:$A$401,$A11,Afirmaciones!$B$2:$B$401,"rag")=0,"",IF(SUMPRODUCT((Afirmaciones!$A$2:$A$401=$A11)*(Afirmaciones!$F$2:$F$401="CORRECTA")*(Afirmaciones!$H$2:$H$401<>"no_resp")*ISNUMBER(SEARCH(";"&$B11&";",";"&SUBSTITUTE(Afirmaciones!$G$2:$G$401," ","")&";"))*(Afirmaciones!$B$2:$B$401="rag"))>0,1,0)) | G11: =IF(COUNTIFS(Afirmaciones!$A$2:$A$401,$A11,Afirmaciones!$B$2:$B$401,"llm")=0,"",IF(SUMPRODUCT((Afirmaciones!$A$2:$A$401=$A11)*(Afirmaciones!$F$2:$F$401="CORRECTA")*(Afirmaciones!$H$2:$H$401<>"no_resp")*ISNUMBER(SEARCH(";"&$B11&";",";"&SUBSTITUTE(Afirmaciones!$G$2:$G$401," ","")&";"))*(Afirmaciones!$B$2:$B$401="llm"))>0,1,0)) | H11: =IF(COUNTIFS(Afirmaciones!$A$2:$A$401,$A11,Afirmaciones!$B$2:$B$401,"rag")=0,"",IF(SUMPRODUCT((Afirmaciones!$A$2:$A$401=$A11)*(Afirmaciones!$F$2:$F$401="CORRECTA")*(Afirmaciones!$H$2:$H$401<>"no_resp")*ISNUMBER(SEARCH(";"&$B11&";",";"&SUBSTITUTE(Afirmaciones!$G$2:$G$401," ","")&";"))*(Afirmaciones!$B$2:$B$401="rag")*(Afirmaciones!$I$2:$I$401="SOSTENIDA"))>0,1,0))
A12: p03 | B12: H1 | C12: Persistencia = el adversario intenta mantener su punto de apoyo | D12: 2 | E12: SI | F12: =IF(COUNTIFS(Afirmaciones!$A$2:$A$401,$A12,Afirmaciones!$B$2:$B$401,"rag")=0,"",IF(SUMPRODUCT((Afirmaciones!$A$2:$A$401=$A12)*(Afirmaciones!$F$2:$F$401="CORRECTA")*(Afirmaciones!$H$2:$H$401<>"no_resp")*ISNUMBER(SEARCH(";"&$B12&";",";"&SUBSTITUTE(Afirmaciones!$G$2:$G$401," ","")&";"))*(Afirmaciones!$B$2:$B$401="rag"))>0,1,0)) | G12: =IF(COUNTIFS(Afirmaciones!$A$2:$A$401,$A12,Afirmaciones!$B$2:$B$401,"llm")=0,"",IF(SUMPRODUCT((Afirmaciones!$A$2:$A$401=$A12)*(Afirmaciones!$F$2:$F$401="CORRECTA")*(Afirmaciones!$H$2:$H$401<>"no_resp")*ISNUMBER(SEARCH(";"&$B12&";",";"&SUBSTITUTE(Afirmaciones!$G$2:$G$401," ","")&";"))*(Afirmaciones!$B$2:$B$401="llm"))>0,1,0)) | H12: =IF(COUNTIFS(Afirmaciones!$A$2:$A$401,$A12,Afirmaciones!$B$2:$B$401,"rag")=0,"",IF(SUMPRODUCT((Afirmaciones!$A$2:$A$401=$A12)*(Afirmaciones!$F$2:$F$401="CORRECTA")*(Afirmaciones!$H$2:$H$401<>"no_resp")*ISNUMBER(SEARCH(";"&$B12&";",";"&SUBSTITUTE(Afirmaciones!$G$2:$G$401," ","")&";"))*(Afirmaciones!$B$2:$B$401="rag")*(Afirmaciones!$I$2:$I$401="SOSTENIDA"))>0,1,0))
A13: p03 | B13: H2 | C13: Conservar acceso pese a reinicios, cambios de credenciales u otras interrupciones | D13: 1 | E13: SI | F13: =IF(COUNTIFS(Afirmaciones!$A$2:$A$401,$A13,Afirmaciones!$B$2:$B$401,"rag")=0,"",IF(SUMPRODUCT((Afirmaciones!$A$2:$A$401=$A13)*(Afirmaciones!$F$2:$F$401="CORRECTA")*(Afirmaciones!$H$2:$H$401<>"no_resp")*ISNUMBER(SEARCH(";"&$B13&";",";"&SUBSTITUTE(Afirmaciones!$G$2:$G$401," ","")&";"))*(Afirmaciones!$B$2:$B$401="rag"))>0,1,0)) | G13: =IF(COUNTIFS(Afirmaciones!$A$2:$A$401,$A13,Afirmaciones!$B$2:$B$401,"llm")=0,"",IF(SUMPRODUCT((Afirmaciones!$A$2:$A$401=$A13)*(Afirmaciones!$F$2:$F$401="CORRECTA")*(Afirmaciones!$H$2:$H$401<>"no_resp")*ISNUMBER(SEARCH(";"&$B13&";",";"&SUBSTITUTE(Afirmaciones!$G$2:$G$401," ","")&";"))*(Afirmaciones!$B$2:$B$401="llm"))>0,1,0)) | H13: =IF(COUNTIFS(Afirmaciones!$A$2:$A$401,$A13,Afirmaciones!$B$2:$B$401,"rag")=0,"",IF(SUMPRODUCT((Afirmaciones!$A$2:$A$401=$A13)*(Afirmaciones!$F$2:$F$401="CORRECTA")*(Afirmaciones!$H$2:$H$401<>"no_resp")*ISNUMBER(SEARCH(";"&$B13&";",";"&SUBSTITUTE(Afirmaciones!$G$2:$G$401," ","")&";"))*(Afirmaciones!$B$2:$B$401="rag")*(Afirmaciones!$I$2:$I$401="SOSTENIDA"))>0,1,0))
... A34: p09 | B34: H6 | C34: M1047 Audit | D34: 1 | E34: SI | F34: =IF(COUNTIFS(Afirmaciones!$A$2:$A$401,$A34,Afirmaciones!$B$2:$B$401,"rag")=0,"",IF(SUMPRODUCT((Afirmaciones!$A$2:$A$401=$A34)*(Afirmaciones!$F$2:$F$401="CORRECTA")*(Afirmaciones!$H$2:$H$401<>"no_resp")*ISNUMBER(SEARCH(";"&$B34&";",";"&SUBSTITUTE(Afirmaciones!$G$2:$G$401," ","")&";"))*(Afirmaciones!$B$2:$B$401="rag"))>0,1,0)) -> 0 | G34: =IF(COUNTIFS(Afirmaciones!$A$2:$A$401,$A34,Afirmaciones!$B$2:$B$401,"llm")=0,"",IF(SUMPRODUCT((Afirmaciones!$A$2:$A$401=$A34)*(Afirmaciones!$F$2:$F$401="CORRECTA")*(Afirmaciones!$H$2:$H$401<>"no_resp")*ISNUMBER(SEARCH(";"&$B34&";",";"&SUBSTITUTE(Afirmaciones!$G$2:$G$401," ","")&";"))*(Afirmaciones!$B$2:$B$401="llm"))>0,1,0)) -> 0 | H34: =IF(COUNTIFS(Afirmaciones!$A$2:$A$401,$A34,Afirmaciones!$B$2:$B$401,"rag")=0,"",IF(SUMPRODUCT((Afirmaciones!$A$2:$A$401=$A34)*(Afirmaciones!$F$2:$F$401="CORRECTA")*(Afirmaciones!$H$2:$H$401<>"no_resp")*ISNUMBER(SEARCH(";"&$B34&";",";"&SUBSTITUTE(Afirmaciones!$G$2:$G$401," ","")&";"))*(Afirmaciones!$B$2:$B$401="rag")*(Afirmaciones!$I$2:$I$401="SOSTENIDA"))>0,1,0)) -> 0

Sheet Contextos
A1: qid | B1: rank | C1: point_id | D1: attack_id | E1: chunk | F1: score | G1: texto del fragmento
A2: p01 | B2: 1 | C2: 0a79d1de-5953-5bf1-91d8-c87bbbf93bc8 | D2: T1059.001 | E2: 0/11 | F2: 1 | G2: # T1059.001 - PowerShell Type: sub-technique | Domain: enterprise-attack | ATT&CK version: 19.2 Tactics: execution Platforms: Windows Sub-technique of: T1059 Command and Scripting Interpreter ## Description Adversaries may abuse PowerShell commands and scripts for execution. PowerShell is a powerful interactive command-line interface and scripting environment included in the Windows operating system. Adversaries can use PowerShell to perform a number of actions, including discovery of information and execution of code. Examples include the <code>Start-Process</code> cmdlet which can be used to run an executable and the <code>Invoke-Command</code> cmdlet which runs a command locally or on a remote computer (though administrator permissions are required to use PowerShell to connect to remote systems). PowerShell may also be used to download and run executables from the Internet, which can be executed from disk or in memory without touching disk.
A3: p01 | B3: 2 | C3: 4890209d-7610-5835-817d-6f8eb92c4ff3 | D3: S1193 | E3: 0/1 | F3: 0.3922 | G3: # S1193 - TAMECAT Type: software | Domain: enterprise-attack | ATT&CK version: 19.2 Software type: malware | Aliases: TAMECAT | Platforms: Windows ## Description [TAMECAT](https://attack.mitre.org/software/S1193) is a malware that is used by [APT42](https://attack.mitre.org/groups/G1044) to execute PowerShell or C# content. ## Techniques used - T1047 Windows Management Instrumentation - T1059.001 PowerShell - T1059.003 Windows Command Shell - T1059.005 Visual Basic - T1071.001 Web Protocols - T1105 Ingress Tool Transfer - T1132.001 Standard Encoding - T1518.001 Security Software Discovery - T1573.001 Symmetric Cryptography ## Used by - G1044 APT42
A4: p01 | B4: 3 | C4: a2e64c2d-7e66-5e5a-86df-0543d7957b56 | D4: G0099 | E4: 1/3 | F4: 0.3333 | G4: # G0099 - APT-C-36 institutions and entities in the financial, energy, and professional manufacturing sectors across Colombia and other Latin American countries. ## Techniques used - T1027 Obfuscated Files or Information - T1027.003 Steganography - T1027.013 Encrypted/Encoded File - T1027.016 Junk Code Insertion - T1036.004 Masquerade Task or Service - T1036.005 Match Legitimate Resource Name or Location - T1047 Windows Management Instrumentation - T1053.005 Scheduled Task - T1055.012 Process Hollowing - T1059.001 PowerShell - T1059.005 Visual Basic - T1059.007 JavaScript - T1105 Ingress Tool Transfer - T1133 External Remote Services - T1204.001 Malicious Link - T1204.002 Malicious File - T1480 Execution Guardrails - T1534 Internal Spearphishing - T1564.003 Hidden Window - T1566.001 Spearphishing Attachment - T1566.002 Spearphishing Link - T1568 Dynamic Resolution - T1571 Non-Standard Port - T1574.001 DLL - T1583.001 Domains - T1583.003 Virtual Private Server - T1583.006 Web Services - T1584.005 Botnet - T1586.002 Email Accounts - T1586.003 Cloud Accounts - T1587.001 Malware - T1588.001 Malware - T1588.002 Tool - T1593 Search Open Websites/Domains - T1608.001 Upload Malware - T1683.001 Written Content - T1683.002 Audio-Visual Content - T1684.001 Impersonation
A5: p01 | B5: 4 | C5: 12155368-afb0-5e72-bdbd-189ee840f96e | D5: T1059 | E5: 5/10 | F5: 0.2556 | G5: # T1059 - Command and Scripting Interpreter interpreter installations. - M1042 Disable or Remove Feature or Program: Disable or remove any unnecessary or unused shells or interpreters. ## Sub-techniques - T1059.007 JavaScript - T1059.002 AppleScript - T1059.010 AutoHotKey & AutoIT - T1059.009 Cloud API - T1059.008 Network Device CLI - T1059.001 PowerShell - T1059.004 Unix Shell - T1059.011 Lua - T1059.013 Container CLI/API - T1059.005 Visual Basic - T1059.003 Windows Command Shell - T1059.012 Hypervisor CLI - T1059.006 Python ## Procedure examples - C0005 Operation Spalax (campaign): For [Operation Spalax](https://attack.mitre.org/campaigns/C0005), the threat actors used Nullsoft Scriptable Install System (NSIS) scripts to install malware. - C0029 Cutting Edge (campaign): During [Cutting Edge](https://attack.mitre.org/campaigns/C0029), threat actors used Perl scripts to enable the deployment of the THINSPOOL shell script dropper and for enumerating host data. - C0046 ArcaneDoor (campaign): [ArcaneDoor](https://attack.mitre.org/campaigns/C0046) included the adversary executing command line interface (CLI) commands.
A6: p01 | B6: 5 | C6: 3176af7f-1b20-500d-8754-9e2746f08472 | D6: S0393 | E6: 0/1 | F6: 0.25 | G6: # S0393 - PowerStallion Type: software | Domain: enterprise-attack | ATT&CK version: 19.2 Software type: malware | Aliases: PowerStallion | Platforms: Windows ## Description [PowerStallion](https://attack.mitre.org/software/S0393) is a lightweight [PowerShell](https://attack.mitre.org/techniques/T1059/001) backdoor used by [Turla](https://attack.mitre.org/groups/G0010), possibly as a recovery access tool to install other backdoors. ## Techniques used - T1027 Obfuscated Files or Information - T1057 Process Discovery - T1059.001 PowerShell - T1070.006 Timestomp - T1102.002 Bidirectional Communication ## Used by - G0010 Turla
A7: p02 | B7: 1 | C7: b2a9cfd5-44fa-5197-8cfd-a36ce303763f | D7: T1586 | E7: 2/3 | F7: 0.5 | G7: # T1586 - Compromise Accounts organization. Much of this activity will take place outside the visibility of the target organization, making detection of this behavior difficult. Detection efforts may be focused on related stages of the adversary lifecycle, such as during Initial Access (ex: [Phishing](https://attack.mitre.org/techniques/T1566)). Monitor and analyze traffic patterns and packet inspection associated to protocol(s) that do not follow the expected protocol standards and traffic flows (e.g extraneous packets that do not belong to established flows, gratuitous or anomalous traffic patterns, anomalous syntax, or structure). Consider correlation with process monitoring and command line to detect anomalous processes execution and command line arguments associated to traffic patterns (e.g. monitor anomalies in use of files that do not normally initiate connections for respective protocol(s)). ## Mitigations - M1056 Pre-compromise: This technique cannot be easily mitigated with preventive controls since it is based on behaviors performed outside of the scope of enterprise defenses and controls. ## Sub-techniques - T1586.001 Social Media Accounts - T1586.003 Cloud Accounts - T1586.002 Email Accounts
A8: p02 | B8: 2 | C8: af42649d-952f-5dfb-afab-8c8e51a00019 | D8: T1566 | E8: 0/8 | F8: 0.5 | G8: # T1566 - Phishing Type: technique | Domain: enterprise-attack | ATT&CK version: 19.2 Tactics: initial-access Platforms: Identity Provider, Linux, macOS, Office Suite, SaaS, Windows ## Description Adversaries may send phishing messages to gain access to victim systems. All forms of phishing are electronically delivered social engineering. Phishing can be targeted, known as spearphishing. In spearphishing, a specific individual, company, or industry will be targeted by the adversary. More generally, adversaries can conduct non-targeted phishing, such as in mass malware spam campaigns.
A9: p02 | B9: 3 | C9: 7d5a91ab-56d5-5ca2-b89b-c33ea61c6f5c | D9: T1566.004 | E9: 0/4 | F9: 0.3611 | G9: # T1566.004 - Spearphishing Voice Type: sub-technique | Domain: enterprise-attack | ATT&CK version: 19.2 Tactics: initial-access Platforms: Linux, macOS, Windows, Identity Provider Sub-technique of: T1566 Phishing ## Description Adversaries may use voice communications to ultimately gain access to victim systems. Spearphishing voice is a specific variant of spearphishing. It is different from other forms of spearphishing in that it employs the use of manipulating a user into providing access to systems through a phone call or other forms of voice communications. Spearphishing frequently involves social engineering techniques, such as posing as a trusted source (ex: [Impersonation](https://attack.mitre.org/techniques/T1684/001)) and/or creating a sense of urgency or alarm for the recipient.
A10: p02 | B10: 4 | C10: ff4c0835-7fe5-59cd-a94d-d82a9c87c07c | D10: TA0001 | E10: 0/1 | F10: 0.3333 | G10: # TA0001 - Initial Access Type: tactic | Domain: enterprise-attack | ATT&CK version: 19.2 Shortname: initial-access ## Description The adversary is trying to get into your network. Initial Access consists of techniques that use various entry vectors to gain their initial foothold within a network. Techniques used to gain a foothold include targeted spearphishing and exploiting weaknesses on public-facing web servers. Footholds gained through initial access may allow for continued access, like valid accounts and use of external remote services, or may be limited-use due to changing passwords. ## Techniques in this tactic - T1078 Valid Accounts - T1091 Replication Through Removable Media - T1133 External Remote Services - T1189 Drive-by Compromise - T1190 Exploit Public-Facing Application - T1195 Supply Chain Compromise - T1199 Trusted Relationship - T1200 Hardware Additions - T1566 Phishing - T1659 Content Injection - T1669 Wi-Fi Networks
A11: p02 | B11: 5 | C11: f4d8f7cf-221f-59d8-8020-429a851befef | D11: T1598 | E11: 0/6 | F11: 0.3333 | G11: # T1598 - Phishing for Information Type: technique | Domain: enterprise-attack | ATT&CK version: 19.2 Tactics: reconnaissance Platforms: PRE ## Description Adversaries may send phishing messages to elicit sensitive information that can be used during targeting. Phishing for information is an attempt to trick targets into divulging information, frequently credentials or other actionable information. Phishing for information is different from [Phishing](https://attack.mitre.org/techniques/T1566) in that the objective is gathering data from the victim rather than executing malicious code. All forms of phishing are electronically delivered social engineering. Phishing can be targeted, known as spearphishing. In spearphishing, a specific individual, company, or industry will be targeted by the adversary. More generally, adversaries can conduct non-targeted phishing, such as in mass credential harvesting campaigns.
A12: p03 | B12: 1 | C12: 259ce106-5bf5-5095-9060-49c5e3501b01 | D12: TA0003 | E12: 0/2 | F12: 1 | G12: # TA0003 - Persistence Type: tactic | Domain: enterprise-attack | ATT&CK version: 19.2 Shortname: persistence ## Description The adversary is trying to maintain their foothold. Persistence consists of techniques that adversaries use to keep access to systems across restarts, changed credentials, and other interruptions that could cut off their access. Techniques used for persistence include any access, action, or configuration changes that let them maintain their foothold on systems, such as replacing or hijacking legitimate code or adding startup code.
A13: p03 | B13: 2 | C13: e10a631d-09ba-51f0-875b-5eb8736daa53 | D13: T1070.010 | E13: 0/4 | F13: 0.3333 | G13: # T1070.010 - Relocate Malware Type: sub-technique | Domain: enterprise-attack | ATT&CK version: 19.2 Tactics: stealth Platforms: Linux, macOS, Network Devices, Windows Sub-technique of: T1070 Indicator Removal ## Description Once a payload is delivered, adversaries may reproduce copies of the same malware on the victim system to remove evidence of their presence and/or avoid defenses. Copying malware payloads to new locations may also be combined with [File Deletion](https://attack.mitre.org/techniques/T1070/004) to cleanup older artifacts. Relocating malware may be a part of many actions intended to evade defenses. For example, adversaries may copy and rename payloads to better blend into the local environment (i.e., [Match Legitimate Resource Name or Location](https://attack.mitre.org/techniques/T1036/005)). Payloads may also be repositioned to target [File/Path Exclusions](https://attack.mitre.org/techniques/T1564/012) as well as specific locations associated with establishing [Persistence](https://attack.mitre.org/tactics/TA0003).
... A66: p13 | B66: 5 | C66: 60d08f9a-0633-524e-8298-fe7bc19f2408 | D66: T1059.009 | E66: 0/4 | F66: 0.2917 | G66: # T1059.009 - Cloud API Type: sub-technique | Domain: enterprise-attack | ATT&CK version: 19.2 Tactics: execution Platforms: IaaS, Identity Provider, Office Suite, SaaS Sub-technique of: T1059 Command and Scripting Interpreter ## Description Adversaries may abuse cloud APIs to execute malicious commands. APIs available in cloud environments provide various functionalities and are a feature-rich method for programmatic access to nearly all aspects of a tenant. These APIs may be utilized through various methods such as command line interpreters (CLIs), in-browser Cloud Shells, [PowerShell](https://attack.mitre.org/techniques/T1059/001) modules like Azure for PowerShell, or software developer kits (SDKs) available for languages such as [Python](https://attack.mitre.org/techniques/T1059/006). Cloud API functionality may allow for administrative access across all major services in a tenant such as compute, storage, identity and access management (IAM), networking, and security policies.

Sheet Resumen
A1: Lectura (protocolo v2 §5) | B1: RAG | C1: LLM
A2: Respuestas calificadas | B2: =COUNTIFS(Respuestas!$B$2:$B$200,"rag",Respuestas!$L$2:$L$200,">0") -> 4 | C2: =COUNTIFS(Respuestas!$B$2:$B$200,"llm",Respuestas!$L$2:$L$200,">0") -> 4
A3: A. Hechos cubiertos ÷ hechos (respondibles) | B3: =IF(SUMIFS(Respuestas!$M$2:$M$200,Respuestas!$B$2:$B$200,"rag",Respuestas!$L$2:$L$200,">0")=0,"-",SUMIFS(Respuestas!$N$2:$N$200,Respuestas!$B$2:$B$200,"rag",Respuestas!$L$2:$L$200,">0")/SUMIFS(Respuestas!$M$2:$M$200,Respuestas!$B$2:$B$200,"rag",Respuestas!$L$2:$L$200,">0")) -> 0.22222222 | C3: =IF(SUMIFS(Respuestas!$M$2:$M$200,Respuestas!$B$2:$B$200,"llm",Respuestas!$L$2:$L$200,">0")=0,"-",SUMIFS(Respuestas!$N$2:$N$200,Respuestas!$B$2:$B$200,"llm",Respuestas!$L$2:$L$200,">0")/SUMIFS(Respuestas!$M$2:$M$200,Respuestas!$B$2:$B$200,"llm",Respuestas!$L$2:$L$200,">0")) -> 0.22222222
A4: A. Afirmaciones INCORRECTA ÷ afirmaciones de hecho | B4: =IF(SUMIFS(Respuestas!$W$2:$W$200,Respuestas!$B$2:$B$200,"rag",Respuestas!$L$2:$L$200,">0")=0,"-",SUMIFS(Respuestas!$P$2:$P$200,Respuestas!$B$2:$B$200,"rag",Respuestas!$L$2:$L$200,">0")/SUMIFS(Respuestas!$W$2:$W$200,Respuestas!$B$2:$B$200,"rag",Respuestas!$L$2:$L$200,">0")) -> 0 | C4: =IF(SUMIFS(Respuestas!$W$2:$W$200,Respuestas!$B$2:$B$200,"llm",Respuestas!$L$2:$L$200,">0")=0,"-",SUMIFS(Respuestas!$P$2:$P$200,Respuestas!$B$2:$B$200,"llm",Respuestas!$L$2:$L$200,">0")/SUMIFS(Respuestas!$W$2:$W$200,Respuestas!$B$2:$B$200,"llm",Respuestas!$L$2:$L$200,">0")) -> 0.29411765
A5: B. Respuestas con abstención errónea (ABS-E) | B5: =COUNTIFS(Respuestas!$B$2:$B$200,"rag",Respuestas!$Q$2:$Q$200,">0") -> 3 | C5: =COUNTIFS(Respuestas!$B$2:$B$200,"llm",Respuestas!$Q$2:$Q$200,">0") -> 0
A6: B. Respuestas con respuesta sin base (NO-ABS) | B6: =COUNTIFS(Respuestas!$B$2:$B$200,"rag",Respuestas!$R$2:$R$200,">0") -> 0 | C6: =COUNTIFS(Respuestas!$B$2:$B$200,"llm",Respuestas!$R$2:$R$200,">0") -> 1
A7: C. Precisión de citas (sostenidas ÷ afirmaciones de hecho) | B7: =IF(SUMIFS(Respuestas!$W$2:$W$200,Respuestas!$B$2:$B$200,"rag",Respuestas!$L$2:$L$200,">0")=0,"-",SUMIFS(Respuestas!$X$2:$X$200,Respuestas!$B$2:$B$200,"rag",Respuestas!$L$2:$L$200,">0")/SUMIFS(Respuestas!$W$2:$W$200,Respuestas!$B$2:$B$200,"rag",Respuestas!$L$2:$L$200,">0")) -> 0.8 | C7: ="N/A" -> N/A
A8: C. Cobertura de citas (hechos cubiertos y citados ÷ hechos) | B8: =IF(SUMIFS(Respuestas!$M$2:$M$200,Respuestas!$B$2:$B$200,"rag",Respuestas!$L$2:$L$200,">0")=0,"-",SUM(Hechos!$H$2:$H$201)/SUMIFS(Respuestas!$M$2:$M$200,Respuestas!$B$2:$B$200,"rag",Respuestas!$L$2:$L$200,">0")) -> 0.16666667 | C8: ="N/A" -> N/A
A9: C. Afirmaciones SIN-RESPALDO | B9: =SUMIFS(Respuestas!$T$2:$T$200,Respuestas!$B$2:$B$200,"rag") -> 1 | C9: ="N/A" -> N/A
A10: C. Afirmaciones CITA-X | B10: =SUMIFS(Respuestas!$U$2:$U$200,Respuestas!$B$2:$B$200,"rag") -> 0 | C10: ="N/A" -> N/A
A11: C. Afirmaciones SIN-CITA | B11: =SUMIFS(Respuestas!$V$2:$V$200,Respuestas!$B$2:$B$200,"rag") -> 0 | C11: ="N/A" -> N/A
A12: D. Afirmaciones FUERA_REF | B12: =SUMIFS(Respuestas!$S$2:$S$200,Respuestas!$B$2:$B$200,"rag") -> 1 | C12: =SUMIFS(Respuestas!$S$2:$S$200,Respuestas!$B$2:$B$200,"llm") -> 6
A13: N2 promedio (descriptivo, 0-2) | B13: =IFERROR(AVERAGEIFS(Respuestas!$Y$2:$Y$200,Respuestas!$B$2:$B$200,"rag"),"-") -> 0.5 | C13: =IFERROR(AVERAGEIFS(Respuestas!$Y$2:$Y$200,Respuestas!$B$2:$B$200,"llm"),"-") -> 0.5
A14: N3 promedio (descriptivo, 0-2; excluye N/A) | B14: =IFERROR(AVERAGEIFS(Respuestas!$Z$2:$Z$200,Respuestas!$B$2:$B$200,"rag"),"-") -> 1.6666667 | C14: ="N/A" -> N/A
A15: Alerta CRITICA (respuestas) | B15: =COUNTIFS(Respuestas!$B$2:$B$200,"rag",Respuestas!$AA$2:$AA$200,"*CRITICA*") -> 3 | C15: =COUNTIFS(Respuestas!$B$2:$B$200,"llm",Respuestas!$AA$2:$AA$200,"*CRITICA*") -> 4
A16: Alerta RESPALDO (respuestas) | B16: =COUNTIFS(Respuestas!$B$2:$B$200,"rag",Respuestas!$AA$2:$AA$200,"*RESPALDO*") -> 1 | C16: =COUNTIFS(Respuestas!$B$2:$B$200,"llm",Respuestas!$AA$2:$AA$200,"*RESPALDO*") -> 0
A17: Alerta TRUNC (respuestas) | B17: =COUNTIFS(Respuestas!$B$2:$B$200,"rag",Respuestas!$AA$2:$AA$200,"*TRUNC*") -> 0 | C17: =COUNTIFS(Respuestas!$B$2:$B$200,"llm",Respuestas!$AA$2:$AA$200,"*TRUNC*") -> 1
A19: Las lecturas A-D y las alertas se calculan solas desde la hoja Afirmaciones. Con pocas respuestas son conteos descriptivos, sin pruebas de significancia.

Sheet Config
A1: rúbrica | B1: protocolo v2 (borrador) - eval/pilot/protocol_v2.md
A2: plantilla creada | B2: 2026-10-12T12:45:08
A3: corrida de origen | B3: 20260922_064359
A4: evaluador
A5: fecha de calificación
A7: CORRIDA (config.json)
A8: api | B8: http://localhost:8000
A9: model | B9: qwen3:4b-instruct
A10: embed_model | B10: granite-embedding:30m
A11: retrieval | B11: hybrid
A12: top_k | B12: 5
A13: temperature | B13: 0.0
A14: think | B14: False
A15: modes | B15: ['rag', 'llm']
A16: collection_points | B16: 7241
A17: started_at | B17: 2026-09-22T06:43:59
A19: CORPUS (data/manifest.json)
A20: created_at | B20: 2026-09-12T16:14:31.631478+00:00
A21: collection | B21: mitre_attack
A22: embed_model | B22: granite-embedding:30m
A23: embed_dim | B23: 384
A24: doc_prefix
A25: query_prefix
A26: chunk_size | B26: 1200
A27: chunk_overlap | B27: 150
A28: domains | B28: ['enterprise-attack']
A29: attack_versions | B29: {'enterprise-attack': '19.2'}
A30: n_documents | B30: 2616
A31: n_chunks | B31: 7241
A32: points_count | B32: 7241
A33: elapsed_s | B33: 1779.6
